verilog_project/verilog_project/encoder/encoder.v
//easy-to-adjust-mode
module encoder(
    input  [7:0] in,
    output reg [2:0] out
);

integer i;
reg[7:0] J;
reg found;

always@(*) begin
found=0;

for (i = 0; i < 8; i++ ) begin

J=8'b0;
J[i]=1'b1;

for(int k = 1+i; k<8; k++)begin
J[k]=1'bx;
end


if(!found && (in[i] == J[i])) begin
out = i[2:0];
found = 1'b1;
end

else if(in == 8'b0) begin
out = 3'bx;
end

else begin
out = out;
end

end
end

endmodule


//fast-mode(less logic-depth)
module encoder_fast(
    input  [7:0] in,
    output reg [2:0] out
);

always @(*) begin
    casez (in)
        8'bzzzzzzz1: out = 3'b000; // 最低位 1
        8'bzzzzzz10: out = 3'b001;
        8'bzzzzz100: out = 3'b010;
        8'bzzzz1000: out = 3'b011;
        8'bzzz10000: out = 3'b100;
        8'bzz100000: out = 3'b101;
        8'bz1000000: out = 3'b110;
        8'b10000000: out = 3'b111; // 最高位 1
        default:     out = 3'bxxx; // 输入全 0 或非法
    endcase
end

endmodule

verilog_project/encoder/tb_encoder.v

`timescale 1ns/10ps

module tb_encoder;

//VECTORS FOR DUT
reg[7:0] IN;
wire[2:0] OUT;
wire[2:0] OUT_fast;
//VECTORS FOR TESTING

reg TICK;
integer FD, COUNT;
reg [8*31-1:0] COMMENT;
reg [2:0] OUT_EXPECTED;
reg [31:0] VECTORCOUNT, ERRORS;
int i;
reg [31:0] input_coverage [0:7];
reg eof;
reg [7:0]J;

//DUT INSTANTIATION

encoder dut_encoder (.in(IN), .out(OUT));
encoder_fast dut_encoder_fast (.in(IN), .out(OUT_fast));



//DUMP EVERYTHING INTO DUMPFILE

initial begin

$dumpfile ("tb_encoder.vcd");
$dumpvars (0, tb_encoder);

end

//TICKPERIOD

localparam TICKPERIOD = 20;

always begin

#(TICKPERIOD/2) TICK = ~TICK;

end



//TASKS

//task 1 initialize

task initialize; begin

FD = $fopen ("tb_encoder.tv" , "r");
COUNT = $fscanf (FD, "%s", COMMENT);

COUNT = $fscanf (FD, "%s %b %b", COMMENT, IN, OUT_EXPECTED);
TICK = 0;
VECTORCOUNT = 0;
ERRORS = 0;

for(i=0; i<8; i++)begin
input_coverage[i] = 0;
end

eof = 0;


$display ();
$display ("TEST_START-------------------------------------------------------------------------------------------------------------------------------------");
$display ();
$display ("                     | TIME |    IN    | OUT | OUT_fast | OUT_EXPECTED |");
$display ("-----------------------------------------------------------------------------------------------------------------------------------------------");



end
endtask


//task 3 scan_file

task scan_file; begin

COUNT = $fscanf (FD, "%s %b %b", COMMENT, IN, OUT_EXPECTED);
eof = (COUNT == -1);

end
endtask

//task 4 random_in

task random_in; begin


IN =  $urandom %128;
COMMENT = "-";

# ($urandom_range(0.1,10));

end
endtask

//task5 OUT_EXP

task OUT_EXP; begin

reg found;
    found = 1'b0;   // 标记是否已经找到第一个1

    for (int j = 0; j < 8; j++) begin
        if (!found && IN[j]) begin
            OUT_EXPECTED = j[2:0];
            found = 1'b1;  // 找到后再也不更新 out
        end
    end

if(IN == 8'b0)begin
OUT_EXPECTED = 3'bx;
end

end
endtask



//task 5 close

task close; begin

#10;

$fclose (FD);

$display ();
$display ("COVERAGE_REPORT");

for (int j = 0; j < 8; j++ ) begin

J=8'b0;
J[j]=1'b1;

for(int k = 1+j; k<8; k++)begin
J[k]=1'bx;
end

if(input_coverage[j] == 0) begin
$display ("input IN = %b has occured %d times ***ERROR***", J , input_coverage[j]);
ERRORS = ERRORS + 1;
end

else begin
$display ("input IN = %b has occured %d times", J , input_coverage[j]);
end

end


$display ();
$display ("VECTORCOUNT = %d", VECTORCOUNT);
$display ("ERRORS = %15d", ERRORS);
$display ();
$display ("TEST_END--------------------------------------------------------------------------------------------------------------------------");
$display ();

$finish;

end
endtask


//task 6 vectorcount

task vectorcount; begin

VECTORCOUNT = VECTORCOUNT + 1;

end
endtask


//task 7 display_file

task display_file; begin

$display ("%10d %9s | %4d | %8b | %3b | %5b    | %7b      |", VECTORCOUNT, COMMENT, $time, IN, OUT, OUT_fast, OUT_EXPECTED);

end
endtask

//task 8 coverage_update

task coverage_update; begin

reg found;
found = 0;

for (int j = 0; j < 8; j++ ) begin

    if (!found && IN[j]) begin
        input_coverage[j] = input_coverage[j] + 1;
        found = 1'b1;
    end
end

end
endtask




//task 9 errors_warnings_check

task errors_warnings_check; begin


if (OUT !== OUT_EXPECTED) begin

$display ("***ERROR: OUT = %b, OUT_expected = %b", OUT, OUT_EXPECTED);
ERRORS = ERRORS + 1;

end


end
endtask



//DRIVE

//0 initialize

initial begin

initialize;

end

//2 scan file on negedge TICK

always @ (negedge TICK) begin

#1.2;

if (!eof) begin

scan_file;

end
end



//3 check file on posedge TICK

always  @ (posedge TICK) begin

coverage_update;

#0.1;

OUT_EXP;
display_file;
errors_warnings_check;
vectorcount;

end



// eof

initial begin

wait (eof);

$display ();
$display("%13s ***time = %0d,eof ***","",$time);
$display ();

for (i = 0; i < 50; i++) begin


if (IN == 9'b100000000)
begin

vectorcount;
close;

end

else begin

random_in;
end

end

close;

end


endmodule

verilog_project/encoder/tb_encoder.vcd
$date
	Thu Feb  5 05:16:06 2026
$end
$version
	Icarus Verilog
$end
$timescale
	10ps
$end
$scope module tb_encoder $end
$var wire 3 ! OUT_fast [2:0] $end
$var wire 3 " OUT [2:0] $end
$var parameter 32 # TICKPERIOD $end
$var reg 248 $ COMMENT [247:0] $end
$var reg 32 % ERRORS [31:0] $end
$var reg 8 & IN [7:0] $end
$var reg 8 ' J [7:0] $end
$var reg 3 ( OUT_EXPECTED [2:0] $end
$var reg 1 ) TICK $end
$var reg 32 * VECTORCOUNT [31:0] $end
$var reg 1 + eof $end
$var integer 32 , COUNT [31:0] $end
$var integer 32 - FD [31:0] $end
$var integer 32 . i [31:0] $end
$scope module dut_encoder $end
$var wire 8 / in [7:0] $end
$var reg 8 0 J [7:0] $end
$var reg 1 1 found $end
$var reg 3 2 out [2:0] $end
$var integer 32 3 i [31:0] $end
$scope begin $ivl_for_loop4 $end
$var integer 32 4 k [31:0] $end
$upscope $end
$upscope $end
$scope module dut_encoder_fast $end
$var wire 8 5 in [7:0] $end
$var reg 3 6 out [2:0] $end
$upscope $end
$scope task OUT_EXP $end
$scope begin $unm_blk_7 $end
$var reg 1 7 found $end
$scope begin $ivl_for_loop0 $end
$var integer 32 8 j [31:0] $end
$upscope $end
$upscope $end
$upscope $end
$scope task close $end
$scope begin $ivl_for_loop1 $end
$var integer 32 9 j [31:0] $end
$scope begin $ivl_for_loop2 $end
$var integer 32 : k [31:0] $end
$upscope $end
$upscope $end
$upscope $end
$scope task coverage_update $end
$scope begin $unm_blk_18 $end
$var reg 1 ; found $end
$scope begin $ivl_for_loop3 $end
$var integer 32 < j [31:0] $end
$upscope $end
$upscope $end
$upscope $end
$scope task display_file $end
$upscope $end
$scope task errors_warnings_check $end
$upscope $end
$scope task initialize $end
$upscope $end
$scope task random_in $end
$upscope $end
$scope task scan_file $end
$upscope $end
$scope task vectorcount $end
$upscope $end
$upscope $end
$enddefinitions $end
$comment Show the parameter values. $end
$dumpall
b10100 #
$end
#0
$dumpvars
b0 <
x;
b0 :
b0 9
b0 8
x7
b0 6
b1 5
b1000 4
b1000 3
b0 2
11
b10000000 0
b1 /
b1000 .
b10000000000000000000000000000011 -
b11 ,
0+
b0 *
0)
b0 (
bx '
b1 &
b0 %
b1001001010011100100100101010100 $
b0 "
b0 !
$end
#1000
b1000 <
1;
1)
#1010
b1 *
b1000 8
17
#2000
0)
#2120
b1 "
b1 2
b1000 4
b10000000 0
b1000 3
11
b1 !
b1 6
b1 (
b10 &
b10 /
b10 5
b101101 $
#3000
b1000 <
1;
1)
#3010
b10 *
b1000 8
17
#4000
0)
#4120
b10 "
b10 2
b1000 4
b10000000 0
b1000 3
11
b10 !
b10 6
b10 (
b100 &
b100 /
b100 5
#5000
b1000 <
1;
1)
#5010
b11 *
b1000 8
17
#6000
0)
#6120
b11 "
b11 2
b1000 4
b10000000 0
b1000 3
11
b11 !
b11 6
b11 (
b1000 &
b1000 /
b1000 5
#7000
b1000 <
1;
1)
#7010
b100 *
b1000 8
17
#8000
0)
#8120
b100 "
b100 2
b1000 4
b10000000 0
b1000 3
11
b100 !
b100 6
b100 (
b10000 &
b10000 /
b10000 5
#9000
b1000 <
1;
1)
#9010
b101 *
b1000 8
17
#10000
0)
#10120
b101 "
b101 2
b1000 4
b10000000 0
b1000 3
11
b101 !
b101 6
b101 (
b100000 &
b100000 /
b100000 5
#11000
b1000 <
1;
1)
#11010
b110 *
b1000 8
17
#12000
0)
#12120
b110 "
b110 2
b1000 4
b10000000 0
b1000 3
11
b110 !
b110 6
b110 (
b1000000 &
b1000000 /
b1000000 5
#13000
b1000 <
1;
1)
#13010
b111 *
b1000 8
17
#14000
0)
#14120
b111 "
b111 2
b1000 4
b10000000 0
b1000 3
11
b111 !
b111 6
b111 (
b10000000 &
b10000000 /
b10000000 5
#15000
b1000 <
1;
1)
#15010
b1000 *
b1000 8
17
#16000
0)
#16120
b0 ,
#17000
b1000 <
1;
1)
#17010
b1001 *
b1000 8
17
#18000
0)
#18120
b10 "
b10 2
b1000 4
b10000000 0
b1000 3
11
b10 !
b10 6
b100100 &
b100100 /
b100100 5
b0 .
1+
b11111111111111111111111111111111 ,
#18320
b0 "
b0 2
b1000 4
b10000000 0
b1000 3
11
b0 !
b0 6
b1001 &
b1001 /
b1001 5
b1 .
#18520
b1000 4
b10000000 0
b1000 3
11
b1101 &
b1101 /
b1101 5
b10 .
#19000
b1000 <
1;
1)
#19010
b1010 *
b0 (
b1000 8
17
#19320
b1000 4
b10000000 0
b1000 3
11
b1 &
b1 /
b1 5
b100 .
#19820
b1 "
b1 2
b1000 4
b10000000 0
b1000 3
11
b1 !
b1 6
b1110110 &
b1110110 /
b1110110 5
b101 .
#20000
0)
#20420
b0 "
b0 2
b1000 4
b10000000 0
b1000 3
11
b0 !
b0 6
b1101101 &
b1101101 /
b1101101 5
b110 .
#21000
b1000 <
1;
1)
#21010
b1011 *
b1000 8
17
#21220
b1000 4
b10000000 0
b1000 3
11
b1111001 &
b1111001 /
b1111001 5
b111 .
#21620
b1000 4
b10000000 0
b1000 3
11
b1000101 &
b1000101 /
b1000101 5
b1000 .
#21920
b1000 4
b10000000 0
b1000 3
11
b1100101 &
b1100101 /
b1100101 5
b1001 .
#22000
0)
#22120
b1 "
b1 2
b1000 4
b10000000 0
b1000 3
11
b1 !
b1 6
b10010 &
b10010 /
b10010 5
b1010 .
#22920
b1000 4
b10000000 0
b1000 3
11
b1110010 &
b1110010 /
b1110010 5
b1011 .
#23000
b1000 <
1;
1)
#23010
b1100 *
b1 (
b1000 8
17
#23320
b11 "
b11 2
b1000 4
b10000000 0
b1000 3
11
b11 !
b11 6
b1101000 &
b1101000 /
b1101000 5
b1100 .
#23720
b10 "
b10 2
b1000 4
b10000000 0
b1000 3
11
b10 !
b10 6
b1011100 &
b1011100 /
b1011100 5
b1101 .
#24000
0)
#24120
b0 "
b0 2
b1000 4
b10000000 0
b1000 3
11
b0 !
b0 6
b101101 &
b101101 /
b101101 5
b1110 .
#24320
b1000 4
b10000000 0
b1000 3
11
b1100011 &
b1100011 /
b1100011 5
b1111 .
#24820
bx "
bx 2
b1000 4
b10000000 0
b1000 3
01
bx !
bx 6
b0 &
b0 /
b0 5
b10000 .
#25000
b1000 <
0;
1)
#25010
b1101 *
bx (
b1000 8
07
#25420
11
b1 "
b1 2
b1000 4
b10000000 0
b1000 3
b1 !
b1 6
b101010 &
b101010 /
b101010 5
b10001 .
#25720
b0 "
b0 2
b0 !
b0 6
b1000 4
b10000000 0
b1000 3
11
b1101 &
b1101 /
b1101 5
b10011 .
#25820
b1000 4
b10000000 0
b1000 3
11
b1101011 &
b1101011 /
b1101011 5
b10100 .
#26000
0)
#26220
b1 "
b1 2
b1000 4
b10000000 0
b1000 3
11
b1 !
b1 6
b10 &
b10 /
b10 5
b10101 .
#26520
b0 "
b0 2
b1000 4
b10000000 0
b1000 3
11
b0 !
b0 6
b11101 &
b11101 /
b11101 5
b10110 .
#26920
b1000 4
b10000000 0
b1000 3
11
b100011 &
b100011 /
b100011 5
b10111 .
#27000
1;
b1000 <
1)
#27010
b1110 *
17
b0 (
b1000 8
#27420
b1 "
b1 2
b1000 4
b10000000 0
b1000 3
11
b1 !
b1 6
b1001010 &
b1001010 /
b1001010 5
b11000 .
#27520
b1000 4
b10000000 0
b1000 3
11
b1110010 &
b1110010 /
b1110010 5
b11001 .
#28000
0)
#28320
b0 "
b0 2
b1000 4
b10000000 0
b1000 3
11
b0 !
b0 6
b1000001 &
b1000001 /
b1000001 5
b11010 .
#28720
b11 "
b11 2
b1000 4
b10000000 0
b1000 3
11
b11 !
b11 6
b1111000 &
b1111000 /
b1111000 5
b11011 .
#28920
b0 "
b0 2
b1000 4
b10000000 0
b1000 3
11
b0 !
b0 6
b1101011 &
b1101011 /
b1101011 5
b11100 .
#29000
b1000 <
1;
1)
#29010
b1111 *
b1000 8
17
#29820
b1 "
b1 2
b1000 4
b10000000 0
b1000 3
11
b1 !
b1 6
b1000110 &
b1000110 /
b1000110 5
b11101 .
#30000
0)
#30720
b10 "
b10 2
b1000 4
b10000000 0
b1000 3
11
b10 !
b10 6
b111100 &
b111100 /
b111100 5
b11110 .
#31000
b1000 <
1;
1)
#31010
b10000 *
b10 (
b1000 8
17
#31320
b0 "
b0 2
b1000 4
b10000000 0
b1000 3
11
b0 !
b0 6
b1011 &
b1011 /
b1011 5
b11111 .
#31520
b1000 4
b10000000 0
b1000 3
11
b101 &
b101 /
b101 5
b100000 .
#32000
0)
#32220
b1000 4
b10000000 0
b1000 3
11
b111011 &
b111011 /
b111011 5
b100001 .
#32820
b1 "
b1 2
b1000 4
b10000000 0
b1000 3
11
b1 !
b1 6
b1111110 &
b1111110 /
b1111110 5
b100010 .
#33000
b1000 <
1;
1)
#33010
b10001 *
b1 (
b1000 8
17
#33320
b0 "
b0 2
b1000 4
b10000000 0
b1000 3
11
b0 !
b0 6
b1110001 &
b1110001 /
b1110001 5
b100011 .
#34000
0)
#34320
b1 "
b1 2
b1000 4
b10000000 0
b1000 3
11
b1 !
b1 6
b1100010 &
b1100010 /
b1100010 5
b100100 .
#35000
b1000 <
1;
1)
#35010
b10010 *
b1000 8
17
#35020
b0 "
b0 2
b1000 4
b10000000 0
b1000 3
11
b0 !
b0 6
b11111 &
b11111 /
b11111 5
b100101 .
#35820
b11 "
b11 2
b1000 4
b10000000 0
b1000 3
11
b11 !
b11 6
b1111000 &
b1111000 /
b1111000 5
b100110 .
#36000
0)
#36120
b0 "
b0 2
b1000 4
b10000000 0
b1000 3
11
b0 !
b0 6
b11111 &
b11111 /
b11111 5
b100111 .
#36220
b1000 4
b10000000 0
b1000 3
11
b1011011 &
b1011011 /
b1011011 5
b101000 .
#37000
b1000 <
1;
1)
#37010
b10011 *
b0 (
b1000 8
17
#37020
b1000 4
b10000000 0
b1000 3
11
b1001001 &
b1001001 /
b1001001 5
b101001 .
#37420
b1000 4
b10000000 0
b1000 3
11
b1010111 &
b1010111 /
b1010111 5
b101010 .
#37520
b1 "
b1 2
b1000 4
b10000000 0
b1000 3
11
b1 !
b1 6
b10110 &
b10110 /
b10110 5
b101011 .
#38000
0)
#38020
b1000 4
b10000000 0
b1000 3
11
b1000010 &
b1000010 /
b1000010 5
b101100 .
#38920
b0 "
b0 2
b1000 4
b10000000 0
b1000 3
11
b0 !
b0 6
b1110111 &
b1110111 /
b1110111 5
b101101 .
#39000
b1000 <
1;
1)
#39010
b10100 *
b1000 8
17
#39520
b1 "
b1 2
b1000 4
b10000000 0
b1000 3
11
b1 !
b1 6
b10010 &
b10010 /
b10010 5
b101110 .
#39720
b0 "
b0 2
b1000 4
b10000000 0
b1000 3
11
b0 !
b0 6
b1101101 &
b1101101 /
b1101101 5
b101111 .
#40000
0)
#40320
b1000 4
b10000000 0
b1000 3
11
b11111 &
b11111 /
b11111 5
b110000 .
#40720
b1000 4
b10000000 0
b1000 3
11
b101 &
b101 /
b101 5
b110001 .
#40920
b110010 .
#41000
b1000 <
1;
1)
#41010
b10101 *
b1000 8
17
#41920
b1000 9
b1000 :
b10000000 '
