verilog_project/sr_flip_flop/sr_flip_flop.v
// A sr (set ready) flip-flop which is pulse-triggered can be set and reset.

module sr_flip_flop_gate (
    input       clk,        // Clock
    input       s,          // Inputs
    input       r,          // 
    output      q,          // Output
    output      qbar

);      //



    // INTERNAL WIRES
    wire  q1, qbar1, q2, qbar2, s1, r1;
    reg  prev_q, prev_qbar;


    always@(posedge clk)begin
    #0.12;

    prev_q = q;
    prev_qbar = qbar;

    end

    nand (s1, s, clk);
    nand (r1, r, clk);

    // SR- LATCH -------------------------------------
    
    nand (q1, s1, prev_qbar);
    nand (qbar1, r1, prev_q);

    nand (q, s1, qbar1);
    nand (qbar, r1, q1);


    
    
endmodule   
    


module sr_flip_flop_dataflow(
    input       clk,        // Clock
    input       s,          // Inputs
    input       r,          // 
    output      q,          // Output
    output      qbar);      //


    // INTERNAL WIRES
    wire  q1, qbar1, q2, qbar2, s1, r1;
    reg  prev_q, prev_qbar;


    always@(posedge clk)begin
    #0.12;

    prev_q = q;
    prev_qbar = qbar;

    end  


    assign s1 = ~(s & clk);
    assign r1 = ~(r & clk);

    // SR- LATCH -------------------------------------
    
    assign q1 = ~(s1 & prev_qbar);
    assign qbar1 = ~(r1 & prev_q);

    assign q = ~(s1 & qbar1);
    assign qbar = ~(r1 & q1);   

endmodule


module sr_flip_flop_behavioral (
    input       clk,        // Clock
    input       s,          // Inputs
    input       r,          // 
    output reg  q,          // Output
    output wire qbar);      //


assign qbar = ~q;

always @ ( posedge clk ) begin

    case ({s,r})
    2'b00: q <= q;
    2'b01: q <= 1'b0;
    2'b10: q <= 1'b1;
    2'b11: q <= 1'bx;
    endcase
end




endmodule

verilog_project/verilog_project/sr_flip_flop/tb_sr_flip_flop.v
`timescale 1ns/10ps

module tb_sr_flip_flop;

//VECTORS FOR DUT
reg S, R;
wire Q_gate, Q_data, Q_beh, QBAR_gate, QBAR_data, QBAR_beh;

//VECTORS FOR TESTING

reg TICK;
integer FD, COUNT;
reg [8*9-1:0] COMMENT;
reg [8*9-1:0] COMMENT1;
reg [8*9-1:0] COMMENT2;
reg QEXPECTED, QBAREXPECTED;
reg [31:0] VECTORCOUNT, ERRORS;
int i;
reg [31:0] input_coverage [0:15];
reg eof;
reg prev_Qgate;
reg prev_Qbargate;
reg prev_Qdata;
reg prev_Qbardata;
reg prev_Qbeh;
reg prev_Qbarbeh;
reg [1:0] prev_SR;
reg prev_QEx;
reg prev_QExbar;


//DUT INSTANTIATION

sr_flip_flop_gate dut_flip_flop_gate (.s(S), .r(R), .q(Q_gate), .qbar(QBAR_gate), .clk(TICK));
sr_flip_flop_dataflow dut_flip_flop_dataflow (.s(S), .r(R), .q(Q_data), .qbar(QBAR_data), .clk(TICK));
sr_flip_flop_behavioral dut_flip_flop_behavioral (.s(S), .r(R), .q(Q_beh), .qbar(QBAR_beh), .clk(TICK));



//DUMP EVERYTHING INTO DUMPFILE

initial begin

$dumpfile ("tb_sr_flip_flop.vcd");
$dumpvars (0, tb_sr_flip_flop);

end

//TICKPERIOD

localparam TICKPERIOD = 20;

always begin

#(TICKPERIOD/2) TICK = ~TICK;

end


//TASKS

//task 1 initialize

task initialize; begin

FD = $fopen ("tb_sr_flip_flop.tv" , "r");
COUNT = $fscanf (FD, "%s", COMMENT);

COUNT = $fscanf (FD, "%s %b %b %s %s", COMMENT, S, R, COMMENT1, COMMENT2);
TICK = 0;
VECTORCOUNT = 0;
ERRORS = 0;

for ( i = 0 ; i < 16 ; i++ ) begin
input_coverage[i] = 0;
end

eof = 0;

$display ();
$display ("TEST_START------------------------------------------------------------------------------------------------------------------------");
$display ();
$display ("                     | TIME | S | R |  Q_gate  |  Q_data  |  Q_beh  | QBAR_gate | QBAR_data | QBAR_beh | QEXPECTED | QBAREXPECTED |");
$display ("----------------------------------------------------------------------------------------------------------------------------------");



end
endtask

//task2 force_release

task force_release; begin

#0.11;

force Q_gate = 1'b0;
force QBAR_gate = 1'b1;
force Q_data = 1'b0;
force QBAR_data = 1'b1;
force Q_beh = 1'b0;
force QBAR_beh = 1'b1;

#10;

release Q_gate;
release QBAR_gate;
release Q_data;
release QBAR_data;
release Q_beh;
release QBAR_beh;

end
endtask

//task 3 scan_file

task scan_file; begin


COUNT = $fscanf (FD,"%s %b %b %b %b", COMMENT, S, R, QEXPECTED, QBAREXPECTED);
eof = (COUNT == -1);

end
endtask

//task 4 random_in

task random_in; begin

S =  $urandom %7 ;
R =  $urandom %7 ;

case ({S,R})
2'b00: COMMENT =  (((({prev_Qgate,prev_Qbargate}) == 2'b11) || (({prev_Qdata,prev_Qbardata}) == 2'b11) || (({prev_Qbeh,prev_Qbarbeh}) == 2'b11)) || ((({prev_Qgate,prev_Qbargate}) == 2'b00) ||(({prev_Qdata,prev_Qbardata}) == 2'b00) || (({prev_Qbeh,prev_Qbarbeh}) == 2'b00)))? "ILLEGAL": "HOLD";
2'b01: COMMENT = "RESET";
2'b10: COMMENT = "SET";
2'b11: COMMENT = "ILLEGAL";



endcase

#($urandom_range (0.1,10));

end
endtask

//task 5 QEXP

task QEXP; begin

if ((((({prev_Qgate,prev_Qbargate})== 2'b11) || (({prev_Qdata,prev_Qbardata})== 2'b11) || (({prev_Qbeh,prev_Qbarbeh}) == 2'b11)) || ((({prev_Qgate,prev_Qbargate})== 2'b00)||(({prev_Qdata,prev_Qbardata}== 2'b00) || (({prev_Qbeh,prev_Qbarbeh}) == 2'b00))))&& ({S,R} == 2'b00)) begin

QEXPECTED = 1'bx;
QBAREXPECTED = 1'bx;

end


else begin

case ({S,R})
  2'b00: begin
QEXPECTED = prev_QEx;
QBAREXPECTED = prev_QExbar;
end
  2'b01: begin
QEXPECTED = 1'b0;
QBAREXPECTED = 1'b1;
end
  2'b10: begin
QEXPECTED = 1'b1;
QBAREXPECTED = 1'b0;
end
  2'b11: begin
QEXPECTED = 1'bx;
QBAREXPECTED = 1'bx;
end


endcase
end



end
endtask



//task 6 close

task close; begin

#10;
$fclose (FD);

$display ();
$display ("COVERAGE_REPORT");

for ( i = 0; i < 16; i++ ) begin

if(input_coverage[i] == 0) begin

$display ("input %b to input %b has occured %d times (***ERROR***)",i[3:2], i[1:0], input_coverage[i]);
ERRORS = ERRORS +1;

end

else begin

$display ("input %b to input %b has occured %d times",i[3:2], i[1:0], input_coverage[i]);

end

end

$display ();
$display ("VECTORCOUNT = %d", VECTORCOUNT);
$display ("ERRORS = %15d", ERRORS);
$display ();
$display ("TEST_END--------------------------------------------------------------------------------------------------------------------------");
$display ();

$finish;

end
endtask

//task 7 vectorcount

task vectorcount; begin

VECTORCOUNT = VECTORCOUNT + 1;

end
endtask


//task 8 display_file

task display_file; begin

$display ("%10d %9s | %4d | %1d | %1d | %4d     | %4d     | %4d    | %5d     | %5d     | %5d     | %5d     | %6d       |", VECTORCOUNT, COMMENT, $time, S, R, Q_gate, Q_data, Q_beh, QBAR_gate, QBAR_data, QBAR_beh, QEXPECTED, QBAREXPECTED);

end
endtask

//task 9 coverage_update

task coverage_update; begin

input_coverage[{prev_SR, S, R}]++;

end
endtask

//task 10 errors_warnings_check

task errors_warnings_check; begin

if (((((({prev_Qgate,prev_Qbargate})== 2'b11) || (({prev_Qdata,prev_Qbardata})== 2'b11) || (({prev_Qbeh,prev_Qbarbeh}) == 2'b11)) || ((({prev_Qgate,prev_Qbargate})== 2'b00)||(({prev_Qdata,prev_Qbardata}== 2'b00) || (({prev_Qbeh,prev_Qbarbeh}) == 2'b00))))&& ({S,R} == 2'b00))||({S,R} == 2'b11)) begin

if  (((({prev_Qgate,prev_Qbargate})== 2'b00) || (({prev_Qdata,prev_Qbardata})== 2'b00) || (({prev_Qbeh,prev_Qbarbeh})== 2'b00)) && ((({S,R}) == 2'b11) || (({S,R}) == 2'b00))) begin

$display ("***WARNING: ILLEGAL CONDITION,RACING CONDITION");

end

if (((((({prev_Qgate,prev_Qbargate})== 2'b11) || (({prev_Qdata,prev_Qbardata})== 2'b11) || (({prev_Qbeh,prev_Qbarbeh})== 2'b11)) ||
   ((({prev_Qgate,prev_Qbargate})=== 2'bxx) || (({prev_Qdata,prev_Qbardata})=== 2'bxx) || (({prev_Qbeh,prev_Qbarbeh})=== 2'bxx)) ||
   ((({prev_Qgate,prev_Qbargate})== 2'b01) || (({prev_Qdata,prev_Qbardata})== 2'b01) || (({prev_Qbeh,prev_Qbarbeh})== 2'b01)) ||
   ((({prev_Qgate,prev_Qbargate})== 2'b10) || (({prev_Qdata,prev_Qbardata})== 2'b10) || (({prev_Qbeh,prev_Qbarbeh})== 2'b10)))
   && ({S,R} == 2'b11)) ||
   ((({prev_Qgate,prev_Qbargate})== 2'b11) || (({prev_Qdata,prev_Qbardata})== 2'b11) || (({prev_Qbeh,prev_Qbarbeh})== 2'b11)) &&
   ({S,R} == 2'b00))
   begin

$display ("***WARNING: ILLEGAL CONDITION, q = qbar");

end

end

else begin

if (Q_gate !== QEXPECTED) begin

$display ("***ERROR: Q_gate = %b, Q_expected = %b", Q_gate, QEXPECTED);
ERRORS = ERRORS + 1;

end

if (Q_data !== QEXPECTED) begin

$display ("***ERROR: Q_dataflow = %b, Q_expected = %b", Q_data, QEXPECTED);
ERRORS = ERRORS + 1;

end

if (Q_beh !== QEXPECTED) begin

$display ("***ERROR: Q_behavioral = %b, Q_expected = %b", Q_beh, QEXPECTED);
ERRORS = ERRORS + 1;

end

if (QBAR_gate !== QBAREXPECTED) begin

$display ("***ERROR: QBAR_gate = %b, QBAR_expected = %b", QBAR_gate, QBAREXPECTED);
ERRORS = ERRORS + 1;

end

if (QBAR_data !== QBAREXPECTED) begin

$display ("***ERROR: QBAR_dataflow = %b, QBAR_expected = %b", QBAR_data, QBAREXPECTED);
ERRORS = ERRORS + 1;

end

if ( {S,R} !== prev_SR ) begin

$display ("***ERROR: Racing Condition Occur");
ERRORS = ERRORS + 1;

end
end

end
endtask



//DRIVE

//0 initialize

initial begin

initialize;
@(posedge TICK);
force_release;

end


//2 scan file on negedge TICK

always @ (negedge TICK) begin


#1.2;

if (!eof) begin



scan_file;

end
end



//3 check file on posedge TICK

always  @ (posedge TICK) begin

coverage_update;
prev_SR = ({S,R});

#0.1;

QEXP;
display_file;
errors_warnings_check;
vectorcount;

#0.02;
prev_Qgate = Q_gate;
prev_Qbargate = QBAR_gate;
prev_Qdata = Q_data;
prev_Qbardata = QBAR_data;
prev_Qgate = Q_gate;
prev_Qbarbeh = QBAR_beh;
prev_QEx = QEXPECTED;
prev_QExbar = QBAREXPECTED;


end



// eof

initial begin

wait (eof);

$display ();
$display("%13s ***time = %0d,eof ***","",$time);
$display ();

for (i = 0; i < 50; i++) begin


if (S == 1 && R == 2)
begin

vectorcount;
close;

end

else begin


random_in;



end

end

close;

end


endmodule

verilog_project/sr_flip_flop/tb_sr_flip_flop.vcd
$date
	Wed Jan 14 01:45:46 2026
$end
$version
	Icarus Verilog
$end
$timescale
	10ps
$end
$scope module tb_sr_flip_flop $end
$var wire 1 ! Q_gate $end
$var wire 1 " Q_data $end
$var wire 1 # Q_beh $end
$var wire 1 $ QBAR_gate $end
$var wire 1 % QBAR_data $end
$var wire 1 & QBAR_beh $end
$var parameter 32 ' TICKPERIOD $end
$var reg 72 ( COMMENT [71:0] $end
$var reg 72 ) COMMENT1 [71:0] $end
$var reg 72 * COMMENT2 [71:0] $end
$var reg 32 + ERRORS [31:0] $end
$var reg 1 , QBAREXPECTED $end
$var reg 1 - QEXPECTED $end
$var reg 1 . R $end
$var reg 1 / S $end
$var reg 1 0 TICK $end
$var reg 32 1 VECTORCOUNT [31:0] $end
$var reg 1 2 eof $end
$var reg 1 3 prev_QEx $end
$var reg 1 4 prev_QExbar $end
$var reg 1 5 prev_Qbarbeh $end
$var reg 1 6 prev_Qbardata $end
$var reg 1 7 prev_Qbargate $end
$var reg 1 8 prev_Qbeh $end
$var reg 1 9 prev_Qdata $end
$var reg 1 : prev_Qgate $end
$var reg 2 ; prev_SR [1:0] $end
$var integer 32 < COUNT [31:0] $end
$var integer 32 = FD [31:0] $end
$var integer 32 > i [31:0] $end
$scope module dut_flip_flop_behavioral $end
$var wire 1 0 clk $end
$var wire 1 & qbar $end
$var wire 1 . r $end
$var wire 1 / s $end
$var reg 1 # q $end
$upscope $end
$scope module dut_flip_flop_dataflow $end
$var wire 1 0 clk $end
$var wire 1 " q $end
$var wire 1 ? q1 $end
$var wire 1 % qbar $end
$var wire 1 @ qbar1 $end
$var wire 1 . r $end
$var wire 1 A r1 $end
$var wire 1 / s $end
$var wire 1 B s1 $end
$var reg 1 C prev_q $end
$var reg 1 D prev_qbar $end
$upscope $end
$scope module dut_flip_flop_gate $end
$var wire 1 0 clk $end
$var wire 1 ! q $end
$var wire 1 E q1 $end
$var wire 1 $ qbar $end
$var wire 1 F qbar1 $end
$var wire 1 . r $end
$var wire 1 G r1 $end
$var wire 1 / s $end
$var wire 1 H s1 $end
$var reg 1 I prev_q $end
$var reg 1 J prev_qbar $end
$upscope $end
$scope task QEXP $end
$upscope $end
$scope task close $end
$upscope $end
$scope task coverage_update $end
$upscope $end
$scope task display_file $end
$upscope $end
$scope task errors_warnings_check $end
$upscope $end
$scope task force_release $end
$upscope $end
$scope task initialize $end
$upscope $end
$scope task random_in $end
$upscope $end
$scope task scan_file $end
$upscope $end
$scope task vectorcount $end
$upscope $end
$upscope $end
$enddefinitions $end
$comment Show the parameter values. $end
$dumpall
b10100 '
$end
#0
$dumpvars
xJ
xI
1H
1G
xF
xE
xD
xC
1B
1A
x@
x?
b10000 >
b10000000000000000000000000000011 =
b101 <
bx ;
x:
x9
x8
x7
x6
x5
x4
x3
02
b0 1
00
0/
0.
x-
x,
b0 +
b1011000 *
b1011000 )
b1001001010011100100100101010100 (
x&
x%
x$
x#
x"
x!
$end
#1000
b0 ;
10
#1010
b1 1
#1011
1&
0#
1%
0"
1$
0!
#1012
1%
0"
1$
0!
0?
1@
0E
1F
15
16
09
17
0:
1J
0I
1D
0C
#2000
00
#2011
x&
x#
1%
0"
1$
0!
#2120
0,
1-
1/
b10100110100010101010100 (
#3000
0&
1#
0%
1?
1"
0$
0B
1E
1!
b10 ;
0H
10
#3010
b10 1
#3012
0@
0F
04
13
05
06
19
07
1:
0D
1C
0J
1I
#4000
1B
1H
00
#4120
0/
b1001000010011110100110001000100 (
#5000
b0 ;
10
#5010
b11 1
#6000
00
#6120
1,
0-
1.
b101001001000101010100110100010101010100 (
#7000
1&
0#
0"
1@
1%
0!
0A
1F
1$
b1 ;
0G
10
#7010
b100 1
#7012
0?
0E
14
03
15
16
09
17
0:
1D
0C
1J
0I
#8000
1A
1G
00
#8120
0.
b1001000010011110100110001000100 (
#9000
b0 ;
10
#9010
b101 1
#10000
00
#10120
0,
1-
1/
b10100110100010101010100 (
#11000
0&
1#
0%
1?
1"
0$
0B
1E
1!
b10 ;
0H
10
#11010
b110 1
#11012
0@
0F
04
13
05
06
19
07
1:
0D
1C
0J
1I
#12000
1B
1H
00
#12120
0/
b1001000010011110100110001000100 (
#13000
b0 ;
10
#13010
b111 1
#14000
00
#14120
x,
x-
1.
1/
b1001001010011000100110001000101010001110100000101001100 (
#15000
x&
x#
1@
1%
0B
0A
1F
1$
b11 ;
0H
0G
10
#15010
b1000 1
#15012
x4
x3
x5
16
17
1D
1J
#16000
0?
1"
0@
1%
1B
1A
0E
0F
1$
1H
1G
00
#16120
1,
0-
0/
b101001001000101010100110100010101010100 (
#17000
1&
0#
0"
1@
0!
0A
1F
b1 ;
0G
10
#17010
b1001 1
#17012
14
03
15
09
0:
0I
0C
#18000
1A
1G
00
#18120
0.
b1001000010011110100110001000100 (
#19000
b0 ;
10
#19010
b1010 1
#20000
00
#20120
1.
b101001001000101010100110100010101010100 (
#21000
0A
b1 ;
0G
10
#21010
b1011 1
#22000
1A
1G
00
#23000
0A
0G
10
#23010
b1100 1
#24000
1A
1G
00
#25000
0A
0G
10
#25010
b1101 1
#26000
1A
1G
00
#26120
0,
1-
0.
1/
b10100110100010101010100 (
#27000
0&
1#
0%
1?
1"
0$
0B
1E
1!
b10 ;
0H
10
#27010
b1110 1
#27012
0@
0F
04
13
05
06
19
07
1:
0D
1C
0J
1I
#28000
1B
1H
00
#28120
1,
0-
1.
0/
b101001001000101010100110100010101010100 (
#29000
1&
0#
0"
1@
1%
0!
0A
1F
1$
b1 ;
0G
10
#29010
b1111 1
#29012
0?
0E
14
03
15
16
09
17
0:
1J
0I
1D
0C
#30000
1A
1G
00
#30120
x,
x-
1/
b1001001010011000100110001000101010001110100000101001100 (
#31000
x&
x#
1?
1"
0B
0A
1E
1!
b11 ;
0H
0G
10
#31010
b10000 1
#31012
x4
x3
x5
19
1:
1C
1I
#32000
0?
1"
0@
1%
1B
1A
0E
0F
1$
1H
1G
00
#32120
0,
1-
0.
b10100110100010101010100 (
#33000
0&
1#
0%
1?
0$
0B
1E
b10 ;
0H
10
#33010
b10001 1
#33012
04
13
05
06
07
0J
0D
#34000
1B
1H
00
#34120
0/
b1001000010011110100110001000100 (
#35000
b0 ;
10
#35010
b10010 1
#36000
00
#36120
1/
b10100110100010101010100 (
#37000
0B
b10 ;
0H
10
#37010
b10011 1
#38000
1B
1H
00
#38120
1,
0-
1.
0/
b101001001000101010100110100010101010100 (
#39000
1&
0#
0"
1@
1%
0!
0A
1F
1$
b1 ;
0G
10
#39010
b10100 1
#39012
0?
0E
14
03
15
16
09
17
0:
1D
0C
1J
0I
#40000
1A
1G
00
#40120
0,
1-
0.
1/
b10100110100010101010100 (
#41000
0&
1#
0%
1?
1"
0$
0B
1E
1!
b10 ;
0H
10
#41010
b10101 1
#41012
0@
0F
04
13
05
06
19
07
1:
0J
1I
0D
1C
#42000
1B
1H
00
#43000
0B
0H
10
#43010
b10110 1
#44000
1B
1H
00
#45000
0B
0H
10
#45010
b10111 1
#46000
1B
1H
00
#46120
x,
x-
1.
b1001001010011000100110001000101010001110100000101001100 (
#47000
x&
x#
1@
1%
0B
0A
1F
1$
b11 ;
0H
0G
10
#47010
b11000 1
#47012
x4
x3
x5
16
17
1D
1J
#48000
0?
1"
0@
1%
1B
1A
0E
0F
1$
1H
1G
00
#49000
1?
1@
0B
0A
1E
1F
0H
0G
10
#49010
b11001 1
#50000
0?
1"
0@
1%
1B
1A
0E
0F
1$
1H
1G
00
#50120
0.
0/
#51000
b0 ;
10
#51010
b11010 1
#52000
00
#52120
1.
1/
#53000
1?
1@
0B
0A
1E
1F
b11 ;
0H
0G
10
#53010
b11011 1
#54000
0?
1"
0@
1%
1B
1A
0E
0F
1$
1H
1G
00
#54120
1,
0-
0/
b101001001000101010100110100010101010100 (
#55000
1&
0#
0"
1@
0!
0A
1F
b1 ;
0G
10
#55010
b11100 1
#55012
14
03
15
09
0:
0C
0I
#56000
1A
1G
00
#56120
x,
x-
1/
b1001001010011000100110001000101010001110100000101001100 (
#57000
x&
x#
1?
1"
0B
0A
1E
1!
b11 ;
0H
0G
10
#57010
b11101 1
#57012
x4
x3
x5
19
1:
1I
1C
#58000
0?
1"
0@
1%
1B
1A
0E
0F
1$
1H
1G
00
#58120
0,
1-
0.
b10100110100010101010100 (
#59000
0&
1#
0%
1?
0$
0B
1E
b10 ;
0H
10
#59010
b11110 1
#59012
04
13
05
06
07
0D
0J
#60000
1B
1H
00
#60120
x,
x-
1.
b1001001010011000100110001000101010001110100000101001100 (
#61000
x&
x#
1@
1%
0B
0A
1F
1$
b11 ;
0H
0G
10
#61010
b11111 1
#61012
x4
x3
x5
16
17
1J
1D
#62000
0?
1"
0@
1%
1B
1A
0E
0F
1$
1H
1G
00
#63000
1?
1@
0B
0A
1E
1F
0H
0G
10
#63010
b100000 1
#64000
0?
1"
0@
1%
1B
1A
0E
0F
1$
1H
1G
00
#64120
b0 <
#65000
1?
1@
0B
0A
1E
1F
0H
0G
10
#65010
b100001 1
#66000
0?
1"
0@
1%
1B
1A
0E
0F
1$
1H
1G
00
#66120
b101001001000101010100110100010101010100 (
0/
b1 >
12
b11111111111111111111111111111111 <
#66920
b1001001010011000100110001000101010001110100000101001100 (
1/
b10 >
#67000
1?
1@
0B
0A
1E
1F
0H
0G
10
#67010
b100010 1
#67420
0@
1%
0?
1"
1A
0F
1B
0E
1!
1G
1H
0.
0/
b11 >
#68000
00
#68020
b100 >
#69000
b0 ;
10
#69010
b100011 1
#69020
1@
1?
0A
1F
0B
1E
0G
0H
1.
1/
b101 >
#69320
0@
0%
1A
0F
0$
1G
b10100110100010101010100 (
0.
b111 >
#69720
1@
1%
0A
1F
1$
0G
b1001001010011000100110001000101010001110100000101001100 (
1.
b1000 >
#70000
0?
1"
0@
1%
1B
1A
0E
0F
1$
1H
1G
00
#70420
b101001001000101010100110100010101010100 (
0/
b1001 >
#70620
b1001001010011000100110001000101010001110100000101001100 (
1/
b1010 >
#70820
b101001001000101010100110100010101010100 (
0/
b1011 >
#71000
1&
0#
0"
1@
0!
0A
1F
b1 ;
0G
10
#71010
b100100 1
1,
0-
#71012
14
03
15
09
0:
0C
0I
#71120
0%
1?
1"
1A
0$
0B
1E
1!
1G
0H
b10100110100010101010100 (
0.
1/
b1101 >
#71520
1%
0?
0"
1$
1B
0E
0!
1H
b0x00x00x0x00xx000x00xx000100xx0x0100x1110100xx0x0100x100 (
0/
b1110 >
#72000
00
#72120
b1001001010011000100110001000101010001110100000101001100 (
1.
1/
b1111 >
#72620
b0x00x00x0x00xx000x00xx000100xx0x0100x1110100xx0x0100x100 (
0.
0/
b10000 >
#73000
b0 ;
10
#73010
b100101 1
#73620
1?
1"
0A
0B
1E
1!
0G
0H
b1001001010011000100110001000101010001110100000101001100 (
1.
1/
b10001 >
#74000
0?
0"
1%
1B
1A
0E
0!
1$
1H
1G
00
#74020
b0x00x00x0x00xx000x00xx000100xx0x0100x1110100xx0x0100x100 (
0.
0/
b10010 >
#75000
10
#75010
b100110 1
#75020
0A
0G
b101001001000101010100110100010101010100 (
1.
b10011 >
#75920
1A
1G
b0x00x00x0x00xx000x00xx000100xx0x0100x1110100xx0x0100x100 (
0.
b10101 >
#76000
00
#76620
b10100110100010101010100 (
1/
b10110 >
#76820
b1001001010011000100110001000101010001110100000101001100 (
1.
b10111 >
#77000
x&
x#
1?
1"
0B
0A
1E
1!
b11 ;
0H
0G
10
#77010
b100111 1
x,
x-
#77012
x4
x3
x5
19
1:
1I
1C
#77820
0?
0"
1B
0E
0!
1H
b101001001000101010100110100010101010100 (
0/
b11000 >
#78000
1"
0@
1!
1A
0F
1G
00
#78620
b1001001010011000100110001000101010001110100000101001100 (
1/
b11001 >
#78920
b10100110100010101010100 (
0.
b11010 >
#79000
0&
1#
0%
1?
0$
0B
1E
b10 ;
0H
10
#79010
b101000 1
0,
1-
#79012
04
13
05
06
07
0D
0J
#79020
b11011 >
#79420
0"
1@
1%
0!
0A
1F
1$
1B
0G
1H
b101001001000101010100110100010101010100 (
1.
0/
b11100 >
#80000
1"
0@
0%
1!
1A
0F
0$
1G
00
#80220
b10100110100010101010100 (
0.
1/
b11101 >
#81000
0B
0H
10
#81010
b101001 1
#81120
1B
1H
b0x00x00x0x00xx000x00xx000100xx0x0100x1110100xx0x0100x100 (
0/
b11110 >
#81620
1@
1%
0A
1F
1$
0B
0G
0H
b1001001010011000100110001000101010001110100000101001100 (
1.
1/
b11111 >
#82000
1"
0@
0%
1B
1A
0F
0$
1H
1G
00
#82220
b0x00x00x0x00xx000x00xx000100xx0x0100x1110100xx0x0100x100 (
0.
0/
b100000 >
#83000
b0 ;
10
#83010
b101010 1
#83020
0B
0H
b10100110100010101010100 (
1/
b100001 >
#83720
0"
1@
1%
0!
0A
1F
1$
1B
0G
1H
b101001001000101010100110100010101010100 (
1.
0/
b100010 >
#84000
1"
0@
0%
1!
1A
0F
0$
1G
00
#84420
b1001001010011000100110001000101010001110100000101001100 (
1/
b100011 >
#84720
b10100110100010101010100 (
0.
b100100 >
#85000
0B
b10 ;
0H
10
#85010
b101011 1
#85420
1@
1%
0A
1F
1$
0G
b1001001010011000100110001000101010001110100000101001100 (
1.
b100101 >
#85720
0@
0%
1A
0F
0$
1G
b10100110100010101010100 (
0.
b100110 >
#86000
1B
1H
00
#86720
b101001001000101010100110100010101010100 (
1.
0/
b100111 >
#87000
1&
0#
0"
1@
1%
0!
0A
1F
1$
b1 ;
0G
10
#87010
b101100 1
1,
0-
#87012
0?
0E
14
03
15
16
09
17
0:
1D
0C
1J
0I
#87420
0%
1?
1"
1A
0$
0B
1E
1!
1G
0H
b10100110100010101010100 (
0.
1/
b101000 >
#87820
1%
0?
0"
1$
1B
0E
0!
1H
b0x00x00x0x00xx000x00xx000100xx0x0100x1110100xx0x0100x100 (
0/
b101001 >
#88000
00
#88220
b101010 >
#88620
b10100110100010101010100 (
1/
b101011 >
#89000
0&
1#
0%
1?
1"
0$
0B
1E
1!
b10 ;
0H
10
#89010
b101101 1
0,
1-
#89012
0@
0F
04
13
05
06
19
07
1:
0J
1I
0D
1C
#89120
1B
1H
b0x00x00x0x00xx000x00xx000100xx0x0100x1110100xx0x0100x100 (
0/
b101100 >
#89620
1@
1%
0A
1F
1$
0B
0G
0H
b1001001010011000100110001000101010001110100000101001100 (
1.
1/
b101101 >
#90000
1"
0@
0%
1B
1A
0F
0$
1H
1G
00
#90320
b10100110100010101010100 (
0.
b101110 >
#91000
0B
0H
10
#91010
b101110 1
#91220
1B
1H
b0x00x00x0x00xx000x00xx000100xx0x0100x1110100xx0x0100x100 (
0/
b101111 >
#91520
0B
0H
1/
1"
1@
1%
1!
0A
1F
1$
0G
b1001001010011000100110001000101010001110100000101001100 (
1.
b110001 >
#91620
b110010 >
#92000
1"
0@
0%
1B
1A
0F
0$
1H
1G
00
#92620
b10000 >
