verilog_project/dff_pulse_triggered/dff_pulse_triggered.v
// A d (delay) flip-flop which is pulse-triggered can be set and reset.

module dff_pulse_triggered_gate (
    input       clk,        // Clock
    input       clk2,
    input       d,          
    output      q,          
    output      qbar
);



    // INTERNAL WIRES
    wire q2,qbar2, q3, qbar3, s, r, s1, r1, s2, r2;

    reg  prev_q, prev_qbar, prev_q2, prev_qbar2;


    always@(posedge clk)begin
    #0.12;

    prev_q = q;
    prev_qbar = qbar;
    prev_q2 = q2;
    prev_qbar2 = qbar2;

    end

    assign s = d;
    assign r = ~d;


    // NAND3
    nand (s1, s, clk);

    // NAND4
    nand (r1, r, clk);

    // SR- LATCH -------------------------------------

    nand (q1, s1, prev_qbar2);
    nand (qbar1, r1, prev_q2);
  
    nand (q2, s1, qbar1);
    nand (qbar2, r1, q1);

//SRFF

    nand (s2, q2, clk2);
    nand (r2, qbar2, clk2);

    // SR- LATCH -------------------------------------


    nand (q3, s2, prev_qbar);
    nand (qbar3, r2, prev_q);

    nand (q, s2, qbar3);
    nand (qbar, r2, q3);
   

endmodule



module dff_pulse_triggered_dataflow(
    input       clk,        // Clock
    input       clk2,
    input       d,          
    output      q,          
    output      qbar);      




    // INTERNAL WIRES
    wire q2,qbar2, q3, qbar3, s, r, s1, r1, s2, r2;
    reg  prev_q, prev_qbar, prev_q2, prev_qbar2;


    always@(posedge clk)begin
    #0.12;

    prev_q = q;
    prev_qbar = qbar;
    prev_q2 = q2;
    prev_qbar2 = qbar2;

    end

    assign s = d;
    assign r = ~d;


    // NAND3
    assign s1 = ~(s & clk);

    // NAND4
    assign r1 = ~(r & clk);

    // SR- LATCH -------------------------------------

    assign q1 = ~(s1 & prev_qbar2);
    assign qbar1 = ~(r1 & prev_q2);

    assign q2 = ~(s1 & qbar1);
    assign qbar2 = ~(r1 & q1);


//SRFF

    assign s2 = ~(q2 & clk2);
    assign r2 = ~(qbar2 & clk2);

    // SR- LATCH -------------------------------------


    assign q3 = ~(s2 & prev_qbar);
    assign qbar3 = ~(r2 & prev_q);

    assign q = ~(s2 & qbar3);
    assign qbar = ~(r2 & q3);



endmodule



module dff_pulse_triggered_behavioral (
    input        clk,        // Clock
    input        clk2,
    input        d,          //
    output reg   q,          // Output
    output wire  qbar
);

assign qbar = ~q;

always @ ( posedge clk ) begin

    if (clk2) begin

    q <= d;

    end else begin
    
    q <= q;

    end

end




endmodule

verilog_project/verilog_project/dff_pulse_triggered/tb_dff_pulse_triggered.v
`timescale 1ns/10ps

module tb_dff_pulse_triggered;

//VECTORS FOR DUT
reg  D;
     
         
wire Q_gate, Q_data, Q_beh, QBAR_gate, QBAR_data, QBAR_beh; 
     


//VECTORS FOR TESTING

reg TICK;
reg TICK2;
integer FD, COUNT;
reg [8*9-1:0] COMMENT;
reg [8*9-1:0] COMMENT1;
reg [8*9-1:0] COMMENT2;
reg QEXPECTED, QBAREXPECTED;
reg [31:0] VECTORCOUNT, ERRORS;
int i;
reg [31:0] input_coverage [0:3];
reg eof;
reg prev_D;
reg prev_Qgate;
reg prev_Qbargate;
reg prev_Qdata;
reg prev_Qbardata;
reg prev_Qbeh;
reg prev_Qbarbeh;
reg prev_QEx;
reg prev_QExbar;


//DUT INSTANTIATION

dff_pulse_triggered_gate dut_dff_pulse_triggered_gate (.d(D), .q(Q_gate), .qbar(QBAR_gate), .clk(TICK), .clk2(TICK2));
dff_pulse_triggered_dataflow dut_dff_pulse_triggered_dataflow (.d(D), .q(Q_data), .qbar(QBAR_data), .clk(TICK), .clk2(TICK2));
dff_pulse_triggered_behavioral dut_dff_pulse_triggered_behavioral (.d(D), .q(Q_beh), .qbar(QBAR_beh), .clk(TICK), .clk2(TICK2));



//DUMP EVERYTHING INTO DUMPFILE

initial begin

$dumpfile ("tb_dff_pulse_triggered.vcd");
$dumpvars (0, tb_dff_pulse_triggered);

end

//TICKPERIOD

localparam TICKPERIOD = 20;

always begin

#(TICKPERIOD/2) TICK = ~TICK;

end

//TICK2


always begin

#(TICKPERIOD) TICK2 = ~TICK2;

end



//TASKS

//task 1 initialize

task initialize; begin

FD = $fopen ("tb_dff_pulse_triggered.tv" , "r");
COUNT = $fscanf (FD, "%s", COMMENT);

COUNT = $fscanf (FD, "%s %b %s %s", COMMENT, D, COMMENT1, COMMENT2);
TICK = 0;
TICK2 = 0;
VECTORCOUNT = 0;
ERRORS = 0;

for ( i = 0 ; i < 4 ; i++ ) begin
input_coverage[i] = 0;
end

eof = 0;

$display ();
$display ("TEST_START------------------------------------------------------------------------------------------------------------------------");
$display ();
$display ("                     | TIME | D |  Q_gate  |  Q_data  |  Q_beh  | QBAR_gate | QBAR_data | QEXPECTED | QBAREXPECTED | TICK2 |");
$display ("----------------------------------------------------------------------------------------------------------------------------------");



end
endtask


//task 3 scan_file

task scan_file; begin


COUNT = $fscanf (FD,"%s %b %b %b", COMMENT, D, QEXPECTED, QBAREXPECTED);
eof = (COUNT == -1);

end
endtask

//task 4 random_in

task random_in; begin

D =  $urandom %5 ;

case (D)
1'b0: COMMENT = "RESET";
1'b1: COMMENT = "SET";

endcase

#($urandom_range (0.1,10));

end
endtask

//task 5 QEXP

task QEXP; begin


case ( {D,TICK2} )
  2'b01: begin
QEXPECTED = 1'b0;
QBAREXPECTED = 1'b1;
end
  2'b11: begin
QEXPECTED = 1'b1;
QBAREXPECTED = 1'b0;
end

default: begin
QEXPECTED = prev_QEx;
QBAREXPECTED = prev_QExbar;
end

endcase



end
endtask



//task 6 close

task close; begin

#10;
$fclose (FD);

$display ();
$display ("COVERAGE_REPORT");

for ( i = 0; i < 4; i++ ) begin

if(input_coverage[i] == 0) begin

$display ("input %b to input %b has occured %d times (***ERROR***)",i[1], i[0], input_coverage[i]);
ERRORS = ERRORS +1;

end

else begin

$display ("input %b to input %b has occured %d times",i[1], i[0], input_coverage[i]);

end

end

$display ();
$display ("VECTORCOUNT = %d", VECTORCOUNT);
$display ("ERRORS = %15d", ERRORS);
$display ();
$display ("TEST_END--------------------------------------------------------------------------------------------------------------------------");
$display ();

$finish;

end
endtask

//task 7 vectorcount

task vectorcount; begin

VECTORCOUNT = VECTORCOUNT + 1;

end
endtask

//task 8 display_file

task display_file; begin

$display ("%10d %9s | %4d | %1d | %4d     | %4d     | %4d    | %5d     | %5d     | %5d     | %6d       | %3d   | ", VECTORCOUNT, COMMENT, $time, D, Q_gate, Q_data, Q_beh, QBAR_gate, QBAR_data, QEXPECTED, QBAREXPECTED, TICK2);

end
endtask

//task 9 coverage_update

task coverage_update; begin

input_coverage[{prev_D, D}]++;

end
endtask

//task 10 errors_check

task errors_check; begin



if (Q_gate !== QEXPECTED) begin

$display ("***ERROR: Q_gate = %b, Q_expected = %b", Q_gate, QEXPECTED);
ERRORS = ERRORS + 1;

end

if (Q_data !== QEXPECTED) begin

$display ("***ERROR: Q_dataflow = %b, Q_expected = %b", Q_data, QEXPECTED);
ERRORS = ERRORS + 1;

end

if (Q_beh !== QEXPECTED) begin

$display ("***ERROR: Q_behavioral = %b, Q_expected = %b", Q_beh, QEXPECTED);
ERRORS = ERRORS + 1;

end

if (QBAR_gate !== QBAREXPECTED) begin

$display ("***ERROR: QBAR_gate = %b, QBAR_expected = %b", QBAR_gate, QBAREXPECTED);
ERRORS = ERRORS + 1;

end

if (QBAR_data !== QBAREXPECTED) begin

$display ("***ERROR: QBAR_dataflow = %b, QBAR_expected = %b", QBAR_data, QBAREXPECTED);
ERRORS = ERRORS + 1;

end

if ( D !== prev_D ) begin

$display ("***ERROR: Racing Condition Occur");
ERRORS = ERRORS + 1;

end


end
endtask



//DRIVE

//0 initialize

initial begin

initialize;


end


//2 scan file on negedge TICK

always @ (negedge TICK) begin


#1.2;

if (!eof) begin



scan_file;

end
end



//3 check file on posedge TICK

always  @ (posedge TICK) begin

coverage_update;
prev_D = D;

#0.1;

QEXP;
display_file;
errors_check;
vectorcount;

#0.02;

prev_Qgate = Q_gate;
prev_Qbargate = QBAR_gate;
prev_Qdata = Q_data;
prev_Qbardata = QBAR_data;
prev_Qgate = Q_gate;
prev_Qbarbeh = QBAR_beh;
prev_QEx = QEXPECTED;
prev_QExbar = QBAREXPECTED;



end



// eof

initial begin

wait (eof);

$display ();
$display("%13s ***time = %0d,eof ***","",$time);
$display ();

for (i = 0; i < 50; i++) begin


if ( D == 2)
begin

vectorcount;
close;

end

else begin

random_in;

end
end


close;

end


endmodule

verilog_project/verilog_project/dff_pulse_triggered/tb_dff_pulse_triggered.vcd
$date
	Wed Jan 14 01:11:25 2026
$end
$version
	Icarus Verilog
$end
$timescale
	10ps
$end
$scope module tb_dff_pulse_triggered $end
$var wire 1 ! Q_gate $end
$var wire 1 " Q_data $end
$var wire 1 # Q_beh $end
$var wire 1 $ QBAR_gate $end
$var wire 1 % QBAR_data $end
$var wire 1 & QBAR_beh $end
$var parameter 32 ' TICKPERIOD $end
$var reg 72 ( COMMENT [71:0] $end
$var reg 72 ) COMMENT1 [71:0] $end
$var reg 72 * COMMENT2 [71:0] $end
$var reg 1 + D $end
$var reg 32 , ERRORS [31:0] $end
$var reg 1 - QBAREXPECTED $end
$var reg 1 . QEXPECTED $end
$var reg 1 / TICK $end
$var reg 1 0 TICK2 $end
$var reg 32 1 VECTORCOUNT [31:0] $end
$var reg 1 2 eof $end
$var reg 1 3 prev_D $end
$var reg 1 4 prev_QEx $end
$var reg 1 5 prev_QExbar $end
$var reg 1 6 prev_Qbarbeh $end
$var reg 1 7 prev_Qbardata $end
$var reg 1 8 prev_Qbargate $end
$var reg 1 9 prev_Qdata $end
$var reg 1 : prev_Qgate $end
$var integer 32 ; COUNT [31:0] $end
$var integer 32 < FD [31:0] $end
$var integer 32 = i [31:0] $end
$scope module dut_dff_pulse_triggered_behavioral $end
$var wire 1 / clk $end
$var wire 1 0 clk2 $end
$var wire 1 + d $end
$var wire 1 & qbar $end
$var reg 1 # q $end
$upscope $end
$scope module dut_dff_pulse_triggered_dataflow $end
$var wire 1 / clk $end
$var wire 1 0 clk2 $end
$var wire 1 + d $end
$var wire 1 " q $end
$var wire 1 > q1 $end
$var wire 1 ? q2 $end
$var wire 1 @ q3 $end
$var wire 1 % qbar $end
$var wire 1 A qbar1 $end
$var wire 1 B qbar2 $end
$var wire 1 C qbar3 $end
$var wire 1 D r $end
$var wire 1 E r1 $end
$var wire 1 F r2 $end
$var wire 1 G s $end
$var wire 1 H s1 $end
$var wire 1 I s2 $end
$var reg 1 J prev_q $end
$var reg 1 K prev_q2 $end
$var reg 1 L prev_qbar $end
$var reg 1 M prev_qbar2 $end
$upscope $end
$scope module dut_dff_pulse_triggered_gate $end
$var wire 1 / clk $end
$var wire 1 0 clk2 $end
$var wire 1 + d $end
$var wire 1 ! q $end
$var wire 1 N q1 $end
$var wire 1 O q2 $end
$var wire 1 P q3 $end
$var wire 1 $ qbar $end
$var wire 1 Q qbar1 $end
$var wire 1 R qbar2 $end
$var wire 1 S qbar3 $end
$var wire 1 T r $end
$var wire 1 U r1 $end
$var wire 1 V r2 $end
$var wire 1 W s $end
$var wire 1 X s1 $end
$var wire 1 Y s2 $end
$var reg 1 Z prev_q $end
$var reg 1 [ prev_q2 $end
$var reg 1 \ prev_qbar $end
$var reg 1 ] prev_qbar2 $end
$upscope $end
$scope task QEXP $end
$upscope $end
$scope task close $end
$upscope $end
$scope task coverage_update $end
$upscope $end
$scope task display_file $end
$upscope $end
$scope task errors_check $end
$upscope $end
$scope task initialize $end
$upscope $end
$scope task random_in $end
$upscope $end
$scope task scan_file $end
$upscope $end
$scope task vectorcount $end
$upscope $end
$upscope $end
$enddefinitions $end
$comment Show the parameter values. $end
$dumpall
b10100 '
$end
#0
$dumpvars
x]
x\
x[
xZ
1Y
1X
0W
1V
1U
1T
xS
xR
xQ
xP
xO
xN
xM
xL
xK
xJ
1I
1H
0G
1F
1E
1D
xC
xB
xA
x@
x?
x>
b100 =
b10000000000000000000000000000011 <
b100 ;
x:
x9
x8
x7
x6
x5
x4
x3
02
b0 1
00
0/
x.
x-
b0 ,
0+
b1011000 *
b1011000 )
b1001001010011100100100101010100 (
x&
x%
x$
x#
x"
x!
$end
#1000
0?
1A
1B
0O
0E
1Q
1R
03
0U
1/
#1010
b1 1
#1012
0>
0N
1]
0[
1M
0K
#2000
0"
1C
1%
0!
1E
0F
1S
1$
1U
0V
0/
10
#2120
1-
0.
b101001001000101010100110100010101010100 (
#3000
1&
0#
0E
0U
1/
#3010
b10 1
#3012
0@
0P
15
04
16
17
09
18
0:
1L
0J
1\
0Z
#4000
1E
1F
1U
1V
0/
00
#5000
0E
0U
1/
#5010
b11 1
#6000
1E
0F
1U
0V
0/
10
#6120
0D
0T
0-
1.
1G
1W
1+
b10100110100010101010100 (
#7000
0&
1#
0%
1F
1@
1"
0B
0I
0$
1>
1?
1V
1P
1!
0R
0Y
0H
1N
1O
13
0X
1/
#7010
b100 1
#7012
0A
0C
0Q
0S
05
14
06
07
19
08
1:
0M
1K
0L
1J
0]
1[
0\
1Z
#8000
1H
1I
1X
1Y
0/
00
#9000
0H
0X
1/
#9010
b101 1
#10000
1H
0I
1X
0Y
0/
10
#10120
1D
1T
1-
0.
0G
0W
0+
b101001001000101010100110100010101010100 (
#11000
1&
0#
0"
1I
1C
1%
0?
0F
0!
1A
1B
1Y
1S
1$
0O
0V
0E
1Q
1R
03
0U
1/
#11010
b110 1
#11012
0>
0@
0N
0P
15
04
16
17
09
18
0:
1M
0K
1L
0J
1]
0[
1\
0Z
#12000
1E
1F
1U
1V
0/
00
#12120
0D
0T
0-
1.
1G
1W
1+
b10100110100010101010100 (
#13000
0B
1>
1?
0R
0H
1N
1O
13
0X
1/
#13010
b111 1
1-
0.
#13012
0A
0Q
0]
1[
0M
1K
#14000
0%
1@
1"
0$
1H
0I
1P
1!
1X
0Y
0/
10
#14120
0-
1.
#15000
0&
1#
0H
0X
1/
#15010
b1000 1
#15012
0C
0S
05
14
06
07
19
08
1:
0L
1J
0\
1Z
#16000
1H
1I
1X
1Y
0/
00
#16120
b0 ;
#17000
0H
0X
1/
#17010
b1001 1
#18000
1H
0I
1X
0Y
0/
10
#18120
b0 =
12
b11111111111111111111111111111111 ;
#18320
1D
1T
b101001001000101010100110100010101010100 (
0G
0W
0+
b1 =
#18520
b10 =
#19000
1&
0#
0"
1I
1C
1%
0?
0F
0!
1A
1B
1Y
1S
1$
0O
0V
0E
1Q
1R
03
0U
1/
#19010
b1010 1
1-
0.
#19012
0>
0@
0N
0P
15
04
16
17
09
18
0:
1M
0K
1L
0J
1]
0[
1\
0Z
#19320
b100 =
#19820
0%
1F
1@
1"
0B
0I
0$
1>
1?
1P
1!
1V
1E
0Y
0R
0H
1N
1O
1U
0D
0X
0T
b10100110100010101010100 (
1G
1W
1+
b101 =
#20000
1B
1%
0>
0?
0@
0"
1R
1$
1H
0N
0O
1I
0P
0!
1X
1Y
0/
00
#20420
1D
1T
b101001001000101010100110100010101010100 (
0G
0W
0+
b110 =
#21000
0E
0U
1/
#21010
b1011 1
#21220
b111 =
#21620
b1000 =
#21920
0B
1>
1?
1E
0R
0H
1N
1O
1U
0D
0X
0T
b10100110100010101010100 (
1G
1W
1+
b1001 =
#22000
0F
1B
1%
0>
0?
0V
0@
0"
1R
1$
1H
0N
0O
1I
0P
0!
1X
1Y
0/
10
#22120
b1010 =
#22920
1D
1T
b101001001000101010100110100010101010100 (
0G
0W
0+
b1011 =
#23000
0E
0U
1/
#23010
b1100 1
#23320
b1100 =
#23720
b1101 =
#24000
1E
1F
1U
1V
0/
00
#24120
0D
0T
b10100110100010101010100 (
1G
1W
1+
b1110 =
#24320
1D
1T
b101001001000101010100110100010101010100 (
0G
0W
0+
b1111 =
#24820
b10000 =
#25000
0E
0U
1/
#25010
b1101 1
#25420
b10001 =
#25720
0B
1>
1?
1E
0R
0H
1N
1O
1U
0D
0X
0T
b10100110100010101010100 (
1G
1W
1+
b10011 =
#25820
b10100 =
#26000
0F
1B
1%
0>
0?
0V
0@
0"
1R
1$
1H
0N
0O
1I
0P
0!
1X
1Y
0/
10
#26220
1D
1T
b101001001000101010100110100010101010100 (
0G
0W
0+
b10101 =
#26520
b10110 =
#26920
b10111 =
#27000
0E
0U
1/
#27010
b1110 1
#27420
0%
1F
1@
1"
0B
0I
0$
1>
1?
1P
1!
1V
1E
0Y
0R
0H
1N
1O
1U
0D
0X
0T
b10100110100010101010100 (
1G
1W
1+
b11000 =
#27520
1%
0@
0"
0F
1I
1B
1$
0>
0?
0P
0!
0V
0E
1Y
1R
1H
0N
0O
0U
1D
1X
1T
b101001001000101010100110100010101010100 (
0G
0W
0+
b11001 =
#28000
1E
1F
1U
1V
0/
00
#28320
b11010 =
#28720
0D
0T
b10100110100010101010100 (
1G
1W
1+
b11011 =
#28920
1D
1T
b101001001000101010100110100010101010100 (
0G
0W
0+
b11100 =
#29000
0E
0U
1/
#29010
b1111 1
#29820
b11101 =
#30000
1E
0F
1U
0V
0/
10
#30720
0D
0T
b10100110100010101010100 (
1G
1W
1+
b11110 =
#31000
0&
1#
0%
1F
1@
1"
0B
0I
0$
1>
1?
1V
1P
1!
0R
0Y
0H
1N
1O
13
0X
1/
#31010
b10000 1
0-
1.
#31012
0A
0C
0Q
0S
05
14
06
07
19
08
1:
0M
1K
0L
1J
0]
1[
0\
1Z
#31320
0"
1I
1C
1%
0?
0F
0!
1A
1B
1Y
1S
1$
0O
0V
0E
1Q
1R
1H
0U
1D
1X
1T
b101001001000101010100110100010101010100 (
0G
0W
0+
b11111 =
#31520
b100000 =
#32000
1?
1"
0A
0B
0C
0%
1O
1!
1E
0Q
0R
1F
0S
0$
1U
1V
0/
00
#32220
0D
0T
b10100110100010101010100 (
1G
1W
1+
b100001 =
#32820
1D
1T
b101001001000101010100110100010101010100 (
0G
0W
0+
b100010 =
#33000
0?
1A
1B
0O
0E
1Q
1R
03
0U
1/
#33010
b10001 1
#33012
0>
0N
1]
0[
1M
0K
#33320
0B
1>
1?
1E
0R
0H
1N
1O
1U
0D
0X
0T
b10100110100010101010100 (
1G
1W
1+
b100011 =
#34000
0"
1C
1%
0F
1B
0!
1S
1$
0>
0?
0V
1R
1H
0N
0O
1I
1X
1Y
0/
10
#34320
1D
1T
b101001001000101010100110100010101010100 (
0G
0W
0+
b100100 =
#35000
1&
0#
0E
0U
1/
#35010
b10010 1
1-
0.
#35012
0@
0P
15
04
16
17
09
18
0:
1L
0J
1\
0Z
#35020
b100101 =
#35820
0%
1F
1@
1"
0B
0I
0$
1>
1?
1P
1!
1V
1E
0Y
0R
0H
1N
1O
1U
0D
0X
0T
b10100110100010101010100 (
1G
1W
1+
b100110 =
#36000
1B
1%
0>
0?
0@
0"
1R
1$
1H
0N
0O
1I
0P
0!
1X
1Y
0/
00
#36120
1D
1T
b101001001000101010100110100010101010100 (
0G
0W
0+
b100111 =
#36220
0D
0T
b10100110100010101010100 (
1G
1W
1+
b101000 =
#37000
0B
1>
1?
0R
0H
1N
1O
13
0X
1/
#37010
b10011 1
#37012
0A
0Q
0]
1[
0M
1K
#37020
b101001 =
#37420
b101010 =
#37520
b101011 =
#38000
0%
1@
1"
0$
1H
0I
1P
1!
1X
0Y
0/
10
#38020
b101100 =
#38920
b101101 =
#39000
0&
1#
0H
0X
1/
#39010
b10100 1
0-
1.
#39012
0C
0S
05
14
06
07
19
08
1:
0L
1J
0\
1Z
#39520
b101110 =
#39720
0"
1I
1C
1%
0?
0F
0!
1A
1B
1Y
1S
1$
0O
0V
0E
1Q
1R
1H
0U
1D
1X
1T
b101001001000101010100110100010101010100 (
0G
0W
0+
b101111 =
#40000
1?
1"
0A
0B
0C
0%
1O
1!
1E
0Q
0R
1F
0S
0$
1U
1V
0/
00
#40320
b110000 =
#40720
0D
0T
b10100110100010101010100 (
1G
1W
1+
b110001 =
#40920
b110010 =
#41000
0H
0X
1/
#41010
b10101 1
#41920
b100 =
