verilog_project/half_adder/half_adder.v
module half_adder_gate(
input a,b,
output sum,
output cout
);

xor xor1(sum,a,b);
and and1(cout,a,b);

endmodule


module half_adder_dataflow(
input a,b,
output sum,
output cout
);

assign sum = a^b;
assign cout = a&b;


endmodule


module half_adder_behavioral(
input a,b,
output reg sum,
output reg cout
);

always@(a or b)begin

{cout,sum} <= a + b;

end

endmodule

verilog_project/half_adder/tb_half_adder.v
`timescale 1ns/10ps

module tb_half_adder;

//VECTORS FOR DUT
reg A, B;
wire SUM_gate, COUT_gate;
wire SUM_data, COUT_data;
wire SUM_beh, COUT_beh;

//VECTORS FOR TESTING

reg TICK;
integer FD, COUNT;
reg [8*9-1:0] COMMENT;
reg SUM_EXPECTED, COUT_EXPECTED;
reg [31:0] VECTORCOUNT, ERRORS;
int i;
reg [31:0] input_coverage [0:7];
reg eof;



//DUT INSTANTIATION

half_adder_gate dut_half_adder_gate (.a(A), .b(B), .sum(SUM_gate), .cout(COUT_gate));
half_adder_dataflow dut_half_adder_dataflow (.a(A), .b(B), .sum(SUM_data), .cout(COUT_data));
half_adder_behavioral dut_half_adder_behavioral (.a(A), .b(B), .sum(SUM_beh), .cout(COUT_beh));



//DUMP EVERYTHING INTO DUMPFILE

initial begin

$dumpfile ("tb_half_adder.vcd");
$dumpvars (0, tb_half_adder);

end

//TICKPERIOD

localparam TICKPERIOD = 20;

always begin

#(TICKPERIOD/2) TICK = ~TICK;

end



//TASKS

//task 1 initialize

task initialize; begin

FD = $fopen ("tb_half_adder.tv" , "r");
COUNT = $fscanf (FD, "%s", COMMENT);

COUNT = $fscanf (FD, "%s %b %b %b %b", COMMENT, A, B, SUM_EXPECTED, COUT_EXPECTED);
TICK = 0;
VECTORCOUNT = 0;
ERRORS = 0;

for ( i = 0 ; i < 4 ; i++ ) begin
input_coverage[i] = 0;
end

eof = 0;

$display ();
$display ("TEST_START-------------------------------------------------------------------------------------------------------------------------------------");
$display ();
$display ("                     | TIME | A | B | COUT_gate | SUM_gate | COUT_data | SUM_data | COUT_beh | SUM_beh | COUT_EXPECTED | SUM_EXPECTED |");
$display ("-----------------------------------------------------------------------------------------------------------------------------------------------");



end
endtask


//task 3 scan_file

task scan_file; begin

COUNT = $fscanf (FD, "%s %b %b %b %b", COMMENT, A, B, SUM_EXPECTED, COUT_EXPECTED);
eof = (COUNT == -1);

end
endtask

//task 4 random_in

task random_in; begin


A =  $urandom %2 ;
B =  $urandom %2 ;

COMMENT = "-";

#($urandom_range (0.1,10));

end
endtask

//task5 SUM_EXP

task SUM_EXP; begin

SUM_EXPECTED = A ^ B;

end
endtask


//task6 COUT_EXP

task COUT_EXP; begin

COUT_EXPECTED = (A&B);

end
endtask


//task 5 close

task close; begin

#10;
$fclose (FD);

$display ();
$display ("COVERAGE_REPORT");

for ( i = 0; i < 4; i++ ) begin

if(input_coverage[i] == 0) begin

$display ("input A = %b & B = %b has occured %d times (***ERROR***)", i[1], i[0], input_coverage[i]);
ERRORS = ERRORS +1;

end

else begin

$display ("input A = %b & B = %b has occured %d times", i[1], i[0], input_coverage[i]);

end

end

$display ();
$display ("VECTORCOUNT = %d", VECTORCOUNT);
$display ("ERRORS = %15d", ERRORS);
$display ();
$display ("TEST_END--------------------------------------------------------------------------------------------------------------------------");
$display ();

$finish;

end
endtask


//task 6 vectorcount

task vectorcount; begin

VECTORCOUNT = VECTORCOUNT + 1;

end
endtask


//task 7 display_file

task display_file; begin

$display ("%10d %9s | %4d | %1d | %1d | %5d     | %5d    | %5d     | %5d    | %4d     | %4d    | %7d       | %6d       |", VECTORCOUNT, COMMENT, $time, A, B, COUT_gate, SUM_gate, COUT_data, SUM_data, COUT_beh, SUM_beh, COUT_EXPECTED, SUM_EXPECTED);

end
endtask

//task 8 coverage_update

task coverage_update; begin

input_coverage[{A,B}]++;

end
endtask

//task 9 errors_warnings_check

task errors_warnings_check; begin



if (COUT_gate !== COUT_EXPECTED) begin

$display ("***ERROR: COUT_gate = %b, COUT_expected = %b", COUT_gate, COUT_EXPECTED);
ERRORS = ERRORS + 1;

end

if (SUM_gate !== SUM_EXPECTED) begin

$display ("***ERROR: SUM_gate = %b, SUM_expected = %b", SUM_gate, SUM_EXPECTED);
ERRORS = ERRORS + 1;

end


if (COUT_data !== COUT_EXPECTED) begin

$display ("***ERROR: COUT_data = %b, COUT_expected = %b", COUT_data, COUT_EXPECTED);
ERRORS = ERRORS + 1;

end

if (SUM_data !== SUM_EXPECTED) begin

$display ("***ERROR: SUM_data = %b, SUM_expected = %b", SUM_data, SUM_EXPECTED);
ERRORS = ERRORS + 1;

end


if (COUT_beh !== COUT_EXPECTED) begin

$display ("***ERROR: COUT_beh = %b, COUT_expected = %b", COUT_beh, COUT_EXPECTED);
ERRORS = ERRORS + 1;

end

if (SUM_beh !== SUM_EXPECTED) begin

$display ("***ERROR: SUM_beh = %b, SUM_expected = %b", SUM_beh, SUM_EXPECTED);
ERRORS = ERRORS + 1;

end



end
endtask



//DRIVE

//0 initialize

initial begin

initialize;


end

//2 scan file on negedge TICK

always @ (negedge TICK) begin

#1.2;

if (!eof) begin

scan_file;

end
end



//3 check file on posedge TICK

always  @ (posedge TICK) begin

coverage_update;

#0.1;

COUT_EXP;
SUM_EXP;
display_file;
errors_warnings_check;
vectorcount;

end



// eof

initial begin

wait (eof);

$display ();
$display("%13s ***time = %0d,eof ***","",$time);
$display ();

for (i = 0; i < 50; i++) begin


if (A == 1 && B == 2)
begin

vectorcount;
close;

end

else begin


random_in;


end

end


close;

end


endmodule

verilog_project/half_adder/tb_half_adder.vcd
$date
	Wed Feb  4 01:48:40 2026
$end
$version
	Icarus Verilog
$end
$timescale
	10ps
$end
$scope module tb_half_adder $end
$var wire 1 ! SUM_gate $end
$var wire 1 " SUM_data $end
$var wire 1 # SUM_beh $end
$var wire 1 $ COUT_gate $end
$var wire 1 % COUT_data $end
$var wire 1 & COUT_beh $end
$var parameter 32 ' TICKPERIOD $end
$var reg 1 ( A $end
$var reg 1 ) B $end
$var reg 72 * COMMENT [71:0] $end
$var reg 1 + COUT_EXPECTED $end
$var reg 32 , ERRORS [31:0] $end
$var reg 1 - SUM_EXPECTED $end
$var reg 1 . TICK $end
$var reg 32 / VECTORCOUNT [31:0] $end
$var reg 1 0 eof $end
$var integer 32 1 COUNT [31:0] $end
$var integer 32 2 FD [31:0] $end
$var integer 32 3 i [31:0] $end
$scope module dut_half_adder_behavioral $end
$var wire 1 ( a $end
$var wire 1 ) b $end
$var reg 1 & cout $end
$var reg 1 # sum $end
$upscope $end
$scope module dut_half_adder_dataflow $end
$var wire 1 ( a $end
$var wire 1 ) b $end
$var wire 1 % cout $end
$var wire 1 " sum $end
$upscope $end
$scope module dut_half_adder_gate $end
$var wire 1 ( a $end
$var wire 1 ) b $end
$var wire 1 $ cout $end
$var wire 1 ! sum $end
$upscope $end
$scope task COUT_EXP $end
$upscope $end
$scope task SUM_EXP $end
$upscope $end
$scope task close $end
$upscope $end
$scope task coverage_update $end
$upscope $end
$scope task display_file $end
$upscope $end
$scope task errors_warnings_check $end
$upscope $end
$scope task initialize $end
$upscope $end
$scope task random_in $end
$upscope $end
$scope task scan_file $end
$upscope $end
$scope task vectorcount $end
$upscope $end
$upscope $end
$enddefinitions $end
$comment Show the parameter values. $end
$dumpall
b10100 '
$end
#0
$dumpvars
b100 3
b10000000000000000000000000000011 2
b101 1
00
b0 /
0.
0-
b0 ,
0+
b1001001010011100100100101010100 *
0)
0(
0&
0%
0$
0#
0"
0!
$end
#1000
1.
#1010
b1 /
#2000
0.
#2120
b101101 *
#3000
1.
#3010
b10 /
#4000
0.
#4120
1-
#5000
1.
#5010
b11 /
0-
#6000
0.
#6120
1#
1"
1!
1-
1)
#7000
1.
#7010
b100 /
#8000
0.
#8120
1+
0-
#9000
1.
#9010
b101 /
1-
0+
#10000
0.
#10120
0)
1(
#11000
1.
#11010
b110 /
#12000
0.
#12120
1+
0-
#13000
1.
#13010
b111 /
1-
0+
#14000
0.
#14120
1&
0#
0"
1%
0!
1$
1+
0-
1)
#15000
1.
#15010
b1000 /
#16000
0.
#16120
1-
#17000
1.
#17010
b1001 /
0-
#18000
0.
#18120
b0 1
#19000
1.
#19010
b1010 /
#20000
0.
#20120
1&
0#
0"
1%
0!
1$
1(
b1 3
10
b11111111111111111111111111111111 1
#20920
0&
1#
1"
0%
1!
0$
0)
b10 3
#21000
1.
#21010
b1011 /
1-
0+
#21420
b11 3
#22000
0.
#22020
b100 3
#23000
1.
#23010
b1100 /
#23020
1)
0(
b101 3
#23320
0&
1#
0)
1"
0%
1!
0$
1(
b111 3
#23720
1)
0(
b1000 3
#24000
0.
#24420
1&
0#
0"
1%
0!
1$
1(
b1001 3
#24620
0&
1#
1"
0%
1!
0$
0)
b1010 3
#24820
0#
0"
0!
0(
b1011 3
#25000
1.
#25010
b1101 /
0-
#25120
1&
0#
1%
1$
1(
0"
0!
1)
b1101 3
#25520
0&
0%
0$
0)
0(
b1110 3
#26000
0.
#26120
1&
1%
1$
1)
1(
b1111 3
#26620
0&
0%
0$
0)
0(
b10000 3
#27000
1.
#27010
b1110 /
#27620
1#
1"
1!
1)
b10001 3
#28000
0.
#28020
b10010 3
#29000
1.
#29010
b1111 /
1-
#29020
0#
0"
0!
0)
b10011 3
#29920
1&
1%
1$
1)
1(
b10101 3
#30000
0.
#30620
0&
1#
1"
0%
1!
0$
0)
b10110 3
#30820
1&
0#
0"
1%
0!
1$
1)
b10111 3
#31000
1.
#31010
b10000 /
0-
1+
#31820
0&
0%
0$
0)
0(
b11000 3
#32000
0.
#32620
1#
1"
1!
1(
b11001 3
#32920
b11010 3
#33000
1.
#33010
b10001 /
1-
0+
#33020
1&
0#
0"
1%
0!
1$
1)
b11011 3
#33420
b11100 3
#34000
0.
#34220
0&
0%
0$
0)
0(
b11101 3
#35000
1.
#35010
b10010 /
0-
#35120
1&
1%
1$
1)
1(
b11110 3
#35620
0&
1#
1"
0%
1!
0$
0(
b11111 3
#36000
0.
#36220
1&
0#
0"
1%
0!
1$
1(
b100000 3
#37000
1.
#37010
b10011 /
1+
#37020
0&
1#
1"
0%
1!
0$
0(
b100001 3
#37720
0)
1(
b100010 3
#38000
0.
#38420
0#
0"
0!
0(
b100011 3
#38720
b100100 3
#39000
1.
#39010
b10100 /
0+
#39420
1&
1%
1$
1)
1(
b100101 3
#39720
0&
1#
1"
0%
1!
0$
0)
b100110 3
#40000
0.
#40720
b100111 3
#41000
1.
#41010
b10101 /
1-
#41420
1&
0#
0"
1%
0!
1$
1)
b101000 3
#41820
b101001 3
#42000
0.
#42220
0&
1#
1"
0%
1!
0$
0)
b101010 3
#42620
1)
0(
b101011 3
#43000
1.
#43010
b10110 /
#43120
0#
0"
0!
0)
b101100 3
#43620
1#
1"
1!
1(
b101101 3
#44000
0.
#44320
b101110 3
#45000
1.
#45010
b10111 /
#45220
1)
0(
b101111 3
#45520
1&
0#
0"
1%
0!
1$
1(
b110001 3
#45620
b110010 3
#46000
0.
#46620
b100 3
