verilog_project/verilog_project/register_8_bit_posedge_sync_enable/dff_posedge_sync_enable1.v
// A jk (Jack Kilby) flip-flop which is sync clear at posedge can be set and reset and by creating a versatile memory element, invalid state is prevented.



module dff_posedge_sync_enable1 (
    input  wire clk,
    input  wire enable,
    input  wire d,
    output reg  q,
    output wire qbar
);


    assign qbar = ~q;


//D FLIP-FLOP WITH SYNC ENABLE
    always @(posedge clk) begin

        if (enable) begin
            q <= d;
        end else begin

            q <= q;

        end


     end

endmodule

verilog_project/verilog_project/register_8_bit_posedge_sync_enable/dff_posedge_sync_enable.v
// A jk (Jack Kilby) flip-flop which is sync clear at posedge can be set and reset and by creating a versatile memory element, invalid state is prevented.



module dff_posedge_sync_enable (
    input  wire clk,
    input  wire enable,
    input  wire d,
    output reg  q,
    output wire qbar
);


    assign qbar = ~q;


//D FLIP-FLOP WITH SYNC ENABLE
    always @(posedge clk) begin

        if (enable) begin
            q <= d;
        end else begin

            q <= q;

        end


     end

endmodule

verilog_project/verilog_project/register_8_bit_posedge_sync_enable/8_bit_register_posedge_sync_enable.v
module register_8_bit_posedge_sync_enable(
input clk,
input en,
input [7:0]d,
output [7:0]q
);

wire NOTHING;

dff_posedge_sync_enable dff_posedge_sync_enable0(.clk(clk),.enable(en),.d(d[0]),.q(q[0]),.qbar(NOTHING));
dff_posedge_sync_enable dff_posedge_sync_enable1(.clk(clk),.enable(en),.d(d[1]),.q(q[1]),.qbar(NOTHING));
dff_posedge_sync_enable dff_posedge_sync_enable2(.clk(clk),.enable(en),.d(d[2]),.q(q[2]),.qbar(NOTHING));
dff_posedge_sync_enable dff_posedge_sync_enable3(.clk(clk),.enable(en),.d(d[3]),.q(q[3]),.qbar(NOTHING));
dff_posedge_sync_enable dff_posedge_sync_enable4(.clk(clk),.enable(en),.d(d[4]),.q(q[4]),.qbar(NOTHING));
dff_posedge_sync_enable dff_posedge_sync_enable5(.clk(clk),.enable(en),.d(d[5]),.q(q[5]),.qbar(NOTHING));
dff_posedge_sync_enable dff_posedge_sync_enable6(.clk(clk),.enable(en),.d(d[6]),.q(q[6]),.qbar(NOTHING));
dff_posedge_sync_enable dff_posedge_sync_enable7(.clk(clk),.enable(en),.d(d[7]),.q(q[7]),.qbar(NOTHING));

endmodule

verilog_project/register_8_bit_posedge_sync_enable/input_register.v
module input_register(
input int TICKPERIOD,
input TICK,
output reg EN,
output reg [DATA_WIDTH-1:0] D,
output reg eof,
output reg done,
output reg flag_init,
output reg flag_01,flag_10,flag_00,flag_11,flag_freq,
output reg [4:0] start_test
);

reg [7:0]ch;
reg int mode;
reg int burst;

//PARAMETER
parameter DATA_WIDTH = 8;

//TASK

//task 1 initialize
task initialize; begin
ch = $urandom_range(32,126);

{EN,D} = {1'b0,ch};



eof=0;


end
endtask


//task2 task general_input
task general_input; begin

ch = $urandom_range(32,126);

//EOF
if(flag_freq)begin
eof = 1;
end

//TEST of ENABLE changes frequently

else if(flag_11) begin

//display start test
if(start_test[4] !==1)begin
$display ();
$display("%12s ***time = %0d, TEST of ENABLE changes frequently***","",$time);
$display ();
start_test[4] = 1;
end

//input section
repeat(4)begin
{EN,D} = {~EN,ch};
@(posedge TICK);
end
flag_freq = 1;

end

//TEST of ENABLE maintains 1

else if(flag_00) begin
//display start test
if(start_test[3] !==1)begin
$display ();
$display("%12s ***time = %0d, TEST of ENABLE maintains 1***","",$time);
$display ();
start_test[3] = 1;
end

//input section
repeat(4)begin
{EN,D} = {1'b1,~ch};
@(posedge TICK);
end
flag_11 = 1;

end

//TEST of ENABLE maintains 0

else if(flag_10) begin

//display start test
if(start_test[2] !==1)begin
$display ();
$display("%12s ***time = %0d, TEST of ENABLE maintains 0***","",$time);
$display ();
start_test[2] = 1;
end

//input section
repeat(4)begin
{EN,D} = {1'b0,ch};
@(posedge TICK);
end
flag_00 = 1;

end

//TEST of ENABLE changes from 1 to 0

else if(flag_01) begin

//display start test
if(start_test[1] !==1)begin
$display ();
$display("%12s ***time = %0d, TEST of ENABLE changes from 1 to 0***","",$time);
$display ();
start_test[1] = 1;
end

//input section
{EN,D} = {1'b0,ch};
flag_10 = 1;

end


//TEST of ENABLE changes from 0 to 1

else if(flag_init) begin

//display start test
if(start_test[0] !==1)begin
$display ();
$display("%12s ***time = %0d, TEST of ENABLE changes from 0 to 1***","",$time);
$display ();
start_test[0] = 1;
end

//input section
{EN,D} = {1'b1,ch};
flag_01 = 1;

end

//INITIAL INPUT
else begin
flag_init = 1;
end

end
endtask



//RANDOM IN

task random_in; begin

ch= $urandom_range(32,126);

mode = $urandom_range(0,2);
burst = $urandom_range (1,5);

repeat(burst)begin

@(posedge TICK);

# ($urandom_range(0.1,10));

case(mode)
0:begin
EN = 1'b0; D = ch;
end
1:begin
EN = 1'b1; D = ch;
end
2:begin
EN = ~EN; D = ch;
end
endcase

end

end
endtask



//DRIVER

//INITITALIZE
initial begin
initialize;
end


//INPUT

always @ (posedge TICK) begin

if (!eof) begin
general_input;
end
end

//AFTER EOF

initial begin

wait (eof);

for (int i = 0; i < 50; i++) begin
if(i==49)begin
random_in;
done = 1;
end else begin
random_in;
end
end

end



endmodule

verilog_project/register_8_bit_posedge_sync_enable/tb_register_8_bit_posedge_sync_enable.v
`timescale 1ns/1ps
module tb_register_8_bit_posedge_sync_enable;

//VECTORS FOR DUT
reg TICK;
wire EN;
wire [DATA_WIDTH-1:0] D;
wire [DATA_WIDTH-1:0] Q;

//VECTORS FOR TESTING
reg [8*31-1:0] COMMENT;
wire EMPTY_EXPECTED,FULL_EXPECTED;
reg [DATA_WIDTH-1:0] Q_EXPECTED;
reg [ADDR_WIDTH-1:0] prev_ADDR_EXPECTED;
wire [ADDR_WIDTH-1:0] ADDR_EXPECTED;
wire [DATA_WIDTH-1:0]DATA_OUT_EXPECTED;
reg [31:0] VECTORCOUNT, ERRORS;
int i;
reg [31:0] prev_state_input_coverage[0:23];
reg [31:0] state_input_coverage[0:23];
reg [31:0] wrap_coverage;
wire eof;
reg [ADDR_WIDTH:0]prev_W_PTR;
reg [ADDR_WIDTH:0]prev_R_PTR;
reg [1:0]prev_state;
reg [DATA_WIDTH-1:0] MEM [0:MEM_DEPTH-1];
wire NEXT_W,NEXT_R;
wire WRAP;
wire done;
reg [ADDR_WIDTH:0] ADDR0_EXPECTED;
wire NOTHING;
reg flag_X;
reg prev_en[0:3];
reg flag_init;
wire flag_01,flag_10,flag_00,flag_11,flag_freq;
reg [4:0]c;
wire [4:0]start_test;

parameter DATA_WIDTH = 8, ADDR_WIDTH = 4, MEM_DEPTH = 16, TICKPERIOD = 20;


//DUT INSTANTIATION

input_register dut_input_register (.TICKPERIOD(TICKPERIOD), .TICK(TICK), .EN(EN), .D(D), .eof(eof), .done(done), .flag_init(flag_init),
                                   .flag_01(flag_01), .flag_10(flag_10), .flag_00(flag_00),.flag_11(flag_11),.flag_freq(flag_freq),
                                   .start_test(start_test));

register_8_bit_posedge_sync_enable dut_register_8_bit_posedge_sync_enable (.clk(TICK), .en(EN), .d(D), .q(Q));



// OUT_EXP

dff_posedge_sync_enable1 dff_posedge_sync_enable1_0(.clk(TICK),.enable(EN),.d(D[0]),.q(Q_EXPECTED[0]),.qbar(NOTHING));
dff_posedge_sync_enable1 dff_posedge_sync_enable1_1(.clk(TICK),.enable(EN),.d(D[1]),.q(Q_EXPECTED[1]),.qbar(NOTHING));
dff_posedge_sync_enable1 dff_posedge_sync_enable1_2(.clk(TICK),.enable(EN),.d(D[2]),.q(Q_EXPECTED[2]),.qbar(NOTHING));
dff_posedge_sync_enable1 dff_posedge_sync_enable1_3(.clk(TICK),.enable(EN),.d(D[3]),.q(Q_EXPECTED[3]),.qbar(NOTHING));
dff_posedge_sync_enable1 dff_posedge_sync_enable1_4(.clk(TICK),.enable(EN),.d(D[4]),.q(Q_EXPECTED[4]),.qbar(NOTHING));
dff_posedge_sync_enable1 dff_posedge_sync_enable1_5(.clk(TICK),.enable(EN),.d(D[5]),.q(Q_EXPECTED[5]),.qbar(NOTHING));
dff_posedge_sync_enable1 dff_posedge_sync_enable1_6(.clk(TICK),.enable(EN),.d(D[6]),.q(Q_EXPECTED[6]),.qbar(NOTHING));
dff_posedge_sync_enable1 dff_posedge_sync_enable1_7(.clk(TICK),.enable(EN),.d(D[7]),.q(Q_EXPECTED[7]),.qbar(NOTHING));




//DUMP EVERYTHING INTO DUMPFILE

initial begin

$dumpfile ("tb_register_8_bit_posedge_sync_enable.vcd");
$dumpvars (0, tb_register_8_bit_posedge_sync_enable);

end


//TICKPERIOD


always begin
#(TICKPERIOD/2) TICK <= ~TICK;
end



//TASKS

//task 1 initialize

task initialize; begin

TICK = 0;
VECTORCOUNT = 0;
ERRORS = 0;

for(i=0; i<5; i++)begin
prev_state_input_coverage[i] = 0;
state_input_coverage[i] = 0;
end


$display ();
$display ("I apply both inputs and computations simutaneously on the posedge of the clock, so the output is delayed by one cycle");
$display ();
$display ("TEST_START------------------------------------------------------------------------");
$display ();
$display ("                                | TIME | EN |    D     |    Q     | Q_EXPECTED |");
$display ("----------------------------------------------------------------------------------");


end
endtask




//task4 COMMENT
task comment; begin


if(eof)begin
COMMENT = "RANDOM_INPUT";
end
else if(start_test[4])begin
COMMENT = "change_frequently";
c[3]=1;
end
else if(start_test[3])begin
COMMENT = "mantain_1";
c[2]=1;
end
else if(start_test[2])begin
COMMENT = "mantain_0";
c[1]=1;
end
else if(start_test[1])begin
COMMENT = "1_to_0";
c[0]=1;
end
else if(start_test[0])begin
COMMENT = "0_to_1";
end
else if(flag_init & $time < 2*TICKPERIOD/2)begin
COMMENT = "INIT";
end

end
endtask



//task 5 close

task close; begin

#10;

$display ();
$display ("COVERAGE_REPORT");
$display ();
$display ();
$display ();



for (int j = 0; j < 5; j++ ) begin

if(j<2)begin
if(state_input_coverage[j] == 0) begin
$display ("state of en = %b to en = %b has occured %d times ***ERROR***", j[0], ~j[0], state_input_coverage[j]);
ERRORS = ERRORS + 1;
end
else begin
$display ("state of en = %b to en = %b has occured %d times ", j[0], ~j[0], state_input_coverage[j]);
end
end
else if (j<4)begin
if(state_input_coverage[j] == 0) begin
$display ("state of en maintain %b has occured %d times ***ERROR***", j[0], state_input_coverage[j]);
ERRORS = ERRORS + 1;
end
else begin
$display ("state of en maintain %b has occured %d times", j[0], state_input_coverage[j]);
end
end
else if (j==4)begin
if(state_input_coverage[j] == 0) begin
$display ("state of en changes freqly has occured %d times ***ERROR*** ", state_input_coverage[j]);
ERRORS = ERRORS + 1;
end
else begin
$display ("state of en changes freqly has occured %d times ", state_input_coverage[j]);
end
end

end

$display ();
$display ("VECTORCOUNT = %d", VECTORCOUNT);
$display ("ERRORS = %15d", ERRORS);
$display ();
$display ("TEST_END--------------------------------------------------------------------------------------------------------------------------");
$display ();

$finish;

end
endtask


//task 6 vectorcount

task vectorcount; begin

VECTORCOUNT = VECTORCOUNT + 1;

end
endtask


//task 7 display_file

task display_file; begin

$display ("%10d %20s | %4d | %2b | %8b | %8b |  %8b  |", VECTORCOUNT, COMMENT, $time, EN, D, Q, Q_EXPECTED);
end
endtask



//task 8 in_coverage_update

task coverage_update; begin


if(flag_01)begin
state_input_coverage[0]++;
end
if(flag_10)begin
state_input_coverage[1]++;
end
if(flag_00)begin
state_input_coverage[2]++;
end
if(flag_11)begin
state_input_coverage[3]++;
end
if(flag_freq)begin
state_input_coverage[4]++;
end


end
endtask




//task 9 errors_warnings_check

task errors_warnings_check; begin

if (Q !== Q_EXPECTED) begin
$display ("***ERROR: Q = %b, Q_expected = %b", Q, Q_EXPECTED);
ERRORS = ERRORS + 1;
end

end
endtask



//DRIVE

//0 initialize

initial begin

initialize;

end



//3 check file on  posedge TICK


always  @ (posedge TICK) begin
coverage_update;

#0.1;
comment;
display_file;
errors_warnings_check;
vectorcount;

#0.1;
prev_en[0] <= EN;
prev_en[1] <= prev_en[0];
prev_en[2] <= prev_en[1];
prev_en[3] <= prev_en[2];

for(int j=0; j<5; j++)begin
prev_state_input_coverage[j] <= state_input_coverage[j];
end

end


// eof

initial begin

wait (eof);

$display ();
$display("%13s ***time = %0d,eof ***","",$time);
$display ();
$display ("random stimulus to improve coverage");

end

always@(posedge TICK)begin

if (Q_EXPECTED === 9'b100000000)
begin
vectorcount;
close;
end

else if(done)begin
close;
end

end


endmodule

verilog_project/verilog_project/register_8_bit_posedge_sync_enable/tb_register_8_bit_posedge_sync_enable.vcd
$date
	Mon Apr  6 03:33:24 2026
$end
$version
	Icarus Verilog
$end
$timescale
	1ps
$end
$scope module tb_register_8_bit_posedge_sync_enable $end
$var wire 1 ! NOTHING $end
$var wire 5 " start_test [4:0] $end
$var wire 1 # flag_init $end
$var wire 1 $ flag_freq $end
$var wire 1 % flag_11 $end
$var wire 1 & flag_10 $end
$var wire 1 ' flag_01 $end
$var wire 1 ( flag_00 $end
$var wire 1 ) eof $end
$var wire 1 * done $end
$var wire 8 + Q_EXPECTED [7:0] $end
$var wire 8 , Q [7:0] $end
$var wire 1 - EN $end
$var wire 8 . D [7:0] $end
$var parameter 32 / ADDR_WIDTH $end
$var parameter 32 0 DATA_WIDTH $end
$var parameter 32 1 MEM_DEPTH $end
$var parameter 32 2 TICKPERIOD $end
$var reg 248 3 COMMENT [247:0] $end
$var reg 32 4 ERRORS [31:0] $end
$var reg 1 5 TICK $end
$var reg 32 6 VECTORCOUNT [31:0] $end
$var reg 5 7 c [4:0] $end
$var integer 32 8 i [31:0] $end
$scope module dff_posedge_sync_enable1_0 $end
$var wire 1 5 clk $end
$var wire 1 9 d $end
$var wire 1 ! qbar $end
$var wire 1 - enable $end
$var reg 1 : q $end
$upscope $end
$scope module dff_posedge_sync_enable1_1 $end
$var wire 1 5 clk $end
$var wire 1 ; d $end
$var wire 1 ! qbar $end
$var wire 1 - enable $end
$var reg 1 < q $end
$upscope $end
$scope module dff_posedge_sync_enable1_2 $end
$var wire 1 5 clk $end
$var wire 1 = d $end
$var wire 1 ! qbar $end
$var wire 1 - enable $end
$var reg 1 > q $end
$upscope $end
$scope module dff_posedge_sync_enable1_3 $end
$var wire 1 5 clk $end
$var wire 1 ? d $end
$var wire 1 ! qbar $end
$var wire 1 - enable $end
$var reg 1 @ q $end
$upscope $end
$scope module dff_posedge_sync_enable1_4 $end
$var wire 1 5 clk $end
$var wire 1 A d $end
$var wire 1 ! qbar $end
$var wire 1 - enable $end
$var reg 1 B q $end
$upscope $end
$scope module dff_posedge_sync_enable1_5 $end
$var wire 1 5 clk $end
$var wire 1 C d $end
$var wire 1 ! qbar $end
$var wire 1 - enable $end
$var reg 1 D q $end
$upscope $end
$scope module dff_posedge_sync_enable1_6 $end
$var wire 1 5 clk $end
$var wire 1 E d $end
$var wire 1 ! qbar $end
$var wire 1 - enable $end
$var reg 1 F q $end
$upscope $end
$scope module dff_posedge_sync_enable1_7 $end
$var wire 1 5 clk $end
$var wire 1 G d $end
$var wire 1 ! qbar $end
$var wire 1 - enable $end
$var reg 1 H q $end
$upscope $end
$scope module dut_input_register $end
$var wire 1 5 TICK $end
$var wire 32 I TICKPERIOD [31:0] $end
$var parameter 32 J DATA_WIDTH $end
$var reg 8 K D [7:0] $end
$var reg 1 - EN $end
$var reg 8 L ch [7:0] $end
$var reg 1 * done $end
$var reg 1 ) eof $end
$var reg 1 ( flag_00 $end
$var reg 1 ' flag_01 $end
$var reg 1 & flag_10 $end
$var reg 1 % flag_11 $end
$var reg 1 $ flag_freq $end
$var reg 1 # flag_init $end
$var reg 5 M start_test [4:0] $end
$var integer 32 N burst [31:0] $end
$var integer 32 O mode [31:0] $end
$scope begin $ivl_for_loop2 $end
$var integer 32 P i [31:0] $end
$upscope $end
$scope task general_input $end
$upscope $end
$scope task initialize $end
$upscope $end
$scope task random_in $end
$upscope $end
$upscope $end
$scope module dut_register_8_bit_posedge_sync_enable $end
$var wire 1 Q NOTHING $end
$var wire 1 5 clk $end
$var wire 8 R d [7:0] $end
$var wire 1 - en $end
$var wire 8 S q [7:0] $end
$scope module dff_posedge_sync_enable0 $end
$var wire 1 5 clk $end
$var wire 1 T d $end
$var wire 1 - enable $end
$var wire 1 Q qbar $end
$var reg 1 U q $end
$upscope $end
$scope module dff_posedge_sync_enable1 $end
$var wire 1 5 clk $end
$var wire 1 V d $end
$var wire 1 - enable $end
$var wire 1 Q qbar $end
$var reg 1 W q $end
$upscope $end
$scope module dff_posedge_sync_enable2 $end
$var wire 1 5 clk $end
$var wire 1 X d $end
$var wire 1 - enable $end
$var wire 1 Q qbar $end
$var reg 1 Y q $end
$upscope $end
$scope module dff_posedge_sync_enable3 $end
$var wire 1 5 clk $end
$var wire 1 Z d $end
$var wire 1 - enable $end
$var wire 1 Q qbar $end
$var reg 1 [ q $end
$upscope $end
$scope module dff_posedge_sync_enable4 $end
$var wire 1 5 clk $end
$var wire 1 \ d $end
$var wire 1 - enable $end
$var wire 1 Q qbar $end
$var reg 1 ] q $end
$upscope $end
$scope module dff_posedge_sync_enable5 $end
$var wire 1 5 clk $end
$var wire 1 ^ d $end
$var wire 1 - enable $end
$var wire 1 Q qbar $end
$var reg 1 _ q $end
$upscope $end
$scope module dff_posedge_sync_enable6 $end
$var wire 1 5 clk $end
$var wire 1 ` d $end
$var wire 1 - enable $end
$var wire 1 Q qbar $end
$var reg 1 a q $end
$upscope $end
$scope module dff_posedge_sync_enable7 $end
$var wire 1 5 clk $end
$var wire 1 b d $end
$var wire 1 - enable $end
$var wire 1 Q qbar $end
$var reg 1 c q $end
$upscope $end
$upscope $end
$scope begin $ivl_for_loop1 $end
$var integer 32 d j [31:0] $end
$upscope $end
$scope task close $end
$scope begin $ivl_for_loop0 $end
$var integer 32 e j [31:0] $end
$upscope $end
$upscope $end
$scope task comment $end
$upscope $end
$scope task coverage_update $end
$upscope $end
$scope task display_file $end
$upscope $end
$scope task errors_warnings_check $end
$upscope $end
$scope task initialize $end
$upscope $end
$scope task vectorcount $end
$upscope $end
$upscope $end
$enddefinitions $end
$comment Show the parameter values. $end
$dumpall
b1000 J
b10100 2
b10000 1
b1000 0
b100 /
$end
#0
$dumpvars
b0 e
b0 d
xc
0b
xa
1`
x_
0^
x]
1\
x[
0Z
xY
1X
xW
1V
xU
0T
bx S
b1010110 R
xQ
b0 P
b0 O
b0 N
bx M
b1010110 L
b1010110 K
b10100 I
xH
0G
xF
1E
xD
0C
xB
1A
x@
0?
x>
1=
x<
1;
x:
09
b101 8
bx 7
b0 6
05
b0 4
bx 3
b1010110 .
0-
bx ,
bx +
x*
0)
x(
x'
x&
x%
x$
x#
bx "
x!
$end
#10000
1#
b110111 L
15
#10100
b1 6
b1001001010011100100100101010100 3
#10200
b101 d
#20000
05
#30000
1T
0V
0X
0\
1^
0`
0E
1C
0A
0=
0;
19
1'
1-
b100001 .
b100001 K
b100001 R
bx1 "
bx1 M
b100001 L
15
#30100
b10 6
b1100000101111101110100011011110101111100110001 3
#30200
b101 d
#40000
05
#50000
1U
0W
0Y
0[
0]
1_
0a
b100001 ,
b100001 S
0c
1:
0<
0>
0@
0B
1D
0F
b100001 +
0H
0T
1V
1\
1A
1;
09
1&
0-
b110010 .
b110010 K
b110010 R
bx11 "
bx11 M
b110010 L
15
#50100
b11 6
bx1 7
b1100010101111101110100011011110101111100110000 3
#50200
b101 d
#60000
05
#70000
1T
0V
0^
1`
1E
0C
0;
19
b1010001 .
b1010001 K
b1010001 R
bx111 "
bx111 M
b1010001 L
15
#70100
b100 6
bx11 7
b11011010110000101101110011101000110000101101001011011100101111100110000 3
#70200
b101 d
#80000
05
#90000
15
#90100
b101 6
#90200
b101 d
#100000
05
#110000
15
#110100
b110 6
#110200
b101 d
#120000
05
#130000
15
#130100
b111 6
#130200
b101 d
#140000
05
#150000
1(
15
#150100
b1000 6
#150200
b101 d
#160000
05
#170000
0T
1V
1X
0`
1b
1G
0E
1=
1;
09
1-
b10010110 .
b10010110 K
b10010110 R
bx1111 "
bx1111 M
b1101001 L
15
#170100
b1001 6
bx111 7
b11011010110000101101110011101000110000101101001011011100101111100110001 3
#170200
b101 d
#180000
05
#190000
1H
0D
1B
1>
1<
b10010110 +
0:
1c
0_
1]
1Y
1W
b10010110 ,
b10010110 S
0U
15
#190100
b1010 6
#190200
b101 d
#200000
05
#210000
15
#210100
b1011 6
#210200
b101 d
#220000
05
#230000
15
#230100
b1100 6
#230200
b101 d
#240000
05
#250000
1%
15
#250100
b1101 6
#250200
b101 d
#260000
05
#270000
0X
1^
0b
0G
1C
0=
0-
b110010 .
b110010 K
b110010 R
b11111 "
b11111 M
b110010 L
15
#270100
b1110 6
bx1111 7
b110001101101000011000010110111001100111011001010101111101100110011100100110010101110001011101010110010101101110011101000110110001111001 3
#270200
b101 d
#280000
05
#290000
0Y
1_
b110010 ,
b110010 S
0c
0>
1D
b110010 +
0H
1-
15
#290100
b1111 6
#290200
b101 d
#300000
05
#310000
0-
15
#310100
b10000 6
#310200
b101 d
#320000
05
#330000
1-
15
#330100
b10001 6
#330200
b101 d
#340000
05
#350000
1$
15
#350100
b10010 6
#350200
b101 d
#360000
05
#370000
b100 N
b1 O
1)
b1001111 L
15
#370100
b10011 6
b10100100100000101001110010001000100111101001101010111110100100101001110010100000101010101010100 3
#370200
b101 d
#380000
05
#390000
15
#390100
b10100 6
#390200
b101 d
#396000
1T
1X
1Z
0\
0^
1`
1E
0C
0A
1?
1=
19
b1001111 .
b1001111 K
b1001111 R
#400000
05
#410000
1U
1Y
1[
0]
0_
b1001111 ,
b1001111 S
1a
1:
1>
1@
0B
0D
b1001111 +
1F
15
#410100
b10101 6
#410200
b101 d
#420000
05
#430000
15
#430100
b10110 6
#430200
b101 d
#440000
05
#450000
15
#450100
b10111 6
#450200
b101 d
#460000
05
b10 N
b1000100 L
b1 P
#470000
15
#470100
b11000 6
#470200
b101 d
#480000
05
0T
0V
0Z
0?
0;
09
b1000100 .
b1000100 K
b1000100 R
#490000
0U
0W
b1000100 ,
b1000100 S
0[
0:
0<
b1000100 +
0@
15
#490100
b11001 6
#490200
b101 d
#492000
b101 N
b10 O
b100011 L
b10 P
#500000
05
#510000
15
#510100
b11010 6
#510200
b101 d
#514000
1T
1V
0X
1^
0`
0E
1C
0=
1;
19
b100011 .
b100011 K
b100011 R
0-
#520000
05
#530000
15
#530100
b11011 6
#530200
b101 d
#534000
1-
#540000
05
#550000
0F
1D
0>
1<
b100011 +
1:
0a
1_
0Y
1W
b100011 ,
b100011 S
1U
15
#550100
b11100 6
#550200
b101 d
#554000
0-
#560000
05
#570000
15
#570100
b11101 6
#570200
b101 d
#577000
1-
#580000
05
#590000
15
#590100
b11110 6
#590200
b101 d
#594000
b1 N
b0 O
b101000 L
b11 P
0-
#600000
05
#610000
15
#610100
b11111 6
#610200
b101 d
#615000
0T
0V
1Z
1?
0;
09
b101 N
b1 O
b110111 L
b100 P
b101000 .
b101000 K
b101000 R
#620000
05
#630000
15
#630100
b100000 6
#630200
b101 d
#633000
1T
1V
1X
0Z
1\
1A
0?
1=
1;
19
b110111 .
b110111 K
b110111 R
1-
#640000
05
#650000
1Y
b110111 ,
b110111 S
1]
1>
b110111 +
1B
15
#650100
b100001 6
#650200
b101 d
#660000
05
#670000
15
#670100
b100010 6
#670200
b101 d
#680000
05
#690000
15
#690100
b100011 6
#690200
b101 d
#700000
05
#710000
15
#710100
b100100 6
#710200
b101 d
#711000
b1 N
b1100011 L
b101 P
#720000
05
#730000
15
#730100
b100101 6
#730200
b101 d
#733000
0X
0\
1`
1E
0A
0=
b11 N
b1010101 L
b110 P
b1100011 .
b1100011 K
b1100011 R
#740000
05
#750000
1F
0B
b1100011 +
0>
1a
0]
b1100011 ,
b1100011 S
0Y
15
#750100
b100110 6
#750200
b101 d
#755000
0V
1X
1\
0^
0C
1A
1=
0;
b1010101 .
b1010101 K
b1010101 R
#760000
05
#770000
0W
1Y
1]
b1010101 ,
b1010101 S
0_
0<
1>
1B
b1010101 +
0D
15
#770100
b100111 6
#770200
b101 d
#780000
05
#790000
15
#790100
b101000 6
#790200
b101 d
#791000
b100 N
b10 O
b1111100 L
b111 P
#800000
05
#810000
15
#810100
b101001 6
#810200
b101 d
#814000
0T
1Z
1^
1C
1?
09
b1111100 .
b1111100 K
b1111100 R
0-
#820000
05
#830000
15
#830100
b101010 6
#830200
b101 d
#838000
1-
#840000
05
#850000
0U
1[
b1111100 ,
b1111100 S
1_
0:
1@
b1111100 +
1D
15
#850100
b101011 6
#850200
b101 d
#852000
0-
#860000
05
#870000
15
#870100
b101100 6
#870200
b101 d
#880000
05
b101 N
b1110001 L
b1000 P
1-
#890000
15
#890100
b101101 6
#890200
b101 d
#894000
1T
0X
0Z
0?
0=
19
b1110001 .
b1110001 K
b1110001 R
0-
#900000
05
#910000
15
#910100
b101110 6
#910200
b101 d
#916000
1-
#920000
05
#930000
1U
0Y
b1110001 ,
b1110001 S
0[
1:
0>
b1110001 +
0@
0-
15
#930100
b101111 6
#930200
b101 d
#940000
05
#950000
15
#950100
b110000 6
#950200
b101 d
#952000
1-
#960000
05
#970000
15
#970100
b110001 6
#970200
b101 d
#978000
b100 N
b0 O
b1011110 L
b1001 P
0-
#980000
05
#990000
15
#990100
b110010 6
#990200
b101 d
#992000
0T
1V
1X
1Z
0^
0C
1?
1=
1;
09
b1011110 .
b1011110 K
b1011110 R
#1000000
05
#1010000
15
#1010100
b110011 6
#1010200
b101 d
#1020000
05
#1030000
15
#1030100
b110100 6
#1030200
b101 d
#1040000
05
#1050000
15
#1050100
b110101 6
#1050200
b101 d
#1060000
05
b101 N
b1 O
b1100001 L
b1010 P
#1070000
15
#1070100
b110110 6
#1070200
b101 d
#1078000
1T
0V
0X
0Z
0\
1^
1C
0A
0?
0=
0;
19
b1100001 .
b1100001 K
b1100001 R
1-
#1080000
05
#1090000
b1100001 ,
b1100001 S
0]
b1100001 +
0B
15
#1090100
b110111 6
#1090200
b101 d
#1100000
05
#1110000
15
#1110100
b111000 6
#1110200
b101 d
#1120000
05
#1130000
15
#1130100
b111001 6
#1130200
b101 d
#1140000
05
#1150000
15
#1150100
b111010 6
#1150200
b101 d
#1151000
b1 N
b10 O
b110000 L
b1011 P
#1160000
05
#1170000
15
#1170100
b111011 6
#1170200
b101 d
#1174000
0T
1\
0`
0E
1A
09
b100 N
b0 O
b1001000 L
b1100 P
b110000 .
b110000 K
b110000 R
0-
#1180000
05
#1190000
15
#1190100
b111100 6
#1190200
b101 d
#1195000
1Z
0\
0^
1`
1E
0C
0A
1?
b1001000 .
b1001000 K
b1001000 R
#1200000
05
#1210000
15
#1210100
b111101 6
#1210200
b101 d
#1220000
05
#1230000
15
#1230100
b111110 6
#1230200
b101 d
#1240000
05
#1250000
15
#1250100
b111111 6
#1250200
b101 d
#1252000
b10 N
b1 O
b1011010 L
b1101 P
#1260000
05
#1270000
15
#1270100
b1000000 6
#1270200
b101 d
#1277000
1V
1\
1A
1;
b1011010 .
b1011010 K
b1011010 R
1-
#1280000
05
#1290000
0U
1W
1[
1]
b1011010 ,
b1011010 S
0_
0:
1<
1@
1B
b1011010 +
0D
15
#1290100
b1000001 6
#1290200
b101 d
#1296000
b100 N
b1010101 L
b1110 P
#1300000
05
#1310000
15
#1310100
b1000010 6
#1310200
b101 d
#1310
b111111 5
#1250200
b101 c
#1252000
b10 M
b1 N
b1011010 L
b1101 O
#1260000
04
#1270000
b101 e
14
#1270100
b1000000 5
#1270200
b101 c
#1277000
1U
1[
1A
1;
b1011010 -
b1011010 K
b1011010 Q
1,
#1280000
04
#1290000
0T
1V
1Z
1\
b1011010 +
b1011010 R
0^
0:
1<
1@
1B
b1011010 *
0D
b101 e
14
#1290100
b1000001 5
#1290200
b101 c
#1296000
b100 M
b1010101 L
b1110 O
#1300000
04
#1310000
b101 e
14
#1310100
b1000010 5
#1310200
b101 c
#1312000
1S
0U
1W
0Y
0?
1=
0;
19
b1010101 -
b1010101 K
b1010101 Q
#1320000
04
#1330000
1T
0V
1X
b1010101 +
b1010101 R
0Z
1:
0<
1>
b1010101 *
0@
b101 e
14
#1330100
b1000011 5
#1330200
b101 c
#1340000
04
#1350000
b101 e
14
#1350100
b1000100 5
#1350200
b101 c
#1360000
04
#1370000
b101 e
14
#1370100
b1000101 5
#1370200
b101 c
#1371000
b10 M
b10 N
b1010111 L
b1111 O
#1380000
04
#1390000
b101 e
14
#1390100
b1000110 5
#1390200
b101 c
#1393000
1U
1;
b1010111 -
b1010111 K
b1010111 Q
0,
#1400000
04
#1410000
b101 e
14
#1410100
b1000111 5
#1410200
b101 c
#1413000
b100 M
b0 N
b1111101 L
b10000 O
1,
#1420000
04
#1430000
 K
b1011100 R
1-
#1520000
05
#1530000
0U
0W
b1011100 ,
b1011100 S
1[
0:
0<
b1011100 +
1@
15
#1530100
b1001101 6
#1530200
b101 d
#1537000
b11 N
b1 O
b1010111 L
b10010 P
0-
#1540000
05
#1550000
15
#1550100
b1001110 6
#1550200
b101 d
#1552000
1T
1V
0Z
0?
1;
19
b1010111 .
b1010111 K
b1010111 R
1-
#1560000
05
#1570000
1U
1W
b1010111 ,
b1010111 S
0[
1:
1<
b1010111 +
0@
15
#1570100
b1001111 6
#1570200
b101 d
#1580000
05
#1590000
15
#1590100
b1010000 6
#1590200
b101 d
#1594000
b1100110 L
b10011 P
#1600000
05
#1610000
15
#1610100
b1010001 6
#1610200
b101 d
#1616000
0T
0\
1^
1C
0A
09
b1100110 .
b1100110 K
b1100110 R
#1620000
05
#1630000
1D
0B
b1100110 +
0:
1_
0]
b1100110 ,
b1100110 S
0U
15
#1630100
b1010010 6
#1630200
b101 d
#1640000
05
#1650000
15
#1650100
b1010011 6
#1650200
b101 d
#1655000
b0 O
b1111000 L
b10100 P
#1660000
05
#1670000
15
#1670100
b1010100 6
#1670200
b101 d
