verilog_project/verilog_project/demultiplexer/demultiplexer.v
module demultiplexer(
input y,
input [1:0]sel,
output reg a,b,c,d
);

always@(y or sel) begin

case(sel)
2'b00: begin 
a = y; b = 1'b0; c = 1'b0; d = 1'b0;   
end
2'b01: begin 
a = 1'b0; b = y; c = 1'b0; d = 1'b0;   
end
2'b10: begin 
a = 1'b0; b = 1'b0; c = y; d = 1'b0;   
end
2'b11: begin 
a = 1'b0; b = 1'b0; c = 1'b0; d = y;
end

endcase

end

endmodule

verilog_project/demultiplexer/tb_demultiplexer.v
`timescale 1ns/10ps

module tb_demultiplexer;

//VECTORS FOR DUT
reg Y;
reg[1:0] SEL;
wire A,B,C,D;

//VECTORS FOR TESTING

reg TICK;
integer FD, COUNT;
reg [8*31-1:0] COMMENT;
reg A_EXPECTED,B_EXPECTED,C_EXPECTED,D_EXPECTED;
reg [31:0] VECTORCOUNT, ERRORS;
int i;
reg [31:0] input_coverage [0:7];
reg eof;
reg [7:0]J;

//DUT INSTANTIATION

demultiplexer dut_demultiplexer (.y(Y), .sel(SEL), .a(A), .b(B), .c(C), .d(D));



//DUMP EVERYTHING INTO DUMPFILE

initial begin

$dumpfile ("tb_demultiplexer.vcd");
$dumpvars (0, tb_demultiplexer);

end

//TICKPERIOD

localparam TICKPERIOD = 20;

always begin

#(TICKPERIOD/2) TICK = ~TICK;

end



//TASKS

//task 1 initialize

task initialize; begin

FD = $fopen ("tb_demultiplexer.tv" , "r");
COUNT = $fscanf (FD, "%s", COMMENT);

COUNT = $fscanf (FD, "%s %b %b %b %b %b %b", COMMENT, Y, SEL, A_EXPECTED, B_EXPECTED, C_EXPECTED, D_EXPECTED);
TICK = 0;
VECTORCOUNT = 0;
ERRORS = 0;

for(i=0; i<8; i++)begin
input_coverage[i] = 0;
end

eof = 0;


$display ();
$display ("TEST_START-------------------------------------------------------------------------------------------------------------------------------------");
$display ();
$display ("                     | TIME | Y | SEL | A | B | C | D | A_EXPECTED | B_EXPECTED | C_EXPECTED | D_EXPECTED |");
$display ("-----------------------------------------------------------------------------------------------------------------------------------------------");



end
endtask


//task 3 scan_file

task scan_file; begin

COUNT = $fscanf (FD, "%s %b %b %b %b %b %b", COMMENT, Y, SEL, A_EXPECTED, B_EXPECTED, C_EXPECTED, D_EXPECTED);
eof = (COUNT == -1);

end
endtask

//task 4 random_in

task random_in; begin


Y =  $urandom %2;
SEL = (Y == 0)? 2'b00: $urandom %4;

COMMENT = "-";

# ($urandom_range(0.1,10));

end
endtask

//task5 OUT_EXP

task OUT_EXP; begin

case(SEL)
2'b00: begin
A_EXPECTED = Y; B_EXPECTED = 1'b0; C_EXPECTED = 1'b0; D_EXPECTED = 1'b0;
end
2'b01: begin
A_EXPECTED = 1'b0; B_EXPECTED = Y; C_EXPECTED = 1'b0; D_EXPECTED = 1'b0;
end
2'b10: begin
A_EXPECTED = 1'b0; B_EXPECTED = 1'b0; C_EXPECTED = Y; D_EXPECTED = 1'b0;
end
2'b11: begin
A_EXPECTED = 1'b0; B_EXPECTED = 1'b0; C_EXPECTED = 1'b0; D_EXPECTED = Y;
end

endcase

end
endtask



//task 5 close

task close; begin

#10;

$fclose (FD);

$display ();
$display ("COVERAGE_REPORT");

for (int j = 0; j < 8; j++ ) begin


if(input_coverage[j] == 0) begin
$display ("input Y = %b with SEL = %b has occured %d times ***ERROR***", j[2], j[1:0] , input_coverage[j]);
ERRORS = ERRORS + 1;
end

else if(j>0 && j<4) begin
$display ("input Y = %b with SEL = %b has occured %d times ***SAME LOGIC AS Y=1'b0 with SEL=2'b00*** ", j[2], j[1:0] , input_coverage[j]);
end


else begin
$display ("input Y = %b with SEL = %b has occured %d times ", j[2], j[1:0] , input_coverage[j]);
end

end


$display ();
$display ("VECTORCOUNT = %d", VECTORCOUNT);
$display ("ERRORS = %15d", ERRORS);
$display ();
$display ("TEST_END--------------------------------------------------------------------------------------------------------------------------");
$display ();

$finish;

end
endtask


//task 6 vectorcount

task vectorcount; begin

VECTORCOUNT = VECTORCOUNT + 1;

end
endtask


//task 7 display_file

task display_file; begin

$display ("%10d %9s | %4d | %1b | %1b  | %1b | %1b | %1b | %1b | %5b      | %5b      | %5b      | %5b      |", VECTORCOUNT, COMMENT, $time, Y, SEL, A, B, C, D, A_EXPECTED, B_EXPECTED, C_EXPECTED, D_EXPECTED);

end
endtask

//task 8 coverage_update

task coverage_update; begin

input_coverage[{Y,SEL}]++;

if(Y == 1'b0 && SEL == 2'b00)begin
for(int j=1; j<4; j++)
input_coverage[j]++;
end

end
endtask




//task 9 errors_warnings_check

task errors_warnings_check; begin


if (A !== A_EXPECTED) begin

$display ("***ERROR: A = %b, A_expected = %b", A, A_EXPECTED);
ERRORS = ERRORS + 1;

end


if (B !== B_EXPECTED) begin

$display ("***ERROR: B = %b, B_expected = %b", B, B_EXPECTED);
ERRORS = ERRORS + 1;

end


if (C !== C_EXPECTED) begin

$display ("***ERROR: C = %b, C_expected = %b", C, C_EXPECTED);
ERRORS = ERRORS + 1;

end


if (D !== D_EXPECTED) begin

$display ("***ERROR: D = %b, D_expected = %b", D, D_EXPECTED);
ERRORS = ERRORS + 1;

end

end
endtask



//DRIVE

//0 initialize

initial begin

initialize;

end

//2 scan file on negedge TICK

always @ (negedge TICK) begin

#1.2;

if (!eof) begin

scan_file;

end
end



//3 check file on posedge TICK

always  @ (posedge TICK) begin

coverage_update;

#0.1;

OUT_EXP;
display_file;
errors_warnings_check;
vectorcount;

end



// eof

initial begin

wait (eof);

$display ();
$display("%13s ***time = %0d,eof ***","",$time);
$display ();

for (i = 0; i < 50; i++) begin


if (Y == 1'b1 && SEL == 3'b100)
begin

vectorcount;
close;

end

else begin

random_in;
end

end

close;

end


endmodule

verilog_project/verilog_project/demultiplexer/tb_demultiplexer.vcd
$date
	Thu Feb  5 14:32:53 2026
$end
$version
	Icarus Verilog
$end
$timescale
	10ps
$end
$scope module tb_demultiplexer $end
$var wire 1 ! D $end
$var wire 1 " C $end
$var wire 1 # B $end
$var wire 1 $ A $end
$var parameter 32 % TICKPERIOD $end
$var reg 1 & A_EXPECTED $end
$var reg 1 ' B_EXPECTED $end
$var reg 248 ( COMMENT [247:0] $end
$var reg 1 ) C_EXPECTED $end
$var reg 1 * D_EXPECTED $end
$var reg 32 + ERRORS [31:0] $end
$var reg 2 , SEL [1:0] $end
$var reg 1 - TICK $end
$var reg 32 . VECTORCOUNT [31:0] $end
$var reg 1 / Y $end
$var reg 1 0 eof $end
$var integer 32 1 COUNT [31:0] $end
$var integer 32 2 FD [31:0] $end
$var integer 32 3 i [31:0] $end
$scope module dut_demultiplexer $end
$var wire 2 4 sel [1:0] $end
$var wire 1 / y $end
$var reg 1 $ a $end
$var reg 1 # b $end
$var reg 1 " c $end
$var reg 1 ! d $end
$upscope $end
$scope task OUT_EXP $end
$upscope $end
$scope task close $end
$scope begin $ivl_for_loop0 $end
$var integer 32 5 j [31:0] $end
$upscope $end
$upscope $end
$scope task coverage_update $end
$scope begin $ivl_for_loop1 $end
$var integer 32 6 j [31:0] $end
$upscope $end
$upscope $end
$scope task display_file $end
$upscope $end
$scope task errors_warnings_check $end
$upscope $end
$scope task initialize $end
$upscope $end
$scope task random_in $end
$upscope $end
$scope task scan_file $end
$upscope $end
$scope task vectorcount $end
$upscope $end
$upscope $end
$enddefinitions $end
$comment Show the parameter values. $end
$dumpall
b10100 %
$end
#0
$dumpvars
b0 6
b0 5
b0 4
b1000 3
b10000000000000000000000000000011 2
b111 1
00
0/
b0 .
0-
b0 ,
b0 +
0*
0)
b1001001010011100100100101010100 (
0'
0&
0$
0#
0"
0!
$end
#1000
b100 6
1-
#1010
b1 .
#2000
0-
#2120
b101101 (
#3000
b100 6
1-
#3010
b10 .
#4000
0-
#4120
1$
1&
1/
#5000
1-
#5010
b11 .
#6000
0-
#6120
1#
0$
1'
0&
b1 ,
b1 4
#7000
1-
#7010
b100 .
#8000
0-
#8120
1"
0#
1)
0'
b10 ,
b10 4
#9000
1-
#9010
b101 .
#10000
0-
#10120
1!
0"
1*
0)
b11 ,
b11 4
#11000
1-
#11010
b110 .
#12000
0-
#12120
b0 1
#13000
1-
#13010
b111 .
#14000
0-
#14120
0!
b0 ,
b0 4
0/
b0 3
10
b11111111111111111111111111111111 1
#14320
1!
b11 ,
b11 4
1/
b1 3
#14820
0!
1#
b1 ,
b1 4
b11 3
#15000
1-
#15010
b1000 .
0*
1'
#15620
b100 3
#16000
0-
#16420
1"
0#
b10 ,
b10 4
b101 3
#16820
0"
b0 ,
b0 4
0/
b110 3
#17000
b100 6
1-
#17010
b1001 .
0'
#17820
1"
b10 ,
b10 4
1/
b111 3
#18000
0-
#18620
0"
b0 ,
b0 4
0/
b1000 3
#19000
b100 6
1-
#19010
b1010 .
#19020
b1001 3
#19420
b1010 3
#19820
1#
b1 ,
b1 4
1/
b1011 3
#20000
0-
#20020
0#
b0 ,
b0 4
0/
b1100 3
#20220
b1101 3
#21000
b100 6
1-
#21010
b1011 .
#21120
1!
0"
b11 ,
b11 4
1/
b1111 3
#21820
0!
1"
b10 ,
b10 4
b10000 3
#22000
0-
#22120
1!
0"
b11 ,
b11 4
b10001 3
#22720
0!
b0 ,
b0 4
0/
b10010 3
#23000
b100 6
1-
#23010
b1100 .
#23120
b10011 3
#24000
0-
#24120
b10100 3
#24720
b10101 3
#25000
b100 6
1-
#25010
b1101 .
#25520
1!
b11 ,
b11 4
1/
b10110 3
#26000
0-
#26420
0!
b0 ,
b0 4
0/
b10111 3
#27000
b100 6
1-
#27010
b1110 .
#27320
b11000 3
#27920
1#
b1 ,
b1 4
1/
b11001 3
#28000
0-
#28720
1!
0#
b11 ,
b11 4
b11010 3
#29000
1-
#29010
b1111 .
1*
#29320
0!
b0 ,
b0 4
0/
b11011 3
#29820
1#
b1 ,
b1 4
1/
b11100 3
#30000
0-
#30520
0#
b0 ,
b0 4
0/
b11101 3
#31000
b100 6
1-
#31010
b10000 .
0*
#31320
1$
1/
b11110 3
#31620
b11111 3
#31720
1#
0$
b1 ,
b1 4
b100000 3
#32000
0-
#32120
b100001 3
#32920
0#
b0 ,
b0 4
0/
b100010 3
#33000
b100 6
1-
#33010
b10001 .
#33320
b100011 3
#33520
1"
b10 ,
b10 4
1/
b100100 3
#33720
0"
1#
b1 ,
b1 4
b100101 3
#34000
0-
#34320
b100110 3
#34520
b100111 3
#34620
0#
b0 ,
b0 4
0/
b101000 3
#35000
b100 6
1-
#35010
b10010 .
#35320
b101001 3
#35620
b101010 3
#36000
0-
#36620
b101011 3
#37000
b100 6
1-
#37010
b10011 .
#37320
1!
b11 ,
b11 4
1/
b101100 3
#37620
0!
1$
b0 ,
b0 4
b101101 3
#38000
0-
#38620
1"
0$
b10 ,
b10 4
b101110 3
#39000
1-
#39010
b10100 .
1)
#39320
0"
1#
b1 ,
b1 4
b101111 3
#39720
b110000 3
#40000
0-
#40120
0#
1$
b0 ,
b0 4
b110001 3
#40520
b110010 3
#41000
1-
#41010
b10101 .
0)
1&
#41520
b1000 5
