verilog_project/xor/xor.v
module xor_gate(
input a,b,
output q
);

  xor (q,a,b);

endmodule


module xor_dataflow(
input a,b,
output q
);

  assign q = a ^ b;

endmodule


module xor_behavioral(
input a,b,
output reg q
);

  always @ (a or b) begin
    q <= a ^ b;
  end

endmodule

verilog_project/verilog_project/xor/tb_xor.v
`timescale 1ns/10ps

module tb_xor;

//VECTORS FOR DUT
reg A,B;
wire Q_gate, Q_data, Q_beh;

//VECTORS FOR TESTING

integer FD, COUNT;
reg TICK;
reg [8*9-1:0] COMMENT;
reg QEXPECTED;
reg [31:0] VECTORCOUNT, ERRORS;
int i;
reg [31:0] input_coverage[0:15];
reg eof;
reg[1:0] prev_AB;
reg prev_QEx;
reg prev_QExbar;


//DUT INSTANTIATION

xor_gate dut_xor_gate (.a(A), .b(B), .q(Q_gate));
xor_dataflow dut_xor_dataflow (.a(A), .b(B), .q(Q_data));
xor_behavioral dut_xor_behavioral (.a(A), .b(B), .q(Q_beh));



//DUMP EVERYTHING INTO DUMPFILE

initial begin

$dumpfile ("tb_xor.vcd");
$dumpvars (0, tb_xor);

end

//TICKPERIOD

localparam TICKPERIOD = 20;

always begin

#(TICKPERIOD/2) TICK = ~TICK;

end


//TASKS

//task 1 initialize

task initialize; begin

FD = $fopen ("tb_xor.tv" , "r");
COUNT = $fscanf (FD, "%s", COMMENT);

COUNT = $fscanf (FD, "%s %b %b %b", COMMENT, A, B, QEXPECTED);
TICK = 0;
VECTORCOUNT = 0;
ERRORS = 0;

for ( i = 0 ; i < 16 ; i++ ) begin
input_coverage[i] = 0;
end

eof = 0;

$display ();
$display ("TEST_START------------------------------------------------------------------------------------------------------------------------");
$display ();
$display ("                     | TIME | A | B |  Q_gate  |  Q_data  |  Q_beh  | QEXPECTED |");
$display ("----------------------------------------------------------------------------------------------------------------------------------");



end
endtask



//task 2 scan_file

task scan_file; begin


COUNT = $fscanf (FD,"%s %s %b %b", COMMENT, A, B, QEXPECTED);
eof = (COUNT == -1);

end
endtask

//task 3 random_in

task random_in; begin

A =  $urandom %2 ;
B =  $urandom %2 ;

case ({A,B})
2'b00: COMMENT = "LOW";
2'b01: COMMENT = "HIGH";
2'b10: COMMENT = "HIGH";
2'b11: COMMENT = "LOW";

endcase

#($urandom_range (0.1,10));

end
endtask

//task 4 QEXP

task QEXP; begin


case ( {A,B} )

 2'b00: begin
QEXPECTED = 1'b0;
end
 2'b01: begin
QEXPECTED = 1'b1;
end
 2'b10: begin
QEXPECTED = 1'b1;
end
 2'b11: begin
QEXPECTED = 1'b0;
end


endcase



end
endtask



//task 5 close

task close; begin


#10;
$fclose (FD);

$display ();
$display ("COVERAGE_REPORT");

for ( i = 0; i < 16; i++ ) begin

if(input_coverage[i] == 0) begin

$display ("input %b to input %b has occured %d times (***ERROR***)",i[3:2], i[1:0], input_coverage[i]);
ERRORS = ERRORS +1;

end

else begin

$display ("input %b to input %b has occured %d times",i[3:2], i[1:0], input_coverage[i]);

end

end

$display ();
$display ("VECTORCOUNT = %d", VECTORCOUNT);
$display ("ERRORS = %15d", ERRORS);
$display ();
$display ("TEST_END--------------------------------------------------------------------------------------------------------------------------");
$display ();

$finish;

end
endtask


//task 6 vectorcount

task vectorcount; begin

VECTORCOUNT = VECTORCOUNT + 1;

end
endtask


//task 7 display_file

task display_file; begin

$display ("%10d %9s | %4d | %1d | %1d | %4d     | %4d     | %4d    | %5d     |", VECTORCOUNT, COMMENT, $time, A, B, Q_gate, Q_data, Q_beh, QEXPECTED);

end
endtask

//task 8 coverage_update

task coverage_update; begin

input_coverage[{prev_AB, A, B}]++;

end
endtask

//task 10 errors_check

task errors_check; begin


if (Q_gate !== QEXPECTED) begin

$display ("***ERROR: Q_gate = %b, Q_expected = %b", Q_gate, QEXPECTED);
ERRORS = ERRORS + 1;

end

if (Q_data !== QEXPECTED) begin

$display ("***ERROR: Q_dataflow = %b, Q_expected = %b", Q_data, QEXPECTED);
ERRORS = ERRORS + 1;

end

if (Q_beh !== QEXPECTED) begin

$display ("***ERROR: Q_behavioral = %b, Q_expected = %b", Q_beh, QEXPECTED);
ERRORS = ERRORS + 1;

end


end
endtask



//DRIVE

//0 initialize

initial begin

initialize;

end


//2 scan file on negedge TICK

always @ (negedge TICK) begin


#1.2;

if (!eof) begin



scan_file;

end
end



//3 check file on posedge TICK

always  @ (posedge TICK) begin

coverage_update;
prev_AB = {A,B};

#0.1;

QEXP;
display_file;
errors_check;
vectorcount;

#0.02;

prev_QEx = QEXPECTED;



end



// eof

initial begin

wait (eof);

$display ();
$display("%13s ***time = %0d,eof ***","",$time);
$display ();

for (i = 0; i < 50; i++) begin


if ( A == 1 && B == 2)
begin

vectorcount;
close;

end

else begin

random_in;

end
end


close;

end


endmodule

verilog_project/xor/tb_xor.vcd
$date
	Wed Jan 14 01:19:13 2026
$end
$version
	Icarus Verilog
$end
$timescale
	10ps
$end
$scope module tb_xor $end
$var wire 1 ! Q_gate $end
$var wire 1 " Q_data $end
$var wire 1 # Q_beh $end
$var parameter 32 $ TICKPERIOD $end
$var reg 1 % A $end
$var reg 1 & B $end
$var reg 72 ' COMMENT [71:0] $end
$var reg 32 ( ERRORS [31:0] $end
$var reg 1 ) QEXPECTED $end
$var reg 1 * TICK $end
$var reg 32 + VECTORCOUNT [31:0] $end
$var reg 1 , eof $end
$var reg 2 - prev_AB [1:0] $end
$var reg 1 . prev_QEx $end
$var integer 32 / COUNT [31:0] $end
$var integer 32 0 FD [31:0] $end
$var integer 32 1 i [31:0] $end
$scope module dut_xor_behavioral $end
$var wire 1 % a $end
$var wire 1 & b $end
$var reg 1 # q $end
$upscope $end
$scope module dut_xor_dataflow $end
$var wire 1 % a $end
$var wire 1 & b $end
$var wire 1 " q $end
$upscope $end
$scope module dut_xor_gate $end
$var wire 1 % a $end
$var wire 1 & b $end
$var wire 1 ! q $end
$upscope $end
$scope task QEXP $end
$upscope $end
$scope task close $end
$upscope $end
$scope task coverage_update $end
$upscope $end
$scope task display_file $end
$upscope $end
$scope task errors_check $end
$upscope $end
$scope task initialize $end
$upscope $end
$scope task random_in $end
$upscope $end
$scope task scan_file $end
$upscope $end
$scope task vectorcount $end
$upscope $end
$upscope $end
$enddefinitions $end
$comment Show the parameter values. $end
$dumpall
b10100 $
$end
#0
$dumpvars
b10000 1
b10000000000000000000000000000011 0
b100 /
x.
bx -
0,
b0 +
0*
0)
b0 (
b1001001010011100100100101010100 '
0&
0%
0#
0"
0!
$end
#1000
b0 -
1*
#1010
b1 +
#1012
0.
#2000
0*
#2120
b10011000100111101010111 '
#3000
1*
#3010
b10 +
#4000
0*
#4120
1#
1"
1!
1)
1&
b1001000010010010100011101001000 '
#5000
b1 -
1*
#5010
b11 +
#5012
1.
#6000
0*
#6120
0#
0"
0!
0)
0&
b10011000100111101010111 '
#7000
b0 -
1*
#7010
b100 +
#7012
0.
#8000
0*
#8120
1#
1"
1!
1)
1%
b1001000010010010100011101001000 '
#9000
b10 -
1*
#9010
b101 +
#9012
1.
#10000
0*
#10120
0#
0"
0!
0)
0%
b10011000100111101010111 '
#11000
b0 -
1*
#11010
b110 +
#11012
0.
#12000
0*
#12120
1&
1%
#13000
b11 -
1*
#13010
b111 +
#14000
0*
#14120
1#
1"
1!
1)
0%
b1001000010010010100011101001000 '
#15000
b1 -
1*
#15010
b1000 +
#15012
1.
#16000
0*
#16120
0#
0"
0!
0)
0&
b10011000100111101010111 '
#17000
b0 -
1*
#17010
b1001 +
#17012
0.
#18000
0*
#18120
1#
1"
1!
1)
1&
b1001000010010010100011101001000 '
#19000
b1 -
1*
#19010
b1010 +
#19012
1.
#20000
0*
#21000
1*
#21010
b1011 +
#22000
0*
#23000
1*
#23010
b1100 +
#24000
0*
#24120
0&
1%
#25000
b10 -
1*
#25010
b1101 +
#26000
0*
#26120
1&
0%
#27000
b1 -
1*
#27010
b1110 +
#28000
0*
#28120
0#
0"
0!
0)
1%
b10011000100111101010111 '
#29000
b11 -
1*
#29010
b1111 +
#29012
0.
#30000
0*
#30120
1#
1"
1!
1)
0&
b1001000010010010100011101001000 '
#31000
b10 -
1*
#31010
b10000 +
#31012
1.
#32000
0*
#32120
0#
0"
0!
0)
0%
b10011000100111101010111 '
#33000
b0 -
1*
#33010
b10001 +
#33012
0.
#34000
0*
#34120
1#
1"
1!
1)
1%
b1001000010010010100011101001000 '
#35000
b10 -
1*
#35010
b10010 +
#35012
1.
#36000
0*
#36120
1&
0%
#37000
b1 -
1*
#37010
b10011 +
#38000
0*
#38120
0&
1%
#39000
b10 -
1*
#39010
b10100 +
#40000
0*
#41000
1*
#41010
b10101 +
#42000
0*
#43000
1*
#43010
b10110 +
#44000
0*
#44120
0#
0"
0!
0)
1&
b10011000100111101010111 '
#45000
b11 -
1*
#45010
b10111 +
#45012
0.
#46000
0*
#47000
1*
#47010
b11000 +
#48000
0*
#48120
0&
0%
#49000
b0 -
1*
#49010
b11001 +
#50000
0*
#50120
1&
1%
#51000
b11 -
1*
#51010
b11010 +
#52000
0*
#52120
1#
1"
1!
1)
0%
b1001000010010010100011101001000 '
#53000
b1 -
1*
#53010
b11011 +
#53012
1.
#54000
0*
#54120
0#
0"
0!
0)
1%
b10011000100111101010111 '
#55000
b11 -
1*
#55010
b11100 +
#55012
0.
#56000
0*
#56120
1#
1"
1!
1)
0&
b1001000010010010100011101001000 '
#57000
b10 -
1*
#57010
b11101 +
#57012
1.
#58000
0*
#58120
0#
0"
0!
0)
1&
b10011000100111101010111 '
#59000
b11 -
1*
#59010
b11110 +
#59012
0.
#60000
0*
#61000
1*
#61010
b11111 +
#62000
0*
#62120
b0 /
#63000
1*
#63010
b100000 +
#64000
0*
#64120
0#
0"
0!
b10011000100111101010111 '
1%
b1 1
1,
b11111111111111111111111111111111 /
#64920
1#
1"
1!
b1001000010010010100011101001000 '
0&
b10 1
#65000
b10 -
1*
#65010
b100001 +
1)
#65012
1.
#65420
b11 1
#66000
0*
#66020
b100 1
#67000
1*
#67010
b100010 +
#67020
1&
0%
b101 1
#67320
1#
0&
1"
1!
b1001000010010010100011101001000 '
1%
b111 1
#67720
1&
0%
b1000 1
#68000
0*
#68420
0#
0"
0!
b10011000100111101010111 '
1%
b1001 1
#68620
1#
1"
1!
b1001000010010010100011101001000 '
0&
b1010 1
#68820
0#
0"
0!
b10011000100111101010111 '
0%
b1011 1
#69000
b0 -
1*
#69010
b100011 +
0)
#69012
0.
#69120
0#
1%
0"
0!
b10011000100111101010111 '
1&
b1101 1
#69520
0&
0%
b1110 1
#70000
0*
#70120
1&
1%
b1111 1
#70620
0&
0%
b10000 1
#71000
1*
#71010
b100100 +
#71620
1#
1"
1!
b1001000010010010100011101001000 '
1&
b10001 1
#72000
0*
#72020
b10010 1
#73000
b1 -
1*
#73010
b100101 +
1)
#73012
1.
#73020
0#
0"
0!
b10011000100111101010111 '
0&
b10011 1
#73920
1&
1%
b10101 1
#74000
0*
#74620
1#
1"
1!
b1001000010010010100011101001000 '
0&
b10110 1
#74820
0#
0"
0!
b10011000100111101010111 '
1&
b10111 1
#75000
b11 -
1*
#75010
b100110 +
0)
#75012
0.
#75820
0&
0%
b11000 1
#76000
0*
#76620
1#
1"
1!
b1001000010010010100011101001000 '
1%
b11001 1
#76920
b11010 1
#77000
b10 -
1*
#77010
b100111 +
1)
#77012
1.
#77020
0#
0"
0!
b10011000100111101010111 '
1&
b11011 1
#77420
b11100 1
#78000
0*
#78220
0&
0%
b11101 1
#79000
b0 -
1*
#79010
b101000 +
0)
#79012
0.
#79120
1&
1%
b11110 1
#79620
1#
1"
1!
b1001000010010010100011101001000 '
0%
b11111 1
#80000
0*
#80220
0#
0"
0!
b10011000100111101010111 '
1%
b100000 1
#81000
b11 -
1*
#81010
b101001 +
#81020
1#
1"
1!
b1001000010010010100011101001000 '
0%
b100001 1
#81720
0&
1%
b100010 1
#82000
0*
#82420
0#
0"
0!
b10011000100111101010111 '
0%
b100011 1
#82720
b100100 1
#83000
b0 -
1*
#83010
b101010 +
#83420
1&
1%
b100101 1
#83720
1#
1"
1!
b1001000010010010100011101001000 '
0&
b100110 1
#84000
0*
#84720
b100111 1
#85000
b10 -
1*
#85010
b101011 +
1)
#85012
1.
#85420
0#
0"
0!
b10011000100111101010111 '
1&
b101000 1
#85820
b101001 1
#86000
0*
#86220
1#
1"
1!
b1001000010010010100011101001000 '
0&
b101010 1
#86620
1&
0%
b101011 1
#87000
b1 -
1*
#87010
b101100 +
#87120
0#
0"
0!
b10011000100111101010111 '
0&
b101100 1
#87620
1#
1"
1!
b1001000010010010100011101001000 '
1%
b101101 1
#88000
0*
#88320
b101110 1
#89000
b10 -
1*
#89010
b101101 +
#89220
1&
0%
b101111 1
#89520
0#
0"
0!
b10011000100111101010111 '
1%
b110001 1
#89620
b110010 1
#90000
0*
#90620
b10000 1
