verilog_project/dual_port_ram_asynchronous/dual_port_ram_asynchronous.v
module dual_port_ram_asynchronous(
input clk_a,
input we_a, //write enable
input [ADDR_WIDTH-1:0]addr_a,
input [DATA_WIDTH-1:0]data_in_a,
output reg [DATA_WIDTH-1:0]data_out_a,

input clk_b,
input we_b, //write enable
input [ADDR_WIDTH-1:0]addr_b,
input [DATA_WIDTH-1:0]data_in_b,
output reg [DATA_WIDTH-1:0]data_out_b
);

parameter DATA_WIDTH = 8, ADDR_WIDTH = 4, MEM_DEPTH = 16;

reg [DATA_WIDTH-1:0]mem[MEM_DEPTH-1:0];


always@(posedge clk_a)begin

if(we_a)begin

mem[addr_a] <= data_in_a;
data_out_a <= mem[addr_a]; //验证时改成data_out = mem[addr]，在data_in了之后，blocking

end

else begin
data_out_a <= mem[addr_a];
end

end


always@(posedge clk_b)begin

if(we_b)begin

mem[addr_b] <= data_in_b;
data_out_b <= mem[addr_b]; //验证时改成data_out = mem[addr]，在data_in了之后，blocking

end

else begin
data_out_b <= mem[addr_b];
end

end


endmodule

verilog_project/verilog_project/dual_port_ram_asynchronous/tb_dual_port_ram_asynchronous.v
`timescale 1ns/10ps

module tb_dual_port_ram_asynchronous;

//VECTORS FOR DUT
reg WE_A, WE_B;
reg [ADDR_WIDTH-1:0] ADDR_A, ADDR_B;
reg [DATA_WIDTH-1:0] DATA_IN_A, DATA_IN_B;
wire [DATA_WIDTH-1:0] DATA_OUT_A, DATA_OUT_B;

//VECTORS FOR TESTING

reg TICK, TICK_A, TICK_B;
integer FD, COUNT;
reg [8*31-1:0] COMMENT;
reg [DATA_WIDTH-1:0]DATA_OUT_A_EXPECTED,DATA_OUT_B_EXPECTED;
reg [31:0] VECTORCOUNT, ERRORS;
int i;
reg [31:0] input_coverage_TICKA[0:1];
reg [31:0] input_coverage_TICKB[0:1];
reg [31:0] input_coverage_a[0:5'b11111];
reg [31:0] input_coverage_b[0:5'b11111];
reg eof;
reg [4:0]prev_INPUT_A;
reg [4:0]prev_INPUT_B;
reg [DATA_WIDTH-1:0] MEM [0:MEM_DEPTH-1];

parameter DATA_WIDTH = 8, ADDR_WIDTH = 4, MEM_DEPTH = 16;


//DUT INSTANTIATION

dual_port_ram_asynchronous dut_dual_port_ram_asynchronous (.clk_a(TICK_A), .we_a(WE_A), .addr_a(ADDR_A), .data_in_a(DATA_IN_A), .data_out_a(DATA_OUT_A), .clk_b(TICK_B), .we_b(WE_B), .addr_b(ADDR_B), .data_in_b(DATA_IN_B), .data_out_b(DATA_OUT_B));


//DUMP EVERYTHING INTO DUMPFILE

initial begin

$dumpfile ("tb_dual_port_ram_asynchronous.vcd");
$dumpvars (0, tb_dual_port_ram_asynchronous);

end


//TICKPERIOD

localparam TICKPERIOD = 20;

always begin
#(TICKPERIOD/2) TICK <= ~TICK;
end

always begin
#(TICKPERIOD/2) TICK_A <= ~TICK_A;
end

always begin
#(TICKPERIOD) TICK_B <= ~TICK_B;
end

//TASKS

//task 1 initialize

task initialize; begin

FD = $fopen ("tb_dual_port_ram_asynchronous.tv" , "r");
COUNT = $fscanf (FD, "%s", COMMENT);

COUNT = $fscanf (FD, "%s %b %b %s %b %b %s ", COMMENT, WE_A, ADDR_A, DATA_IN_A, WE_B, ADDR_B, DATA_IN_B);
TICK = 0;
TICK_A = 0;
TICK_B = 0;
VECTORCOUNT = 0;
ERRORS = 0;

for(i=0; i<2; i++)begin
input_coverage_TICKA[i] = 0;
input_coverage_TICKB[i] = 0;
end

for(i=0; i<=5'b11111; i++)begin
if(i<2 || i>5'b01111)begin
input_coverage_a[i] = 0;
end
end


for(i=0; i<=5'b11111; i++)begin
if(i<2 || i>5'b01111)begin
input_coverage_b[i] = 0;
end
end


eof = 0;

$display ();
$display ("TEST_START--------------------------------------------------------------------------------------------------------------------------------------------------------------------");
$display ();
$display ("                     | TIME | TICK_A | WE_A | ADDR_A | DATA_IN_A | DATA_OUT_A | DATA_OUT_A_EXPECTED | TICK_B | WE_B | ADDR_B | DATA_IN_B | DATA_OUT_B | DATA_OUT_B_EXPECTED |");
$display ("------------------------------------------------------------------------------------------------------------------------------------------------------------------------------");

#10;
force TICK_A = 0;
#20;
release TICK_A;

end
endtask


//task 3 scan_file

task scan_file; begin

COUNT = $fscanf (FD, "%s %b %b %s %b %b %s", COMMENT, WE_A, ADDR_A, DATA_IN_A, WE_B, ADDR_B, DATA_IN_B);
eof = (COUNT == -1);

end
endtask

//task 4 random_in

task random_in; begin
reg[DATA_WIDTH-1:0] temp;

WE_A =  $urandom %2;
ADDR_A = (WE_A == 0)?$urandom %2 : $urandom %16;
DATA_IN_A = $urandom_range(32,126);

WE_B =  $urandom %2;
temp = (WE_B == 0)?$urandom %2 : $urandom %16;
DATA_IN_B = $urandom_range(32,126);

if(temp == ADDR_A)begin
if($urandom%2)begin
ADDR_B = (temp == MEM_DEPTH-1)? temp-1: temp+1;
end
else begin
ADDR_B = (temp == 0)? temp+1: temp-1;
end
end

else
ADDR_B = temp;

COMMENT = "-";

# ($urandom_range(0.1,10));

end
endtask



//task5 OUT_EXP

task OUT_EXP_A; begin

if(WE_A)begin
MEM[ADDR_A] <= DATA_IN_A;
DATA_OUT_A_EXPECTED <= MEM[ADDR_A];
end

else begin
DATA_OUT_A_EXPECTED <= MEM[ADDR_A];
end

end
endtask

task OUT_EXP_B; begin

if(WE_B)begin
MEM[ADDR_B] <= DATA_IN_B;
DATA_OUT_B_EXPECTED <= MEM[ADDR_B];
end

else begin
DATA_OUT_B_EXPECTED <= MEM[ADDR_B];
end


end
endtask



//task 5 close

task close; begin

#10;

$fclose (FD);

$display ();
$display ("COVERAGE_REPORT");
$display ();
$display ("1.for WE_A==0 and WE_B==0, only test two input combinations as others combination has identical behavior");
$display ();

for (int j = 0; j < 2; j++ ) begin

if(input_coverage_TICKA[j] == 0) begin
$display ("input TICK_A = %b has occured %22s%-2d times ***ERROR***", j[0],"", input_coverage_TICKA[j]);
ERRORS = ERRORS + 1;
end


else begin
$display ("input TICK_A = %b has occured %22s%-2d times", j[0],"", input_coverage_TICKA[j]);
end

end


for (int j = 0; j < 5'b11111; j++ ) begin

if(j<2 || j>5'b01111) begin

if(input_coverage_a[j] < 2) begin            // data in need to at least come across same address for 2 times to ensure data in is successfully written into the address 
$display ("input WE_A = %b, ADDR_A = %b has occured %9s%-2d times ***ERROR***", j[4], j[3:0],"", input_coverage_a[j]);
ERRORS = ERRORS + 1;
end


else begin
$display ("input WE_A = %b, ADDR_A = %b has occured %9s%-2d times", j[4], j[3:0],"", input_coverage_a[j]);
end
end

else begin
//NOTHING
end
end


for (int j = 0; j < 2; j++ ) begin

if(input_coverage_TICKB[j] == 0) begin
$display ("input TICK_B = %b has occured %22s%-2d times ***ERROR***", j[0],"", input_coverage_TICKB[j]);
ERRORS = ERRORS + 1;
end


else begin
$display ("input TICK_B = %b has occured %22s%-2d times", j[0],"", input_coverage_TICKB[j]);
end

end


for (int j = 0; j < 5'b11111; j++ ) begin

if(j<2 || j>5'b01111) begin

if(input_coverage_b[j] < 2) begin
$display ("input WE_B = %b, ADDR_B = %b has occured %9s%-2d times ***ERROR***", j[4], j[3:0],"", input_coverage_b[j]);
ERRORS = ERRORS + 1;
end


else begin
$display ("input WE_B = %b, ADDR_B = %b has occured %9s%-2d times", j[4], j[3:0],"", input_coverage_b[j]);
end
end

else begin
//NOTHING
end
end



$display ();
$display ("VECTORCOUNT = %d", VECTORCOUNT);
$display ("ERRORS = %15d", ERRORS);
$display ();
$display ("TEST_END--------------------------------------------------------------------------------------------------------------------------");
$display ();

$finish;

end
endtask


//task 6 vectorcount

task vectorcount; begin

VECTORCOUNT = VECTORCOUNT + 1;

end
endtask


//task 7 display_file

task display_file_A; begin

$display ("_____________________________________________________________________________________________________");
$display ("%10d %9s | %4d | %3b    | %2b   | %5b  | %5c     | %5c      | %10c          |", VECTORCOUNT, COMMENT, $time, TICK_A, WE_A, ADDR_A, DATA_IN_A, DATA_OUT_A, DATA_OUT_A_EXPECTED);
$display ("-----------------------------------------------------------------------------------------------------");

end
endtask


task display_file_B; begin


$display ("%100s__________________________________________________________________________","");
$display ("%10d %9s | %4d |%70s | %3b    | %2b   | %5b  | %5c     | %5c      | %10c          |", VECTORCOUNT, COMMENT, $time, "", TICK_B, WE_B, ADDR_B, DATA_IN_B, DATA_OUT_B, DATA_OUT_B_EXPECTED);
$display ("%100s--------------------------------------------------------------------------","");

end
endtask

//task 8 in_coverage_update

task in_coverage_update; begin

input_coverage_TICKA[{TICK_A}]++;
input_coverage_TICKB[{TICK_B}]++;
input_coverage_a[{WE_A,ADDR_A}]++;
input_coverage_b[{WE_B,ADDR_B}]++;

end
endtask


//task 9 errors_warnings_check

task errors_warnings_check_A; begin


if (DATA_OUT_A !== DATA_OUT_A_EXPECTED) begin

$display ("***ERROR: DATA_OUT_A = %b, DATA_OUT_A_expected = %b", DATA_OUT_A, DATA_OUT_A_EXPECTED);
ERRORS = ERRORS + 1;

end

if (({WE_A,ADDR_A} !== prev_INPUT_A) && TICK_A) begin

$display ("***ERROR: INPUT_A - RACING CONDITION OCCUR");
ERRORS = ERRORS + 1;

end

end
endtask

task errors_warnings_check_B; begin

if (DATA_OUT_B !== DATA_OUT_B_EXPECTED) begin

$display ("***ERROR: DATA_OUT_B = %b, DATA_OUT_B_expected = %b", DATA_OUT_B, DATA_OUT_B_EXPECTED);
ERRORS = ERRORS + 1;

end

if ({WE_B,ADDR_B} !== prev_INPUT_B && TICK_B) begin

$display ("***ERROR: INPUT_B - RACING CONDITION OCCUR");
ERRORS = ERRORS + 1;

end


end
endtask



//DRIVE

//0 initialize

initial begin

initialize;

end

//2 scan file on negedge TICK

always @ (negedge TICK) begin
#9.9;
if (!eof) begin

scan_file;

end
end


//3 check file on posedge TICK

always  @ (posedge TICK_A) begin
prev_INPUT_A = {WE_A,ADDR_A};
in_coverage_update;
OUT_EXP_A;

#0.1;
display_file_A;
errors_warnings_check_A;
vectorcount;


end


always  @ (posedge TICK_B) begin
prev_INPUT_B = {WE_B,ADDR_B};
in_coverage_update;
OUT_EXP_B;

#0.1;
display_file_B;
errors_warnings_check_B;
vectorcount;


end



// eof

initial begin

wait (eof);

$display ();
$display("%13s ***time = %0d,eof ***","",$time);
$display ();

for (i = 0; i < 50; i++) begin


if (TICK_A == 1'b1 && WE_A == 1'b0 && ADDR_A == 5'b10000 || TICK_B == 1'b1 && WE_B == 1'b0 && ADDR_B == 5'b10000)
begin

vectorcount;
close;

end

else begin

random_in;
end

end

close;

end


endmodule

verilog_project/dual_port_ram_asynchronous/tb_dual_port_ram_asynchronous.vcd
$date
	Fri Feb 13 07:29:20 2026
$end
$version
	Icarus Verilog
$end
$timescale
	10ps
$end
$scope module tb_dual_port_ram_asynchronous $end
$var wire 8 ! DATA_OUT_B [7:0] $end
$var wire 8 " DATA_OUT_A [7:0] $end
$var parameter 32 # ADDR_WIDTH $end
$var parameter 32 $ DATA_WIDTH $end
$var parameter 32 % MEM_DEPTH $end
$var parameter 32 & TICKPERIOD $end
$var reg 4 ' ADDR_A [3:0] $end
$var reg 4 ( ADDR_B [3:0] $end
$var reg 248 ) COMMENT [247:0] $end
$var reg 8 * DATA_IN_A [7:0] $end
$var reg 8 + DATA_IN_B [7:0] $end
$var reg 8 , DATA_OUT_A_EXPECTED [7:0] $end
$var reg 8 - DATA_OUT_B_EXPECTED [7:0] $end
$var reg 32 . ERRORS [31:0] $end
$var reg 1 / TICK $end
$var reg 1 0 TICK_A $end
$var reg 1 1 TICK_B $end
$var reg 32 2 VECTORCOUNT [31:0] $end
$var reg 1 3 WE_A $end
$var reg 1 4 WE_B $end
$var reg 1 5 eof $end
$var reg 5 6 prev_INPUT_A [4:0] $end
$var reg 5 7 prev_INPUT_B [4:0] $end
$var integer 32 8 COUNT [31:0] $end
$var integer 32 9 FD [31:0] $end
$var integer 32 : i [31:0] $end
$scope module dut_dual_port_ram_asynchronous $end
$var wire 4 ; addr_a [3:0] $end
$var wire 4 < addr_b [3:0] $end
$var wire 1 0 clk_a $end
$var wire 1 1 clk_b $end
$var wire 8 = data_in_a [7:0] $end
$var wire 8 > data_in_b [7:0] $end
$var wire 1 3 we_a $end
$var wire 1 4 we_b $end
$var parameter 32 ? ADDR_WIDTH $end
$var parameter 32 @ DATA_WIDTH $end
$var parameter 32 A MEM_DEPTH $end
$var reg 8 B data_out_a [7:0] $end
$var reg 8 C data_out_b [7:0] $end
$upscope $end
$scope task OUT_EXP_A $end
$upscope $end
$scope task OUT_EXP_B $end
$upscope $end
$scope task close $end
$scope begin $ivl_for_loop0 $end
$var integer 32 D j [31:0] $end
$upscope $end
$scope begin $ivl_for_loop1 $end
$var integer 32 E j [31:0] $end
$upscope $end
$scope begin $ivl_for_loop2 $end
$var integer 32 F j [31:0] $end
$upscope $end
$scope begin $ivl_for_loop3 $end
$var integer 32 G j [31:0] $end
$upscope $end
$upscope $end
$scope task display_file_A $end
$upscope $end
$scope task display_file_B $end
$upscope $end
$scope task errors_warnings_check_A $end
$upscope $end
$scope task errors_warnings_check_B $end
$upscope $end
$scope task in_coverage_update $end
$upscope $end
$scope task initialize $end
$upscope $end
$scope task random_in $end
$scope begin $unm_blk_12 $end
$var reg 8 H temp [7:0] $end
$upscope $end
$upscope $end
$scope task scan_file $end
$upscope $end
$scope task vectorcount $end
$upscope $end
$upscope $end
$enddefinitions $end
$comment Show the parameter values. $end
$dumpall
b10000 A
b1000 @
b100 ?
b10100 &
b10000 %
b1000 $
b100 #
$end
#0
$dumpvars
bx H
b0 G
b0 F
b0 E
b0 D
bx C
bx B
b1100001 >
b110000 =
b1 <
b0 ;
b100000 :
b10000000000000000000000000000011 9
b111 8
bx 7
bx 6
05
04
03
b0 2
01
00
0/
b0 .
bx -
bx ,
b1100001 +
b110000 *
b1001001010011100100100101010100 )
b1 (
b0 '
bx "
bx !
$end
#1000
1/
00
#2000
b1 7
0/
11
#2010
b1 2
#2990
b1100010 +
b1100010 >
b110001 *
b110001 =
b101101 )
#3000
b0 6
1/
10
#3010
b10 2
#4000
00
0/
01
#4990
b1100011 +
b1100011 >
14
b110010 *
b110010 =
13
#5000
b10000 6
10
1/
#5010
b11 2
#6000
b10001 7
00
0/
11
#6010
b100 2
#6990
b1100100 +
b1100100 >
b10 (
b10 <
b110011 *
b110011 =
b1 '
b1 ;
#7000
b1100011 ,
b1100011 "
b1100011 B
b10001 6
10
1/
#7010
b101 2
#8000
00
0/
01
#8990
b1100101 +
b1100101 >
b1 (
b1 <
b110100 *
b110100 =
b10 '
b10 ;
#9000
bx ,
bx "
bx B
b10010 6
10
1/
#9010
b110 2
#10000
b110011 -
b110011 !
b110011 C
00
0/
11
#10010
b111 2
#10990
b1100110 +
b1100110 >
b10 (
b10 <
b110101 *
b110101 =
b11 '
b11 ;
#11000
b10011 6
10
1/
#11010
b1000 2
#12000
00
0/
01
#12990
b1100111 +
b1100111 >
b110110 *
b110110 =
b100 '
b100 ;
#13000
b10100 6
10
1/
#13010
b1001 2
#14000
b110100 -
b110100 !
b110100 C
b10010 7
00
0/
11
#14010
b1010 2
#14990
b1101000 +
b1101000 >
b110111 *
b110111 =
b101 '
b101 ;
#15000
b10101 6
10
1/
#15010
b1011 2
#16000
00
0/
01
#16990
b1101001 +
b1101001 >
b11 (
b11 <
b111000 *
b111000 =
b110 '
b110 ;
#17000
b10110 6
10
1/
#17010
b1100 2
#18000
b110101 -
b110101 !
b110101 C
b10011 7
00
0/
11
#18010
b1101 2
#18990
b1101010 +
b1101010 >
b111001 *
b111001 =
b111 '
b111 ;
#19000
b10111 6
10
1/
#19010
b1110 2
#20000
00
0/
01
#20990
b1100001 +
b1100001 >
b110000 *
b110000 =
b1000 '
b1000 ;
#21000
b11000 6
10
1/
#21010
b1111 2
#22000
b1101001 -
b1101001 !
b1101001 C
00
0/
11
#22010
b10000 2
#22990
b1100010 +
b1100010 >
b100 (
b100 <
b110001 *
b110001 =
b1001 '
b1001 ;
#23000
b11001 6
10
1/
#23010
b10001 2
#24000
00
0/
01
#24990
b1100011 +
b1100011 >
b110010 *
b110010 =
b1010 '
b1010 ;
#25000
b11010 6
10
1/
#25010
b10010 2
#26000
b110110 -
b110110 !
b110110 C
b10100 7
00
0/
11
#26010
b10011 2
#26990
b1100100 +
b1100100 >
b110011 *
b110011 =
b1011 '
b1011 ;
#27000
b11011 6
10
1/
#27010
b10100 2
#28000
00
0/
01
#28990
b1100101 +
b1100101 >
b101 (
b101 <
b110100 *
b110100 =
b1100 '
b1100 ;
#29000
b11100 6
10
1/
#29010
b10101 2
#30000
b110111 -
b110111 !
b110111 C
b10101 7
00
0/
11
#30010
b10110 2
#30990
b1100110 +
b1100110 >
b110101 *
b110101 =
b1101 '
b1101 ;
#31000
b11101 6
10
1/
#31010
b10111 2
#32000
00
0/
01
#32990
b1100111 +
b1100111 >
b110110 *
b110110 =
b1110 '
b1110 ;
#33000
b11110 6
10
1/
#33010
b11000 2
#34000
b1100101 -
b1100101 !
b1100101 C
00
0/
11
#34010
b11001 2
#34990
b1101000 +
b1101000 >
b110 (
b110 <
b110111 *
b110111 =
b1111 '
b1111 ;
#35000
b11111 6
10
1/
#35010
b11010 2
#36000
00
0/
01
#36990
b1101001 +
b1101001 >
b111000 *
b111000 =
b0 '
b0 ;
03
#37000
b110010 ,
b110010 "
b110010 B
b0 6
10
1/
#37010
b11011 2
#38000
b111000 -
b111000 !
b111000 C
b10110 7
00
0/
11
#38010
b11100 2
#38990
b1101010 +
b1101010 >
b111001 *
b111001 =
13
#39000
b10000 6
10
1/
#39010
b11101 2
#40000
00
0/
01
#40990
b1100001 +
b1100001 >
b111 (
b111 <
b110000 *
b110000 =
b1 '
b1 ;
#41000
b1100101 ,
b1100101 "
b1100101 B
b10001 6
10
1/
#41010
b11110 2
#42000
b111001 -
b111001 !
b111001 C
b10111 7
00
0/
11
#42010
b11111 2
#42990
b1100010 +
b1100010 >
b110001 *
b110001 =
b10 '
b10 ;
#43000
b1100111 ,
b1100111 "
b1100111 B
b10010 6
10
1/
#43010
b100000 2
#44000
00
0/
01
#44990
b1100011 +
b1100011 >
b110010 *
b110010 =
b11 '
b11 ;
#45000
b1100001 ,
b1100001 "
b1100001 B
b10011 6
10
1/
#45010
b100001 2
#46000
b1100001 -
b1100001 !
b1100001 C
00
0/
11
#46010
b100010 2
#46990
b1100100 +
b1100100 >
b1000 (
b1000 <
b110011 *
b110011 =
b100 '
b100 ;
#47000
b1100011 ,
b1100011 "
b1100011 B
b10100 6
10
1/
#47010
b100011 2
#48000
00
0/
01
#48990
b1100101 +
b1100101 >
b110100 *
b110100 =
b101 '
b101 ;
#49000
b1100111 ,
b1100111 "
b1100111 B
b10101 6
10
1/
#49010
b100100 2
#50000
b110000 -
b110000 !
b110000 C
b11000 7
00
0/
11
#50010
b100101 2
#50990
b1100110 +
b1100110 >
b110101 *
b110101 =
b110 '
b110 ;
#51000
b1101001 ,
b1101001 "
b1101001 B
b10110 6
10
1/
#51010
b100110 2
#52000
00
0/
01
#52990
b1100111 +
b1100111 >
b1001 (
b1001 <
b110110 *
b110110 =
b111 '
b111 ;
#53000
b1100011 ,
b1100011 "
b1100011 B
b10111 6
10
1/
#53010
b100111 2
#54000
b110001 -
b110001 !
b110001 C
b11001 7
00
0/
11
#54010
b101000 2
#54990
b1101000 +
b1101000 >
b110111 *
b110111 =
b1000 '
b1000 ;
#55000
b1100101 ,
b1100101 "
b1100101 B
b11000 6
10
1/
#55010
b101001 2
#56000
00
0/
01
#56990
b1101001 +
b1101001 >
b1000 (
b1000 <
b111000 *
b111000 =
b1001 '
b1001 ;
#57000
b1100111 ,
b1100111 "
b1100111 B
b11001 6
10
1/
#57010
b101010 2
#58000
b110111 -
b110111 !
b110111 C
b11000 7
00
0/
11
#58010
b101011 2
#58990
b1101010 +
b1101010 >
b1011 (
b1011 <
b111001 *
b111001 =
b1010 '
b1010 ;
#59000
b110010 ,
b110010 "
b110010 B
b11010 6
10
1/
#59010
b101100 2
#60000
00
0/
01
#60990
b1100001 +
b1100001 >
b1010 (
b1010 <
b110000 *
b110000 =
b1011 '
b1011 ;
#61000
b110011 ,
b110011 "
b110011 B
b11011 6
10
1/
#61010
b101101 2
#62000
b111001 -
b111001 !
b111001 C
b11010 7
00
0/
11
#62010
b101110 2
#62990
b1100010 +
b1100010 >
b110001 *
b110001 =
b1100 '
b1100 ;
#63000
b110100 ,
b110100 "
b110100 B
b11100 6
10
1/
#63010
b101111 2
#64000
00
0/
01
#64990
b1100011 +
b1100011 >
b1011 (
b1011 <
b110010 *
b110010 =
b1101 '
b1101 ;
#65000
b110101 ,
b110101 "
b110101 B
b11101 6
10
1/
#65010
b110000 2
#66000
b110000 -
b110000 !
b110000 C
b11011 7
00
0/
11
#66010
b110001 2
#66990
b1100100 +
b1100100 >
b110011 *
b110011 =
b1110 '
b1110 ;
#67000
b110110 ,
b110110 "
b110110 B
b11110 6
10
1/
#67010
b110010 2
#68000
00
0/
01
#68990
b1100101 +
b1100101 >
b110100 *
b110100 =
b1111 '
b1111 ;
#69000
b110111 ,
b110111 "
b110111 B
b11111 6
10
1/
#69010
b110011 2
#70000
b1100011 -
b1100011 !
b1100011 C
00
0/
11
#70010
b110100 2
#70990
b1100110 +
b1100110 >
b1100 (
b1100 <
b110101 *
b110101 =
b0 '
b0 ;
03
#71000
b111001 ,
b111001 "
b111001 B
b0 6
10
1/
#71010
b110101 2
#72000
00
0/
01
#72990
b1100111 +
b1100111 >
b110110 *
b110110 =
13
#73000
b10000 6
10
1/
#73010
b110110 2
#74000
b110001 -
b110001 !
b110001 C
b11100 7
00
0/
11
#74010
b110111 2
#74990
b1101000 +
b1101000 >
b110111 *
b110111 =
b1 '
b1 ;
#75000
b110000 ,
b110000 "
b110000 B
b10001 6
10
1/
#75010
b111000 2
#76000
00
0/
01
#76990
b1101001 +
b1101001 >
b1101 (
b1101 <
b111000 *
b111000 =
b10 '
b10 ;
#77000
b110001 ,
b110001 "
b110001 B
b10010 6
10
1/
#77010
b111001 2
#78000
b110010 -
b110010 !
b110010 C
b11101 7
00
0/
11
#78010
b111010 2
#78990
b1101010 +
b1101010 >
b111001 *
b111001 =
b11 '
b11 ;
#79000
b110010 ,
b110010 "
b110010 B
b10011 6
10
1/
#79010
b111011 2
#80000
00
0/
01
#80990
b1100001 +
b1100001 >
b110000 *
b110000 =
b100 '
b100 ;
#81000
b110011 ,
b110011 "
b110011 B
b10100 6
10
1/
#81010
b111100 2
#82000
b1101001 -
b1101001 !
b1101001 C
00
0/
11
#82010
b111101 2
#82990
b1100010 +
b1100010 >
b1110 (
b1110 <
b110001 *
b110001 =
b101 '
b101 ;
#83000
b110100 ,
b110100 "
b110100 B
b10101 6
10
1/
#83010
b111110 2
#84000
00
0/
01
#84990
b1100011 +
b1100011 >
b110010 *
b110010 =
b110 '
b110 ;
#85000
b110101 ,
b110101 "
b110101 B
b10110 6
10
1/
#85010
b111111 2
#86000
b110011 -
b110011 !
b110011 C
b11110 7
00
0/
11
#86010
b1000000 2
#86990
b1100100 +
b1100100 >
b110011 *
b110011 =
b111 '
b111 ;
#87000
b110110 ,
b110110 "
b110110 B
b10111 6
10
1/
#87010
b1000001 2
#88000
00
0/
01
#88990
b1100101 +
b1100101 >
b1111 (
b1111 <
b110100 *
b110100 =
b1000 '
b1000 ;
#89000
b1101001 ,
b1101001 "
b1101001 B
b11000 6
10
1/
#89010
b1000010 2
#90000
b110100 -
b110100 !
b110100 C
b11111 7
00
0/
11
#90010
b1000011 2
#90990
b1100110 +
b1100110 >
b110101 *
b110101 =
b1001 '
b1001 ;
#91000
b111000 ,
b111000 "
b111000 B
b11001 6
10
1/
#91010
b1000100 2
#92000
00
0/
01
#92990
b1100111 +
b1100111 >
b110110 *
b110110 =
b1010 '
b1010 ;
#93000
b1100001 ,
b1100001 "
b1100001 B
b11010 6
10
1/
#93010
b1000101 2
#94000
b1100101 -
b1100101 !
b1100101 C
00
0/
11
#94010
b1000110 2
#94990
b1101000 +
b1101000 >
b0 (
b0 <
b110111 *
b110111 =
b1011 '
b1011 ;
#95000
b1100101 ,
b1100101 "
b1100101 B
b11011 6
10
1/
#95010
b1000111 2
#96000
00
0/
01
#96990
b1101001 +
b1101001 >
b111000 *
b111000 =
b1100 '
b1100 ;
#97000
b1100111 ,
b1100111 "
b1100111 B
b11100 6
10
1/
#97010
b1001000 2
#98000
b110110 -
b110110 !
b110110 C
b10000 7
00
0/
11
#98010
b1001001 2
#98990
b1110011 +
b1110011 >
b111001 *
b111001 =
b1101 '
b1101 ;
#99000
b1100001 ,
b1100001 "
b1100001 B
b11101 6
10
1/
#99010
b1001010 2
#100000
00
0/
01
#100990
b0 8
#101000
b111001 ,
b111001 "
b111001 B
10
1/
#101010
b1001011 2
#102000
b1101001 -
b1101001 !
b1101001 C
00
0/
11
#102010
b1001100 2
#102990
b1101 (
b1101 <
b1101001 +
b1101001 >
b1101 H
b100001 *
b100001 =
b1 '
b1 ;
03
b0 :
15
b11111111111111111111111111111111 8
#103000
b110111 ,
b110111 "
b110111 B
b1 6
10
1/
#103010
b1001101 2
#103190
b0 (
b0 <
b1111011 +
b1111011 >
b1 H
04
b1010010 *
b1010010 =
b1 :
#104000
00
0/
01
#104190
b111 (
b111 <
b100011 +
b100011 >
b111 H
14
b111111 *
b111111 =
b10 :
#104990
04
13
b0 (
b0 <
b1101111 +
b1101111 >
b0 H
b1010001 *
b1010001 =
b11 '
b11 ;
b100 :
#105000
b111001 ,
b111001 "
b111001 B
b10011 6
10
1/
#105010
b1001110 2
#105290
b1010 (
b1010 <
b1000101 +
b1000101 >
b1010 H
14
b1000110 *
b1000110 =
b1 '
b1 ;
03
b110 :
#105390
b1 (
b1 <
b111001 +
b111001 >
b0 H
04
b1011011 *
b1011011 =
b0 '
b0 ;
b111 :
#106000
b110111 -
b110111 !
b110111 C
b1 7
00
0/
11
#106010
b1001111 2
#106290
b110101 +
b110101 >
b1 H
b1000011 *
b1000011 =
b1000 :
#107000
b1110011 ,
b1110011 "
b1110011 B
b0 6
10
1/
#107010
b1010000 2
#107090
b1111100 +
b1111100 >
b1011010 *
b1011010 =
b1011 '
b1011 ;
13
b1001 :
#108000
00
0/
01
#108090
b1000 (
b1000 <
b1000010 +
b1000010 >
b1000 H
14
b1101101 *
b1101101 =
b0 '
b0 ;
03
b1010 :
#108390
b0 (
b0 <
b1001000 +
b1001000 >
b0 H
b1101001 *
b1101001 =
b1 '
b1 ;
b1011 :
#108490
b1 (
b1 <
b1011010 +
b1011010 >
b1 H
04
b1000100 *
b1000100 =
b0 '
b0 ;
b1100 :
#108990
b11 (
b11 <
b1101000 +
b1101000 >
b11 H
14
b1011010 *
b1011010 =
b1 '
b1 ;
b1101 :
#109000
b110111 ,
b110111 "
b110111 B
b1 6
10
1/
#109010
b1010001 2
#109190
b0 (
b0 <
b111000 +
b111000 >
b0 H
04
b101011 *
b101011 =
b1001 '
b1001 ;
13
b1110 :
#109490
b11 (
b11 <
b101000 +
b101000 >
b11 H
14
b100111 *
b100111 =
b0 '
b0 ;
03
b1111 :
#109790
b110 (
b110 <
b1100000 +
b1100000 >
b110 H
b1111101 *
b1111101 =
b100 '
b100 ;
13
b10000 :
#110000
b110010 -
b110010 !
b110010 C
b10110 7
00
0/
11
#110010
b1010010 2
#110390
b1111 (
b1111 <
b1100110 +
b1100110 >
b1111 H
b110010 *
b110010 =
b1010 '
b1010 ;
b10001 :
#110990
b1 (
b1 <
b111100 +
b111100 >
b0 H
04
b1101111 *
b1101111 =
b0 '
b0 ;
03
b10010 :
#111000
b1110011 ,
b1110011 "
b1110011 B
b0 6
10
1/
#111010
b1010011 2
#111390
b101010 +
b101010 >
b110011 *
b110011 =
b10011 :
#111690
b1011 (
b1011 <
b101110 +
b101110 >
b1011 H
14
b100000 *
b100000 =
b1 '
b1 ;
b10100 :
#112000
00
0/
01
#112690
b1 (
b1 <
b101100 +
b101100 >
b1 H
04
b1110101 *
b1110101 =
b110 '
b110 ;
13
b10101 :
#113000
b1100000 ,
b1100000 "
b1100000 B
b10110 6
10
1/
#113010
b1010100 2
#113190
b0 (
b0 <
b101000 +
b101000 >
b0 H
b1000001 *
b1000001 =
b1001 '
b1001 ;
b10110 :
#113590
b1001 (
b1001 <
b100101 +
b100101 >
b1001 H
14
b1010100 *
b1010100 =
b0 '
b0 ;
03
b10111 :
#114000
b110101 -
b110101 !
b110101 C
b11001 7
00
0/
11
#114010
b1010101 2
#114390
b0 (
b0 <
b1110010 +
b1110010 >
b1 H
04
b1100010 *
b1100010 =
b1 '
b1 ;
b11000 :
#115000
b110111 ,
b110111 "
b110111 B
b1 6
10
1/
#115010
b1010110 2
#115390
b110 (
b110 <
b1110011 +
b1110011 >
b110 H
14
b1000010 *
b1000010 =
b1010 '
b1010 ;
13
b11001 :
#115990
b0 (
b0 <
b1100111 +
b1100111 >
b0 H
04
b1111000 *
b1111000 =
b1 '
b1 ;
03
b11010 :
#116000
00
0/
01
#116390
b111 (
b111 <
b111110 +
b111110 >
b111 H
14
b1001110 *
b1001110 =
b1001 '
b1001 ;
13
b11011 :
#117000
b100101 ,
b100101 "
b100101 B
b11001 6
10
1/
#117010
b1010111 2
#117190
b0 (
b0 <
b1000100 +
b1000100 >
b1 H
b101001 *
b101001 =
b1 '
b1 ;
03
b11100 :
#117890
b1101110 +
b1101110 >
b0 H
04
b111001 *
b111001 =
b1100 '
b1100 ;
13
b11101 :
#118000
b1110011 -
b1110011 !
b1110011 C
b0 7
00
0/
11
#118010
b1011000 2
#118190
b1 (
b1 <
b111010 +
b111010 >
b111101 *
b111101 =
b0 '
b0 ;
03
b11110 :
