verilog_project/verilog_project/decoder/decoder.v
//easy-to-adjust-mode
module decoder(
    input  [2:0] in,
    output reg [7:0] out
);

integer i;
reg[7:0] J;
reg found;

always@(*) begin
found=0;

for (i = 0; i < 8; i++ ) begin

J=8'b0;
J[i]=1'b1;


if(!found && (in == i[2:0])) begin
out = J;
found = 1'b1;
end

else begin
out = out;
end

end
end

endmodule


//fast-mode(less logic-depth)
module decoder_fast(
    input  [2:0] in,
    output reg [7:0] out
);

 always @ ( * ) begin
        case (in)
            3'b000 : out = 8'b00000001;
            3'b001 : out = 8'b00000010;
            3'b010 : out = 8'b00000100;
            3'b011 : out = 8'b00001000;
            3'b100 : out = 8'b00010000;
            3'b101 : out = 8'b00100000;
            3'b110 : out = 8'b01000000;
            3'b111 : out = 8'b10000000;
        endcase
    end

endmodule

verilog_project/decoder/tb_decoder.v
`timescale 1ns/10ps

module tb_decoder;

//VECTORS FOR DUT
reg[2:0] IN;
wire[7:0] OUT;
wire[7:0] OUT_fast;
//VECTORS FOR TESTING

reg TICK;
integer FD, COUNT;
reg [8*31-1:0] COMMENT;
reg [7:0] OUT_EXPECTED;
reg [31:0] VECTORCOUNT, ERRORS;
int i;
reg [31:0] input_coverage [0:7];
reg eof;
reg [7:0]J;

//DUT INSTANTIATION

decoder dut_decoder (.in(IN), .out(OUT));
decoder_fast dut_decoder_fast (.in(IN), .out(OUT_fast));



//DUMP EVERYTHING INTO DUMPFILE

initial begin

$dumpfile ("tb_decoder.vcd");
$dumpvars (0, tb_decoder);

end

//TICKPERIOD

localparam TICKPERIOD = 20;

always begin

#(TICKPERIOD/2) TICK = ~TICK;

end



//TASKS

//task 1 initialize

task initialize; begin

FD = $fopen ("tb_decoder.tv" , "r");
COUNT = $fscanf (FD, "%s", COMMENT);

COUNT = $fscanf (FD, "%s %b %b", COMMENT, IN, OUT_EXPECTED);
TICK = 0;
VECTORCOUNT = 0;
ERRORS = 0;

for(i=0; i<8; i++)begin
input_coverage[i] = 0;
end

eof = 0;


$display ();
$display ("TEST_START-------------------------------------------------------------------------------------------------------------------------------------");
$display ();
$display ("                     | TIME | IN  |   OUT    | OUT_fast | OUT_EXPECTED |");
$display ("-----------------------------------------------------------------------------------------------------------------------------------------------");



end
endtask


//task 3 scan_file

task scan_file; begin

COUNT = $fscanf (FD, "%s %b %b", COMMENT, IN, OUT_EXPECTED);
eof = (COUNT == -1);

end
endtask

//task 4 random_in

task random_in; begin


IN =  $urandom %8;
COMMENT = "-";

# ($urandom_range(0.1,10));

end
endtask

//task5 OUT_EXP

task OUT_EXP; begin

reg found;
    found = 1'b0;   // 标记是否已经找到第一个1
     
    
    for (int j = 0; j < 8; j++) begin

     J=8'b0;
     J[j]=1'b1;
    
     if (!found && IN == j[2:0]) begin
            OUT_EXPECTED = J;
            found = 1'b1;  // 找到后再也不更新 out
        end
    end


end
endtask



//task 5 close

task close; begin

#10;

$fclose (FD);

$display ();
$display ("COVERAGE_REPORT");

for (int j = 0; j < 8; j++ ) begin


if(input_coverage[j] == 0) begin
$display ("input IN = %b has occured %d times ***ERROR***", j[2:0], input_coverage[j]);
ERRORS = ERRORS + 1;
end

else begin
$display ("input IN = %b has occured %d times", j[2:0], input_coverage[j]);
end

end


$display ();
$display ("VECTORCOUNT = %d", VECTORCOUNT);
$display ("ERRORS = %15d", ERRORS);
$display ();
$display ("TEST_END--------------------------------------------------------------------------------------------------------------------------");
$display ();

$finish;

end
endtask


//task 6 vectorcount

task vectorcount; begin

VECTORCOUNT = VECTORCOUNT + 1;

end
endtask


//task 7 display_file

task display_file; begin

$display ("%10d %9s | %3d | %2b  | %8b | %8b | %10b   |", VECTORCOUNT, COMMENT, $time, IN, OUT, OUT_fast, OUT_EXPECTED);

end
endtask

//task 8 coverage_update

task coverage_update; begin

input_coverage[IN]++;

end
endtask




//task 9 errors_warnings_check

task errors_warnings_check; begin


if (OUT !== OUT_EXPECTED) begin

$display ("***ERROR: OUT = %b, OUT_expected = %b", OUT, OUT_EXPECTED);
ERRORS = ERRORS + 1;

end

if (OUT_fast !== OUT_EXPECTED) begin

$display ("***ERROR: OUT_fast = %b, OUT_expected = %b", OUT_fast, OUT_EXPECTED);
ERRORS = ERRORS + 1;

end


end
endtask



//DRIVE

//0 initialize

initial begin

initialize;

end

//2 scan file on negedge TICK

always @ (negedge TICK) begin

#1.2;

if (!eof) begin

scan_file;

end
end



//3 check file on posedge TICK

always  @ (posedge TICK) begin

coverage_update;

#0.1;

OUT_EXP;
display_file;
errors_warnings_check;
vectorcount;

end



// eof

initial begin

wait (eof);

$display ();
$display("%13s ***time = %0d,eof ***","",$time);
$display ();

for (i = 0; i < 50; i++) begin


if (IN == 4'b1000)
begin

vectorcount;
close;

end

else begin

random_in;
end

end

close;

end


endmodule

verilog_project/decoder/tb_decoder.vcd
$date
	Wed Feb  4 02:35:17 2026
$end
$version
	Icarus Verilog
$end
$timescale
	10ps
$end
$scope module tb_decoder $end
$var wire 8 ! OUT_fast [7:0] $end
$var wire 8 " OUT [7:0] $end
$var parameter 32 # TICKPERIOD $end
$var reg 248 $ COMMENT [247:0] $end
$var reg 32 % ERRORS [31:0] $end
$var reg 3 & IN [2:0] $end
$var reg 8 ' J [7:0] $end
$var reg 8 ( OUT_EXPECTED [7:0] $end
$var reg 1 ) TICK $end
$var reg 32 * VECTORCOUNT [31:0] $end
$var reg 1 + eof $end
$var integer 32 , COUNT [31:0] $end
$var integer 32 - FD [31:0] $end
$var integer 32 . i [31:0] $end
$scope module dut_decoder $end
$var wire 3 / in [2:0] $end
$var reg 8 0 J [7:0] $end
$var reg 1 1 found $end
$var reg 8 2 out [7:0] $end
$var integer 32 3 i [31:0] $end
$upscope $end
$scope module dut_decoder_fast $end
$var wire 3 4 in [2:0] $end
$var reg 8 5 out [7:0] $end
$upscope $end
$scope task OUT_EXP $end
$scope begin $unm_blk_7 $end
$var reg 1 6 found $end
$scope begin $ivl_for_loop0 $end
$var integer 32 7 j [31:0] $end
$upscope $end
$upscope $end
$upscope $end
$scope task close $end
$scope begin $ivl_for_loop1 $end
$var integer 32 8 j [31:0] $end
$upscope $end
$upscope $end
$scope task coverage_update $end
$upscope $end
$scope task display_file $end
$upscope $end
$scope task errors_warnings_check $end
$upscope $end
$scope task initialize $end
$upscope $end
$scope task random_in $end
$upscope $end
$scope task scan_file $end
$upscope $end
$scope task vectorcount $end
$upscope $end
$upscope $end
$enddefinitions $end
$comment Show the parameter values. $end
$dumpall
b10100 #
$end
#0
$dumpvars
b0 8
b0 7
x6
b1 5
b0 4
b1000 3
b1 2
11
b10000000 0
b0 /
b1000 .
b10000000000000000000000000000011 -
b11 ,
0+
b0 *
0)
b1 (
bx '
b0 &
b0 %
b1001001010011100100100101010100 $
b1 "
b1 !
$end
#1000
1)
#1010
b1 *
b1000 7
b10000000 '
16
#2000
0)
#2120
b10 "
b10 2
b10000000 0
b1000 3
11
b10 !
b10 5
b10 (
b1 &
b1 /
b1 4
b101101 $
#3000
1)
#3010
b10 *
b10000000 '
b1000 7
16
#4000
0)
#4120
b100 "
b100 2
b10000000 0
b1000 3
11
b100 !
b100 5
b100 (
b10 &
b10 /
b10 4
#5000
1)
#5010
b11 *
b10000000 '
b1000 7
16
#6000
0)
#6120
b1000 "
b1000 2
b10000000 0
b1000 3
11
b1000 !
b1000 5
b1000 (
b11 &
b11 /
b11 4
#7000
1)
#7010
b100 *
b10000000 '
b1000 7
16
#8000
0)
#8120
b10000 "
b10000 2
b10000000 0
b1000 3
11
b10000 !
b10000 5
b10000 (
b100 &
b100 /
b100 4
#9000
1)
#9010
b101 *
b10000000 '
b1000 7
16
#10000
0)
#10120
b100000 "
b100000 2
b10000000 0
b1000 3
11
b100000 !
b100000 5
b100000 (
b101 &
b101 /
b101 4
#11000
1)
#11010
b110 *
b10000000 '
b1000 7
16
#12000
0)
#12120
b1000000 "
b1000000 2
b10000000 0
b1000 3
11
b1000000 !
b1000000 5
b1000000 (
b110 &
b110 /
b110 4
#13000
1)
#13010
b111 *
b10000000 '
b1000 7
16
#14000
0)
#14120
b10000000 "
b10000000 2
b10000000 0
b1000 3
11
b10000000 !
b10000000 5
b10000000 (
b111 &
b111 /
b111 4
#15000
1)
#15010
b1000 *
b10000000 '
b1000 7
16
#16000
0)
#16120
b0 ,
#17000
1)
#17010
b1001 *
b10000000 '
b1000 7
16
#18000
0)
#18120
b10000 "
b10000 2
b10000000 0
b1000 3
11
b10000 !
b10000 5
b100 &
b100 /
b100 4
b0 .
1+
b11111111111111111111111111111111 ,
#18320
b10 "
b10 2
b10000000 0
b1000 3
11
b10 !
b10 5
b1 &
b1 /
b1 4
b1 .
#18520
b100000 "
b100000 2
b10000000 0
b1000 3
11
b100000 !
b100000 5
b101 &
b101 /
b101 4
b10 .
#19000
1)
#19010
b1010 *
b100000 (
b10000000 '
b1000 7
16
#19320
b10 "
b10 2
b10000000 0
b1000 3
11
b10 !
b10 5
b1 &
b1 /
b1 4
b100 .
#19820
b1000000 "
b1000000 2
b10000000 0
b1000 3
11
b1000000 !
b1000000 5
b110 &
b110 /
b110 4
b101 .
#20000
0)
#20420
b100000 "
b100000 2
b10000000 0
b1000 3
11
b100000 !
b100000 5
b101 &
b101 /
b101 4
b110 .
#21000
1)
#21010
b1011 *
b10000000 '
b1000 7
16
#21220
b10 "
b10 2
b10000000 0
b1000 3
11
b10 !
b10 5
b1 &
b1 /
b1 4
b111 .
#21620
b100000 "
b100000 2
b10000000 0
b1000 3
11
b100000 !
b100000 5
b101 &
b101 /
b101 4
b1000 .
#21920
b1001 .
#22000
0)
#22120
b100 "
b100 2
b10000000 0
b1000 3
11
b100 !
b100 5
b10 &
b10 /
b10 4
b1010 .
#22920
b1011 .
#23000
1)
#23010
b1100 *
b100 (
b10000000 '
b1000 7
16
#23320
b1 "
b1 2
b10000000 0
b1000 3
11
b1 !
b1 5
b0 &
b0 /
b0 4
b1100 .
#23720
b10000 "
b10000 2
b10000000 0
b1000 3
11
b10000 !
b10000 5
b100 &
b100 /
b100 4
b1101 .
#24000
0)
#24120
b100000 "
b100000 2
b10000000 0
b1000 3
11
b100000 !
b100000 5
b101 &
b101 /
b101 4
b1110 .
#24320
b1000 "
b1000 2
b10000000 0
b1000 3
11
b1000 !
b1000 5
b11 &
b11 /
b11 4
b1111 .
#24820
b1 "
b1 2
b10000000 0
b1000 3
11
b1 !
b1 5
b0 &
b0 /
b0 4
b10000 .
#25000
1)
#25010
b1101 *
b1 (
b10000000 '
b1000 7
16
#25420
b100 "
b100 2
b10000000 0
b1000 3
11
b100 !
b100 5
b10 &
b10 /
b10 4
b10001 .
#25720
b100000 "
b100000 2
b10000000 0
b1000 3
11
b100000 !
b100000 5
b101 &
b101 /
b101 4
b10011 .
#25820
b1000 "
b1000 2
b10000000 0
b1000 3
11
b1000 !
b1000 5
b11 &
b11 /
b11 4
b10100 .
#26000
0)
#26220
b100 "
b100 2
b10000000 0
b1000 3
11
b100 !
b100 5
b10 &
b10 /
b10 4
b10101 .
#26520
b100000 "
b100000 2
b10000000 0
b1000 3
11
b100000 !
b100000 5
b101 &
b101 /
b101 4
b10110 .
#26920
b1000 "
b1000 2
b10000000 0
b1000 3
11
b1000 !
b1000 5
b11 &
b11 /
b11 4
b10111 .
#27000
1)
#27010
b1110 *
b1000 (
b10000000 '
b1000 7
16
#27420
b100 "
b100 2
b10000000 0
b1000 3
11
b100 !
b100 5
b10 &
b10 /
b10 4
b11000 .
#27520
b11001 .
#28000
0)
#28320
b10 "
b10 2
b10000000 0
b1000 3
11
b10 !
b10 5
b1 &
b1 /
b1 4
b11010 .
#28720
b1 "
b1 2
b10000000 0
b1000 3
11
b1 !
b1 5
b0 &
b0 /
b0 4
b11011 .
#28920
b1000 "
b1000 2
b10000000 0
b1000 3
11
b1000 !
b1000 5
b11 &
b11 /
b11 4
b11100 .
#29000
1)
#29010
b1111 *
b10000000 '
b1000 7
16
#29820
b1000000 "
b1000000 2
b10000000 0
b1000 3
11
b1000000 !
b1000000 5
b110 &
b110 /
b110 4
b11101 .
#30000
0)
#30720
b10000 "
b10000 2
b10000000 0
b1000 3
11
b10000 !
b10000 5
b100 &
b100 /
b100 4
b11110 .
#31000
1)
#31010
b10000 *
b10000 (
b10000000 '
b1000 7
16
#31320
b1000 "
b1000 2
b10000000 0
b1000 3
11
b1000 !
b1000 5
b11 &
b11 /
b11 4
b11111 .
#31520
b100000 "
b100000 2
b10000000 0
b1000 3
11
b100000 !
b100000 5
b101 &
b101 /
b101 4
b100000 .
#32000
0)
#32220
b1000 "
b1000 2
b10000000 0
b1000 3
11
b1000 !
b1000 5
b11 &
b11 /
b11 4
b100001 .
#32820
b1000000 "
b1000000 2
b10000000 0
b1000 3
11
b1000000 !
b1000000 5
b110 &
b110 /
b110 4
b100010 .
#33000
1)
#33010
b10001 *
b1000000 (
b10000000 '
b1000 7
16
#33320
b10 "
b10 2
b10000000 0
b1000 3
11
b10 !
b10 5
b1 &
b1 /
b1 4
b100011 .
#34000
0)
#34320
b100 "
b100 2
b10000000 0
b1000 3
11
b100 !
b100 5
b10 &
b10 /
b10 4
b100100 .
#35000
1)
#35010
b10010 *
b100 (
b10000000 '
b1000 7
16
#35020
b10000000 "
b10000000 2
b10000000 0
b1000 3
11
b10000000 !
b10000000 5
b111 &
b111 /
b111 4
b100101 .
#35820
b1 "
b1 2
b10000000 0
b1000 3
11
b1 !
b1 5
b0 &
b0 /
b0 4
b100110 .
#36000
0)
#36120
b10000000 "
b10000000 2
b10000000 0
b1000 3
11
b10000000 !
b10000000 5
b111 &
b111 /
b111 4
b100111 .
#36220
b1000 "
b1000 2
b10000000 0
b1000 3
11
b1000 !
b1000 5
b11 &
b11 /
b11 4
b101000 .
#37000
1)
#37010
b10011 *
b1000 (
b10000000 '
b1000 7
16
#37020
b10 "
b10 2
b10000000 0
b1000 3
11
b10 !
b10 5
b1 &
b1 /
b1 4
b101001 .
#37420
b10000000 "
b10000000 2
b10000000 0
b1000 3
11
b10000000 !
b10000000 5
b111 &
b111 /
b111 4
b101010 .
#37520
b1000000 "
b1000000 2
b10000000 0
b1000 3
11
b1000000 !
b1000000 5
b110 &
b110 /
b110 4
b101011 .
#38000
0)
#38020
b100 "
b100 2
b10000000 0
b1000 3
11
b100 !
b100 5
b10 &
b10 /
b10 4
b101100 .
#38920
b10000000 "
b10000000 2
b10000000 0
b1000 3
11
b10000000 !
b10000000 5
b111 &
b111 /
b111 4
b101101 .
#39000
1)
#39010
b10100 *
b10000000 (
b10000000 '
b1000 7
16
#39520
b100 "
b100 2
b10000000 0
b1000 3
11
b100 !
b100 5
b10 &
b10 /
b10 4
b101110 .
#39720
b100000 "
b100000 2
b10000000 0
b1000 3
11
b100000 !
b100000 5
b101 &
b101 /
b101 4
b101111 .
#40000
0)
#40320
b10000000 "
b10000000 2
b10000000 0
b1000 3
11
b10000000 !
b10000000 5
b111 &
b111 /
b111 4
b110000 .
#40720
b100000 "
b100000 2
b10000000 0
b1000 3
11
b100000 !
b100000 5
b101 &
b101 /
b101 4
b110001 .
#40920
b110010 .
#41000
1)
#41010
b10101 *
b100000 (
b10000000 '
b1000 7
16
#41920
b1000 8
