verilog_project/verilog_project/dual_port_ram_synchronous/dual_port_ram_synchronous.v
module dual_port_ram_synchronous(
input clk,

input we_a, //write enable
input [ADDR_WIDTH-1:0]addr_a,
input [DATA_WIDTH-1:0]data_in_a,
output reg [DATA_WIDTH-1:0]data_out_a,

input we_b, //write enable
input [ADDR_WIDTH-1:0]addr_b,
input [DATA_WIDTH-1:0]data_in_b,
output reg [DATA_WIDTH-1:0]data_out_b
);

parameter DATA_WIDTH = 8, ADDR_WIDTH = 4, MEM_DEPTH = 16;

reg [DATA_WIDTH-1:0]mem[MEM_DEPTH-1:0];


always@(posedge clk)begin

if(we_a)begin

mem[addr_a] <= data_in_a;
data_out_a <= mem[addr_a];

end

else begin
data_out_a <= mem[addr_a];
end

end


always@(posedge clk)begin

if(we_b)begin

mem[addr_b] <= data_in_b;
data_out_b <= mem[addr_b]; 

end

else begin
data_out_b <= mem[addr_b];
end

end


endmodule

verilog_project/verilog_project/dual_port_ram_synchronous/tb_dual_port_ram_synchronous.v
`timescale 1ns/10ps

module tb_dual_port_ram_synchronous;

//VECTORS FOR DUT
reg WE_A, WE_B;
reg [ADDR_WIDTH-1:0] ADDR_A, ADDR_B;
reg [DATA_WIDTH-1:0] DATA_IN_A, DATA_IN_B;
wire [DATA_WIDTH-1:0] DATA_OUT_A, DATA_OUT_B;

//VECTORS FOR TESTING

reg TICK;
integer FD, COUNT;
reg [8*31-1:0] COMMENT;
reg [DATA_WIDTH-1:0]DATA_OUT_A_EXPECTED,DATA_OUT_B_EXPECTED;
reg [DATA_WIDTH-1:0]DATA_OUT_A_EXPECTED1,DATA_OUT_B_EXPECTED1;
reg [31:0] VECTORCOUNT, ERRORS;
int i;
reg [31:0] input_coverage_TICKA[0:1];
reg [31:0] input_coverage_TICKB[0:1];
reg [31:0] input_coverage_a[0:5'b11111];
reg [31:0] input_coverage_b[0:5'b11111];
reg eof;
reg [4:0]prev_INPUT_A;
reg [4:0]prev_INPUT_B;
reg [DATA_WIDTH-1:0] MEM [0:MEM_DEPTH-1];

parameter DATA_WIDTH = 8, ADDR_WIDTH = 4, MEM_DEPTH = 16;


//DUT INSTANTIATION

dual_port_ram_synchronous dut_dual_port_ram_synchronous (.clk(TICK), .we_a(WE_A), .addr_a(ADDR_A), .data_in_a(DATA_IN_A), .data_out_a(DATA_OUT_A), .we_b(WE_B), .addr_b(ADDR_B), .data_in_b(DATA_IN_B), .data_out_b(DATA_OUT_B));


//DUMP EVERYTHING INTO DUMPFILE

initial begin

$dumpfile ("tb_dual_port_ram_synchronous.vcd");
$dumpvars (0, tb_dual_port_ram_synchronous);

end


//TICKPERIOD

localparam TICKPERIOD = 20;

always begin
#(TICKPERIOD/2) TICK <= ~TICK;
end


//TASKS

//task 1 initialize

task initialize; begin

FD = $fopen ("tb_dual_port_ram_synchronous.tv" , "r");
COUNT = $fscanf (FD, "%s", COMMENT);

COUNT = $fscanf (FD, "%s %b %b %s %b %b %s", COMMENT, WE_A, ADDR_A, DATA_IN_A, WE_B, ADDR_B, DATA_IN_B);
TICK = 0;
VECTORCOUNT = 0;
ERRORS = 0;

for(i=0; i<2; i++)begin
input_coverage_TICKA[i] = 0;
input_coverage_TICKB[i] = 0;
end

for(i=0; i<=5'b11111; i++)begin
if(i<2 || i>5'b01111)begin
input_coverage_a[i] = 0;
end
end


for(i=0; i<=5'b11111; i++)begin
if(i<2 || i>5'b01111)begin
input_coverage_b[i] = 0;
end
end


eof = 0;

$display ();
$display ("TEST_START--------------------------------------------------------------------------------------------------------------------------------------------------");
$display ();
$display ("                     | TIME | WE_A | ADDR_A | DATA_IN_A | DATA_OUT_A | DATA_OUT_A_EXPECTED | WE_B | ADDR_B | DATA_IN_B | DATA_OUT_B | DATA_OUT_B_EXPECTED |");
$display ("------------------------------------------------------------------------------------------------------------------------------------------------------------");


end
endtask


//task 3 scan_file

task scan_file; begin

COUNT = $fscanf (FD, "%s %b %b %s %b %b %s ", COMMENT, WE_A, ADDR_A, DATA_IN_A, WE_B, ADDR_B, DATA_IN_B);
eof = (COUNT == -1);

end
endtask

//task 4 random_in

task random_in; begin
reg[DATA_WIDTH-1:0] temp;

WE_A =  $urandom %2;
ADDR_A = (WE_A == 0)?$urandom %2 : $urandom %16;
DATA_IN_A = $urandom_range(32,126);

WE_B =  $urandom %2;
temp = (WE_B == 0)?$urandom %2 : $urandom %16;
DATA_IN_B = $urandom_range(32,126);

if(temp == ADDR_A)begin
if($urandom%2)begin
ADDR_B = (temp == MEM_DEPTH-1)? temp-1: temp+1;
end
else begin
ADDR_B = (temp == 0)? temp+1: temp-1;
end
end

else
ADDR_B = temp;

COMMENT = "-";

# ($urandom_range(0.1,10));

end
endtask



//task5 OUT_EXP

task OUT_EXP; begin

if(WE_A)begin
MEM[ADDR_A] <= DATA_IN_A;
DATA_OUT_A_EXPECTED <= MEM[ADDR_A];
end

else begin
DATA_OUT_A_EXPECTED <= MEM[ADDR_A];
end


if(WE_B)begin
MEM[ADDR_B] <= DATA_IN_B;
DATA_OUT_B_EXPECTED <= MEM[ADDR_B];
end

else begin
DATA_OUT_B_EXPECTED <= MEM[ADDR_B];
end


end
endtask



//task 5 close

task close; begin

#10;

$fclose (FD);

$display ();
$display ("COVERAGE_REPORT");
$display ();
$display ("1.for WE_A==0 and WE_B==0, only test two input combinations as others combination has identical behavior");
$display ();



for (int j = 0; j < 5'b11111; j++ ) begin

if(j<2 || j>5'b01111) begin

if(input_coverage_a[j] < 2) begin            // data in need to at least come across same address for 2 times to ensure data in is successfully written into the address
$display ("input WE_A = %b, ADDR_A = %b has occured %d times ***ERROR***", j[4], j[3:0], input_coverage_a[j]);
ERRORS = ERRORS + 1;
end


else begin
$display ("input WE_A = %b, ADDR_A = %b has occured %d times", j[4], j[3:0], input_coverage_a[j]);
end
end

else begin
//NOTHING
end
end




for (int j = 0; j < 5'b11111; j++ ) begin

if(j<2 || j>5'b01111) begin

if(input_coverage_b[j] < 2) begin
$display ("input WE_B = %b, ADDR_B = %b has occured %d times ***ERROR***", j[4], j[3:0], input_coverage_b[j]);
ERRORS = ERRORS + 1;
end


else begin
$display ("input WE_B = %b, ADDR_B = %b has occured %d times", j[4], j[3:0], input_coverage_b[j]);
end
end

else begin
//NOTHING
end
end



$display ();
$display ("VECTORCOUNT = %d", VECTORCOUNT);
$display ("ERRORS = %15d", ERRORS);
$display ();
$display ("TEST_END--------------------------------------------------------------------------------------------------------------------------");
$display ();

$finish;

end
endtask


//task 6 vectorcount

task vectorcount; begin

VECTORCOUNT = VECTORCOUNT + 1;

end
endtask


//task 7 display_file

task display_file; begin

$display ("%10d %9s | %4d | %2b   | %5b  | %5c     | %5c      | %10c          | %2b   | %5b  | %5c     | %5c      | %10c          |", VECTORCOUNT, COMMENT, $time, WE_A, ADDR_A, DATA_IN_A, DATA_OUT_A, DATA_OUT_A_EXPECTED, WE_B, ADDR_B, DATA_IN_B, DATA_OUT_B, DATA_OUT_B_EXPECTED);

end
endtask



//task 8 in_coverage_update

task in_coverage_update; begin

input_coverage_a[{WE_A,ADDR_A}]++;
input_coverage_b[{WE_B,ADDR_B}]++;

end
endtask


//task 9 errors_warnings_check

task errors_warnings_check; begin


if (DATA_OUT_A !== DATA_OUT_A_EXPECTED) begin

$display ("***ERROR: DATA_OUT_A = %b, DATA_OUT_A_expected = %b", DATA_OUT_A, DATA_OUT_A_EXPECTED);
ERRORS = ERRORS + 1;

end

if ({WE_A,ADDR_A} !== prev_INPUT_A) begin

$display ("***ERROR: INPUT_A - RACING CONDITION OCCUR");
ERRORS = ERRORS + 1;

end

if (DATA_OUT_B !== DATA_OUT_B_EXPECTED) begin

$display ("***ERROR: DATA_OUT_B = %b, DATA_OUT_B_expected = %b", DATA_OUT_B, DATA_OUT_B_EXPECTED);
ERRORS = ERRORS + 1;

end

if ({WE_B,ADDR_B} !== prev_INPUT_B) begin

$display ("***ERROR: INPUT_B - RACING CONDITION OCCUR");
ERRORS = ERRORS + 1;

end


end
endtask



//DRIVE

//0 initialize

initial begin

initialize;

end

//2 scan file on negedge TICK

always @ (negedge TICK) begin
#9.9;
if (!eof) begin

scan_file;

end
end


//3 check file on posedge TICK

always  @ (posedge TICK) begin
prev_INPUT_A = {WE_A,ADDR_A};
prev_INPUT_B = {WE_B,ADDR_B};
in_coverage_update;
OUT_EXP;

#0.1;
display_file;
errors_warnings_check;
vectorcount;


end



// eof

initial begin

wait (eof);

$display ();
$display("%13s ***time = %0d,eof ***","",$time);
$display ();

for (i = 0; i < 50; i++) begin


if (WE_A == 1'b0 && ADDR_A == 5'b10000 || WE_B == 1'b0 && ADDR_B == 5'b10000)
begin

vectorcount;
close;

end

else begin

random_in;
end

end

close;

end


endmodule

verilog_project/verilog_project/dual_port_ram_synchronous/tb_dual_port_ram_synchronous.vcd
$date
	Fri Feb 13 07:31:49 2026
$end
$version
	Icarus Verilog
$end
$timescale
	10ps
$end
$scope module tb_dual_port_ram_synchronous $end
$var wire 8 ! DATA_OUT_B [7:0] $end
$var wire 8 " DATA_OUT_A [7:0] $end
$var parameter 32 # ADDR_WIDTH $end
$var parameter 32 $ DATA_WIDTH $end
$var parameter 32 % MEM_DEPTH $end
$var parameter 32 & TICKPERIOD $end
$var reg 4 ' ADDR_A [3:0] $end
$var reg 4 ( ADDR_B [3:0] $end
$var reg 248 ) COMMENT [247:0] $end
$var reg 8 * DATA_IN_A [7:0] $end
$var reg 8 + DATA_IN_B [7:0] $end
$var reg 8 , DATA_OUT_A_EXPECTED [7:0] $end
$var reg 8 - DATA_OUT_B_EXPECTED [7:0] $end
$var reg 32 . ERRORS [31:0] $end
$var reg 1 / TICK $end
$var reg 32 0 VECTORCOUNT [31:0] $end
$var reg 1 1 WE_A $end
$var reg 1 2 WE_B $end
$var reg 1 3 eof $end
$var reg 5 4 prev_INPUT_A [4:0] $end
$var reg 5 5 prev_INPUT_B [4:0] $end
$var integer 32 6 COUNT [31:0] $end
$var integer 32 7 FD [31:0] $end
$var integer 32 8 i [31:0] $end
$scope module dut_dual_port_ram_synchronous $end
$var wire 4 9 addr_a [3:0] $end
$var wire 4 : addr_b [3:0] $end
$var wire 1 / clk $end
$var wire 8 ; data_in_a [7:0] $end
$var wire 8 < data_in_b [7:0] $end
$var wire 1 1 we_a $end
$var wire 1 2 we_b $end
$var parameter 32 = ADDR_WIDTH $end
$var parameter 32 > DATA_WIDTH $end
$var parameter 32 ? MEM_DEPTH $end
$var reg 8 @ data_out_a [7:0] $end
$var reg 8 A data_out_b [7:0] $end
$upscope $end
$scope task OUT_EXP $end
$upscope $end
$scope task close $end
$scope begin $ivl_for_loop0 $end
$var integer 32 B j [31:0] $end
$upscope $end
$scope begin $ivl_for_loop1 $end
$var integer 32 C j [31:0] $end
$upscope $end
$upscope $end
$scope task display_file $end
$upscope $end
$scope task errors_warnings_check $end
$upscope $end
$scope task in_coverage_update $end
$upscope $end
$scope task initialize $end
$upscope $end
$scope task random_in $end
$scope begin $unm_blk_10 $end
$var reg 8 D temp [7:0] $end
$upscope $end
$upscope $end
$scope task scan_file $end
$upscope $end
$scope task vectorcount $end
$upscope $end
$upscope $end
$enddefinitions $end
$comment Show the parameter values. $end
$dumpall
b10000 ?
b1000 >
b100 =
b10100 &
b10000 %
b1000 $
b100 #
$end
#0
$dumpvars
bx D
b0 C
b0 B
bx A
bx @
b1100001 <
b110000 ;
b1 :
b0 9
b100000 8
b10000000000000000000000000000011 7
b111 6
bx 5
bx 4
03
02
01
b0 0
0/
b0 .
bx -
bx ,
b1100001 +
b110000 *
b1001001010011100100100101010100 )
b1 (
b0 '
bx "
bx !
$end
#1000
b1 5
b0 4
1/
#1010
b1 0
#2000
0/
#2990
b1100010 +
b1100010 <
b110001 *
b110001 ;
b101101 )
#3000
1/
#3010
b10 0
#4000
0/
#4990
b1100011 +
b1100011 <
12
b110010 *
b110010 ;
11
#5000
b10001 5
b10000 4
1/
#5010
b11 0
#6000
0/
#6990
b1100100 +
b1100100 <
b10 (
b10 :
b110011 *
b110011 ;
b1 '
b1 9
#7000
b1100011 ,
b1100011 "
b1100011 @
b10010 5
b10001 4
1/
#7010
b100 0
#8000
0/
#8990
b1100101 +
b1100101 <
b11 (
b11 :
b110100 *
b110100 ;
b10 '
b10 9
#9000
b1100100 ,
b1100100 "
b1100100 @
b10011 5
b10010 4
1/
#9010
b101 0
#10000
0/
#10990
b1100110 +
b1100110 <
b100 (
b100 :
b110101 *
b110101 ;
b11 '
b11 9
#11000
b1100101 ,
b1100101 "
b1100101 @
b10100 5
b10011 4
1/
#11010
b110 0
#12000
0/
#12990
b1100111 +
b1100111 <
b101 (
b101 :
b110110 *
b110110 ;
b100 '
b100 9
#13000
b1100110 ,
b1100110 "
b1100110 @
b10101 5
b10100 4
1/
#13010
b111 0
#14000
0/
#14990
b1101000 +
b1101000 <
b110 (
b110 :
b110111 *
b110111 ;
b101 '
b101 9
#15000
b1100111 ,
b1100111 "
b1100111 @
b10110 5
b10101 4
1/
#15010
b1000 0
#16000
0/
#16990
b1101001 +
b1101001 <
b111 (
b111 :
b111000 *
b111000 ;
b110 '
b110 9
#17000
b1101000 ,
b1101000 "
b1101000 @
b10111 5
b10110 4
1/
#17010
b1001 0
#18000
0/
#18990
b1101010 +
b1101010 <
b1000 (
b1000 :
b111001 *
b111001 ;
b111 '
b111 9
#19000
b1101001 ,
b1101001 "
b1101001 @
b11000 5
b10111 4
1/
#19010
b1010 0
#20000
0/
#20990
b1100001 +
b1100001 <
b1001 (
b1001 :
b110000 *
b110000 ;
b1000 '
b1000 9
#21000
b1101010 ,
b1101010 "
b1101010 @
b11001 5
b11000 4
1/
#21010
b1011 0
#22000
0/
#22990
b1100010 +
b1100010 <
b1010 (
b1010 :
b110001 *
b110001 ;
b1001 '
b1001 9
#23000
b1100001 ,
b1100001 "
b1100001 @
b11010 5
b11001 4
1/
#23010
b1100 0
#24000
0/
#24990
b1100011 +
b1100011 <
b1011 (
b1011 :
b110010 *
b110010 ;
b1010 '
b1010 9
#25000
b1100010 ,
b1100010 "
b1100010 @
b11011 5
b11010 4
1/
#25010
b1101 0
#26000
0/
#26990
b1100100 +
b1100100 <
b1100 (
b1100 :
b110011 *
b110011 ;
b1011 '
b1011 9
#27000
b1100011 ,
b1100011 "
b1100011 @
b11100 5
b11011 4
1/
#27010
b1110 0
#28000
0/
#28990
b1100101 +
b1100101 <
b1101 (
b1101 :
b110100 *
b110100 ;
b1100 '
b1100 9
#29000
b1100100 ,
b1100100 "
b1100100 @
b11101 5
b11100 4
1/
#29010
b1111 0
#30000
0/
#30990
b1100110 +
b1100110 <
b1110 (
b1110 :
b110101 *
b110101 ;
b1101 '
b1101 9
#31000
b1100101 ,
b1100101 "
b1100101 @
b11110 5
b11101 4
1/
#31010
b10000 0
#32000
0/
#32990
b1100111 +
b1100111 <
b1111 (
b1111 :
b110110 *
b110110 ;
b1110 '
b1110 9
#33000
b1100110 ,
b1100110 "
b1100110 @
b11111 5
b11110 4
1/
#33010
b10001 0
#34000
0/
#34990
b1101000 +
b1101000 <
b0 (
b0 :
b110111 *
b110111 ;
b1111 '
b1111 9
#35000
b110010 -
b1100111 ,
b110010 !
b110010 A
b1100111 "
b1100111 @
b10000 5
b11111 4
1/
#35010
b10010 0
#36000
0/
#36990
b1101010 +
b1101010 <
b1 (
b1 :
b111001 *
b111001 ;
b0 '
b0 9
#37000
b110011 -
b1101000 ,
b1101000 "
b1101000 @
b110011 !
b110011 A
b10001 5
b10000 4
1/
#37010
b10011 0
#38000
0/
#38990
b1100001 +
b1100001 <
b10 (
b10 :
b110000 *
b110000 ;
b1 '
b1 9
#39000
b110100 -
b1101010 ,
b110100 !
b110100 A
b1101010 "
b1101010 @
b10010 5
b10001 4
1/
#39010
b10100 0
#40000
0/
#40990
b1100010 +
b1100010 <
b11 (
b11 :
b110001 *
b110001 ;
b10 '
b10 9
#41000
b110101 -
b1100001 ,
b1100001 "
b1100001 @
b110101 !
b110101 A
b10011 5
b10010 4
1/
#41010
b10101 0
#42000
0/
#42990
b1100011 +
b1100011 <
b100 (
b100 :
b110010 *
b110010 ;
b11 '
b11 9
#43000
b110110 -
b1100010 ,
b110110 !
b110110 A
b1100010 "
b1100010 @
b10100 5
b10011 4
1/
#43010
b10110 0
#44000
0/
#44990
b1100100 +
b1100100 <
b101 (
b101 :
b110011 *
b110011 ;
b100 '
b100 9
#45000
b110111 -
b1100011 ,
b1100011 "
b1100011 @
b110111 !
b110111 A
b10101 5
b10100 4
1/
#45010
b10111 0
#46000
0/
#46990
b1100101 +
b1100101 <
b110 (
b110 :
b110100 *
b110100 ;
b101 '
b101 9
#47000
b111000 -
b1100100 ,
b111000 !
b111000 A
b1100100 "
b1100100 @
b10110 5
b10101 4
1/
#47010
b11000 0
#48000
0/
#48990
b1100110 +
b1100110 <
b111 (
b111 :
b110101 *
b110101 ;
b110 '
b110 9
#49000
b111001 -
b1100101 ,
b1100101 "
b1100101 @
b111001 !
b111001 A
b10111 5
b10110 4
1/
#49010
b11001 0
#50000
0/
#50990
b1100111 +
b1100111 <
b1000 (
b1000 :
b110110 *
b110110 ;
b111 '
b111 9
#51000
b110000 -
b1100110 ,
b110000 !
b110000 A
b1100110 "
b1100110 @
b11000 5
b10111 4
1/
#51010
b11010 0
#52000
0/
#52990
b1101000 +
b1101000 <
b1001 (
b1001 :
b110111 *
b110111 ;
b1000 '
b1000 9
#53000
b110001 -
b1100111 ,
b1100111 "
b1100111 @
b110001 !
b110001 A
b11001 5
b11000 4
1/
#53010
b11011 0
#54000
0/
#54990
b1101001 +
b1101001 <
b1010 (
b1010 :
b111000 *
b111000 ;
b1001 '
b1001 9
#55000
b110010 -
b1101000 ,
b110010 !
b110010 A
b1101000 "
b1101000 @
b11010 5
b11001 4
1/
#55010
b11100 0
#56000
0/
#56990
b1101010 +
b1101010 <
b1011 (
b1011 :
b111001 *
b111001 ;
b1010 '
b1010 9
#57000
b110011 -
b1101001 ,
b1101001 "
b1101001 @
b110011 !
b110011 A
b11011 5
b11010 4
1/
#57010
b11101 0
#58000
0/
#58990
b1100001 +
b1100001 <
b1100 (
b1100 :
b110000 *
b110000 ;
b1011 '
b1011 9
#59000
b110100 -
b1101010 ,
b110100 !
b110100 A
b1101010 "
b1101010 @
b11100 5
b11011 4
1/
#59010
b11110 0
#60000
0/
#60990
b1100010 +
b1100010 <
b1101 (
b1101 :
b110001 *
b110001 ;
b1100 '
b1100 9
#61000
b110101 -
b1100001 ,
b1100001 "
b1100001 @
b110101 !
b110101 A
b11101 5
b11100 4
1/
#61010
b11111 0
#62000
0/
#62990
b1100011 +
b1100011 <
b1110 (
b1110 :
b110010 *
b110010 ;
b1101 '
b1101 9
#63000
b110110 -
b1100010 ,
b110110 !
b110110 A
b1100010 "
b1100010 @
b11110 5
b11101 4
1/
#63010
b100000 0
#64000
0/
#64990
b1100100 +
b1100100 <
b1111 (
b1111 :
b110011 *
b110011 ;
b1110 '
b1110 9
#65000
b110111 -
b1100011 ,
b1100011 "
b1100011 @
b110111 !
b110111 A
b11111 5
b11110 4
1/
#65010
b100001 0
#66000
0/
#66990
b1100101 +
b1100101 <
b0 (
b0 :
b110100 *
b110100 ;
b1111 '
b1111 9
#67000
b111001 -
b1100100 ,
b111001 !
b111001 A
b1100100 "
b1100100 @
b10000 5
b11111 4
1/
#67010
b100010 0
#68000
0/
#68990
b1101 (
b1101 :
b1101001 +
b1101001 <
b1101 D
b100001 *
b100001 ;
b1 '
b1 9
01
b0 8
13
b11111111111111111111111111111111 6
#69000
b110010 -
b110000 ,
b110000 "
b110000 @
b110010 !
b110010 A
b11101 5
b1 4
1/
#69010
b100011 0
#69190
b0 (
b0 :
b1111011 +
b1111011 <
b1 D
02
b1010010 *
b1010010 ;
b1 8
#70000
0/
#70190
b111 (
b111 :
b100011 +
b100011 <
b111 D
12
b111111 *
b111111 ;
b10 8
#70990
02
11
b0 (
b0 :
b1101111 +
b1101111 <
b0 D
b1010001 *
b1010001 ;
b11 '
b11 9
b100 8
#71000
b1100101 -
b110010 ,
b1100101 !
b1100101 A
b110010 "
b110010 @
b0 5
b10011 4
1/
#71010
b100100 0
#71290
b1010 (
b1010 :
b1000101 +
b1000101 <
b1010 D
12
b1000110 *
b1000110 ;
b1 '
b1 9
01
b110 8
#71390
b1 (
b1 :
b111001 +
b111001 <
b0 D
02
b1011011 *
b1011011 ;
b0 '
b0 9
b111 8
#72000
0/
#72290
b110101 +
b110101 <
b1 D
b1000011 *
b1000011 ;
b1000 8
#73000
b110000 -
b1100101 ,
b1100101 "
b1100101 @
b110000 !
b110000 A
b1 5
b0 4
1/
#73010
b100101 0
#73090
b1111100 +
b1111100 <
b1011010 *
b1011010 ;
b1011 '
b1011 9
11
b1001 8
#74000
0/
#74090
b1000 (
b1000 :
b1000010 +
b1000010 <
b1000 D
12
b1101101 *
b1101101 ;
b0 '
b0 9
01
b1010 8
#74390
b0 (
b0 :
b1001000 +
b1001000 <
b0 D
b1101001 *
b1101001 ;
b1 '
b1 9
b1011 8
#74490
b1 (
b1 :
b1011010 +
b1011010 <
b1 D
02
b1000100 *
b1000100 ;
b0 '
b0 9
b1100 8
#74990
b11 (
b11 :
b1101000 +
b1101000 <
b11 D
12
b1011010 *
b1011010 ;
b1 '
b1 9
b1101 8
#75000
b1010001 -
b110000 ,
b1010001 !
b1010001 A
b110000 "
b110000 @
b10011 5
b1 4
1/
#75010
b100110 0
#75190
b0 (
b0 :
b111000 +
b111000 <
b0 D
02
b101011 *
b101011 ;
b1001 '
b1001 9
11
b1110 8
#75490
b11 (
b11 :
b101000 +
b101000 <
b11 D
12
b100111 *
b100111 ;
b0 '
b0 9
01
b1111 8
#75790
b110 (
b110 :
b1100000 +
b1100000 <
b110 D
b1111101 *
b1111101 ;
b100 '
b100 9
11
b10000 8
#76000
0/
#76390
b1111 (
b1111 :
b1100110 +
b1100110 <
b1111 D
b110010 *
b110010 ;
b1010 '
b1010 9
b10001 8
#76990
b1 (
b1 :
b111100 +
b111100 <
b0 D
02
b1101111 *
b1101111 ;
b0 '
b0 9
01
b10010 8
#77000
b110000 -
b1100101 ,
b1100101 "
b1100101 @
b110000 !
b110000 A
b1 5
b0 4
1/
#77010
b100111 0
#77390
b101010 +
b101010 <
b110011 *
b110011 ;
b10011 8
#77690
b1011 (
b1011 :
b101110 +
b101110 <
b1011 D
12
b100000 *
b100000 ;
b1 '
b1 9
b10100 8
#78000
0/
#78690
b1 (
b1 :
b101100 +
b101100 <
b1 D
02
b1110101 *
b1110101 ;
b110 '
b110 9
11
b10101 8
#79000
b110101 ,
b110101 "
b110101 @
b10110 4
1/
#79010
b101000 0
#79190
b0 (
b0 :
b101000 +
b101000 <
b0 D
b1000001 *
b1000001 ;
b1001 '
b1001 9
b10110 8
#79590
b1001 (
b1001 :
b100101 +
b100101 <
b1001 D
12
b1010100 *
b1010100 ;
b0 '
b0 9
01
b10111 8
#80000
0/
#80390
b0 (
b0 :
b1110010 +
b1110010 <
b1 D
02
b1100010 *
b1100010 ;
b1 '
b1 9
b11000 8
#81000
b1100101 -
b110000 ,
b110000 "
b110000 @
b1100101 !
b1100101 A
b0 5
b1 4
1/
#81010
b101001 0
#81390
b110 (
b110 :
b1110011 +
b1110011 <
b110 D
12
b1000010 *
b1000010 ;
b1010 '
b1010 9
11
b11001 8
#81990
b0 (
b0 :
b1100111 +
b1100111 <
b0 D
02
b1111000 *
b1111000 ;
b1 '
b1 9
01
b11010 8
#82000
0/
#82390
b111 (
b111 :
b111110 +
b111110 <
b111 D
12
b1001110 *
b1001110 ;
b1001 '
b1001 9
11
b11011 8
#83000
b110110 -
b111000 ,
b110110 !
b110110 A
b111000 "
b111000 @
b10111 5
b11001 4
1/
#83010
b101010 0
#83190
b0 (
b0 :
b1000100 +
b1000100 <
b1 D
b101001 *
b101001 ;
b1 '
b1 9
01
b11100 8
#83890
b1101110 +
b1101110 <
b0 D
02
b111001 *
b111001 ;
b1100 '
b1100 9
11
b11101 8
#84000
0/
#84190
b1 (
b1 :
b111010 +
b111010 <
b111101 *
b111101 ;
b0 '
b0 9
01
b11110 8
#84290
b1011 (
b1011 :
b1000101 +
b1000101 <
b1011 D
12
b1110101 *
b1110101 ;
b1000 '
b1000 9
11
b11111 8
#85000
b110000 -
b110111 ,
b110111 "
b110111 @
b110000 !
b110000 A
b11011 5
b11000 4
1/
#85010
b101011 0
#85190
b1 (
b1 :
b1100111 +
b1100111 <
b0 D
02
b1110001 *
b1110001 ;
b0 '
b0 9
01
b100000 8
#86000
0/
#86190
b1110101 +
b1110101 <
b1000011 *
b1000011 ;
b100001 8
#86490
b1001 (
b1001 :
b1011001 +
b1011001 <
b1001 D
12
b100010 *
b100010 ;
b1 '
b1 9
b100010 8
#86690
b1 (
b1 :
b1101010 +
b1101010 <
b1 D
02
b1101000 *
b1101000 ;
b1011 '
b1011 9
11
b100011 8
#87000
b1000101 ,
b1000101 "
b1000101 @
b1 5
b11011 4
1/
#87010
b101100 0
#87290
b1111011 +
b1111011 <
b1000100 *
b1000100 ;
b100100 8
#87890
b1000 (
b1000 :
b1011111 +
b1011111 <
b1000 D
12
b101100 *
b101100 ;
b110 '
b110 9
b100101 8
#87990
b1010010 +
b1010010 <
b100000 *
b100000 ;
b10 '
b10 9
b100110 8
#88000
0/
#88290
b1 (
b1 :
b1110100 +
b1110100 <
b1 D
b111101 *
b111101 ;
b101 '
b101 9
b100111 8
#88890
01
b1011 (
b1011 :
b1111101 +
b1111101 <
b1011 D
12
b1011111 *
b1011111 ;
b1 '
b1 9
b101001 8
#89000
b1101000 -
b110000 ,
b110000 "
b110000 @
b1101000 !
b1101000 A
b11011 5
b1 4
1/
#89010
b101101 0
#89790
b1001 (
b1001 :
b101101 +
b101101 <
b1001 D
b111111 *
b111111 ;
b100 '
b100 9
11
b101010 8
#90000
0/
#90790
b0 (
b0 :
b101100 +
b101100 <
b0 D
02
b111101 *
b111101 ;
b1 '
b1 9
b101011 8
#91000
b1100101 -
b1100101 !
b1100101 A
b0 5
b10001 4
1/
#91010
b101110 0
#91590
b1 (
b1 :
b1101000 +
b1101000 <
b1 D
b1001111 *
b1001111 ;
b0 '
b0 9
01
b101100 8
#92000
0/
#92590
b1110011 +
b1110011 <
b100111 *
b100111 ;
b101101 8
#93000
b111101 -
b1100101 ,
b1100101 "
b1100101 @
b111101 !
b111101 A
b1 5
b0 4
1/
#93010
b101111 0
#93390
b1010011 +
b1010011 <
b0 D
b1011010 *
b1011010 ;
11
b101110 8
#93990
b111010 +
b111010 <
b1 D
12
b111000 *
b111000 ;
b1001 '
b1001 9
b101111 8
#94000
0/
#94090
b1011 (
b1011 :
b1110001 +
b1110001 <
b1011 D
b1010001 *
b1010001 ;
b1100 '
b1100 9
b110000 8
#94590
b1 (
b1 :
b1100100 +
b1100100 <
b0 D
02
b1011111 *
b1011111 ;
b0 '
b0 9
01
b110001 8
#95000
1/
#95010
b110000 0
#95590
b110010 8
#96000
0/
#96590
b11111 C
b11111 B
