verilog_project/d_flip_flop/d_flip_flop.v
// A d (delay) flip-flop which is pulse-triggered can be set and reset.

module d_flip_flop_gate (
    input       clk,        // Clock
    input       clk1,
    input       d,          //
    output      q,          // Output
    output      qbar
);

     

    // INTERNAL WIRES
    wire   s, r, s1, r1;
    
    assign s = d;
    assign r = ~d;
    

    // NAND3
    nand (s1, s, clk);

    // NAND4
    nand (r1, r, clk);

    // SR- LATCH -------------------------------------

    // NAND1
    nand (q, s1, qbar);

    // NAND2
    nand (qbar, r1, q);



endmodule



module d_flip_flop_dataflow(
    input       clk,        // Clock
    input       d,          //
    output      q,          // Output
    output      qbar);      //


    // INTERNAL WIRES
    wire   s, r, s1, r1;
    
    assign s = d;
    assign r = ~d;
    
    // NAND3
    assign s1 = ~(s & clk);

    // NAND4
    assign r1 = ~(r & clk);

    // SR- LATCH -------------------------------------

    // NAND1
    assign q = ~(s1 & qbar);

    // NAND2
    assign qbar = ~(r1 & q);


endmodule

module d_flip_flop_behavioral (
    input        clk,        // Clock
    input        d,          //
    output reg   q,          // Output
    output wire  qbar
);      

assign qbar = ~q;

always @ ( posedge clk ) begin

    case ( d )

    1'b0: q = 1'b0;
    1'b1: q = 1'b1;

    endcase
end




endmodule

verilog_project/verilog_project/d_flip_flop/tb_d_flip_flop.v
`timescale 1ns/10ps

module tb_d_flip_flop;

//VECTORS FOR DUT
reg D;
wire Q_gate, Q_data, Q_beh, QBAR_gate, QBAR_data, QBAR_beh;

//VECTORS FOR TESTING

reg TICK;
integer FD, COUNT;
reg [8*9-1:0] COMMENT;
reg [8*9-1:0] COMMENT1;
reg [8*9-1:0] COMMENT2;
reg QEXPECTED, QBAREXPECTED;
reg [31:0] VECTORCOUNT, ERRORS;
int i;
reg [31:0] input_coverage [0:3];
reg eof;
reg prev_D;
reg prev_QEx;
reg prev_QExbar;


//DUT INSTANTIATION

d_flip_flop_gate dut_d_flip_flop_gate (.d(D), .q(Q_gate), .qbar(QBAR_gate), .clk(TICK));
d_flip_flop_dataflow dut_d_flip_flop_dataflow (.d(D), .q(Q_data), .qbar(QBAR_data), .clk(TICK));
d_flip_flop_behavioral dut_d_flip_flop_behavioral (.d(D), .q(Q_beh), .qbar(QBAR_beh), .clk(TICK));



//DUMP EVERYTHING INTO DUMPFILE

initial begin

$dumpfile ("tb_d_flip_flop.vcd");
$dumpvars (0, tb_d_flip_flop);

end

//TICKPERIOD

localparam TICKPERIOD = 20;

always begin

#(TICKPERIOD/2) TICK = ~TICK;

end



//TASKS

//task 1 initialize

task initialize; begin

FD = $fopen ("tb_d_flip_flop.tv" , "r");
COUNT = $fscanf (FD, "%s", COMMENT);

COUNT = $fscanf (FD, "%s %b %s %s", COMMENT, D, COMMENT1, COMMENT2);
TICK = 0;
VECTORCOUNT = 0;
ERRORS = 0;

for ( i = 0 ; i < 4 ; i++ ) begin
input_coverage[i] = 0;
end

eof = 0;

$display ();
$display ("TEST_START------------------------------------------------------------------------------------------------------------------------");
$display ();
$display ("                     | TIME | D |  Q_gate  |  Q_data  |  Q_beh  | QBAR_gate | QBAR_data | QEXPECTED | QBAREXPECTED |");
$display ("----------------------------------------------------------------------------------------------------------------------------------");



end
endtask



//task 2 scan_file

task scan_file; begin


COUNT = $fscanf (FD,"%s %b %b %b", COMMENT, D, QEXPECTED, QBAREXPECTED);
eof = (COUNT == -1);

end
endtask

//task 3 random_in

task random_in; begin

D =  $urandom %2 ;

case (D)
1'b0: COMMENT = "RESET";
1'b1: COMMENT = "SET";

endcase

#($urandom_range (0.1,10));

end
endtask

//task 4 QEXP

task QEXP; begin


case ( D )
  1'b0: begin
QEXPECTED = 1'b0;
QBAREXPECTED = 1'b1;
end
  1'b1: begin
QEXPECTED = 1'b1;
QBAREXPECTED = 1'b0;
end


endcase




end
endtask



//task 5 close

task close; begin

#10;
$fclose (FD);

$display ();
$display ("COVERAGE_REPORT");

for ( i = 0; i < 4; i++ ) begin

if(input_coverage[i] == 0) begin

$display ("input %b to input %b has occured %d times (***ERROR***)",i[1], i[0], input_coverage[i]);
ERRORS = ERRORS +1;

end

else begin

$display ("input %b to input %b has occured %d times",i[1], i[0], input_coverage[i]);

end

end

$display ();
$display ("VECTORCOUNT = %d", VECTORCOUNT);
$display ("ERRORS = %15d", ERRORS);
$display ();
$display ("TEST_END--------------------------------------------------------------------------------------------------------------------------");
$display ();

$finish;

end
endtask

//task 6 vectorcount

task vectorcount; begin

VECTORCOUNT = VECTORCOUNT + 1;

end
endtask

//task 7 display_file

task display_file; begin

$display ("%10d %9s | %4d | %1d | %4d     | %4d     | %4d    | %5d     | %5d     | %5d     | %6d       |", VECTORCOUNT, COMMENT, $time, D, Q_gate, Q_data, Q_beh, QBAR_gate, QBAR_data, QEXPECTED, QBAREXPECTED);

end
endtask

//task 8 coverage_update

task coverage_update; begin

input_coverage[{prev_D, D}]++;

end
endtask

//task 10 errors_check

task errors_check; begin


if (Q_gate !== QEXPECTED) begin

$display ("***ERROR: Q_gate = %b, Q_expected = %b", Q_gate, QEXPECTED);
ERRORS = ERRORS + 1;

end

if (Q_data !== QEXPECTED) begin

$display ("***ERROR: Q_dataflow = %b, Q_expected = %b", Q_data, QEXPECTED);
ERRORS = ERRORS + 1;

end

if (Q_beh !== QEXPECTED) begin

$display ("***ERROR: Q_behavioral = %b, Q_expected = %b", Q_beh, QEXPECTED);
ERRORS = ERRORS + 1;

end

if (QBAR_gate !== QBAREXPECTED) begin

$display ("***ERROR: QBAR_gate = %b, QBAR_expected = %b", QBAR_gate, QBAREXPECTED);
ERRORS = ERRORS + 1;

end

if (QBAR_data !== QBAREXPECTED) begin

$display ("***ERROR: QBAR_dataflow = %b, QBAR_expected = %b", QBAR_data, QBAREXPECTED);
ERRORS = ERRORS + 1;

end

if ( D !== prev_D ) begin

$display ("***ERROR: Racing Condition Occur");
ERRORS = ERRORS + 1;

end


end
endtask



//DRIVE

//0 initialize

initial begin

initialize;

end


//2 scan file on negedge TICK

always @ (negedge TICK) begin


#1.2;

if (!eof) begin



scan_file;

end
end



//3 check file on posedge TICK

always  @ (posedge TICK) begin

coverage_update;
prev_D = D;

#0.1;

QEXP;
display_file;
errors_check;
vectorcount;

#0.1;

prev_QEx = QEXPECTED;
prev_QExbar = QBAREXPECTED;



end



// eof

initial begin

wait (eof);

$display ();
$display("%13s ***time = %0d,eof ***","",$time);
$display ();

for (i = 0; i < 50; i++) begin


if ( D == 2)
begin

vectorcount;
close;

end

else begin

random_in;

end
end


close;

end


endmodule

verilog_project/d_flip_flop/tb_d_flip_flop.vcd
$date
	Tue Jan 13 18:08:52 2026
$end
$version
	Icarus Verilog
$end
$timescale
	10ps
$end
$scope module tb_d_flip_flop $end
$var wire 1 ! Q_gate $end
$var wire 1 " Q_data $end
$var wire 1 # Q_beh $end
$var wire 1 $ QBAR_gate $end
$var wire 1 % QBAR_data $end
$var wire 1 & QBAR_beh $end
$var parameter 32 ' TICKPERIOD $end
$var reg 72 ( COMMENT [71:0] $end
$var reg 72 ) COMMENT1 [71:0] $end
$var reg 72 * COMMENT2 [71:0] $end
$var reg 1 + D $end
$var reg 32 , ERRORS [31:0] $end
$var reg 1 - QBAREXPECTED $end
$var reg 1 . QEXPECTED $end
$var reg 1 / TICK $end
$var reg 32 0 VECTORCOUNT [31:0] $end
$var reg 1 1 eof $end
$var reg 1 2 prev_D $end
$var reg 1 3 prev_QEx $end
$var reg 1 4 prev_QExbar $end
$var integer 32 5 COUNT [31:0] $end
$var integer 32 6 FD [31:0] $end
$var integer 32 7 i [31:0] $end
$scope module dut_d_flip_flop_behavioral $end
$var wire 1 / clk $end
$var wire 1 + d $end
$var wire 1 & qbar $end
$var reg 1 # q $end
$upscope $end
$scope module dut_d_flip_flop_dataflow $end
$var wire 1 / clk $end
$var wire 1 + d $end
$var wire 1 " q $end
$var wire 1 % qbar $end
$var wire 1 8 r $end
$var wire 1 9 r1 $end
$var wire 1 : s $end
$var wire 1 ; s1 $end
$upscope $end
$scope module dut_d_flip_flop_gate $end
$var wire 1 / clk $end
$var wire 1 < clk1 $end
$var wire 1 + d $end
$var wire 1 ! q $end
$var wire 1 $ qbar $end
$var wire 1 = r $end
$var wire 1 > r1 $end
$var wire 1 ? s $end
$var wire 1 @ s1 $end
$upscope $end
$scope task QEXP $end
$upscope $end
$scope task close $end
$upscope $end
$scope task coverage_update $end
$upscope $end
$scope task display_file $end
$upscope $end
$scope task errors_check $end
$upscope $end
$scope task initialize $end
$upscope $end
$scope task random_in $end
$upscope $end
$scope task scan_file $end
$upscope $end
$scope task vectorcount $end
$upscope $end
$upscope $end
$enddefinitions $end
$comment Show the parameter values. $end
$dumpall
b10100 '
$end
#0
$dumpvars
1@
0?
1>
1=
z<
1;
0:
19
18
b100 7
b10000000000000000000000000000011 6
b100 5
x4
x3
x2
01
b0 0
0/
x.
x-
b0 ,
0+
b1011000 *
b1011000 )
b1001001010011100100100101010100 (
x&
x%
x$
x#
x"
x!
$end
#1000
0"
1%
0!
1&
09
1$
02
0#
0>
1/
#1010
b1 0
1-
0.
#1020
14
03
#2000
19
1>
0/
#2120
b101001001000101010100110100010101010100 (
#3000
09
0>
1/
#3010
b10 0
#4000
19
1>
0/
#5000
09
0>
1/
#5010
b11 0
#6000
19
1>
0/
#6120
08
0=
0-
1.
1:
1?
1+
b10100110100010101010100 (
#7000
0%
1"
0$
0&
0;
1!
12
1#
0@
1/
#7010
b100 0
#7020
04
13
#8000
1;
1@
0/
#9000
0;
0@
1/
#9010
b101 0
#10000
1;
1@
0/
#10120
18
1=
1-
0.
0:
0?
0+
b101001001000101010100110100010101010100 (
#11000
0"
1%
0!
1&
09
1$
02
0#
0>
1/
#11010
b110 0
#11020
14
03
#12000
19
1>
0/
#12120
08
0=
0-
1.
1:
1?
1+
b10100110100010101010100 (
#13000
0%
1"
0$
0&
0;
1!
12
1#
0@
1/
#13010
b111 0
#13020
04
13
#14000
1;
1@
0/
#15000
0;
0@
1/
#15010
b1000 0
#16000
1;
1@
0/
#16120
b0 5
#17000
0;
0@
1/
#17010
b1001 0
#18000
1;
1@
0/
#18120
18
1=
b101001001000101010100110100010101010100 (
0:
0?
0+
b0 7
11
b11111111111111111111111111111111 5
#18320
08
0=
b10100110100010101010100 (
1:
1?
1+
b1 7
#18520
b10 7
#19000
0;
0@
1/
#19010
b1010 0
#19320
b100 7
#19820
0"
1%
0!
09
1$
1;
0>
18
1@
1=
b101001001000101010100110100010101010100 (
0:
0?
0+
b101 7
#20000
19
1>
0/
#20420
08
0=
b10100110100010101010100 (
1:
1?
1+
b110 7
#21000
0%
1"
0$
0;
1!
0@
1/
#21010
b1011 0
#21220
b111 7
#21620
b1000 7
#21920
b1001 7
#22000
1;
1@
0/
#22120
18
1=
b101001001000101010100110100010101010100 (
0:
0?
0+
b1010 7
#22920
b1011 7
#23000
0"
1%
0!
1&
09
1$
02
0#
0>
1/
#23010
b1100 0
1-
0.
#23020
14
03
#23320
b1100 7
#23720
b1101 7
#24000
19
1>
0/
#24120
08
0=
b10100110100010101010100 (
1:
1?
1+
b1110 7
#24320
b1111 7
#24820
18
1=
b101001001000101010100110100010101010100 (
0:
0?
0+
b10000 7
#25000
09
0>
1/
#25010
b1101 0
#25420
b10001 7
#25720
0%
1"
19
0$
0;
1!
1>
08
0@
0=
b10100110100010101010100 (
1:
1?
1+
b10011 7
#25820
b10100 7
#26000
1;
1@
0/
#26220
18
1=
b101001001000101010100110100010101010100 (
0:
0?
0+
b10101 7
#26520
08
0=
b10100110100010101010100 (
1:
1?
1+
b10110 7
#26920
b10111 7
#27000
0&
0;
12
1#
0@
1/
#27010
b1110 0
0-
1.
#27020
04
13
#27420
0"
1%
0!
09
1$
1;
0>
18
1@
1=
b101001001000101010100110100010101010100 (
0:
0?
0+
b11000 7
#27520
b11001 7
#28000
19
1>
0/
#28320
08
0=
b10100110100010101010100 (
1:
1?
1+
b11010 7
#28720
18
1=
b101001001000101010100110100010101010100 (
0:
0?
0+
b11011 7
#28920
08
0=
b10100110100010101010100 (
1:
1?
1+
b11100 7
#29000
0%
1"
0$
0;
1!
0@
1/
#29010
b1111 0
#29820
0"
1%
0!
09
1$
1;
0>
18
1@
1=
b101001001000101010100110100010101010100 (
0:
0?
0+
b11101 7
#30000
19
1>
0/
#30720
b11110 7
#31000
1&
09
02
0#
0>
1/
#31010
b10000 0
1-
0.
#31020
14
03
#31320
0%
1"
19
0$
0;
1!
1>
08
0@
0=
b10100110100010101010100 (
1:
1?
1+
b11111 7
#31520
b100000 7
#32000
1;
1@
0/
#32220
b100001 7
#32820
18
1=
b101001001000101010100110100010101010100 (
0:
0?
0+
b100010 7
#33000
0"
1%
0!
09
1$
0>
1/
#33010
b10001 0
#33320
0%
1"
19
0$
0;
1!
1>
08
0@
0=
b10100110100010101010100 (
1:
1?
1+
b100011 7
#34000
1;
1@
0/
#34320
18
1=
b101001001000101010100110100010101010100 (
0:
0?
0+
b100100 7
#35000
0"
1%
0!
09
1$
0>
1/
#35010
b10010 0
#35020
0%
1"
19
0$
0;
1!
1>
08
0@
0=
b10100110100010101010100 (
1:
1?
1+
b100101 7
#35820
0"
1%
0!
09
1$
1;
0>
18
1@
1=
b101001001000101010100110100010101010100 (
0:
0?
0+
b100110 7
#36000
19
1>
0/
#36120
08
0=
b10100110100010101010100 (
1:
1?
1+
b100111 7
#36220
b101000 7
#37000
0%
1"
0$
0&
0;
1!
12
1#
0@
1/
#37010
b10011 0
0-
1.
#37020
04
13
b101001 7
#37420
b101010 7
#37520
0"
1%
0!
09
1$
1;
0>
18
1@
1=
b101001001000101010100110100010101010100 (
0:
0?
0+
b101011 7
#38000
19
1>
0/
#38020
b101100 7
#38920
08
0=
b10100110100010101010100 (
1:
1?
1+
b101101 7
#39000
0%
1"
0$
0;
1!
0@
1/
#39010
b10100 0
#39520
0"
1%
0!
09
1$
1;
0>
18
1@
1=
b101001001000101010100110100010101010100 (
0:
0?
0+
b101110 7
#39720
0%
1"
19
0$
0;
1!
1>
08
0@
0=
b10100110100010101010100 (
1:
1?
1+
b101111 7
#40000
1;
1@
0/
#40320
b110000 7
#40720
b110001 7
#40920
b110010 7
#41000
0;
0@
1/
#41010
b10101 0
#41920
b100 7
