verilog_project/verilog_project/multiplexer_1bit_8to1/multiplexer_1bit_8to1.v
module multiplexer_1bit_8to1(
input a,b,c,
input [7:0]d,
output reg y,
output w
);

assign w=~y;

always@(a or b or c or d) begin

case ({a,b,c})
3'b000: y = d[0]; 
3'b001: y = d[1];
3'b010: y = d[2];
3'b011: y = d[3];
3'b100: y = d[4];
3'b101: y = d[5];
3'b110: y = d[6];
3'b111: y = d[7];
endcase

end

endmodule

verilog_project/multiplexer_1bit_8to1/tb_multiplexer_1bit_8to1.v
module tb_multiplexer_1bit_8to1;

//VECTORS FOR DUT
reg A,B,C;
reg[7:0]D; 
wire Y;
wire W;

//VECTORS FOR TESTING

reg TICK;
integer FD, COUNT;
reg [8*31-1:0] COMMENT;
reg Y_EXPECTED;
reg W_EXPECTED;
reg [31:0] VECTORCOUNT, ERRORS;
int i;
reg [31:0] input_coverage [0:7];
reg eof;
reg [7:0]J;

//DUT INSTANTIATION

multiplexer_1bit_8to1 dut_multiplexer_1bit_8to1 (.a(A), .b(B), .c(C), .d(D), .y(Y), .w(W));



//DUMP EVERYTHING INTO DUMPFILE

initial begin

$dumpfile ("tb_multiplexer_1bit_8to1.vcd");
$dumpvars (0, tb_multiplexer_1bit_8to1);

end

//TICKPERIOD

localparam TICKPERIOD = 20;

always begin

#(TICKPERIOD/2) TICK = ~TICK;

end



//TASKS

//task 1 initialize

task initialize; begin

FD = $fopen ("tb_multiplexer_1bit_8to1.tv" , "r");
COUNT = $fscanf (FD, "%s", COMMENT);

COUNT = $fscanf (FD, "%s %b %b %b %b %b %b ", COMMENT, A, B, C, D,Y_EXPECTED,W_EXPECTED);
TICK = 0;
VECTORCOUNT = 0;
ERRORS = 0;

for(i=0; i<8; i++)begin
input_coverage[i] = 0;
end

eof = 0;


$display ();
$display ("TEST_START-------------------------------------------------------------------------------------------------------------------------------------");
$display ();
$display ("                     | TIME | A | B | C |    D     | Y | Y_EXPECTED | W | W_EXPECTED |");
$display ("-----------------------------------------------------------------------------------------------------------------------------------------------");



end
endtask


//task 3 scan_file

task scan_file; begin
COUNT = $fscanf (FD, "%s %b %b %b %b %b ", COMMENT, A, B, C, D,Y_EXPECTED,W_EXPECTED);
eof = (COUNT == -1);

end
endtask

//task 4 random_in

task random_in; begin


{A,B,C} =  $urandom %8;
D = $urandom %256;

COMMENT = "-";

# ($urandom_range(0.1,10));

end
endtask

//task5 OUT_EXP

task OUT_EXP; begin


case ({A,B,C})
3'b000: Y_EXPECTED = D[0];
3'b001: Y_EXPECTED = D[1];
3'b010: Y_EXPECTED = D[2];
3'b011: Y_EXPECTED = D[3];
3'b100: Y_EXPECTED = D[4];
3'b101: Y_EXPECTED = D[5];
3'b110: Y_EXPECTED = D[6];
3'b111: Y_EXPECTED = D[7];
endcase


W_EXPECTED = ~Y_EXPECTED;

end
endtask



//task 5 close

task close; begin

#10;

$fclose (FD);

$display ();
$display ("COVERAGE_REPORT");

for (int j = 0; j < 8; j++ ) begin


if(input_coverage[j] == 0) begin
$display ("input A = %b, B = %b, C= %b has occured %d times ***ERROR***", j[2], j[1], j[0], input_coverage[j]);
ERRORS = ERRORS + 1;
end

else begin
$display ("input A = %b, B = %b, C= %b has occured %d times", j[2], j[1], j[0], input_coverage[j]);
end

end


$display ();
$display ("VECTORCOUNT = %d", VECTORCOUNT);
$display ("ERRORS = %15d", ERRORS);
$display ();
$display ("TEST_END--------------------------------------------------------------------------------------------------------------------------");
$display ();

$finish;

end
endtask


//task 6 vectorcount

task vectorcount; begin

VECTORCOUNT = VECTORCOUNT + 1;

end
endtask


//task 7 display_file

task display_file; begin

$display ("%10d %9s | %4d | %1b | %1b | %1b | %8b | %1b | %5b      | %1b | %5b      |", VECTORCOUNT, COMMENT, $time, A, B, C, D, Y, Y_EXPECTED,W, W_EXPECTED);

end
endtask

//task 8 coverage_update

task coverage_update; begin

input_coverage[{A,B,C}]++;

end
endtask




//task 9 errors_warnings_check

task errors_warnings_check; begin


if (Y !== Y_EXPECTED) begin

$display ("***ERROR: Y = %b, Y_expected = %b", Y, Y_EXPECTED);
ERRORS = ERRORS + 1;

end

if (W !== W_EXPECTED) begin

$display ("***ERROR: W = %b, W_expected = %b", W, W_EXPECTED);
ERRORS = ERRORS + 1;

end

end
endtask



//DRIVE

//0 initialize

initial begin

initialize;

end




//2 scan file on negedge TICK

always @ (negedge TICK) begin

#1.2;

if (!eof) begin

scan_file;

end
end



//3 check file on posedge TICK

always  @ (posedge TICK) begin

coverage_update;

#0.1;

OUT_EXP;
display_file;
errors_warnings_check;
vectorcount;

end



// eof

initial begin

wait (eof);

$display ();
$display("%13s ***time = %0d,eof ***","",$time);
$display ();

for (i = 0; i < 50; i++) begin


if ({A,B,C} == 4'b1000)
begin

vectorcount;
close;

end

else begin

random_in;
end

end

close;

end


endmodule

verilog_project/multiplexer_1bit_8to1/tb_multiplexer_1bit_8to1.vcd
$date
	Thu Apr 23 04:10:27 2026
$end
$version
	Icarus Verilog
$end
$timescale
	1s
$end
$scope module tb_multiplexer_1bit_8to1 $end
$var wire 1 ! Y $end
$var wire 1 " W $end
$var parameter 32 # TICKPERIOD $end
$var reg 1 $ A $end
$var reg 1 % B $end
$var reg 1 & C $end
$var reg 248 ' COMMENT [247:0] $end
$var reg 8 ( D [7:0] $end
$var reg 32 ) ERRORS [31:0] $end
$var reg 1 * TICK $end
$var reg 32 + VECTORCOUNT [31:0] $end
$var reg 1 , W_EXPECTED $end
$var reg 1 - Y_EXPECTED $end
$var reg 1 . eof $end
$var integer 32 / COUNT [31:0] $end
$var integer 32 0 FD [31:0] $end
$var integer 32 1 i [31:0] $end
$scope module dut_multiplexer_1bit_8to1 $end
$var wire 1 $ a $end
$var wire 1 % b $end
$var wire 1 & c $end
$var wire 8 2 d [7:0] $end
$var wire 1 " w $end
$var reg 1 ! y $end
$upscope $end
$scope task OUT_EXP $end
$upscope $end
$scope task close $end
$scope begin $ivl_for_loop0 $end
$var integer 32 3 j [31:0] $end
$upscope $end
$upscope $end
$scope task coverage_update $end
$upscope $end
$scope task display_file $end
$upscope $end
$scope task errors_warnings_check $end
$upscope $end
$scope task initialize $end
$upscope $end
$scope task random_in $end
$upscope $end
$scope task scan_file $end
$upscope $end
$scope task vectorcount $end
$upscope $end
$upscope $end
$enddefinitions $end
$comment Show the parameter values. $end
$dumpall
b10100 #
$end
#0
$dumpvars
b0 3
b10101010 2
b1000 1
b10000000000000000000000000000011 0
b111 /
0.
0-
1,
b0 +
0*
b0 )
b10101010 (
b1001001010011100100100101010100 '
0&
0%
0$
1"
0!
$end
#10
b1 +
1*
#20
0*
#21
b110 /
b101101 '
#30
b10 +
1*
#40
0*
#41
b1 /
b110001 '
#50
b11 +
1*
#60
0*
#61
0"
1!
b110 /
1-
1&
b101101 '
#70
b100 +
0,
1*
#80
0*
#81
b1 /
b110000 '
#90
b101 +
1*
#100
0*
#101
1"
0!
b110 /
0-
0&
1%
b101101 '
#110
b110 +
1,
1*
#120
0*
#121
b1 /
b110001 '
#130
b111 +
1*
#140
0*
#141
0"
1!
b110 /
1-
1&
b101101 '
#150
b1000 +
0,
1*
#160
0*
#161
b1 /
b110000 '
#170
b1001 +
1*
#180
0*
#181
1"
0!
b110 /
0-
0&
0%
1$
b101101 '
#190
b1010 +
1,
1*
#200
0*
#201
b1 /
b110001 '
#210
b1011 +
1*
#220
0*
#221
0"
1!
b110 /
1-
1&
b101101 '
#230
b1100 +
0,
1*
#240
0*
#241
b1 /
b110000 '
#250
b1101 +
1*
#260
0*
#261
1"
0!
b110 /
0-
0&
1%
b101101 '
#270
b1110 +
1,
1*
#280
0*
#281
b1 /
b110001 '
#290
b1111 +
1*
#300
0*
#301
0"
1!
b110 /
1-
1&
b101101 '
#310
b10000 +
0,
1*
#320
0*
#321
b1 /
b110000 '
#330
b10001 +
1*
#340
0*
#341
0$
0"
1!
b101101 '
b1101 (
b1101 2
1%
1&
b1 1
1.
b11111111111111111111111111111111 /
#349
1"
0!
b10010 (
b10010 2
1$
0%
b10 1
#350
b10010 +
1,
0-
1*
#354
0"
1!
b1110110 (
b1110110 2
b11 1
#360
1"
0!
b10001100 (
b10001100 2
b100 1
0*
#370
b10011 +
0,
1-
0"
1!
b11000101 (
b11000101 2
1%
0&
b101 1
1*
#373
b11110010 (
b11110010 2
1%
1&
b111 1
#377
b11000101 (
b11000101 2
0$
0%
0&
b1000 1
#380
0*
#384
b101101 (
b101101 2
1$
1&
b1001 1
#386
b1010 (
b1010 2
0$
1%
b1010 1
#388
1"
0!
b10101010 (
b10101010 2
0%
0&
b1011 1
#390
b10100 +
1,
0-
1*
#391
0"
1!
1&
b1101011 (
b1101011 2
0$
1%
b1101 1
#395
b10101110 (
b10101110 2
0&
b1110 1
#400
0*
#401
1"
0!
b100011 (
b100011 2
1$
1&
b1111 1
#406
0"
1!
b111100 (
b111100 2
0$
0&
b10000 1
#410
b10101 +
0,
1-
1*
#416
1"
0!
b1000001 (
b1000001 2
b10001 1
#420
0"
1!
b10001001 (
b10001001 2
0%
b10010 1
0*
#430
b10110 +
b11000110 (
b11000110 2
1$
1%
b10011 1
1*
#439
0$
1&
1"
0!
b10000101 (
b10000101 2
0%
b10101 1
#440
0*
#446
0"
1!
b111010 (
b111010 2
1%
b10110 1
#448
b11110001 (
b11110001 2
1$
0%
b10111 1
#450
b10111 +
1*
#458
b1001100 (
b1001100 2
0$
1%
0&
b11000 1
#460
0*
#466
b11111000 (
b11111000 2
1$
1&
b11001 1
#469
1"
0!
b1011100 (
b1011100 2
b11010 1
#470
b11000 +
1,
0-
b1001001 (
b1001001 2
0$
0%
b11011 1
1*
#474
b1010001 (
b1010001 2
1$
1%
b11100 1
#480
0*
#482
b11000010 (
b11000010 2
0%
0&
b11101 1
#490
b11001 +
1*
#491
b111101 (
b111101 2
1%
1&
b11110 1
#496
0"
1!
b1101101 (
b1101101 2
0&
b11111 1
#500
0*
#502
b11010011 (
b11010011 2
1&
b100000 1
#510
b11010 +
0,
1-
b1011011 (
b1011011 2
0$
0%
0&
b100001 1
1*
#517
1"
0!
b101010 (
b101010 2
1$
1%
1&
b100010 1
#520
0*
#524
b10001110 (
b10001110 2
0&
b100011 1
#527
0"
1!
b100110 (
b100110 2
0$
b100100 1
#530
b11011 +
1*
#534
b101111 (
b101111 2
1&
b100101 1
#537
1"
0!
b1000100 (
b1000100 2
1$
b100110 1
#540
0*
#547
b11100110 (
b11100110 2
0$
b100111 1
#550
b11100 +
1,
0-
1*
#554
b11101101 (
b11101101 2
0%
b101000 1
#558
0"
1!
b10110101 (
b10110101 2
1$
b101001 1
#560
0*
#562
1"
0!
b1000100 (
b1000100 2
0$
b101010 1
#566
b10101011 (
b10101011 2
1%
0&
b101011 1
#570
b11101 +
1*
#571
0"
1!
b10011010 (
b10011010 2
1$
0%
b101100 1
#576
1"
0!
b1010110 (
b1010110 2
0$
1%
1&
b101101 1
#580
0*
#583
b1010 (
b1010 2
1$
b101110 1
#590
b11110 +
1*
#592
0"
1!
b1111001 (
b1111001 2
0$
0%
0&
b101111 1
#595
1&
b11011011 (
b11011011 2
0$
b110001 1
#596
b110010 1
#600
0*
#606
b1000 3
