verilog_project/not/not.v
module not_gate(
    input       a,    
    output      q
);      

    not (q, a);

endmodule



module not_dataflow(
    input       a,    
    output      q
);      

    assign q = ~a;

endmodule



module not_behavioral(
    input       a,     
    output reg  q
);       

    always @(a) begin
        q <= ~a;
    end

endmodule

verilog_project/not/tb_not.v
`timescale 1ns/10ps

module tb_not;

//VECTORS FOR DUT
reg A;
wire Q_gate, Q_data, Q_beh;

//VECTORS FOR TESTING

reg TICK;
integer FD, COUNT;
reg [8*9-1:0] COMMENT;
reg QEXPECTED;
reg [31:0] VECTORCOUNT, ERRORS;
int i;
reg [31:0] input_coverage[3:0];
reg eof;
reg prev_A;
reg prev_QEx;
reg prev_QExbar;


//DUT INSTANTIATION

not_gate dut_not_gate (.a(A), .q(Q_gate));
not_dataflow dut_not_dataflow (.a(A), .q(Q_data));
not_behavioral dut_not_behavioral (.a(A), .q(Q_beh));



//DUMP EVERYTHING INTO DUMPFILE

initial begin

$dumpfile ("tb_not.vcd");
$dumpvars (0, tb_not);

end

//TICKPERIOD

localparam TICKPERIOD = 20;

always begin

#(TICKPERIOD/2) TICK = ~TICK;

end



//TASKS

//task 1 initialize

task initialize; begin

FD = $fopen ("tb_not.tv" , "r");
COUNT = $fscanf (FD, "%s", COMMENT);

COUNT = $fscanf (FD, "%s %b %b", COMMENT, A, QEXPECTED);
TICK = 0;
VECTORCOUNT = 0;
ERRORS = 0;

for ( i = 0 ; i < 4 ; i++ ) begin
input_coverage[i] = 0;
end

eof = 0;

$display ();
$display ("TEST_START------------------------------------------------------------------------------------------------------------------------");
$display ();
$display ("                     | TIME | A |  Q_gate  |  Q_data  |  Q_beh  | QEXPECTED |");
$display ("----------------------------------------------------------------------------------------------------------------------------------");



end
endtask



//task 2 scan_file

task scan_file; begin


COUNT = $fscanf (FD,"%s %b %b", COMMENT, A, QEXPECTED);
eof = (COUNT == -1);

end
endtask

//task 3 random_in

task random_in; begin


A =  $urandom %5 ;

case (A)
1'b0: COMMENT = "HIGH";
1'b1: COMMENT = "LOW";

endcase

#($urandom_range (0.1,10));

end
endtask

//task 4 QEXP

task QEXP; begin

case (A)

 1'b0: begin
QEXPECTED = 1'b1;
end
 1'b1: begin
QEXPECTED = 1'b0;
end
 
endcase



end
endtask



//task 5 close

task close; begin


#10;
$fclose (FD);

$display ();
$display ("COVERAGE_REPORT");

for ( i = 0; i < 4; i++ ) begin

if(input_coverage[i] == 0) begin

$display ("input %b to input %b has occured %d times (***ERROR***)",i[1], i[0], input_coverage[i]);
ERRORS = ERRORS +1;

end

else begin

$display ("input %b to input %b has occured %d times",i[1], i[0], input_coverage[i]);

end

end

$display ();
$display ("VECTORCOUNT = %d", VECTORCOUNT);
$display ("ERRORS = %15d", ERRORS);
$display ();
$display ("TEST_END--------------------------------------------------------------------------------------------------------------------------");
$display ();

$finish;

end
endtask

//task 6 vectorcount

task vectorcount; begin

VECTORCOUNT = VECTORCOUNT + 1;

end
endtask


//task 7 display_file

task display_file; begin

$display ("%10d %9s | %4d | %1d | %4d     | %4d     | %4d    | %5d     |", VECTORCOUNT, COMMENT, $time, A, Q_gate, Q_data, Q_beh, QEXPECTED);

end
endtask

//task 8 coverage_update

task coverage_update; begin

input_coverage[{prev_A, A}]++;

end
endtask

//task 10 errors_check

task errors_check; begin


if (Q_gate !== QEXPECTED) begin

$display ("***ERROR: Q_gate = %b, Q_expected = %b", Q_gate, QEXPECTED);
ERRORS = ERRORS + 1;

end

if (Q_data !== QEXPECTED) begin

$display ("***ERROR: Q_dataflow = %b, Q_expected = %b", Q_data, QEXPECTED);
ERRORS = ERRORS + 1;

end

if (Q_beh !== QEXPECTED) begin

$display ("***ERROR: Q_behavioral = %b, Q_expected = %b", Q_beh, QEXPECTED);
ERRORS = ERRORS + 1;

end


end
endtask



//DRIVE

//0 initialize

initial begin

initialize;

end


//2 scan file on negedge TICK

always @ (negedge TICK) begin


#1.2;

if (!eof) begin



scan_file;

end
end



//3 check file on posedge TICK

always  @ (posedge TICK) begin
coverage_update;
prev_A = A;

#0.1;

QEXP;
display_file;
errors_check;
vectorcount;

#0.02;

prev_QEx = QEXPECTED;



end



// eof

initial begin

wait (eof);

$display ();
$display("%13s ***time = %0d,eof ***","",$time);
$display ();

for (i = 0; i < 50; i++) begin


if ( A == 2 )
begin

vectorcount;
close;

end

else begin

random_in;

end
end


close;

end


endmodule

verilog_project/verilog_project/not/tb_not.vcd
$date
	Mon Apr 13 06:58:25 2026
$end
$version
	Icarus Verilog
$end
$timescale
	10ps
$end
$scope module tb_not $end
$var wire 1 ! Q_gate $end
$var wire 1 " Q_data $end
$var wire 1 # Q_beh $end
$var parameter 32 $ TICKPERIOD $end
$var reg 1 % A $end
$var reg 72 & COMMENT [71:0] $end
$var reg 32 ' ERRORS [31:0] $end
$var reg 1 ( QEXPECTED $end
$var reg 1 ) TICK $end
$var reg 32 * VECTORCOUNT [31:0] $end
$var reg 1 + eof $end
$var reg 1 , prev_A $end
$var reg 1 - prev_QEx $end
$var integer 32 . COUNT [31:0] $end
$var integer 32 / FD [31:0] $end
$var integer 32 0 i [31:0] $end
$scope module dut_not_behavioral $end
$var wire 1 % a $end
$var reg 1 # q $end
$upscope $end
$scope module dut_not_dataflow $end
$var wire 1 % a $end
$var wire 1 " q $end
$upscope $end
$scope module dut_not_gate $end
$var wire 1 % a $end
$var wire 1 ! q $end
$upscope $end
$scope task QEXP $end
$upscope $end
$scope task close $end
$upscope $end
$scope task coverage_update $end
$upscope $end
$scope task display_file $end
$upscope $end
$scope task errors_check $end
$upscope $end
$scope task initialize $end
$upscope $end
$scope task random_in $end
$upscope $end
$scope task scan_file $end
$upscope $end
$scope task vectorcount $end
$upscope $end
$upscope $end
$enddefinitions $end
$comment Show the parameter values. $end
$dumpall
b10100 $
$end
#0
$dumpvars
b100 0
b10000000000000000000000000000011 /
b11 .
x-
x,
0+
b0 *
0)
1(
b0 '
b1001001010011100100100101010100 &
0%
1#
1"
1!
$end
#1000
0,
1)
#1010
b1 *
#1012
1-
#2000
0)
#2120
b1001000010010010100011101001000 &
#3000
1)
#3010
b10 *
#4000
0)
#5000
1)
#5010
b11 *
#6000
0)
#6120
0#
0"
0!
0(
1%
b10011000100111101010111 &
#7000
1,
1)
#7010
b100 *
#7012
0-
#8000
0)
#9000
1)
#9010
b101 *
#10000
0)
#10120
1#
1"
1!
1(
0%
b1001000010010010100011101001000 &
#11000
0,
1)
#11010
b110 *
#11012
1-
#12000
0)
#12120
0#
0"
0!
0(
1%
b10011000100111101010111 &
#13000
1,
1)
#13010
b111 *
#13012
0-
#14000
0)
#15000
1)
#15010
b1000 *
#16000
0)
#16120
b0 .
#17000
1)
#17010
b1001 *
#18000
0)
#18120
b0 0
1+
b11111111111111111111111111111111 .
#18320
1#
1"
1!
b1001000010010010100011101001000 &
0%
b1 0
#18520
b10 0
#19000
0,
1)
#19010
b1010 *
1(
#19012
1-
#19320
b100 0
#19820
0#
0"
0!
b10011000100111101010111 &
1%
b101 0
#20000
0)
#20420
1#
1"
1!
b1001000010010010100011101001000 &
0%
b110 0
#21000
1)
#21010
b1011 *
#21220
b111 0
#21620
b1000 0
#21920
0#
0"
0!
b10011000100111101010111 &
1%
b1001 0
#22000
0)
#22120
b1010 0
#22920
1#
1"
1!
b1001000010010010100011101001000 &
0%
b1011 0
#23000
1)
#23010
b1100 *
#23320
b1100 0
#23720
b1101 0
#24000
0)
#24120
0#
0"
0!
b10011000100111101010111 &
1%
b1110 0
#24320
1#
1"
1!
b1001000010010010100011101001000 &
0%
b1111 0
#24820
b10000 0
#25000
1)
#25010
b1101 *
#25420
b10001 0
#25720
0#
0"
0!
b10011000100111101010111 &
1%
b10011 0
#25820
b10100 0
#26000
0)
#26220
1#
1"
1!
b1001000010010010100011101001000 &
0%
b10101 0
#26520
b10110 0
#26920
b10111 0
#27000
1)
#27010
b1110 *
#27420
0#
0"
0!
b10011000100111101010111 &
1%
b11000 0
#27520
1#
1"
1!
b1001000010010010100011101001000 &
0%
b11001 0
#28000
0)
#28320
b11010 0
#28720
0#
0"
0!
b10011000100111101010111 &
1%
b11011 0
#28920
1#
1"
1!
b1001000010010010100011101001000 &
0%
b11100 0
#29000
1)
#29010
b1111 *
#29820
b11101 0
#30000
0)
#30720
0#
0"
0!
b10011000100111101010111 &
1%
b11110 0
#31000
1,
1)
#31010
b10000 *
0(
#31012
0-
#31320
1#
1"
1!
b1001000010010010100011101001000 &
0%
b11111 0
#31520
b100000 0
#32000
0)
#32220
0#
0"
0!
b10011000100111101010111 &
1%
b100001 0
#32820
1#
1"
1!
b1001000010010010100011101001000 &
0%
b100010 0
#33000
0,
1)
#33010
b10001 *
1(
#33012
1-
#33320
0#
0"
0!
b10011000100111101010111 &
1%
b100011 0
#34000
0)
#34320
1#
1"
1!
b1001000010010010100011101001000 &
0%
b100100 0
#35000
1)
#35010
b10010 *
#35020
b100101 0
#35820
0#
0"
0!
b10011000100111101010111 &
1%
b100110 0
#36000
0)
#36120
1#
1"
1!
b1001000010010010100011101001000 &
0%
b100111 0
#36220
0#
0"
0!
b10011000100111101010111 &
1%
b101000 0
#37000
1,
1)
#37010
b10011 *
0(
#37012
0-
#37020
b101001 0
#37420
b101010 0
#37520
b101011 0
#38000
0)
#38020
b101100 0
#38920
b101101 0
#39000
1)
#39010
b10100 *
#39520
b101110 0
#39720
1#
1"
1!
b1001000010010010100011101001000 &
0%
b101111 0
#40000
0)
#40320
b110000 0
#40720
0#
0"
0!
b10011000100111101010111 &
1%
b110001 0
#40920
b110010 0
#41000
1)
#41010
b10101 *
#41920
b100 0
