verilog_project/verilog_project/dff_posedge_sync_enable/dff_posedge_sync_enable.v
// A jk (Jack Kilby) flip-flop which is sync clear at posedge can be set and reset and by creating a versatile memory element, invalid state is prevented.



module dff_posedge_sync_enable_behavioral (
    input  wire clk,
    input  wire enable,
    input  wire d,   
    output reg  q,
    output wire qbar
);


    assign qbar = ~q;


//D FLIP-FLOP WITH SYNC ENABLE
    always @(posedge clk) begin

        if (enable) begin
            q <= d;
        end else begin

            q <= q;

        end
        

     end

endmodule

verilog_project/dff_posedge_sync_enable/tb_dff_posedge_sync_enable.v
`timescale 1ns/10ps

module tb_dff_posedge_sync_enable;

//VECTORS FOR DUT
reg  D;

wire Q_beh, 
     QBAR_beh;


//VECTORS FOR TESTING

reg TICK;
reg ENABLE;
integer FD, COUNT;
reg [8*9-1:0] COMMENT;
reg [8*9-1:0] COMMENT1;
reg [8*9-1:0] COMMENT2;
reg QEXPECTED, QBAREXPECTED;
reg [31:0] VECTORCOUNT, ERRORS;
int i;
reg [31:0] input_coverage [0:3];
reg eof;
reg prev_D;
reg prev_QEx;
reg prev_QExbar;


//DUT INSTANTIATION

dff_posedge_sync_enable_behavioral dut_dff_posedge_sync_enable_behavioral (.d(D), .q(Q_beh), .qbar(QBAR_beh), .clk(TICK), .enable(ENABLE));



//DUMP EVERYTHING INTO DUMPFILE

initial begin

$dumpfile ("tb_dff_posedge_sync_enable.vcd");
$dumpvars (0, tb_dff_posedge_sync_enable);

end

//TICKPERIOD

localparam TICKPERIOD = 20;

always begin

#(TICKPERIOD/2) TICK = ~TICK;

end

//ENABLE


always begin

#(TICKPERIOD) ENABLE = ~ENABLE;

end



//TASKS

//task 1 initialize

task initialize; begin

FD = $fopen ("tb_dff_posedge_sync_enable.tv" , "r");
COUNT = $fscanf (FD, "%s", COMMENT);

COUNT = $fscanf (FD, "%s %b %s %s", COMMENT, D, COMMENT1, COMMENT2);
TICK = 0;
ENABLE = 1;
VECTORCOUNT = 0;
ERRORS = 0;

for ( i = 0 ; i < 4 ; i++ ) begin
input_coverage[i] = 0;
end

eof = 0;

$display ();
$display ("TEST_START------------------------------------------------------------------------------------------------------------------------");
$display ();
$display ("                     | TIME | D |  Q_beh  | QEXPECTED | QBAREXPECTED | ENABLE |");
$display ("----------------------------------------------------------------------------------------------------------------------------------");



end
endtask


//task 2 scan_file

task scan_file; begin


COUNT = $fscanf (FD,"%s %b %b %b", COMMENT, D, QEXPECTED, QBAREXPECTED);
eof = (COUNT == -1);

end
endtask

//task 3 random_in

task random_in; begin

D =  $urandom %5 ;

case (D)
1'b0: COMMENT = "RESET";
1'b1: COMMENT = "SET";

endcase

#($urandom_range (0.1,10));

end
endtask

//task 4 QEXP

task QEXP; begin


case ( {D,ENABLE} )
  2'b01: begin
QEXPECTED = 1'b0;
QBAREXPECTED = 1'b1;
end
  2'b11: begin
QEXPECTED = 1'b1;
QBAREXPECTED = 1'b0;
end

default: begin
QEXPECTED = prev_QEx;
QBAREXPECTED = prev_QExbar;
end

endcase



end
endtask



//task 5 close


task close; begin

#10;
$fclose (FD);

$display ();
$display ("COVERAGE_REPORT");

for ( i = 0; i < 4; i++ ) begin

if(input_coverage[i] == 0) begin

$display ("input %b to input %b has occured %d times (***ERROR***)",i[1], i[0], input_coverage[i]);
ERRORS = ERRORS +1;

end

else begin

$display ("input %b to input %b has occured %d times",i[1], i[0], input_coverage[i]);

end

end

$display ();
$display ("VECTORCOUNT = %d", VECTORCOUNT);
$display ("ERRORS = %15d", ERRORS);
$display ();
$display ("TEST_END--------------------------------------------------------------------------------------------------------------------------");
$display ();

$finish;

end
endtask

//task 6 vectorcount

task vectorcount; begin

VECTORCOUNT = VECTORCOUNT + 1;

end
endtask


//task 7 display_file

task display_file; begin

$display ("%10d %9s | %4d | %1d | %4d    | %5d     | %6d       | %4d   | ", VECTORCOUNT, COMMENT, $time, D, Q_beh, QEXPECTED, QBAREXPECTED, ENABLE);

end
endtask

//task 8 coverage_update

task coverage_update; begin

input_coverage[{prev_D, D}]++;

end
endtask

//task 9 errors_check

task errors_check; begin




if (Q_beh !== QEXPECTED) begin

$display ("***ERROR: Q_behavioral = %b, Q_expected = %b", Q_beh, QEXPECTED);
ERRORS = ERRORS + 1;

end


if ( D !== prev_D ) begin

$display ("***ERROR: Racing Condition Occur");
ERRORS = ERRORS + 1;

end


end
endtask



//DRIVE

//0 initialize

initial begin

initialize;

end


//2 scan file on negedge TICK

always @ (negedge TICK) begin


#1.2;

if (!eof) begin

scan_file;

end
end



//3 check file on posedge TICK

always  @ (posedge TICK) begin

coverage_update;
prev_D = D;

#0.1;

QEXP;
display_file;
errors_check;
vectorcount;

#0.02;
prev_QEx = QEXPECTED;
prev_QExbar = QBAREXPECTED;



end



// eof

initial begin

wait (eof);

$display ();
$display("%13s ***time = %0d,eof ***","",$time);
$display ();

for (i = 0; i < 50; i++) begin


if ( D == 2)
begin

vectorcount;
close;

end

else begin

random_in;

end
end


close;

end


endmodule

verilog_project/dff_posedge_sync_enable/tb_dff_posedge_sync_enable.vcd
$date
	Wed Jan 14 01:14:24 2026
$end
$version
	Icarus Verilog
$end
$timescale
	10ps
$end
$scope module tb_dff_posedge_sync_enable $end
$var wire 1 ! Q_beh $end
$var wire 1 " QBAR_beh $end
$var parameter 32 # TICKPERIOD $end
$var reg 72 $ COMMENT [71:0] $end
$var reg 72 % COMMENT1 [71:0] $end
$var reg 72 & COMMENT2 [71:0] $end
$var reg 1 ' D $end
$var reg 1 ( ENABLE $end
$var reg 32 ) ERRORS [31:0] $end
$var reg 1 * QBAREXPECTED $end
$var reg 1 + QEXPECTED $end
$var reg 1 , TICK $end
$var reg 32 - VECTORCOUNT [31:0] $end
$var reg 1 . eof $end
$var reg 1 / prev_D $end
$var reg 1 0 prev_QEx $end
$var reg 1 1 prev_QExbar $end
$var integer 32 2 COUNT [31:0] $end
$var integer 32 3 FD [31:0] $end
$var integer 32 4 i [31:0] $end
$scope module dut_dff_posedge_sync_enable_behavioral $end
$var wire 1 , clk $end
$var wire 1 ' d $end
$var wire 1 ( enable $end
$var wire 1 " qbar $end
$var reg 1 ! q $end
$upscope $end
$scope task QEXP $end
$upscope $end
$scope task close $end
$upscope $end
$scope task coverage_update $end
$upscope $end
$scope task display_file $end
$upscope $end
$scope task errors_check $end
$upscope $end
$scope task initialize $end
$upscope $end
$scope task random_in $end
$upscope $end
$scope task scan_file $end
$upscope $end
$scope task vectorcount $end
$upscope $end
$upscope $end
$enddefinitions $end
$comment Show the parameter values. $end
$dumpall
b10100 #
$end
#0
$dumpvars
b100 4
b10000000000000000000000000000011 3
b100 2
x1
x0
x/
0.
b0 -
0,
x+
x*
b0 )
1(
0'
b1011000 &
b1011000 %
b1001001010011100100100101010100 $
x"
x!
$end
#1000
1"
0!
0/
1,
#1010
b1 -
1*
0+
#1012
11
00
#2000
0,
0(
#2120
b101001001000101010100110100010101010100 $
#3000
1,
#3010
b10 -
#4000
0,
1(
#5000
1,
#5010
b11 -
#6000
0,
0(
#6120
0*
1+
1'
b10100110100010101010100 $
#7000
1/
1,
#7010
b100 -
1*
0+
#8000
0,
1(
#8120
0*
1+
#9000
0"
1!
1,
#9010
b101 -
#9012
01
10
#10000
0,
0(
#10120
1*
0+
0'
b101001001000101010100110100010101010100 $
#11000
0/
1,
#11010
b110 -
0*
1+
#12000
0,
1(
#12120
1'
b10100110100010101010100 $
#13000
1/
1,
#13010
b111 -
#14000
0,
0(
#15000
1,
#15010
b1000 -
#16000
0,
1(
#16120
b0 2
#17000
1,
#17010
b1001 -
#18000
0,
0(
#18120
b0 4
1.
b11111111111111111111111111111111 2
#18320
b101001001000101010100110100010101010100 $
0'
b1 4
#18520
b10 4
#19000
0/
1,
#19010
b1010 -
#19320
b100 4
#19820
b10100110100010101010100 $
1'
b101 4
#20000
0,
1(
#20420
b101001001000101010100110100010101010100 $
0'
b110 4
#21000
1"
0!
1,
#21010
b1011 -
1*
0+
#21012
11
00
#21220
b111 4
#21620
b1000 4
#21920
b10100110100010101010100 $
1'
b1001 4
#22000
0,
0(
#22120
b1010 4
#22920
b101001001000101010100110100010101010100 $
0'
b1011 4
#23000
1,
#23010
b1100 -
#23320
b1100 4
#23720
b1101 4
#24000
0,
1(
#24120
b10100110100010101010100 $
1'
b1110 4
#24320
b101001001000101010100110100010101010100 $
0'
b1111 4
#24820
b10000 4
#25000
1,
#25010
b1101 -
#25420
b10001 4
#25720
b10100110100010101010100 $
1'
b10011 4
#25820
b10100 4
#26000
0,
0(
#26220
b101001001000101010100110100010101010100 $
0'
b10101 4
#26520
b10110 4
#26920
b10111 4
#27000
1,
#27010
b1110 -
#27420
b10100110100010101010100 $
1'
b11000 4
#27520
b101001001000101010100110100010101010100 $
0'
b11001 4
#28000
0,
1(
#28320
b11010 4
#28720
b10100110100010101010100 $
1'
b11011 4
#28920
b101001001000101010100110100010101010100 $
0'
b11100 4
#29000
1,
#29010
b1111 -
#29820
b11101 4
#30000
0,
0(
#30720
b10100110100010101010100 $
1'
b11110 4
#31000
1/
1,
#31010
b10000 -
#31320
b101001001000101010100110100010101010100 $
0'
b11111 4
#31520
b100000 4
#32000
0,
1(
#32220
b10100110100010101010100 $
1'
b100001 4
#32820
b101001001000101010100110100010101010100 $
0'
b100010 4
#33000
0/
1,
#33010
b10001 -
#33320
b10100110100010101010100 $
1'
b100011 4
#34000
0,
0(
#34320
b101001001000101010100110100010101010100 $
0'
b100100 4
#35000
1,
#35010
b10010 -
#35020
b100101 4
#35820
b10100110100010101010100 $
1'
b100110 4
#36000
0,
1(
#36120
b101001001000101010100110100010101010100 $
0'
b100111 4
#36220
b10100110100010101010100 $
1'
b101000 4
#37000
0"
1!
1/
1,
#37010
b10011 -
0*
1+
#37012
01
10
#37020
b101001 4
#37420
b101010 4
#37520
b101011 4
#38000
0,
0(
#38020
b101100 4
#38920
b101101 4
#39000
1,
#39010
b10100 -
#39520
b101110 4
#39720
b101001001000101010100110100010101010100 $
0'
b101111 4
#40000
0,
1(
#40320
b110000 4
#40720
b10100110100010101010100 $
1'
b110001 4
#40920
b110010 4
#41000
1,
#41010
b10101 -
#41920
b100 4
