verilog_project/verilog_project/fifo_synchronous/dual_port_ram_synchronous1.v
module dual_port_ram_synchronous1(
input clk,
input rst,
input we_a, //write enable
input [ADDR_WIDTH-1:0]addr_a,
input [DATA_WIDTH-1:0]data_in_a,
output reg [DATA_WIDTH-1:0]data_out_a,

input we_b, //write enable
input [ADDR_WIDTH-1:0]addr_b,
input [DATA_WIDTH-1:0]data_in_b,
output reg [DATA_WIDTH-1:0]data_out_b
);

parameter DATA_WIDTH = 8, ADDR_WIDTH = 4, MEM_DEPTH = 16;

reg [DATA_WIDTH-1:0]mem[MEM_DEPTH-1:0];


always@(posedge clk)begin

if(rst)begin
data_out_a <= 8'h00;
end

else if(we_a)begin
mem[addr_a] <= data_in_a;
data_out_a <= mem[addr_a];

end

else begin
data_out_a <= mem[addr_a];
end

end



always@(posedge clk)begin

if(rst)begin
data_out_b <= 8'h00;
end


else if(we_b)begin
mem[addr_b] <= data_in_b;
data_out_b <= mem[addr_b];

end

else begin
data_out_b <= mem[addr_b];
end


end


endmodule

verilog_project/verilog_project/lifo_synchronous/dual_port_ram_synchronous.v
module dual_port_ram_synchronous(
input clk,
input rst,
input we_a, //write enable
input [ADDR_WIDTH-1:0]addr_a,
input [DATA_WIDTH-1:0]data_in_a,
output reg [DATA_WIDTH-1:0]data_out_a,

input we_b, //write enable
input [ADDR_WIDTH-1:0]addr_b,
input [DATA_WIDTH-1:0]data_in_b,
output reg [DATA_WIDTH-1:0]data_out_b
);

parameter DATA_WIDTH = 8, ADDR_WIDTH = 4, MEM_DEPTH = 16;

reg [DATA_WIDTH-1:0]mem[MEM_DEPTH-1:0];


always@(posedge clk)begin

if(rst)begin
data_out_a <= 8'h00;
end

else if(we_a)begin
mem[addr_a] <= data_in_a;
data_out_a <= mem[addr_a];

end

else begin
data_out_a <= mem[addr_a];
end

end


always@(posedge clk)begin

if(rst)begin
data_out_b <= 8'h00;
end

else if(we_b)begin
mem[addr_b] <= data_in_b;
data_out_b <= mem[addr_b];

end

else begin
data_out_b <= mem[addr_b];
end


end



endmodule

verilog_project/verilog_project/fifo_synchronous/fifo_synchronous.v
module fifo(
input clk,
input rst,
input push,
input pop,
input [7:0] data_in,
output full,empty,
output [addr_width:0] w_ptr,r_ptr,
output [7:0] data_out,
output reg [addr_width:0] addra,
output reg [addr_width:0] addrb,
output reg nextw
);
parameter addr_width = 4;

wire [3:0] addr_a, addr_b;
wire next_w,next_r;



assign next_w = push & !full;
assign next_r = pop & !empty;

assign nextw = next_w;

assign addr_a = w_ptr[addr_width-1:0];
assign addr_b = r_ptr[addr_width-1:0];


always@(posedge clk) begin
addra <= w_ptr;
addrb <= r_ptr;
end



//2.write_pointer
w_ptr_section dut_w_ptr_section (.clk(clk), .rst(rst),.next(next_w), .w_ptr(w_ptr));



//3.read_pointer
r_ptr_section dut_r_ptr_section (.clk(clk), .rst(rst),.next(next_r), .r_ptr(r_ptr));


//1.compare 
compare_and_status_section dut_compare_and_status_section(
.w_ptr(w_ptr), .r_ptr(r_ptr), .empty(empty), .full(full));


//0.dual_port_ram_synchronous

dual_port_ram_synchronous dut_dual_port_ram_synchronous(
.clk(clk), .rst(rst), .we_a(next_w), .addr_a(addr_a), .data_in_a(data_in), .data_out_a(), 
.we_b(1'b0), .addr_b(addr_b), .data_in_b(8'h00), .data_out_b(data_out));



endmodule


module compare_and_status_section(
input [4:0] w_ptr,
input [4:0] r_ptr,
output empty,
output full
);


parameter addr_width = 4;


assign empty = (w_ptr == r_ptr);
assign full = ((w_ptr[addr_width] != r_ptr[addr_width]) && (w_ptr[addr_width-1:0] == r_ptr[addr_width-1:0]));


endmodule





module w_ptr_section(
input clk,
input rst,
input next,
output reg [4:0] w_ptr
);

always@(posedge clk)begin
 
if(rst)
w_ptr <= 5'b0;

else if(next)
w_ptr <= w_ptr + 1;



end

endmodule




module r_ptr_section(
input clk,
input rst,
input next,
output reg [4:0] r_ptr
);

always@(posedge clk)begin
 
if(rst)
r_ptr <= 5'b0;
else if(next)
r_ptr <= r_ptr + 1;


end

endmodule

verilog_project/verilog_project/fifo_synchronous/tb_fifo.v
`timescale 1ns/10ps


module tb_fifo;

//VECTORS FOR DUT
reg RST;
reg PUSH,POP;
reg [DATA_WIDTH-1:0] DATA_IN;
wire FULL, EMPTY;
wire [ADDR_WIDTH:0] W_PTR, R_PTR;
wire [DATA_WIDTH-1:0] DATA_OUT;
wire [ADDR_WIDTH:0] ADDRA_ram,ADDRB_ram;
wire NEXTW;

//VECTORS FOR TESTING

reg TICK;
integer FD, COUNT;
reg [8*31-1:0] COMMENT;
reg EMPTY_EXPECTED,FULL_EXPECTED;
reg [ADDR_WIDTH:0] W_PTR_EXPECTED,R_PTR_EXPECTED;
reg [ADDR_WIDTH:0] prev_ADDRA_EXPECTED,prev_ADDRB_EXPECTED;
reg [ADDR_WIDTH:0] ADDRA_EXPECTED,ADDRB_EXPECTED;
wire [DATA_WIDTH-1:0]DATA_OUT_EXPECTED;
reg [31:0] VECTORCOUNT, ERRORS;
int i;
reg [31:0] state_input_coverage[0:23];
reg [31:0] wrap_coverage;
reg eof;
reg [10:0]prev_INPUT;
reg [4:0]prev_W_PTR;
reg [4:0]prev_R_PTR;
reg [1:0]prev_state;
reg [DATA_WIDTH-1:0] MEM [0:MEM_DEPTH-1];
reg NEXT_W,NEXT_R;
reg [ADDR_WIDTH-1:0]ADDR_A,ADDR_B;
reg WRAP_WR;


parameter DATA_WIDTH = 8, ADDR_WIDTH = 4, MEM_DEPTH = 16;


//DUT INSTANTIATION

fifo dut_fifo (.clk(TICK), .rst(RST), .push(PUSH), .pop(POP), .data_in(DATA_IN), .full(FULL), .empty(EMPTY), .w_ptr(W_PTR), .r_ptr(R_PTR), .data_out(DATA_OUT), .addra(ADDRA_ram), .addrb(ADDRB_ram), .nextw(NEXTW));
dual_port_ram_synchronous1 test_dual_port_ram_synchronous1(
.clk(TICK),.rst(RST), .we_a(NEXT_W), .addr_a(ADDR_A), .data_in_a(DATA_IN), .data_out_a(),
.we_b(1'b0), .addr_b(ADDR_B), .data_in_b(8'h00), .data_out_b(DATA_OUT_EXPECTED));



//DUMP EVERYTHING INTO DUMPFILE

initial begin

$dumpfile ("tb_fifo.vcd");
$dumpvars (0, tb_fifo);

end


//TICKPERIOD

localparam TICKPERIOD = 20;

always begin
#(TICKPERIOD/2) TICK <= ~TICK;
end



//TASKS

//task 1 initialize

task initialize; begin

FD = $fopen ("tb_fifo.tv" , "r");
COUNT = $fscanf (FD, "%s", COMMENT);
COUNT = $fscanf (FD, "%s %b %b %b %s", COMMENT, RST, PUSH, POP, DATA_IN);
TICK = 0;
VECTORCOUNT = 0;
ERRORS = 0;

for(i=0; i<48; i++)begin
state_input_coverage[i] = 0;
end

wrap_coverage = 0;

eof = 0;

$display ();
$display ("TEST_START--------------------------------------------------------------------------------------------------------------------------------------------------");
$display ();
$display ("                     | TIME | RST | PUSH | POP | DATA_IN | ADDR_A | ADDR_A_EXPECTED | ADDR_B | ADDR_B_EXPECTED | WRAP_WR | FULL | FULL_EXPECTED | EMPTY | EMPTY_EXPECTED | W_PTR | W_PTR_EXPECTED | R_PTR | R_PTR_EXPECTED | DATA_OUT | DATA_OUT_EXPECTED |");
$display ("------------------------------------------------------------------------------------------------------------------------------------------------------------");


end
endtask


//task 3 scan_file

task scan_file; begin

COUNT = $fscanf (FD, "%s %b %b %b %s", COMMENT, RST, PUSH, POP, DATA_IN);
eof = (COUNT == -1);

end
endtask

//task 4 random_in

task random_in; begin

RST =  $urandom %2;
POP = $urandom %2;
PUSH = $urandom %2;


# ($urandom_range(0.1,10));

end
endtask

//task4 COMMENT
task comment; begin

case({FULL_EXPECTED,EMPTY_EXPECTED})
2'b00: COMMENT = "NOT_FULL";
2'b01: COMMENT = "EMPTY";
2'b10: COMMENT = "FULL";
default: COMMENT = "ILLEGAL";
endcase

end
endtask

//task4 ADDRAB_ram
task ADDRAB_ram;begin

ADDRA_EXPECTED = W_PTR_EXPECTED;
ADDRB_EXPECTED = R_PTR_EXPECTED;

end
endtask


//task5 NEXTWR_EXP

task NEXTWR_EXP; begin

NEXT_W = PUSH & !FULL_EXPECTED;
NEXT_R = POP & !EMPTY_EXPECTED;




end
endtask

//task5 OUT_EXP
task OUT_EXP; begin

if(RST)begin
W_PTR_EXPECTED = 5'b0;
end 
else if(NEXT_W) begin
W_PTR_EXPECTED = W_PTR_EXPECTED + 1;
end

if(RST)begin
R_PTR_EXPECTED = 5'b0;
end
else if(NEXT_R) begin
R_PTR_EXPECTED = R_PTR_EXPECTED + 1;
end

ADDR_A = W_PTR_EXPECTED[ADDR_WIDTH-1:0];
ADDR_B = R_PTR_EXPECTED[ADDR_WIDTH-1:0];

EMPTY_EXPECTED = (W_PTR_EXPECTED == R_PTR_EXPECTED);
FULL_EXPECTED = ((W_PTR_EXPECTED[ADDR_WIDTH] != R_PTR_EXPECTED[ADDR_WIDTH]) && (W_PTR_EXPECTED[ADDR_WIDTH-1:0] == R_PTR_EXPECTED[ADDR_WIDTH-1:0]));


WRAP_WR = (((ADDRA_EXPECTED[ADDR_WIDTH] != prev_ADDRA_EXPECTED[ADDR_WIDTH]) && (prev_ADDRA_EXPECTED[ADDR_WIDTH-1:0] == 4'b1111)) || ((ADDRB_EXPECTED[ADDR_WIDTH] != prev_ADDRB_EXPECTED[ADDR_WIDTH]) && (prev_ADDRB_EXPECTED[ADDR_WIDTH-1:0] == 4'b1111)));


NEXT_W = PUSH & !FULL_EXPECTED;
NEXT_R = POP & !EMPTY_EXPECTED;



end
endtask

//task 5 close

task close; begin

#10;

$fclose (FD);

$display ();
$display ("COVERAGE_REPORT");
$display ();
$display ();
$display ();



if(wrap_coverage == 0) begin            
$display ("wrap around has occured %58d times ***ERROR***", wrap_coverage);
ERRORS = ERRORS + 1;
end


else begin
$display ("wrap around has occured %58d times", wrap_coverage);
end


for (int j = 0; j < 24; j++ ) begin

if(state_input_coverage[j] == 0) begin            
$display ("state FULL = %b, EMPTY = %b, input RST = %b, PUSH = %b, POP = %b has occured %d times ***ERROR***", j[4], j[3], j[2], j[1], j[0], state_input_coverage[j]);
ERRORS = ERRORS + 1;
end


else begin
$display ("state FULL = %b, EMPTY = %b, input RST = %b, PUSH = %b, POP = %b has occured %d times", j[4], j[3], j[2], j[1], j[0], state_input_coverage[j]);
end
end




$display ();
$display ("VECTORCOUNT = %d", VECTORCOUNT);
$display ("ERRORS = %15d", ERRORS);
$display ();
$display ("TEST_END--------------------------------------------------------------------------------------------------------------------------");
$display ();

$finish;

end
endtask


//task 6 vectorcount

task vectorcount; begin

VECTORCOUNT = VECTORCOUNT + 1;

end
endtask


//task 7 display_file

task display_file; begin

$display ("%10d %9s | %4d | %2b  | %2b   | %2b  | %4c    | %5b  | %10b      | %5b  | %10b      | %4b    | %2b   | %7b       | %3b   | %7b        | %5b | %8b     | %5b | %8b     | %4c     | %9c         |", VECTORCOUNT, COMMENT, $time, RST, PUSH, POP, DATA_IN, ADDRA_ram[3:0], ADDRA_EXPECTED[3:0], ADDRB_ram[3:0], ADDRB_EXPECTED[3:0], WRAP_WR, FULL, FULL_EXPECTED, EMPTY, EMPTY_EXPECTED, W_PTR, W_PTR_EXPECTED, R_PTR, R_PTR_EXPECTED, DATA_OUT, DATA_OUT_EXPECTED);

end
endtask



//task 8 in_coverage_update

task coverage_update; begin

state_input_coverage[{prev_state,RST,PUSH,POP}]++;

for(int j=0;j<3;j++)begin


if(prev_state == j[1:0] && {RST,PUSH,POP} == 3'b111)begin
for(int k=6;k>3;k--)begin
state_input_coverage[{j[1:0],k[2:0]}]++;
end

end
end


if(WRAP_WR)
wrap_coverage++;


end
endtask




//task 9 errors_warnings_check

task errors_warnings_check; begin

if (ADDRA_ram !== ADDRA_EXPECTED) begin

$display ("***ERROR: ADDR_A = %b, ADDR_A_expected = %b", ADDR_A, ADDRA_EXPECTED);
ERRORS = ERRORS + 1;

end

if (ADDRB_ram !== ADDRB_EXPECTED) begin

$display ("***ERROR: ADDR_B = %b, ADDR_B_expected = %b", ADDR_B, ADDRB_EXPECTED);
ERRORS = ERRORS + 1;

end



if (FULL !== FULL_EXPECTED) begin

$display ("***ERROR: FULL = %b, FULL_expected = %b", FULL, FULL_EXPECTED);
ERRORS = ERRORS + 1;

end


if (EMPTY !== EMPTY_EXPECTED) begin

$display ("***ERROR: EMPTY = %b, EMPTY_expected = %b", EMPTY, EMPTY_EXPECTED);
ERRORS = ERRORS + 1;

end


if (W_PTR !== W_PTR_EXPECTED) begin

$display ("***ERROR: W_PTR = %b, W_PTR_expected = %b", W_PTR, W_PTR_EXPECTED);
ERRORS = ERRORS + 1;

end


if (R_PTR !== R_PTR_EXPECTED) begin

$display ("***ERROR: R_PTR = %b, R_PTR_expected = %b", R_PTR, R_PTR_EXPECTED);
ERRORS = ERRORS + 1;

end


if (DATA_OUT !== DATA_OUT_EXPECTED) begin

$display ("***ERROR: DATA_OUT = %b, DATA_OUT_expected = %b", DATA_OUT, DATA_OUT_EXPECTED);
ERRORS = ERRORS + 1;

end

if ({RST,PUSH,POP,DATA_IN} != prev_INPUT) begin
$display("prev_INPUT = %b,INPUT=%b",prev_INPUT,{RST,PUSH,POP,DATA_IN});
$display ("***ERROR: INPUT_B - RACING CONDITION OCCUR");
ERRORS = ERRORS + 1;

end


end
endtask



//DRIVE

//0 initialize

initial begin

initialize;

end

//2 scan file on negedge TICK

always @ (negedge TICK) begin
#9.9;
if (!eof) begin

scan_file;
NEXTWR_EXP;

end
end



//3 check file on posedge TICK

always  @ (posedge TICK) begin
NEXTWR_EXP;
ADDRAB_ram;
prev_INPUT <= {RST,PUSH,POP,DATA_IN};
coverage_update;
OUT_EXP;
#0.1;
comment;
display_file;
errors_warnings_check;
vectorcount;

#0.1;
prev_ADDRA_EXPECTED <= ADDRA_EXPECTED;
prev_ADDRB_EXPECTED <= ADDRB_EXPECTED;
prev_state = {FULL_EXPECTED,EMPTY_EXPECTED};
end



// eof

initial begin

wait (eof);

$display ();
$display("%13s ***time = %0d,eof ***","",$time);
$display ();

for (i = 0; i < 50; i++) begin


if ({FULL,EMPTY,WRAP_WR,RST,PUSH,POP} == 7'b1000000)
begin

vectorcount;
close;

end

else begin

random_in;
NEXTWR_EXP;
end

end

close;

end


endmodule

verilog_project/verilog_project/fifo_synchronous/tb_fifo.vcd
$date
	Sat Feb 21 16:43:32 2026
$end
$version
	Icarus Verilog
$end
$timescale
	10ps
$end
$scope module tb_fifo $end
$var wire 5 ! W_PTR [4:0] $end
$var wire 5 " R_PTR [4:0] $end
$var wire 1 # NEXTW $end
$var wire 1 $ FULL $end
$var wire 1 % EMPTY $end
$var wire 8 & DATA_OUT_EXPECTED [7:0] $end
$var wire 8 ' DATA_OUT [7:0] $end
$var wire 5 ( ADDRB_ram [4:0] $end
$var wire 5 ) ADDRA_ram [4:0] $end
$var parameter 32 * ADDR_WIDTH $end
$var parameter 32 + DATA_WIDTH $end
$var parameter 32 , MEM_DEPTH $end
$var parameter 32 - TICKPERIOD $end
$var reg 5 . ADDRA_EXPECTED [4:0] $end
$var reg 5 / ADDRB_EXPECTED [4:0] $end
$var reg 4 0 ADDR_A [3:0] $end
$var reg 4 1 ADDR_B [3:0] $end
$var reg 248 2 COMMENT [247:0] $end
$var reg 8 3 DATA_IN [7:0] $end
$var reg 1 4 EMPTY_EXPECTED $end
$var reg 32 5 ERRORS [31:0] $end
$var reg 1 6 FULL_EXPECTED $end
$var reg 1 7 NEXT_R $end
$var reg 1 8 NEXT_W $end
$var reg 1 9 POP $end
$var reg 1 : PUSH $end
$var reg 1 ; RST $end
$var reg 5 < R_PTR_EXPECTED [4:0] $end
$var reg 1 = TICK $end
$var reg 32 > VECTORCOUNT [31:0] $end
$var reg 1 ? WRAP_WR $end
$var reg 5 @ W_PTR_EXPECTED [4:0] $end
$var reg 1 A eof $end
$var reg 5 B prev_ADDRA_EXPECTED [4:0] $end
$var reg 5 C prev_ADDRB_EXPECTED [4:0] $end
$var reg 11 D prev_INPUT [10:0] $end
$var reg 2 E prev_state [1:0] $end
$var reg 32 F wrap_coverage [31:0] $end
$var integer 32 G COUNT [31:0] $end
$var integer 32 H FD [31:0] $end
$var integer 32 I i [31:0] $end
$scope module dut_fifo $end
$var wire 1 = clk $end
$var wire 8 J data_in [7:0] $end
$var wire 1 K next_r $end
$var wire 1 L next_w $end
$var wire 1 # nextw $end
$var wire 1 9 pop $end
$var wire 1 : push $end
$var wire 1 ; rst $end
$var wire 5 M w_ptr [4:0] $end
$var wire 5 N r_ptr [4:0] $end
$var wire 1 $ full $end
$var wire 1 % empty $end
$var wire 8 O data_out [7:0] $end
$var wire 4 P addr_b [3:0] $end
$var wire 4 Q addr_a [3:0] $end
$var parameter 32 R addr_width $end
$var reg 5 S addra [4:0] $end
$var reg 5 T addrb [4:0] $end
$scope module dut_compare_and_status_section $end
$var wire 1 $ full $end
$var wire 5 U w_ptr [4:0] $end
$var wire 5 V r_ptr [4:0] $end
$var wire 1 % empty $end
$var parameter 32 W addr_width $end
$upscope $end
$scope module dut_dual_port_ram_synchronous $end
$var wire 4 X addr_a [3:0] $end
$var wire 4 Y addr_b [3:0] $end
$var wire 1 = clk $end
$var wire 8 Z data_in_a [7:0] $end
$var wire 8 [ data_in_b [7:0] $end
$var wire 1 ; rst $end
$var wire 1 L we_a $end
$var wire 1 \ we_b $end
$var parameter 32 ] ADDR_WIDTH $end
$var parameter 32 ^ DATA_WIDTH $end
$var parameter 32 _ MEM_DEPTH $end
$var reg 8 ` data_out_a [7:0] $end
$var reg 8 a data_out_b [7:0] $end
$upscope $end
$scope module dut_r_ptr_section $end
$var wire 1 = clk $end
$var wire 1 K next $end
$var wire 1 ; rst $end
$var reg 5 b r_ptr [4:0] $end
$upscope $end
$scope module dut_w_ptr_section $end
$var wire 1 = clk $end
$var wire 1 L next $end
$var wire 1 ; rst $end
$var reg 5 c w_ptr [4:0] $end
$upscope $end
$upscope $end
$scope module test_dual_port_ram_synchronous1 $end
$var wire 4 d addr_a [3:0] $end
$var wire 4 e addr_b [3:0] $end
$var wire 1 = clk $end
$var wire 8 f data_in_a [7:0] $end
$var wire 8 g data_in_b [7:0] $end
$var wire 1 ; rst $end
$var wire 1 8 we_a $end
$var wire 1 h we_b $end
$var parameter 32 i ADDR_WIDTH $end
$var parameter 32 j DATA_WIDTH $end
$var parameter 32 k MEM_DEPTH $end
$var reg 8 l data_out_a [7:0] $end
$var reg 8 m data_out_b [7:0] $end
$upscope $end
$scope task ADDRAB_ram $end
$upscope $end
$scope task NEXTWR_EXP $end
$upscope $end
$scope task OUT_EXP $end
$upscope $end
$scope task close $end
$scope begin $ivl_for_loop0 $end
$var integer 32 n j [31:0] $end
$upscope $end
$upscope $end
$scope task comment $end
$upscope $end
$scope task coverage_update $end
$scope begin $ivl_for_loop1 $end
$var integer 32 o j [31:0] $end
$scope begin $ivl_for_loop2 $end
$var integer 32 p k [31:0] $end
$upscope $end
$upscope $end
$upscope $end
$scope task display_file $end
$upscope $end
$scope task errors_warnings_check $end
$upscope $end
$scope task initialize $end
$upscope $end
$scope task random_in $end
$upscope $end
$scope task scan_file $end
$upscope $end
$scope task vectorcount $end
$upscope $end
$upscope $end
$enddefinitions $end
$comment Show the parameter values. $end
$dumpall
b10000 k
b1000 j
b100 i
b10000 _
b1000 ^
b100 ]
b100 W
b100 R
b10100 -
b10000 ,
b1000 +
b100 *
$end
#0
$dumpvars
b0 p
b0 o
b0 n
bx m
bx l
0h
b0 g
b110000 f
bx e
bx d
bx c
bx b
bx a
bx `
0\
b0 [
b110000 Z
bx Y
bx X
bx V
bx U
bx T
bx S
bx Q
bx P
bx O
bx N
bx M
0L
0K
b110000 J
b110000 I
b10000000000000000000000000000011 H
b101 G
b0 F
bx E
bx D
bx C
bx B
0A
bx @
x?
b0 >
0=
bx <
0;
0:
09
x8
x7
x6
b0 5
x4
b110000 3
b1001001010011100100100101010100 2
bx 1
bx 0
bx /
bx .
bx )
bx (
bx '
bx &
x%
x$
0#
bx "
bx !
$end
#1000
b110000 D
b11 o
07
08
1=
#1010
b1 >
b1001001010011000100110001000101010001110100000101001100 2
#2000
0=
#2990
xK
x#
xL
x7
x8
19
1:
1;
b101101 2
#3000
1#
1L
0$
0K
b0 P
b0 Y
b0 Q
b0 X
b11100110000 D
b0 &
b0 m
b0 l
b0 '
b0 O
b0 a
b0 `
1%
b0 "
b0 N
b0 V
b0 b
b0 !
b0 M
b0 U
b0 c
07
18
06
14
b0 1
b0 e
b0 0
b0 d
b0 <
b0 @
b11 o
1=
#3010
b10 >
b100010101001101010100000101010001011001 2
#3020
b1 E
#4000
0=
#4990
0#
0L
08
b110001 3
b110001 J
b110001 Z
b110001 f
09
0:
0;
b101101 2
#5000
b110001 D
bx `
bx '
bx O
bx a
b0 (
b0 T
b0 )
b0 S
bx l
bx &
bx m
b11 o
b0 /
b0 .
1=
#5010
b11 >
b100010101001101010100000101010001011001 2
#5020
b0 C
b0 B
#6000
0=
#6990
b110010 3
b110010 J
b110010 Z
b110010 f
19
b101101 2
#7000
b100110010 D
0?
b11 o
1=
#7010
b100 >
b100010101001101010100000101010001011001 2
#8000
0=
#8990
1#
1L
18
b110011 3
b110011 J
b110011 Z
b110011 f
09
1:
b101101 2
#9000
b1 Q
b1 X
b1000110011 D
0%
b1 !
b1 M
b1 U
b1 c
04
b1 0
b1 d
b1 @
b11 o
1=
#9010
b101 >
b100111001001111010101000101111101000110010101010100110001001100 2
#9020
b0 E
#10000
0=
#10990
1K
17
b110100 3
b110100 J
b110100 Z
b110100 f
19
b101101 2
#11000
b1 P
b1 Y
b10 Q
b10 X
b1100110100 D
b110011 &
b110011 m
b1 )
b1 S
b110011 '
b110011 O
b110011 a
b1 "
b1 N
b1 V
b1 b
b10 !
b10 M
b10 U
b10 c
b1 1
b1 e
b10 0
b10 d
b1 <
b10 @
b11 o
b1 .
1=
#11010
b110 >
b100111001001111010101000101111101000110010101010100110001001100 2
#11020
b1 B
#12000
0=
#12990
b110101 3
b110101 J
b110101 Z
b110101 f
b101101 2
#13000
b11 Q
b11 X
b10 P
b10 Y
b1100110101 D
b11 !
b11 M
b11 U
b11 c
0%
b10 "
b10 N
b10 V
b10 b
b110100 '
b110100 O
b110100 a
b1 (
b1 T
b10 )
b10 S
b110100 &
b110100 m
b10 1
b10 e
b11 0
b11 d
b10 <
b11 @
b11 o
b1 /
b10 .
1=
#13010
b111 >
b100111001001111010101000101111101000110010101010100110001001100 2
#13020
b1 C
b10 B
#14000
0=
#14990
b110110 3
b110110 J
b110110 Z
b110110 f
1;
b101101 2
#15000
0K
b0 P
b0 Y
b0 Q
b0 X
b11100110110 D
b0 &
b0 m
b0 l
b10 (
b10 T
b11 )
b11 S
b0 '
b0 O
b0 a
b0 `
1%
b0 "
b0 N
b0 V
b0 b
b0 !
b0 M
b0 U
b0 c
07
14
b0 1
b0 e
b0 0
b0 d
b0 <
b0 @
b11 p
b11 o
b10 /
b11 .
1=
#15010
b1000 >
b100010101001101010100000101010001011001 2
#15020
b10 C
b11 B
b1 E
#16000
0=
#16990
b110111 3
b110111 J
b110111 Z
b110111 f
09
0;
b101101 2
#17000
b1 Q
b1 X
b1000110111 D
0%
b1 !
b1 M
b1 U
b1 c
b110011 `
b110011 '
b110011 O
b110011 a
b0 (
b0 T
b0 )
b0 S
b110011 l
b110011 &
b110011 m
04
b1 0
b1 d
b1 @
b11 o
b0 /
b0 .
1=
#17010
b1001 >
b100111001001111010101000101111101000110010101010100110001001100 2
#17020
b0 C
b0 B
b0 E
#18000
0=
#18990
b111000 3
b111000 J
b111000 Z
b111000 f
b101101 2
#19000
b10 Q
b10 X
b1000111000 D
b110111 &
b110111 m
b110100 l
b1 )
b1 S
b110111 '
b110111 O
b110111 a
b110100 `
b10 !
b10 M
b10 U
b10 c
b10 0
b10 d
b10 @
b11 o
b1 .
1=
#19010
b1010 >
b100111001001111010101000101111101000110010101010100110001001100 2
#19020
b1 B
#20000
0=
#20990
0#
0L
08
b111001 3
b111001 J
b111001 Z
b111001 f
0:
b101101 2
#21000
b111001 D
b110101 `
b10 )
b10 S
b110101 l
b11 o
b10 .
1=
#21010
b1011 >
b100111001001111010101000101111101000110010101010100110001001100 2
#21020
b10 B
#22000
0=
#22990
1K
17
b1100001 3
b1100001 J
b1100001 Z
b1100001 f
19
b101101 2
#23000
b1 P
b1 Y
b101100001 D
b1 "
b1 N
b1 V
b1 b
b1 1
b1 e
b1 <
b11 o
1=
#23010
b1100 >
b100111001001111010101000101111101000110010101010100110001001100 2
#24000
0=
#24990
0K
1#
1L
07
18
b1100010 3
b1100010 J
b1100010 Z
b1100010 f
09
1:
b101101 2
#25000
b11 Q
b11 X
b1001100010 D
b11 !
b11 M
b11 U
b11 c
b111000 '
b111000 O
b111000 a
b1 (
b1 T
b111000 &
b111000 m
b11 0
b11 d
b11 @
b11 o
b1 /
1=
#25010
b1101 >
b100111001001111010101000101111101000110010101010100110001001100 2
#25020
b1 C
#26000
0=
#26990
1K
17
b1100011 3
b1100011 J
b1100011 Z
b1100011 f
19
b101101 2
#27000
b10 P
b10 Y
b100 Q
b100 X
b1101100011 D
bx l
b11 )
b11 S
bx `
b10 "
b10 N
b10 V
b10 b
b100 !
b100 M
b100 U
b100 c
b10 1
b10 e
b100 0
b100 d
b10 <
b100 @
b11 o
b11 .
1=
#27010
b1110 >
b100111001001111010101000101111101000110010101010100110001001100 2
#27020
b11 B
#28000
0=
#28990
b1100100 3
b1100100 J
b1100100 Z
b1100100 f
1;
b101101 2
#29000
0K
b0 Q
b0 X
b0 P
b0 Y
b11101100100 D
1%
b0 !
b0 M
b0 U
b0 c
b0 "
b0 N
b0 V
b0 b
b0 `
b0 '
b0 O
b0 a
b10 (
b10 T
b100 )
b100 S
b0 l
b0 &
b0 m
07
14
b0 1
b0 e
b0 0
b0 d
b0 <
b0 @
b11 p
b11 o
b10 /
b100 .
1=
#29010
b1111 >
b100010101001101010100000101010001011001 2
#29020
b10 C
b100 B
b1 E
#30000
0=
#30990
b1100101 3
b1100101 J
b1100101 Z
b1100101 f
09
0;
b101101 2
#31000
b1 Q
b1 X
b1001100101 D
b110111 &
b110111 m
b110111 l
b0 (
b0 T
b0 )
b0 S
b110111 '
b110111 O
b110111 a
b110111 `
0%
b1 !
b1 M
b1 U
b1 c
04
b1 0
b1 d
b1 @
b11 o
b0 /
b0 .
1=
#31010
b10000 >
b100111001001111010101000101111101000110010101010100110001001100 2
#31020
b0 C
b0 B
b0 E
#32000
0=
#32990
b1100110 3
b1100110 J
b1100110 Z
b1100110 f
b101101 2
#33000
b10 Q
b10 X
b1001100110 D
b10 !
b10 M
b10 U
b10 c
b111000 `
b1100101 '
b1100101 O
b1100101 a
b1 )
b1 S
b111000 l
b1100101 &
b1100101 m
b10 0
b10 d
b10 @
b11 o
b1 .
1=
#33010
b10001 >
b100111001001111010101000101111101000110010101010100110001001100 2
#33020
b1 B
#34000
0=
#34990
0#
0L
08
b1100111 3
b1100111 J
b1100111 Z
b1100111 f
0:
b101101 2
#35000
b1100111 D
b1100010 l
b10 )
b10 S
b1100010 `
b11 o
b10 .
1=
#35010
b10010 >
b100111001001111010101000101111101000110010101010100110001001100 2
#35020
b10 B
#36000
0=
#36990
1K
17
b1101000 3
b1101000 J
b1101000 Z
b1101000 f
19
b101101 2
#37000
b1 P
b1 Y
b101101000 D
b1 "
b1 N
b1 V
b1 b
b1 1
b1 e
b1 <
b11 o
1=
#37010
b10011 >
b100111001001111010101000101111101000110010101010100110001001100 2
#38000
0=
#38990
0K
1#
1L
07
18
b1101001 3
b1101001 J
b1101001 Z
b1101001 f
09
1:
b101101 2
#39000
b11 Q
b11 X
b1001101001 D
b1100110 &
b1100110 m
b1 (
b1 T
b1100110 '
b1100110 O
b1100110 a
b11 !
b11 M
b11 U
b11 c
b11 0
b11 d
b11 @
b11 o
b1 /
1=
#39010
b10100 >
b100111001001111010101000101111101000110010101010100110001001100 2
#39020
b1 C
#40000
0=
#40990
1K
17
b1101010 3
b1101010 J
b1101010 Z
b1101010 f
19
b101101 2
#41000
b100 Q
b100 X
b10 P
b10 Y
b1101101010 D
b100 !
b100 M
b100 U
b100 c
b10 "
b10 N
b10 V
b10 b
b1100011 `
b11 )
b11 S
b1100011 l
b10 1
b10 e
b100 0
b100 d
b10 <
b100 @
b11 o
b11 .
1=
#41010
b10101 >
b100111001001111010101000101111101000110010101010100110001001100 2
#41020
b11 B
#42000
0=
#42990
b1101011 3
b1101011 J
b1101011 Z
b1101011 f
1;
b101101 2
#43000
0K
b0 P
b0 Y
b0 Q
b0 X
b11101101011 D
b0 &
b0 m
b0 l
b10 (
b10 T
b100 )
b100 S
b0 '
b0 O
b0 a
b0 `
1%
b0 "
b0 N
b0 V
b0 b
b0 !
b0 M
b0 U
b0 c
07
14
b0 1
b0 e
b0 0
b0 d
b0 <
b0 @
b11 p
b11 o
b10 /
b100 .
1=
#43010
b10110 >
b100010101001101010100000101010001011001 2
#43020
b10 C
b100 B
b1 E
#44000
0=
#44990
b1101100 3
b1101100 J
b1101100 Z
b1101100 f
b101101 2
#45000
b11101101100 D
b0 (
b0 T
b0 )
b0 S
b11 p
b11 o
b0 /
b0 .
1=
#45010
b10111 >
b100010101001101010100000101010001011001 2
#45020
b0 C
b0 B
#46000
0=
#46990
b1101101 3
b1101101 J
b1101101 Z
b1101101 f
09
0;
b101101 2
#47000
b1 Q
b1 X
b1001101101 D
b1100101 &
b1100101 m
b1100101 l
b1100101 '
b1100101 O
b1100101 a
b1100101 `
0%
b1 !
b1 M
b1 U
b1 c
04
b1 0
b1 d
b1 @
b11 o
1=
#47010
b11000 >
b100111001001111010101000101111101000110010101010100110001001100 2
