verilog_project/verilog_project/t_flip_flop/t_flip_flop.v
// A jk (Jack Kilby) flip-flop which is pulse-triggered can be set and reset and by creating a versatile memory element, invalid state is prevented.

module t_flip_flop_gate (
    input  wire t,
    input  wire clk,
    output wire q,
    output wire qbar
);


    wire j ,k ,s ,r ,q1, qbar1, q2, qbar2;

    reg  prev_q, prev_qbar;

    
    always@(posedge clk)begin
    #0.12;

    prev_q = q;
    prev_qbar = qbar;
    
    end
    
    assign j = t;
    assign k = t;

    nand (s, j, clk, prev_qbar);
    nand (r, k, clk, prev_q);

    nand (q1, s, prev_qbar);
    nand (qbar1, r, prev_q);

    nand (q2, s, qbar1);
    nand (qbar2, r, q1);

    nand (q, s, qbar2);
    nand (qbar, r, q2);


endmodule


module t_flip_flop_dataflow (
    input  wire t,
    input  wire clk,
    output wire q,
    output wire qbar
);

    wire j ,k, s, r, q1, qbar1, q2, qbar2;
    
    reg  prev_q, prev_qbar;

    
    always@(posedge clk)begin
    #0.2;

    prev_q = q;
    prev_qbar = qbar;
    
    end

    assign j = t;
    assign k = t;


    assign s = ~(j & clk & prev_qbar);
    assign r = ~(k & clk & prev_q);

    assign q1 = ~(s & prev_qbar);
    assign qbar1 = ~(r & prev_q);

    assign q2 = ~(s & qbar1);
    assign qbar2= ~(r & q1);

    assign q = ~(s & qbar2);
    assign qbar =~(r & q2);


endmodule


module t_flip_flop_behavioral (
    input  wire t,
    input  wire clk,
    output reg  q,
    output wire qbar
);
                 
  
 
    assign qbar = ~q;

    always @(posedge clk) begin
        case (t)
            1'b0: q <= q;        // HOLD
            1'b1: q <= qbar;     // TOGGLE
        endcase
    end

endmodule

verilog_project/t_flip_flop/tb_t_flip_flop.v
`timescale 1ns/10ps

module tb_t_flip_flop;

//VECTORS FOR DUT
reg T;
wire Q_gate, Q_data, Q_beh, QBAR_gate, QBAR_data, QBAR_beh;

//VECTORS FOR TESTING

reg TICK;
integer FD, COUNT;
reg [8*9-1:0] COMMENT;
reg [8*9-1:0] COMMENT1;
reg [8*9-1:0] COMMENT2;
reg QEXPECTED, QBAREXPECTED;
reg [31:0] VECTORCOUNT, ERRORS;
int i;
reg [31:0] input_coverage[0:3];
reg eof;
reg prev_T;
reg prev_QEx;
reg prev_QExbar;
reg prev_Qgate;
reg prev_Qbargate;
reg prev_Qdata;
reg prev_Qbardata;
reg prev_Qbeh;
reg prev_Qbarbeh;

//DUT INSTANTIATION

t_flip_flop_gate dut_t_flip_flop_gate (.t(T), .q(Q_gate), .qbar(QBAR_gate), .clk(TICK));
t_flip_flop_dataflow dut_t_flip_flop_dataflow (.t(T), .q(Q_data), .qbar(QBAR_data), .clk(TICK));
t_flip_flop_behavioral dut_t_flip_flop_behavioral (.t(T), .q(Q_beh), .qbar(QBAR_beh), .clk(TICK));



//DUMP EVERYTHING INTO DUMPFILE

initial begin

$dumpfile ("tb_t_flip_flop.vcd");
$dumpvars (0, tb_t_flip_flop);

end

//TICKPERIOD

localparam TICKPERIOD = 20;

always begin

#(TICKPERIOD/2) TICK = ~TICK;

end



//TASKS

//task 1 initialize

task initialize; begin

FD = $fopen ("tb_t_flip_flop.tv" , "r");
COUNT = $fscanf (FD, "%s", COMMENT);

COUNT = $fscanf (FD, "%s %b %s %s", COMMENT, T, COMMENT1, COMMENT2);
TICK = 0;
VECTORCOUNT = 0;
ERRORS = 0;

for ( i = 0 ; i < 4 ; i++ ) begin
input_coverage[i] = 0;
end

eof = 0;

$display ();
$display ("TEST_START------------------------------------------------------------------------------------------------------------------------");
$display ();
$display ("                     | TIME | T |  Q_gate  |  Q_data  |  Q_beh  | QBAR_gate | QBAR_data | QEXPECTED | QBAREXPECTED |");
$display ("----------------------------------------------------------------------------------------------------------------------------------");



end
endtask

//task2 force_release

task force_release; begin

#0.11;

force Q_gate = 1'b0;
force QBAR_gate = 1'b1;
force Q_data = 1'b0;
force QBAR_data = 1'b1;
force Q_beh = 1'b0;
force QBAR_beh = 1'b1;
force QEXPECTED = 1'b0;
force QBAREXPECTED = 1'b1;

#10;

release Q_gate;
release QBAR_gate;
release Q_data;
release QBAR_data;
release QEXPECTED;
release QBAREXPECTED;

@(posedge TICK)
#0.1
release Q_beh;
release QBAR_beh;

end
endtask



//task 3 scan_file

task scan_file; begin


COUNT = $fscanf (FD,"%s %b %b %b", COMMENT, T, QEXPECTED, QBAREXPECTED);
eof = (COUNT == -1);

end
endtask

//task 4 random_in

task random_in; begin

T =  $urandom %2 ;

case (T)
1'b0: COMMENT =  (((({prev_Qgate,prev_Qbargate})== 2'b11) || (({prev_Qdata,prev_Qbardata})== 2'b11) || (({prev_Qbeh,prev_Qbarbeh})== 2'b11)) || ((({prev_Qgate,prev_Qbargate})== 2'b00)||(({prev_Qdata,prev_Qbardata})== 2'b00) || (({prev_Qbeh,prev_Qbarbeh})== 2'b00)))? "ILLEGAL":"HOLD";
1'b1: COMMENT =  (((({prev_Qgate,prev_Qbargate})== 2'b11) || (({prev_Qdata,prev_Qbardata})== 2'b11) || (({prev_Qbeh,prev_Qbarbeh})== 2'b11)) || ((({prev_Qgate,prev_Qbargate})== 2'b00)||(({prev_Qdata,prev_Qbardata})== 2'b00) || (({prev_Qbeh,prev_Qbarbeh})== 2'b00)))?"ILLEGAL":"TOGGLE";

endcase

#($urandom_range (0.1,10));

end
endtask

//task 5 QEXP

task QEXP; begin

if (((({prev_Qgate,prev_Qbargate})== 2'b11) || (({prev_Qdata,prev_Qbardata})== 2'b11) || (({prev_Qbeh,prev_Qbarbeh})== 2'b11)) || ((({prev_Qgate,prev_Qbargate})== 2'b00)||(({prev_Qdata,prev_Qbardata})== 2'b00) || (({prev_Qbeh,prev_Qbarbeh})== 2'b00)) && (( T == 1'b0)||( T == 1'b1))) begin

QEXPECTED = 1'bx;
QBAREXPECTED = 1'bx;

end

else begin

case ( T )
  1'b0: begin
QEXPECTED = prev_QEx;
QBAREXPECTED = prev_QExbar;
end
  1'b1: begin
QEXPECTED = ~prev_QEx;
QBAREXPECTED = ~prev_QExbar;
end


endcase
end



end
endtask



//task 6 close

task close; begin

#10;
$fclose (FD);

$display ();
$display ("COVERAGE_REPORT");

for ( i = 0; i < 4; i++ ) begin

if(input_coverage[i] == 0) begin

$display ("input %b to input %b has occured %d times (***ERROR***)",i[1], i[0], input_coverage[i]);
ERRORS = ERRORS +1;

end

else begin

$display ("input %b to input %b has occured %d times",i[1], i[0], input_coverage[i]);

end

end

$display ();
$display ("VECTORCOUNT = %d", VECTORCOUNT);
$display ("ERRORS = %15d", ERRORS);
$display ();
$display ("TEST_END--------------------------------------------------------------------------------------------------------------------------");
$display ();

$finish;

end
endtask


//task 7 vectorcount

task vectorcount; begin

VECTORCOUNT = VECTORCOUNT + 1;

end
endtask


//task 8 display_file

task display_file; begin

$display ("%10d %9s | %4d | %1d | %4d     | %4d     | %4d    | %5d     | %5d     | %5d     | %6d       |", VECTORCOUNT, COMMENT, $time, T, Q_gate, Q_data, Q_beh, QBAR_gate, QBAR_data, QEXPECTED, QBAREXPECTED);

end
endtask

//task 9 coverage_update

task coverage_update; begin

input_coverage[{prev_T, T}]++;

end
endtask

//task 10 errors_check

task errors_check; begin


if  (((({prev_Qgate,prev_Qbargate})== 2'b00) || (({prev_Qdata,prev_Qbardata})== 2'b00) || (({prev_Qbeh,prev_Qbarbeh})== 2'b00)) && (( T == 1'b0)||( T == 1'b1))) begin

$display ("***ERROR: ILLEGAL CONDITION,RACING CONDITION");
ERRORS = ERRORS + 1;

end

if  (((({prev_Qgate,prev_Qbargate})== 2'b11) || (({prev_Qdata,prev_Qbardata})== 2'b11) || (({prev_Qbeh,prev_Qbarbeh})== 2'b11)) && (( T == 1'b0)||( T == 1'b1))) begin

$display ("***ERROR: ILLEGAL CONDITION, q = %b and qbar = %b", QEXPECTED, QBAREXPECTED );
ERRORS = ERRORS + 1;

end



if (Q_gate !== QEXPECTED) begin

$display ("***ERROR: Q_gate = %b, Q_expected = %b", Q_gate, QEXPECTED);
ERRORS = ERRORS + 1;

end

if (Q_data !== QEXPECTED) begin

$display ("***ERROR: Q_dataflow = %b, Q_expected = %b", Q_data, QEXPECTED);
ERRORS = ERRORS + 1;

end

if (Q_beh !== QEXPECTED) begin

$display ("***ERROR: Q_behavioral = %b, Q_expected = %b", Q_beh, QEXPECTED);
ERRORS = ERRORS + 1;

end

if (QBAR_gate !== QBAREXPECTED) begin

$display ("***ERROR: QBAR_gate = %b, QBAR_expected = %b", QBAR_gate, QBAREXPECTED);
ERRORS = ERRORS + 1;

end

if (QBAR_data !== QBAREXPECTED) begin

$display ("***ERROR: QBAR_dataflow = %b, QBAR_expected = %b", QBAR_data, QBAREXPECTED);
ERRORS = ERRORS + 1;

end

if ( T !== prev_T ) begin

$display ("***ERROR: Racing Condition Occur");
ERRORS = ERRORS + 1;

end


end
endtask



//DRIVE

//0 initialize

initial begin

initialize;

@(posedge TICK);

force_release;

end


//2 scan file on negedge TICK

always @ (negedge TICK) begin


#1.2;

if (!eof) begin



scan_file;

end
end



//3 check file on posedge TICK

always  @ (posedge TICK) begin

coverage_update;
prev_T = T;

#0.1;

QEXP;
display_file;
errors_check;
vectorcount;

#0.02;


prev_Qgate    = Q_gate;
prev_Qbargate = QBAR_gate;
prev_Qdata    = Q_data;
prev_Qbardata = QBAR_data;
prev_Qbeh     = Q_beh;
prev_Qbarbeh  = QBAR_beh;
prev_QEx = QEXPECTED;
prev_QExbar = QBAREXPECTED;



end



// eof

initial begin

wait (eof);

$display ();
$display("%13s ***time = %0d,eof ***","",$time);
$display ();

for (i = 0; i < 50; i++) begin


if ( T == 2)
begin

vectorcount;
close;

end

else begin


random_in;



end

end

close;

end


endmodule

verilog_project/verilog_project/t_flip_flop/tb_t_flip_flop.vcd
$date
	Wed Jan 14 01:02:19 2026
$end
$version
	Icarus Verilog
$end
$timescale
	10ps
$end
$scope module tb_t_flip_flop $end
$var wire 1 ! Q_gate $end
$var wire 1 " Q_data $end
$var wire 1 # Q_beh $end
$var wire 1 $ QBAR_gate $end
$var wire 1 % QBAR_data $end
$var wire 1 & QBAR_beh $end
$var parameter 32 ' TICKPERIOD $end
$var reg 72 ( COMMENT [71:0] $end
$var reg 72 ) COMMENT1 [71:0] $end
$var reg 72 * COMMENT2 [71:0] $end
$var reg 32 + ERRORS [31:0] $end
$var reg 1 , QBAREXPECTED $end
$var reg 1 - QEXPECTED $end
$var reg 1 . T $end
$var reg 1 / TICK $end
$var reg 32 0 VECTORCOUNT [31:0] $end
$var reg 1 1 eof $end
$var reg 1 2 prev_QEx $end
$var reg 1 3 prev_QExbar $end
$var reg 1 4 prev_Qbarbeh $end
$var reg 1 5 prev_Qbardata $end
$var reg 1 6 prev_Qbargate $end
$var reg 1 7 prev_Qbeh $end
$var reg 1 8 prev_Qdata $end
$var reg 1 9 prev_Qgate $end
$var reg 1 : prev_T $end
$var integer 32 ; COUNT [31:0] $end
$var integer 32 < FD [31:0] $end
$var integer 32 = i [31:0] $end
$scope module dut_t_flip_flop_behavioral $end
$var wire 1 / clk $end
$var wire 1 & qbar $end
$var wire 1 . t $end
$var reg 1 # q $end
$upscope $end
$scope module dut_t_flip_flop_dataflow $end
$var wire 1 / clk $end
$var wire 1 > j $end
$var wire 1 ? k $end
$var wire 1 " q $end
$var wire 1 @ q1 $end
$var wire 1 A q2 $end
$var wire 1 % qbar $end
$var wire 1 B qbar1 $end
$var wire 1 C qbar2 $end
$var wire 1 D r $end
$var wire 1 E s $end
$var wire 1 . t $end
$var reg 1 F prev_q $end
$var reg 1 G prev_qbar $end
$upscope $end
$scope module dut_t_flip_flop_gate $end
$var wire 1 / clk $end
$var wire 1 H j $end
$var wire 1 I k $end
$var wire 1 ! q $end
$var wire 1 J q1 $end
$var wire 1 K q2 $end
$var wire 1 $ qbar $end
$var wire 1 L qbar1 $end
$var wire 1 M qbar2 $end
$var wire 1 N r $end
$var wire 1 O s $end
$var wire 1 . t $end
$var reg 1 P prev_q $end
$var reg 1 Q prev_qbar $end
$upscope $end
$scope task QEXP $end
$upscope $end
$scope task close $end
$upscope $end
$scope task coverage_update $end
$upscope $end
$scope task display_file $end
$upscope $end
$scope task errors_check $end
$upscope $end
$scope task force_release $end
$upscope $end
$scope task initialize $end
$upscope $end
$scope task random_in $end
$upscope $end
$scope task scan_file $end
$upscope $end
$scope task vectorcount $end
$upscope $end
$upscope $end
$enddefinitions $end
$comment Show the parameter values. $end
$dumpall
b10100 '
$end
#0
$dumpvars
xQ
xP
1O
1N
xM
xL
xK
xJ
0I
0H
xG
xF
1E
1D
xC
xB
xA
x@
0?
0>
b100 =
b10000000000000000000000000000011 <
b100 ;
x:
x9
x8
x7
x6
x5
x4
x3
x2
01
b0 0
0/
0.
x-
x,
b0 +
b1011000 *
b1011000 )
b1001001010011100100100101010100 (
x&
x%
x$
x#
x"
x!
$end
#1000
0:
1/
#1010
b1 0
#1011
1,
0-
1&
0#
1%
0"
1$
0!
#1012
0!
1$
1M
0K
0J
1L
13
02
14
07
15
08
16
09
1Q
0P
#1020
0"
1%
1C
0A
0@
1B
1G
0F
#2000
0/
#2011
1,
0-
1%
0"
1$
0!
#2120
b1001000010011110100110001000100 (
#3000
0#
1/
#3010
b10 0
1&
0#
#4000
0/
#5000
1/
#5010
b11 0
#6000
0/
#6120
0,
1-
1>
1?
1H
1I
1.
b10101000100111101000111010001110100110001000101 (
#7000
0&
1#
0C
0%
1@
1A
1"
0E
0M
0$
1J
1K
1!
1:
0O
1/
#7010
b100 0
#7012
0K
0!
1M
1$
1O
0N
03
12
04
17
05
18
06
19
0Q
1P
#7020
0A
0"
1C
1%
1E
1B
0D
0G
1F
#8000
0%
1A
1"
0B
0C
0$
1D
1K
1!
0L
0M
1N
0/
#8120
1,
0-
#9000
1&
0#
0A
0"
1B
1C
1%
0D
0K
0!
1L
1M
1$
0N
1/
#9010
b101 0
#9012
0$
1K
1!
0M
0O
1N
13
02
14
07
15
08
16
09
1Q
0P
#9020
0C
0%
1A
1"
1@
0E
1D
1G
0F
#10000
0"
1C
1%
0@
0A
0!
1E
1M
1$
0J
0K
1O
0/
#10120
0>
0?
0H
0I
0.
b1001000010011110100110001000100 (
#11000
0:
1/
#11010
b110 0
#12000
0/
#12120
0,
1-
1>
1?
1H
1I
1.
b10101000100111101000111010001110100110001000101 (
#13000
0&
1#
0C
0%
1@
1A
1"
0E
0M
0$
1J
1K
1!
1:
0O
1/
#13010
b111 0
#13012
0K
0!
1M
1$
1O
0N
03
12
04
17
05
18
06
19
0Q
1P
#13020
0A
0"
1C
1%
1E
1B
0D
0G
1F
#14000
0%
1A
1"
0B
0C
0$
1D
1K
1!
0L
0M
1N
0/
#14120
1,
0-
#15000
1&
0#
0A
0"
1B
1C
1%
0D
0K
0!
1L
1M
1$
0N
1/
#15010
b1000 0
#15012
0$
1K
1!
0M
0O
1N
13
02
14
07
15
08
16
09
1Q
0P
#15020
0C
0%
1A
1"
1@
0E
1D
1G
0F
#16000
0"
1C
1%
0@
0A
0!
1E
1M
1$
0J
0K
1O
0/
#16120
b0 ;
#17000
0&
1#
0C
0%
1@
1A
1"
0E
0M
0$
1J
1K
1!
0O
1/
#17010
b1001 0
0,
1-
#17012
0K
0!
1M
1$
1O
0N
03
12
04
17
05
18
06
19
0Q
1P
#17020
0A
0"
1C
1%
1E
1B
0D
0G
1F
#18000
0%
1A
1"
0B
0C
0$
1D
1K
1!
0L
0M
1N
0/
#18120
b1001000010011110100110001000100 (
0>
0?
0H
0I
0.
b0 =
11
b11111111111111111111111111111111 ;
#18320
b10101000100111101000111010001110100110001000101 (
1>
1?
1H
1I
1.
b1 =
#18520
b10 =
#19000
1&
0#
0A
0"
1B
1C
1%
0D
0K
0!
1L
1M
1$
0N
1/
#19010
b1010 0
1,
0-
#19012
0$
1K
1!
0M
0O
1N
13
02
14
07
15
08
16
09
1Q
0P
#19020
0C
0%
1A
1"
1@
0E
1D
1G
0F
#19320
b100 =
#19820
0"
1C
1%
0@
0A
0!
1E
1M
1$
0J
0K
1O
b1001000010011110100110001000100 (
0>
0?
0H
0I
0.
b101 =
#20000
0/
#20420
b10101000100111101000111010001110100110001000101 (
1>
1?
1H
1I
1.
b110 =
#21000
0&
1#
0C
0%
1@
1A
1"
0E
0M
0$
1J
1K
1!
0O
1/
#21010
b1011 0
0,
1-
#21012
0K
0!
1M
1$
1O
0N
03
12
04
17
05
18
06
19
0Q
1P
#21020
0A
0"
1C
1%
1E
1B
0D
0G
1F
#21220
b111 =
#21620
b1000 =
#21920
b1001 =
#22000
0%
1A
1"
0B
0C
0$
1D
1K
1!
0L
0M
1N
0/
#22120
b1001000010011110100110001000100 (
0>
0?
0H
0I
0.
b1010 =
#22920
b1011 =
#23000
0:
1/
#23010
b1100 0
#23320
b1100 =
#23720
b1101 =
#24000
0/
#24120
b10101000100111101000111010001110100110001000101 (
1>
1?
1H
1I
1.
b1110 =
#24320
b1111 =
#24820
b1001000010011110100110001000100 (
0>
0?
0H
0I
0.
b10000 =
#25000
1/
#25010
b1101 0
#25420
b10001 =
#25720
0A
0"
1B
1C
1%
0D
0K
0!
1L
1M
1$
0N
b10101000100111101000111010001110100110001000101 (
1>
1?
1H
1I
1.
b10011 =
#25820
b10100 =
#26000
0%
1A
1"
0B
0C
0$
1D
1K
1!
0L
0M
1N
0/
#26220
b1001000010011110100110001000100 (
0>
0?
0H
0I
0.
b10101 =
#26520
b10101000100111101000111010001110100110001000101 (
1>
1?
1H
1I
1.
b10110 =
#26920
b10111 =
#27000
1&
0#
0A
0"
1B
1C
1%
0D
0K
0!
1L
1M
1$
1:
0N
1/
#27010
b1110 0
1,
0-
#27012
0$
1K
1!
0M
0O
1N
13
02
14
07
15
08
16
09
1Q
0P
#27020
0C
0%
1A
1"
1@
0E
1D
1G
0F
#27420
0"
1C
1%
0@
0A
0!
1E
1M
1$
0J
0K
1O
b1001000010011110100110001000100 (
0>
0?
0H
0I
0.
b11000 =
#27520
b11001 =
#28000
0/
#28320
b10101000100111101000111010001110100110001000101 (
1>
1?
1H
1I
1.
b11010 =
#28720
b1001000010011110100110001000100 (
0>
0?
0H
0I
0.
b11011 =
#28920
b10101000100111101000111010001110100110001000101 (
1>
1?
1H
1I
1.
b11100 =
#29000
0&
1#
0C
0%
1@
1A
1"
0E
0M
0$
1J
1K
1!
0O
1/
#29010
b1111 0
0,
1-
#29012
0K
0!
1M
1$
1O
0N
03
12
04
17
05
18
06
19
0Q
1P
#29020
0A
0"
1C
1%
1E
1B
0D
0G
1F
#29820
0%
1A
1"
0B
0C
0$
1D
1K
1!
0L
0M
1N
b1001000010011110100110001000100 (
0>
0?
0H
0I
0.
b11101 =
#30000
0/
#30720
b11110 =
#31000
0:
1/
#31010
b10000 0
#31320
0A
0"
1B
1C
1%
0D
0K
0!
1L
1M
1$
0N
b10101000100111101000111010001110100110001000101 (
1>
1?
1H
1I
1.
b11111 =
#31520
b100000 =
#32000
0%
1A
1"
0B
0C
0$
1D
1K
1!
0L
0M
1N
0/
#32220
b100001 =
#32820
b1001000010011110100110001000100 (
0>
0?
0H
0I
0.
b100010 =
#33000
1/
#33010
b10001 0
#33320
0A
0"
1B
1C
1%
0D
0K
0!
1L
1M
1$
0N
b10101000100111101000111010001110100110001000101 (
1>
1?
1H
1I
1.
b100011 =
#34000
0%
1A
1"
0B
0C
0$
1D
1K
1!
0L
0M
1N
0/
#34320
b1001000010011110100110001000100 (
0>
0?
0H
0I
0.
b100100 =
#35000
1/
#35010
b10010 0
#35020
0A
0"
1B
1C
1%
0D
0K
0!
1L
1M
1$
0N
b10101000100111101000111010001110100110001000101 (
1>
1?
1H
1I
1.
b100101 =
#35820
0%
1A
1"
0B
0C
0$
1D
1K
1!
0L
0M
1N
b1001000010011110100110001000100 (
0>
0?
0H
0I
0.
b100110 =
#36000
0/
#36120
b10101000100111101000111010001110100110001000101 (
1>
1?
1H
1I
1.
b100111 =
#36220
b101000 =
#37000
1&
0#
0A
0"
1B
1C
1%
0D
0K
0!
1L
1M
1$
1:
0N
1/
#37010
b10011 0
1,
0-
#37012
0$
1K
1!
0M
0O
1N
13
02
14
07
15
08
16
09
1Q
0P
#37020
0C
0%
1A
1"
1@
0E
1D
1G
0F
b101001 =
#37420
b101010 =
#37520
0"
1C
1%
0@
0A
0!
1E
1M
1$
0J
0K
1O
b1001000010011110100110001000100 (
0>
0?
0H
0I
0.
b101011 =
#38000
0/
#38020
b101100 =
#38920
b10101000100111101000111010001110100110001000101 (
1>
1?
1H
1I
1.
b101101 =
#39000
0&
1#
0C
0%
1@
1A
1"
0E
0M
0$
1J
1K
1!
0O
1/
#39010
b10100 0
0,
1-
#39012
0K
0!
1M
1$
1O
0N
03
12
04
17
05
18
06
19
0Q
1P
#39020
0A
0"
1C
1%
1E
1B
0D
0G
1F
#39520
0%
1A
1"
0B
0C
0$
1D
1K
1!
0L
0M
1N
b1001000010011110100110001000100 (
0>
0?
0H
0I
0.
b101110 =
#39720
0A
0"
1B
1C
1%
0D
0K
0!
1L
1M
1$
0N
b10101000100111101000111010001110100110001000101 (
1>
1?
1H
1I
1.
b101111 =
#40000
0%
1A
1"
0B
0C
0$
1D
1K
1!
0L
0M
1N
0/
#40320
b110000 =
#40720
b110001 =
#40920
b110010 =
#41000
1&
0#
0A
0"
1B
1C
1%
0D
0K
0!
1L
1M
1$
0N
1/
#41010
b10101 0
1,
0-
#41012
0$
1K
1!
0M
0O
1N
13
02
14
07
15
08
16
09
1Q
0P
#41020
0C
0%
1A
1"
1@
0E
1D
1G
0F
#41920
b100 =
