verilog_project/verilog_project/jkff_posedge_sync_clear/jkff_posedge_sync_clear.v
// A jk (Jack Kilby) flip-flop which is sync clear at posedge can be set and reset and by creating a versatile memory element, invalid state is prevented.



module jkff_posedge_sync_clear_behavioral (
    input  wire j,
    input  wire k,
    input  wire clk,
    input  wire clrbar,
    output reg  q,
    output wire qbar
);

    parameter NOCHANGE = 2'b00,
              RESET    = 2'b01,
              SET      = 2'b10,
              TOGGLE   = 2'b11;
    
    

    assign qbar = ~q;
    

//JK FLIP-FLOP WITH SYNC CLEAR
    always @(posedge clk) begin
        
        if (~clrbar) begin
            q <= 1'b0;
        end else begin
    
        case ({j,k})
            NOCHANGE: q <= q;        
            RESET   : q <= 1'b0;     
            SET     : q <= 1'b1;     
            TOGGLE  : q <= ~q;       


        endcase
        end
     
     end

endmodule

verilog_project/verilog_project/jkff_posedge_sync_clear/tb_jkff_posedge_sync_clear.v
`timescale 1ns/10ps

module tb_jkff_posedge_sync_clear;

//VECTORS FOR DUT
reg J, K;
wire Q_beh, QBAR_beh;

//VECTORS FOR TESTING

reg TICK;
integer FD, COUNT;
reg [8*9-1:0] COMMENT;
reg [8*9-1:0] COMMENT1;
reg [8*9-1:0] COMMENT2;
reg QEXPECTED, QBAREXPECTED;
reg [31:0] VECTORCOUNT, ERRORS;
int i;
reg [31:0] input_coverage[0:15];
reg eof;
reg [1:0] prev_JK;
reg prev_Qbeh;
reg prev_Qbarbeh;
reg prev_QEx;
reg prev_QExbar;
reg CLRBAR;


//DUT INSTANTIATION

jkff_posedge_sync_clear_behavioral dut_jkff_posedge_sync_clear_behavioral (.j(J), .k(K), .q(Q_beh),.qbar(QBAR_beh), .clk(TICK), .clrbar(CLRBAR));



//DUMP EVERYTHING INTO DUMPFILE

initial begin

$dumpfile ("tb_jkff_posedge_sync_clear.vcd");
$dumpvars (0, tb_jkff_posedge_sync_clear);

end

//TICKPERIOD

localparam TICKPERIOD = 20;

always begin

#(TICKPERIOD/2) TICK = ~TICK;

end

//TICK 2

always begin

# (TICKPERIOD) CLRBAR = ~CLRBAR;

end


//TASKS

//task 1 initialize

task initialize; begin

FD = $fopen ("tb_jkff_posedge_sync_clear.tv" , "r");
COUNT = $fscanf (FD, "%s", COMMENT);

COUNT = $fscanf (FD, "%s %b %b %s %s", COMMENT, J, K, COMMENT1, COMMENT2);
TICK = 0;
VECTORCOUNT = 0;
ERRORS = 0;

for ( i = 0 ; i < 16 ; i++ ) begin
input_coverage[i] = 0;
end

eof = 0;
CLRBAR = 1;

$display ();
$display ("TEST_START------------------------------------------------------------------------------------------------------------------------");
$display ();
$display ("                     | TIME | J | K | Q_beh   | QEXPECTED | QBAREXPECTED | CLRBAR |");
$display ("----------------------------------------------------------------------------------------------------------------------------------");



end
endtask

//task2 force_release

task force_release; begin

#0.11;

force Q_beh = 1'b0;
force QBAR_beh = 1'b1;

#10;

release Q_beh;
release QBAR_beh;

end
endtask

//task 3 scan_file

task scan_file; begin


COUNT = $fscanf (FD,"%s %b %b %b %b", COMMENT, J, K, QEXPECTED, QBAREXPECTED);
eof = (COUNT == -1);

end
endtask

//task 4 random_in

task random_in; begin


J =  $urandom %2 ;
K =  $urandom %2 ;

case ({J,K})
2'b00: COMMENT = ((({prev_Qbeh,prev_Qbarbeh}) == 2'b11) || (({prev_Qbeh,prev_Qbarbeh}) == 2'b00))? "ILLEGAL":"NO_CHANGE";
2'b01: COMMENT = "RESET";
2'b10: COMMENT = "SET";
2'b11: COMMENT = ((({prev_Qbeh,prev_Qbarbeh}) == 2'b11) || (({prev_Qbeh,prev_Qbarbeh}) == 2'b00))? "ILLEGAL": "REVERSE";



endcase

#($urandom_range (0.1,10));

end
endtask

//task 5 QEXP

task QEXP; begin

if (((({prev_Qbeh,prev_Qbarbeh}) == 2'b11) || (({prev_Qbeh,prev_Qbarbeh}) == 2'b00))&& (({J,K} == 2'b00)||({J,K} == 2'b11)) && CLRBAR) begin

QEXPECTED = 1'bx;
QBAREXPECTED = 1'bx;

end


else begin

case ({J,K,CLRBAR})
  3'b001: begin
QEXPECTED = prev_QEx;
QBAREXPECTED = prev_QExbar;
end
  3'b011: begin
QEXPECTED = 1'b0;
QBAREXPECTED = 1'b1;
end
  3'b101: begin
QEXPECTED = 1'b1;
QBAREXPECTED = 1'b0;
end
  3'b111: begin
QEXPECTED = ~prev_QEx;
QBAREXPECTED = ~prev_QExbar;
end

default: begin
QEXPECTED = 1'b0;
QBAREXPECTED = 1'b1;
end

endcase
end



end
endtask



//task 6 close

task close; begin

#10;
$fclose (FD);

$display ();
$display ("COVERAGE_REPORT");

for ( i = 0; i < 16; i++ ) begin

if(input_coverage[i] == 0) begin

$display ("input %b to input %b has occured %d times (***ERROR***)",i[3:2], i[1:0], input_coverage[i]);
ERRORS = ERRORS +1;

end

else begin

$display ("input %b to input %b has occured %d times",i[3:2], i[1:0], input_coverage[i]);

end

end

$display ();
$display ("VECTORCOUNT = %d", VECTORCOUNT);
$display ("ERRORS = %15d", ERRORS);
$display ();
$display ("TEST_END--------------------------------------------------------------------------------------------------------------------------");
$display ();

$finish;

end
endtask

//task 7 vectorcount

task vectorcount; begin

VECTORCOUNT = VECTORCOUNT + 1;

end
endtask


//task 8 display_file

task display_file; begin

$display ("%10d %9s | %4d | %1d | %1d | %4d    | %5d     | %6d       | %4d   |", VECTORCOUNT, COMMENT, $time, J, K, Q_beh, QEXPECTED, QBAREXPECTED, CLRBAR);

end
endtask

//task 9 coverage_update

task coverage_update; begin

input_coverage[{prev_JK, J, K}]++;

end
endtask

//task 10 errors_check

task errors_check; begin


if  ((({prev_Qbeh,prev_Qbarbeh}) == 2'b00) && (({J,K} == 2'b00)||({J,K} == 2'b11))) begin

$display ("***ERROR: ILLEGAL CONDITION,RACING CONDITION");
ERRORS = ERRORS + 1;

end

if  ((({prev_Qbeh,prev_Qbarbeh}) == 2'b11) && (({J,K} == 2'b11)||({J,K} == 2'b00))) begin

$display ("***ERROR: ILLEGAL CONDITION, q = %b and qbar = %b", QEXPECTED, QBAREXPECTED );
ERRORS = ERRORS + 1;

end


if (Q_beh !== QEXPECTED) begin

$display ("***ERROR: Q_behavioral = %b, Q_expected = %b", Q_beh, QEXPECTED);
ERRORS = ERRORS + 1;

end

if ({J,K}!=prev_JK) begin

$display ("***ERROR: Racing Condition Occur");
ERRORS = ERRORS + 1;

end


end
endtask



//DRIVE

//0 initialize

initial begin

initialize;

@(posedge TICK);
force_release;

end


//2 scan file on negedge TICK

always @ (negedge TICK) begin


#5;

if (!eof) begin



scan_file;

end
end



//3 check file on posedge TICK

always  @ (posedge TICK) begin

coverage_update;
prev_JK = ({J,K});

#0.1;

QEXP;
display_file;
errors_check;
vectorcount;

#0.02;
prev_Qbeh = Q_beh;
prev_Qbarbeh = QBAR_beh;
prev_QEx = QEXPECTED;
prev_QExbar = QBAREXPECTED;

end



// eof

initial begin

wait (eof);

$display ();
$display("%13s ***time = %0d,eof ***","",$time);
$display ();

for (i = 0; i < 50; i++) begin


if (J == 1 && K == 2)
begin

vectorcount;
close;

end

else begin


random_in;



end

end

close;

end


endmodule

verilog_project/verilog_project/jkff_posedge_sync_clear/tb_jkff_posedge_sync_clear.vcd
$date
	Wed Jan 14 00:51:46 2026
$end
$version
	Icarus Verilog
$end
$timescale
	10ps
$end
$scope module tb_jkff_posedge_sync_clear $end
$var wire 1 ! Q_beh $end
$var wire 1 " QBAR_beh $end
$var parameter 32 # TICKPERIOD $end
$var reg 1 $ CLRBAR $end
$var reg 72 % COMMENT [71:0] $end
$var reg 72 & COMMENT1 [71:0] $end
$var reg 72 ' COMMENT2 [71:0] $end
$var reg 32 ( ERRORS [31:0] $end
$var reg 1 ) J $end
$var reg 1 * K $end
$var reg 1 + QBAREXPECTED $end
$var reg 1 , QEXPECTED $end
$var reg 1 - TICK $end
$var reg 32 . VECTORCOUNT [31:0] $end
$var reg 1 / eof $end
$var reg 2 0 prev_JK [1:0] $end
$var reg 1 1 prev_QEx $end
$var reg 1 2 prev_QExbar $end
$var reg 1 3 prev_Qbarbeh $end
$var reg 1 4 prev_Qbeh $end
$var integer 32 5 COUNT [31:0] $end
$var integer 32 6 FD [31:0] $end
$var integer 32 7 i [31:0] $end
$scope module dut_jkff_posedge_sync_clear_behavioral $end
$var wire 1 - clk $end
$var wire 1 $ clrbar $end
$var wire 1 ) j $end
$var wire 1 * k $end
$var wire 1 " qbar $end
$var parameter 2 8 NOCHANGE $end
$var parameter 2 9 RESET $end
$var parameter 2 : SET $end
$var parameter 2 ; TOGGLE $end
$var reg 1 ! q $end
$upscope $end
$scope task QEXP $end
$upscope $end
$scope task close $end
$upscope $end
$scope task coverage_update $end
$upscope $end
$scope task display_file $end
$upscope $end
$scope task errors_check $end
$upscope $end
$scope task force_release $end
$upscope $end
$scope task initialize $end
$upscope $end
$scope task random_in $end
$upscope $end
$scope task scan_file $end
$upscope $end
$scope task vectorcount $end
$upscope $end
$upscope $end
$enddefinitions $end
$comment Show the parameter values. $end
$dumpall
b11 ;
b10 :
b1 9
b0 8
b10100 #
$end
#0
$dumpvars
b10000 7
b10000000000000000000000000000011 6
b101 5
x4
x3
x2
x1
bx 0
0/
b0 .
0-
x,
x+
0*
0)
b0 (
b1011000 '
b1011000 &
b1001001010011100100100101010100 %
1$
x"
x!
$end
#1000
b0 0
1-
#1010
b1 .
#1011
1"
0!
#1012
13
04
#2000
0-
0$
#2011
x"
x!
#2500
0+
1,
1)
b10100110100010101010100 %
#3000
1"
0!
b10 0
1-
#3010
b10 .
1+
0,
#3012
12
01
#4000
0-
1$
#4500
0+
1,
0)
b1001000010011110100110001000100 %
#5000
b0 0
1-
#5010
b11 .
1+
0,
#6000
0-
0$
#6500
0+
1,
#7000
1-
#7010
b100 .
1+
0,
#8000
0-
1$
#8500
1*
b101001001000101010100110100010101010100 %
#9000
b1 0
1-
#9010
b101 .
#10000
0-
0$
#10500
0*
b1001000010011110100110001000100 %
#11000
b0 0
1-
#11010
b110 .
#12000
0-
1$
#12500
0+
1,
1)
b10100110100010101010100 %
#13000
0"
1!
b10 0
1-
#13010
b111 .
#13012
02
11
03
14
#14000
0-
0$
#14500
0)
b1001000010011110100110001000100 %
#15000
1"
0!
b0 0
1-
#15010
b1000 .
1+
0,
#15012
12
01
13
04
#16000
0-
1$
#16500
1*
1)
b10101000100111101000111010001110100110001000101 %
#17000
0"
1!
b11 0
1-
#17010
b1001 .
0+
1,
#17012
02
11
03
14
#18000
0-
0$
#18500
1+
0,
0)
b101001001000101010100110100010101010100 %
#19000
1"
0!
b1 0
1-
#19010
b1010 .
#19012
12
01
13
04
#20000
0-
1$
#20500
0*
b1001000010011110100110001000100 %
#21000
b0 0
1-
#21010
b1011 .
#22000
0-
0$
#22500
1*
b101001001000101010100110100010101010100 %
#23000
b1 0
1-
#23010
b1100 .
#24000
0-
1$
#25000
1-
#25010
b1101 .
#26000
0-
0$
#27000
1-
#27010
b1110 .
#28000
0-
1$
#28500
0+
1,
0*
1)
b10100110100010101010100 %
#29000
0"
1!
b10 0
1-
#29010
b1111 .
#29012
02
11
03
14
#30000
0-
0$
#30500
1+
0,
1*
0)
b101001001000101010100110100010101010100 %
#31000
1"
0!
b1 0
1-
#31010
b10000 .
#31012
12
01
13
04
#32000
0-
1$
#32500
0+
1,
1)
b10101000100111101000111010001110100110001000101 %
#33000
0"
1!
b11 0
1-
#33010
b10001 .
#33012
02
11
03
14
#34000
0-
0$
#34500
0*
b10100110100010101010100 %
#35000
1"
0!
b10 0
1-
#35010
b10010 .
1+
0,
#35012
12
01
13
04
#36000
0-
1$
#36500
0+
1,
0)
b1001000010011110100110001000100 %
#37000
b0 0
1-
#37010
b10011 .
1+
0,
#38000
0-
0$
#38500
0+
1,
1)
b10100110100010101010100 %
#39000
b10 0
1-
#39010
b10100 .
1+
0,
#40000
0-
1$
#40500
1*
0)
b101001001000101010100110100010101010100 %
#41000
b1 0
1-
#41010
b10101 .
#42000
0-
0$
#42500
0+
1,
0*
1)
b10100110100010101010100 %
#43000
b10 0
1-
#43010
b10110 .
1+
0,
#44000
0-
1$
#44500
0+
1,
#45000
0"
1!
1-
#45010
b10111 .
#45012
02
11
03
14
#46000
0-
0$
#47000
1"
0!
1-
#47010
b11000 .
1+
0,
#47012
12
01
13
04
#48000
0-
1$
#48500
1*
b10101000100111101000111010001110100110001000101 %
#49000
0"
1!
b11 0
1-
#49010
b11001 .
0+
1,
#49012
02
11
03
14
#50000
0-
0$
#51000
1"
0!
1-
#51010
b11010 .
1+
0,
#51012
12
01
13
04
#52000
0-
1$
#52500
0+
1,
0*
0)
b1001000010011110100110001000100 %
#53000
b0 0
1-
#53010
b11011 .
1+
0,
#54000
0-
0$
#54500
1*
1)
b10101000100111101000111010001110100110001000101 %
#55000
b11 0
1-
#55010
b11100 .
#56000
0-
1$
#56500
0)
b101001001000101010100110100010101010100 %
#57000
b1 0
1-
#57010
b11101 .
#58000
0-
0$
#58500
0+
1,
1)
b10101000100111101000111010001110100110001000101 %
#59000
b11 0
1-
#59010
b11110 .
1+
0,
#60000
0-
1$
#60500
0+
1,
0*
b10100110100010101010100 %
#61000
0"
1!
b10 0
1-
#61010
b11111 .
#61012
02
11
03
14
#62000
0-
0$
#62500
1+
0,
1*
b10101000100111101000111010001110100110001000101 %
#63000
1"
0!
b11 0
1-
#63010
b100000 .
#63012
12
01
13
04
#64000
0-
1$
#64500
0+
1,
#65000
0"
1!
1-
#65010
b100001 .
#65012
02
11
03
14
#66000
0-
0$
#66500
b0 5
#67000
1"
0!
1-
#67010
b100010 .
1+
0,
#67012
12
01
13
04
#68000
0-
1$
#68500
b1010010010001010101011001000101010100100101001101000101 %
1)
b1 7
1/
b11111111111111111111111111111111 5
#69000
0"
1!
1-
#69010
b100011 .
0+
1,
#69012
02
11
03
14
#69300
b10100110100010101010100 %
0*
b10 7
#69800
b11 7
#70000
0-
0$
#70400
b100 7
#71000
1"
0!
b10 0
1-
#71010
b100100 .
1+
0,
#71012
12
01
13
04
#71400
b101001001000101010100110100010101010100 %
1*
0)
b101 7
#71700
0*
b10100110100010101010100 %
1)
b111 7
#72000
0-
1$
#72100
b101001001000101010100110100010101010100 %
1*
0)
b1000 7
#72800
b1010010010001010101011001000101010100100101001101000101 %
1)
b1001 7
#73000
0"
1!
b10100110100010101010100 %
0*
b1010 7
1-
#73010
b100101 .
0+
1,
#73012
02
11
03
14
#73200
b10011100100111101011111010000110100100001000001010011100100011101000101 %
0)
b1011 7
#73500
1)
b1010010010001010101011001000101010100100101001101000101 %
1*
b1101 7
#73900
b10011100100111101011111010000110100100001000001010011100100011101000101 %
0*
0)
b1110 7
#74000
0-
0$
#74500
b1010010010001010101011001000101010100100101001101000101 %
1*
1)
b1111 7
#75000
1"
0!
b0 0
b10011100100111101011111010000110100100001000001010011100100011101000101 %
0*
0)
b10000 7
1-
#75010
b100110 .
1+
0,
#75012
12
01
13
04
#76000
b101001001000101010100110100010101010100 %
1*
b10001 7
0-
1$
#76400
b10010 7
#77000
b1 0
1-
#77010
b100111 .
#77400
b10011100100111101011111010000110100100001000001010011100100011101000101 %
0*
b10011 7
#78000
0-
0$
#78300
b1010010010001010101011001000101010100100101001101000101 %
1*
1)
b10101 7
#79000
b10 0
b10100110100010101010100 %
0*
b10110 7
1-
#79010
b101000 .
#79200
b1010010010001010101011001000101010100100101001101000101 %
1*
b10111 7
#80000
0-
1$
#80200
b10011100100111101011111010000110100100001000001010011100100011101000101 %
0*
0)
b11000 7
#81000
0"
1!
b10100110100010101010100 %
1)
b11001 7
1-
#81010
b101001 .
0+
1,
#81012
02
11
03
14
#81300
b11010 7
#81400
b1010010010001010101011001000101010100100101001101000101 %
1*
b11011 7
#81800
b11100 7
#82000
0-
0$
#82600
b10011100100111101011111010000110100100001000001010011100100011101000101 %
0*
0)
b11101 7
#83000
1"
0!
b0 0
1-
#83010
b101010 .
1+
0,
#83012
12
01
13
04
#83500
b1010010010001010101011001000101010100100101001101000101 %
1*
1)
b11110 7
#84000
b101001001000101010100110100010101010100 %
0)
b11111 7
0-
1$
#84600
b1010010010001010101011001000101010100100101001101000101 %
1)
b100000 7
#85000
0"
1!
b11 0
1-
#85010
b101011 .
0+
1,
#85012
02
11
03
14
#85400
b101001001000101010100110100010101010100 %
0)
b100001 7
#86000
0-
0$
#86100
b10100110100010101010100 %
0*
1)
b100010 7
#86800
b10011100100111101011111010000110100100001000001010011100100011101000101 %
0)
b100011 7
#87000
1"
0!
b0 0
1-
#87010
b101100 .
1+
0,
#87012
12
01
13
04
#87100
b100100 7
#87800
b1010010010001010101011001000101010100100101001101000101 %
1*
1)
b100101 7
#88000
0-
1$
#88100
b10100110100010101010100 %
0*
b100110 7
#89000
0"
1!
b10 0
1-
#89010
b101101 .
0+
1,
#89012
02
11
03
14
#89100
b100111 7
#89800
b1010010010001010101011001000101010100100101001101000101 %
1*
b101000 7
#90000
0-
0$
#90200
b101001 7
#90600
b10100110100010101010100 %
0*
b101010 7
#91000
1"
0!
b1 0
b101001001000101010100110100010101010100 %
1*
0)
b101011 7
1-
#91010
b101110 .
1+
0,
#91012
12
01
13
04
#91500
b10011100100111101011111010000110100100001000001010011100100011101000101 %
0*
b101100 7
#92000
b10100110100010101010100 %
1)
b101101 7
0-
1$
#92700
b101110 7
#93000
0"
1!
b10 0
1-
#93010
b101111 .
0+
1,
#93012
02
11
03
14
#93600
b101001001000101010100110100010101010100 %
1*
0)
b101111 7
#93900
b1010010010001010101011001000101010100100101001101000101 %
1)
b110001 7
#94000
b110010 7
0-
0$
#95000
1"
0!
b11 0
b10000 7
1-
