verilog_project/jkff_pulse_triggered/jkff_pulse_triggered.v
// A jk (Jack Kilby) flip-flop which is pulse-triggered can be set and reset and by creating a versatile memory element, invalid state is prevented`.
`timescale 1ns/ 10ps
module jkff_pulse_triggered_gate (
    input  wire j,
    input  wire k,
    input  wire clk,
    input  wire clk2, 
    output wire q,
    output wire qbar
    
);

    wire q1, qbar1, q2, qbar2, q3, qbar3, q4, qbar4;
    wire s1, r1, s, r;
    reg prev_q, prev_qbar, prev_q3, prev_qbar3;

    always@(posedge clk)begin
    #0.12;

    prev_q = q;
    prev_qbar = qbar;
    prev_q3 = q3;
    prev_qbar3 = qbar3;    

    end


//JKFF

    nand (s1, j, clk, prev_qbar);
    nand (r1, k, clk, prev_q);

    // SR- LATCH -------------------------------------

    nand (q1, s1, prev_qbar3);
    nand (qbar1, r1, prev_q3);

    nand (q2, s1, qbar1);
    nand (qbar2, r1, q1);

    nand (q3, s1, qbar2);
    nand (qbar3, r1, q2);

//SRFF

    nand (s, q3, clk2);
    nand (r, qbar3, clk2);

    // SR- LATCH -------------------------------------

    
    nand (q4, s, prev_qbar);
    nand (qbar4, r, prev_q);

    nand (q, s, qbar4);
    nand (qbar, r, q4);



endmodule


module jkff_pulse_triggered_dataflow (
    input  wire j,
    input  wire k,
    input  wire clk,
    input  wire clk2,
    output wire q,
    output wire qbar
);

    
  
    wire q1, qbar1, q2, qbar2, q3, qbar3, q4, qbar4;
    wire s1, r1, s, r;
    reg prev_q, prev_qbar, prev_q3, prev_qbar3;


   
    always@(posedge clk)begin
    #0.12;

    prev_q = q;
    prev_qbar = qbar;
    prev_q3 = q3;
    prev_qbar3 = qbar3;    

    end

//JKFF

    assign s1 = ~(j & clk & prev_qbar);
    assign r1 = ~(k & clk & prev_q);

    // SR- LATCH -------------------------------------

    assign q1 = ~(s1 & prev_qbar3);
    assign qbar1 = ~(r1 & prev_q3);

    assign q2 = ~(s1 & qbar1);
    assign qbar2 = ~(r1 & q1);

    assign q3 = ~(s1 & qbar2);
    assign qbar3 = ~(r1 & q2);

//SRFF

    assign s = ~(q3 & clk2);
    assign r = ~(qbar3 & clk2);

    // SR- LATCH -------------------------------------

    
    assign q4 = ~(s & prev_qbar);
    assign qbar4 = ~(r & prev_q);

    assign q = ~(s & qbar4);
    assign qbar = ~(r & q4);



endmodule


module jkff_pulse_triggered_behavioral (
    input  wire j,
    input  wire k,
    input  wire clk,
    input  wire clk2,
    output reg  q,
    output wire qbar
);



    assign qbar = ~q;

    always @(posedge clk) begin
        case ({j,k,clk2})
            3'b001: q <= q;        // HOLD
            3'b011: q <= 1'b0;     // RESET
            3'b101: q <= 1'b1;     // SET
            3'b111: q <= ~q;       // TOGGLE
        
            default: q <= q;

        endcase
    end

endmodule

verilog_project/jkff_pulse_triggered/tb_jkff_pulse_triggered.v
`timescale 1ns/10ps

module tb_jkff_pulse_triggered;

//VECTORS FOR DUT
reg J, K;
wire Q_gate, Q_data, Q_beh, QBAR_gate, QBAR_data, QBAR_beh;

//VECTORS FOR TESTING

reg TICK;
integer FD, COUNT;
reg [8*9-1:0] COMMENT;
reg [8*9-1:0] COMMENT1;
reg [8*9-1:0] COMMENT2;
reg QEXPECTED, QBAREXPECTED;
reg [31:0] VECTORCOUNT, ERRORS;
int i;
reg [31:0] input_coverage[15:0];
reg eof;
reg [1:0] prev_JK;
reg TICK2;
reg prev_Qgate;
reg prev_Qbargate;
reg prev_Qdata;
reg prev_Qbardata;
reg prev_Qbeh;
reg prev_Qbarbeh;
reg prev_QEx;
reg prev_QExbar;


//DUT INSTANTIATION

jkff_pulse_triggered_gate dut_jkff_pulse_triggered_gate (.j(J), .k(K), .q(Q_gate), .qbar(QBAR_gate), .clk(TICK),.clk2(TICK2));
jkff_pulse_triggered_dataflow dut_jkff_pulse_triggered_dataflow (.j(J), .k(K), .q(Q_data), .qbar(QBAR_data), .clk(TICK),.clk2(TICK2));
jkff_pulse_triggered_behavioral dut_jkff_pulse_triggered_behavioral (.j(J), .k(K), .q(Q_beh), .qbar(QBAR_beh), .clk(TICK), .clk2(TICK2));



//DUMP EVERYTHING INTO DUMPFILE

initial begin

$dumpfile ("tb_jkff_pulse_triggered.vcd");
$dumpvars (0, tb_jkff_pulse_triggered);

end

//TICKPERIOD

localparam TICKPERIOD = 20;

always begin

#(TICKPERIOD/2) TICK = ~TICK;

end

//TICK 2

always begin

# (TICKPERIOD) TICK2 = ~TICK2;

end


//TASKS

//task 1 initialize

task initialize; begin

FD = $fopen ("tb_jkff_pulse_triggered.tv" , "r");
COUNT = $fscanf (FD, "%s", COMMENT);

COUNT = $fscanf (FD, "%s %b %b %s %s", COMMENT, J, K, COMMENT1, COMMENT2);
TICK = 0;
VECTORCOUNT = 0;
ERRORS = 0;

for ( i = 0 ; i < 16 ; i++ ) begin
input_coverage[i] = 0;
end

eof = 0;
TICK2 = 0;

$display ();
$display ("TEST_START------------------------------------------------------------------------------------------------------------------------");
$display ();
$display ("                     | TIME | J | K |  Q_gate  |  Q_data  |  Q_beh  | QBAR_gate | QBAR_data | QEXPECTED | QBAREXPECTED | CLK2 |");
$display ("----------------------------------------------------------------------------------------------------------------------------------");



end
endtask

//task2 force_release

task force_release; begin

#0.11;

force Q_gate = 1'b0;
force QBAR_gate = 1'b1;
force Q_data = 1'b0;
force QBAR_data = 1'b1;
force Q_beh = 1'b0;
force QBAR_beh = 1'b1;

#10;

release Q_gate;
release QBAR_gate;
release Q_data;
release QBAR_data;
release Q_beh;
release QBAR_beh;

end
endtask



//task 3 scan_file

task scan_file; begin


COUNT = $fscanf (FD,"%s %b %b %b %b", COMMENT, J, K, QEXPECTED, QBAREXPECTED);
eof = (COUNT == -1);

end
endtask

//task 4 random_in

task random_in; begin

J =  $urandom %2 ;
K =  $urandom %2 ;

case ({J,K})
2'b00: COMMENT = (((({prev_Qgate,prev_Qbargate})== 2'b11) || (({prev_Qdata,prev_Qbardata})== 2'b11) || (({prev_Qbeh,prev_Qbarbeh})== 2'b11)) || ((({prev_Qgate,prev_Qbargate})== 2'b00)||(({prev_Qdata,prev_Qbardata})== 2'b00) || (({prev_Qbeh,prev_Qbarbeh})== 2'b00)))? "ILLEGAL":"HOLD";
2'b01: COMMENT = "RESET";
2'b10: COMMENT = "SET";
2'b11: COMMENT =  (((({prev_Qgate,prev_Qbargate})== 2'b11) || (({prev_Qdata,prev_Qbardata})== 2'b11) || (({prev_Qbeh,prev_Qbarbeh})== 2'b11)) || ((({prev_Qgate,prev_Qbargate})== 2'b00)||(({prev_Qdata,prev_Qbardata})== 2'b00) || (({prev_Qbeh,prev_Qbarbeh})== 2'b00)))? "ILLEGAL": "TOGGLE";



endcase

#($urandom_range (0.1,10));

end
endtask

//task 5 QEXP

task QEXP; begin

if  (((({prev_Qgate,prev_Qbargate})== 2'b11) || (({prev_Qdata,prev_Qbardata})== 2'b11) || (({prev_Qbeh,prev_Qbarbeh})== 2'b11)) || ((({prev_Qgate,prev_Qbargate})== 2'b00)||(({prev_Qdata,prev_Qbardata})== 2'b00) || (({prev_Qbeh,prev_Qbarbeh})== 2'b00)) && (({J,K} == 2'b00)||({J,K} == 2'b11))) begin

QEXPECTED = 1'bx;
QBAREXPECTED = 1'bx;

end

else begin

case ({J,K,TICK2})
  3'b001: begin
QEXPECTED = prev_QEx;
QBAREXPECTED = prev_QExbar;
end
  3'b011: begin
QEXPECTED = 1'b0;
QBAREXPECTED = 1'b1;
end
  3'b101: begin
QEXPECTED = 1'b1;
QBAREXPECTED = 1'b0;
end
  3'b111: begin
QEXPECTED = ~prev_QEx;
QBAREXPECTED = ~prev_QExbar;
end


default: begin
QEXPECTED = prev_QEx;
QBAREXPECTED = prev_QExbar;
end

endcase
end


end
endtask



//task 6 close

task close; begin

#10;
$fclose (FD);

$display ();
$display ("COVERAGE_REPORT");

for ( i = 0; i < 16; i++ ) begin

if(input_coverage[i] == 0) begin

$display ("input %b to input %b has occured %d times (***ERROR***)",i[3:2], i[1:0], input_coverage[i]);
ERRORS = ERRORS +1;

end

else begin

$display ("input %b to input %b has occured %d times",i[3:2], i[1:0], input_coverage[i]);

end

end

$display ();
$display ("VECTORCOUNT = %d", VECTORCOUNT);
$display ("ERRORS = %15d", ERRORS);
$display ();
$display ("TEST_END--------------------------------------------------------------------------------------------------------------------------");
$display ();

$finish;

end
endtask

//task 7 vectorcount

task vectorcount; begin

VECTORCOUNT = VECTORCOUNT + 1;

end
endtask


//task 8 display_file

task display_file; begin

$display ("%10d %9s | %4d | %1d | %1d | %4d     | %4d     | %4d    | %5d     | %5d     | %5d     | %6d       | %2d   |", VECTORCOUNT, COMMENT, $time, J, K, Q_gate, Q_data, Q_beh, QBAR_gate, QBAR_data, QEXPECTED, QBAREXPECTED, TICK2);

end
endtask

//task 9 coverage_update

task coverage_update; begin

input_coverage[{prev_JK, J, K}]++;

end
endtask

//task 10 errors_check

task errors_check; begin


if  (((({prev_Qgate,prev_Qbargate})== 2'b00) || (({prev_Qdata,prev_Qbardata})== 2'b00) || (({prev_Qbeh,prev_Qbarbeh})== 2'b00)) && (({J,K} == 2'b00)||({J,K} == 2'b11))) begin

$display ("***ERROR: ILLEGAL CONDITION,RACING CONDITION");
ERRORS = ERRORS + 1;

end

if  (((({prev_Qgate,prev_Qbargate})== 2'b11) || (({prev_Qdata,prev_Qbardata})== 2'b11) || (({prev_Qbeh,prev_Qbarbeh})== 2'b11)) && (({J,K} == 2'b11)||({J,K} == 2'b00))) begin

$display ("***ERROR: ILLEGAL CONDITION, q = qbar");
ERRORS = ERRORS + 1;

end



if (Q_gate !== QEXPECTED) begin

$display ("***ERROR: Q_gate = %b, Q_expected = %b", Q_gate, QEXPECTED);
ERRORS = ERRORS + 1;

end

if (Q_data !== QEXPECTED) begin

$display ("***ERROR: Q_dataflow = %b, Q_expected = %b", Q_data, QEXPECTED);
ERRORS = ERRORS + 1;

end

if (Q_beh !== QEXPECTED) begin

$display ("***ERROR: Q_behavioral = %b, Q_expected = %b", Q_beh, QEXPECTED);
ERRORS = ERRORS + 1;

end

if (QBAR_gate !== QBAREXPECTED) begin

$display ("***ERROR: QBAR_gate = %b, QBAR_expected = %b", QBAR_gate, QBAREXPECTED);
ERRORS = ERRORS + 1;

end

if (QBAR_data !== QBAREXPECTED) begin

$display ("***ERROR: QBAR_dataflow = %b, QBAR_expected = %b", QBAR_data, QBAREXPECTED);
ERRORS = ERRORS + 1;

end

if ( {J,K} !== prev_JK ) begin

$display ("***ERROR: Racing Condition Occur");
ERRORS = ERRORS + 1;

end


end
endtask



//DRIVE

//0 initialize

initial begin

initialize;

@(posedge TICK);

force_release;

end


//2 scan file on negedge TICK

always @ (negedge TICK) begin


#1.2;

if (!eof) begin



scan_file;

end
end



//3 check file on posedge TICK

always  @ (posedge TICK) begin

coverage_update;
prev_JK = ({J,K});

#0.1;

QEXP;
display_file;
errors_check;
vectorcount;

#0.02;

prev_Qgate    <= Q_gate;
prev_Qbargate <= QBAR_gate;
prev_Qdata    <= Q_data;
prev_Qbardata <= QBAR_data;
prev_Qbeh     <= Q_beh;
prev_Qbarbeh  <= QBAR_beh;
prev_QEx      <= QEXPECTED;
prev_QExbar   <= QBAREXPECTED;



end



// eof

initial begin

wait (eof);

$display ();
$display("%13s ***time = %0d,eof ***","",$time);
$display ();

for (i = 0; i < 50; i++) begin


if (J == 1 && K == 2)
begin

vectorcount;
close;

end

else begin


random_in;



end

end

close;

end


endmodule

verilog_project/verilog_project/jkff_pulse_triggered/tb_jkff_pulse_triggered.vcd
$date
	Wed Jan 14 01:47:17 2026
$end
$version
	Icarus Verilog
$end
$timescale
	10ps
$end
$scope module tb_jkff_pulse_triggered $end
$var wire 1 ! Q_gate $end
$var wire 1 " Q_data $end
$var wire 1 # Q_beh $end
$var wire 1 $ QBAR_gate $end
$var wire 1 % QBAR_data $end
$var wire 1 & QBAR_beh $end
$var parameter 32 ' TICKPERIOD $end
$var reg 72 ( COMMENT [71:0] $end
$var reg 72 ) COMMENT1 [71:0] $end
$var reg 72 * COMMENT2 [71:0] $end
$var reg 32 + ERRORS [31:0] $end
$var reg 1 , J $end
$var reg 1 - K $end
$var reg 1 . QBAREXPECTED $end
$var reg 1 / QEXPECTED $end
$var reg 1 0 TICK $end
$var reg 1 1 TICK2 $end
$var reg 32 2 VECTORCOUNT [31:0] $end
$var reg 1 3 eof $end
$var reg 2 4 prev_JK [1:0] $end
$var reg 1 5 prev_QEx $end
$var reg 1 6 prev_QExbar $end
$var reg 1 7 prev_Qbarbeh $end
$var reg 1 8 prev_Qbardata $end
$var reg 1 9 prev_Qbargate $end
$var reg 1 : prev_Qbeh $end
$var reg 1 ; prev_Qdata $end
$var reg 1 < prev_Qgate $end
$var integer 32 = COUNT [31:0] $end
$var integer 32 > FD [31:0] $end
$var integer 32 ? i [31:0] $end
$scope module dut_jkff_pulse_triggered_behavioral $end
$var wire 1 0 clk $end
$var wire 1 1 clk2 $end
$var wire 1 , j $end
$var wire 1 - k $end
$var wire 1 & qbar $end
$var reg 1 # q $end
$upscope $end
$scope module dut_jkff_pulse_triggered_dataflow $end
$var wire 1 0 clk $end
$var wire 1 1 clk2 $end
$var wire 1 , j $end
$var wire 1 - k $end
$var wire 1 " q $end
$var wire 1 @ q1 $end
$var wire 1 A q2 $end
$var wire 1 B q3 $end
$var wire 1 C q4 $end
$var wire 1 % qbar $end
$var wire 1 D qbar1 $end
$var wire 1 E qbar2 $end
$var wire 1 F qbar3 $end
$var wire 1 G qbar4 $end
$var wire 1 H r $end
$var wire 1 I r1 $end
$var wire 1 J s $end
$var wire 1 K s1 $end
$var reg 1 L prev_q $end
$var reg 1 M prev_q3 $end
$var reg 1 N prev_qbar $end
$var reg 1 O prev_qbar3 $end
$upscope $end
$scope module dut_jkff_pulse_triggered_gate $end
$var wire 1 0 clk $end
$var wire 1 1 clk2 $end
$var wire 1 , j $end
$var wire 1 - k $end
$var wire 1 ! q $end
$var wire 1 P q1 $end
$var wire 1 Q q2 $end
$var wire 1 R q3 $end
$var wire 1 S q4 $end
$var wire 1 $ qbar $end
$var wire 1 T qbar1 $end
$var wire 1 U qbar2 $end
$var wire 1 V qbar3 $end
$var wire 1 W qbar4 $end
$var wire 1 X r $end
$var wire 1 Y r1 $end
$var wire 1 Z s $end
$var wire 1 [ s1 $end
$var reg 1 \ prev_q $end
$var reg 1 ] prev_q3 $end
$var reg 1 ^ prev_qbar $end
$var reg 1 _ prev_qbar3 $end
$upscope $end
$scope task QEXP $end
$upscope $end
$scope task close $end
$upscope $end
$scope task coverage_update $end
$upscope $end
$scope task display_file $end
$upscope $end
$scope task errors_check $end
$upscope $end
$scope task force_release $end
$upscope $end
$scope task initialize $end
$upscope $end
$scope task random_in $end
$upscope $end
$scope task scan_file $end
$upscope $end
$scope task vectorcount $end
$upscope $end
$upscope $end
$enddefinitions $end
$comment Show the parameter values. $end
$dumpall
b10100 '
$end
#0
$dumpvars
x_
x^
x]
x\
1[
1Z
1Y
1X
xW
xV
xU
xT
xS
xR
xQ
xP
xO
xN
xM
xL
1K
1J
1I
1H
xG
xF
xE
xD
xC
xB
xA
x@
b10000 ?
b10000000000000000000000000000011 >
b101 =
x<
x;
x:
x9
x8
x7
x6
x5
bx 4
03
b0 2
01
00
x/
x.
0-
0,
b0 +
b1011000 *
b1011000 )
b1001001010011100100100101010100 (
x&
x%
x$
x#
x"
x!
$end
#1000
b0 4
10
#1010
b1 2
#1011
1&
0#
1%
0"
1$
0!
#1012
17
0:
18
0;
19
0<
1%
0"
1$
0!
0C
1G
0S
1W
1^
0\
1N
0L
#2000
xC
xJ
xH
xS
xZ
xX
00
11
#2011
x&
x#
x%
x"
x$
x!
#2120
0.
1/
1,
b10100110100010101010100 (
#3000
0&
1#
0%
1H
1C
1"
0E
0F
0J
1@
1A
1B
0$
1X
1S
1!
0K
0U
0V
0Z
1P
1Q
1R
b10 4
0[
10
#3010
b10 2
#3012
06
15
07
1:
08
1;
09
1<
0D
1K
0G
0T
1[
0W
0O
1M
0N
1L
0_
1]
0^
1\
#4000
1J
1Z
00
01
#4120
0,
b1001000010011110100110001000100 (
#5000
b0 4
10
#5010
b11 2
#6000
0J
0Z
00
11
#6120
1.
0/
1-
b101001001000101010100110100010101010100 (
#7000
1&
0#
0"
1J
1G
1%
0A
0B
0H
1D
1E
1F
0!
1Z
1W
1$
0I
0Q
0R
0X
1T
1U
1V
b1 4
0Y
10
#7010
b100 2
#7012
16
05
17
0:
18
0;
19
0<
0@
0C
1I
0P
0S
1Y
1O
0M
1N
0L
1_
0]
1^
0\
#8000
1H
1X
00
01
#8120
0-
b1001000010011110100110001000100 (
#9000
b0 4
10
#9010
b101 2
#10000
0H
0X
00
11
#10120
0.
1/
1,
b10100110100010101010100 (
#11000
0&
1#
0%
1H
1C
1"
0E
0F
0J
1@
1A
1B
0$
1X
1S
1!
0K
0U
0V
0Z
1P
1Q
1R
b10 4
0[
10
#11010
b110 2
#11012
06
15
07
1:
08
1;
09
1<
0D
1K
0G
0T
1[
0W
0O
1M
0N
1L
0_
1]
0^
1\
#12000
1J
1Z
00
01
#12120
0,
b1001000010011110100110001000100 (
#13000
b0 4
10
#13010
b111 2
#14000
0J
0Z
00
11
#14120
1.
0/
1-
1,
b10101000100111101000111010001110100110001000101 (
#15000
1&
0#
0"
1J
1G
1%
0A
0B
0H
1D
1E
1F
0!
1Z
1W
1$
0I
0Q
0R
0X
1T
1U
1V
b11 4
0Y
10
#15010
b1000 2
#15012
16
05
17
0:
18
0;
19
0<
0%
1H
1"
0E
0F
0J
0$
1A
1B
1X
1!
0V
0Z
1@
1C
0K
1I
1Q
1R
0U
1S
0[
1Y
1O
0M
1N
0L
1_
0]
1^
0\
#16000
0B
1E
1F
1%
0@
0A
0R
0C
0"
1K
1U
1V
1$
0P
0Q
1J
0S
0!
1[
1Z
00
01
#16120
0,
b101001001000101010100110100010101010100 (
#17000
b1 4
10
#17010
b1001 2
#18000
0H
0X
00
11
#18120
0-
b1001000010011110100110001000100 (
#19000
b0 4
10
#19010
b1010 2
#20000
1H
1X
00
01
#20120
1-
b101001001000101010100110100010101010100 (
#21000
b1 4
10
#21010
b1011 2
#22000
0H
0X
00
11
#23000
10
#23010
b1100 2
#24000
1H
1X
00
01
#25000
10
#25010
b1101 2
#26000
0H
0X
00
11
#26120
0.
1/
0-
1,
b10100110100010101010100 (
#27000
0&
1#
0%
1H
1C
1"
0E
0F
0J
1@
1A
1B
0$
1X
1S
1!
0K
0U
0V
0Z
1P
1Q
1R
b10 4
0[
10
#27010
b1110 2
#27012
06
15
07
1:
08
1;
09
1<
0D
1K
0G
0T
1[
0W
0O
1M
0N
1L
0_
1]
0^
1\
#28000
1J
1Z
00
01
#28120
1.
0/
1-
0,
b101001001000101010100110100010101010100 (
#29000
0A
0B
1D
1E
1F
0I
0Q
0R
1T
1U
1V
b1 4
0Y
10
#29010
b1111 2
0.
1/
#29012
0@
0P
1_
0]
1O
0M
#30000
0"
1G
1%
1I
0!
0H
1W
1$
1Y
0X
00
11
#30120
1,
b10101000100111101000111010001110100110001000101 (
#31000
1&
0#
0I
b11 4
0Y
10
#31010
b10000 2
1.
0/
#31012
16
05
17
0:
18
0;
19
0<
0%
1H
1"
0E
0F
0J
0$
1@
1A
1B
1X
1!
0U
0V
0Z
1C
0K
1I
1P
1Q
1R
1S
0[
1Y
1N
0L
1^
0\
#32000
0B
1E
1F
1%
0@
0A
0R
0C
0"
1K
1U
1V
1$
0P
0Q
1J
0S
0!
1[
1Z
00
01
#32120
0.
1/
0-
b10100110100010101010100 (
#33000
0E
0F
1@
1A
1B
0K
0U
0V
1P
1Q
1R
b10 4
0[
10
#33010
b10001 2
1.
0/
#33012
0D
0T
0_
1]
0O
1M
#34000
0%
1C
1"
1K
0$
0J
1S
1!
1[
0Z
00
11
#34120
0.
1/
0,
b1001000010011110100110001000100 (
#35000
b0 4
10
#35010
b10010 2
b100 +
1.
0/
#35012
08
1;
09
1<
0G
0W
0N
1L
0^
1\
#36000
1J
1Z
00
01
#36120
0.
1/
1,
b10100110100010101010100 (
#37000
b10 4
10
#37010
b10011 2
b1000 +
1.
0/
#38000
0J
0Z
00
11
#38120
1-
0,
b101001001000101010100110100010101010100 (
#39000
0"
1J
1G
1%
0A
0B
0H
1D
1E
1F
0!
1Z
1W
1$
0I
0Q
0R
0X
1T
1U
1V
b1 4
0Y
10
#39010
b10100 2
#39012
18
0;
19
0<
0@
0C
1I
0P
0S
1Y
1O
0M
1N
0L
1_
0]
1^
0\
#40000
1H
1X
00
01
#40120
0.
1/
0-
1,
b10100110100010101010100 (
#41000
0E
0F
1@
1A
1B
0K
0U
0V
1P
1Q
1R
b10 4
0[
10
#41010
b10101 2
1.
0/
#41012
0D
0T
0_
1]
0O
1M
#42000
0%
1C
1"
1K
0$
0J
1S
1!
1[
0Z
00
11
#42120
0.
1/
#43000
0&
1#
0K
0[
10
#43010
b10110 2
#43012
06
15
07
1:
08
1;
09
1<
1K
0G
1[
0W
0N
1L
0^
1\
#44000
1J
1Z
00
01
#45000
10
#45010
b10111 2
#46000
0J
0Z
00
11
#46120
1.
0/
1-
b10101000100111101000111010001110100110001000101 (
#47000
1&
0#
0"
1J
1G
1%
0A
0B
0H
1D
1E
1F
0!
1Z
1W
1$
0I
0Q
0R
0X
1T
1U
1V
b11 4
0Y
10
#47010
b11000 2
#47012
16
05
17
0:
18
0;
19
0<
0%
1H
1"
0E
0F
0J
0$
1A
1B
1X
1!
0V
0Z
1@
1C
0K
1I
1Q
1R
0U
1S
0[
1Y
1O
0M
1N
0L
1_
0]
1^
0\
#48000
0B
1E
1F
1%
0@
0A
0R
0C
0"
1K
1U
1V
1$
0P
0Q
1J
0S
0!
1[
1Z
00
01
#48120
0.
1/
#49000
0E
0F
1@
1A
1B
0K
0U
0V
1P
1Q
1R
0[
10
#49010
b11001 2
1.
0/
#49012
0D
0T
0_
1]
0O
1M
#50000
0%
1C
1"
1K
0$
0J
1S
1!
1[
0Z
00
11
#50120
0.
1/
0-
0,
b1001000010011110100110001000100 (
#51000
b0 4
10
#51010
b11010 2
b1100 +
1.
0/
#51012
08
1;
09
1<
0G
0W
0N
1L
0^
1\
#52000
1J
1Z
00
01
#52120
1-
1,
b10101000100111101000111010001110100110001000101 (
#53000
0A
0B
1D
1E
1F
0I
0Q
0R
1T
1U
1V
b11 4
0Y
10
#53010
b11011 2
b10000 +
#53012
0@
0P
1_
0]
1O
0M
#54000
0"
1G
1%
1I
0!
0H
1W
1$
1Y
0X
00
11
#54120
0,
b101001001000101010100110100010101010100 (
#55000
0I
b1 4
0Y
10
#55010
b11100 2
#55012
18
0;
19
0<
0C
1I
0S
1Y
1N
0L
1^
0\
#56000
1H
1X
00
01
#56120
0.
1/
1,
b10101000100111101000111010001110100110001000101 (
#57000
0E
0F
1@
1A
1B
0K
0U
0V
1P
1Q
1R
b11 4
0[
10
#57010
b11101 2
1.
0/
#57012
0D
0T
0_
1]
0O
1M
#58000
0%
1C
1"
1K
0$
0J
1S
1!
1[
0Z
00
11
#58120
0.
1/
0-
b10100110100010101010100 (
#59000
0&
1#
0K
b10 4
0[
10
#59010
b11110 2
#59012
06
15
07
1:
08
1;
09
1<
1K
0G
1[
0W
0N
1L
0^
1\
#60000
1J
1Z
00
01
#60120
1.
0/
1-
b10101000100111101000111010001110100110001000101 (
#61000
0A
0B
1D
1E
1F
0I
0Q
0R
1T
1U
1V
b11 4
0Y
10
#61010
b11111 2
0.
1/
#61012
0@
0P
1_
0]
1O
0M
#62000
0"
1G
1%
1I
0!
0H
1W
1$
1Y
0X
00
11
#63000
1&
0#
0I
0Y
10
#63010
b100000 2
1.
0/
#63012
16
05
17
0:
18
0;
19
0<
0%
1H
1"
0E
0F
0J
0$
1@
1A
1B
1X
1!
0U
0V
0Z
1C
0K
1I
1P
1Q
1R
1S
0[
1Y
1N
0L
1^
0\
#64000
0B
1E
1F
1%
0@
0A
0R
0C
0"
1K
1U
1V
1$
0P
0Q
1J
0S
0!
1[
1Z
00
01
#64120
b0 =
#65000
0E
0F
1@
1A
1B
0K
0U
0V
1P
1Q
1R
0[
10
#65010
b100001 2
#65012
0D
0T
0_
1]
0O
1M
#66000
0%
1C
1"
1K
0$
0J
1S
1!
1[
0Z
00
11
#66120
b10101000100111101000111010001110100110001000101 (
1,
b1 ?
13
b11111111111111111111111111111111 =
#66920
b10100110100010101010100 (
0-
b10 ?
#67000
0&
1#
0K
b10 4
0[
10
#67010
b100010 2
0.
1/
#67012
06
15
07
1:
08
1;
09
1<
1K
0G
1[
0W
0N
1L
0^
1\
#67420
b11 ?
#68000
1J
1Z
00
01
#68020
b100 ?
#69000
10
#69010
b100011 2
#69020
0A
0B
1D
1E
1F
0I
0Q
0R
1T
1U
1V
0Y
b101001001000101010100110100010101010100 (
1-
0,
b101 ?
#69320
0F
1A
1B
0D
0E
0V
1I
1Q
1R
0T
0U
1Y
0-
b10100110100010101010100 (
1,
b111 ?
#69720
0A
0B
1D
1E
1F
0I
0Q
0R
1T
1U
1V
0Y
b101001001000101010100110100010101010100 (
1-
0,
b1000 ?
#70000
0F
0J
1A
1B
1"
0D
0E
0V
0Z
0G
0%
1I
1Q
1R
1!
0T
0U
1H
0W
0$
1Y
1X
00
11
#70420
b10101000100111101000111010001110100110001000101 (
1,
b1001 ?
#70620
b10100110100010101010100 (
0-
b1010 ?
#70820
b1001000010011110100110001000100 (
0,
b1011 ?
#71000
b0 4
10
#71010
b100100 2
#71120
1,
0"
1J
1G
1%
0A
0B
0H
1D
1E
1F
0!
1Z
1W
1$
0I
0Q
0R
0X
1T
1U
1V
0Y
b10101000100111101000111010001110100110001000101 (
1-
b1101 ?
#71520
0G
0%
1H
1"
0F
0J
1A
1B
0W
0$
0D
0E
1X
1!
0V
0Z
1I
1Q
1R
0T
0U
1Y
b1001000010011110100110001000100 (
0-
0,
b1110 ?
#72000
1J
1Z
00
01
#72120
b10101000100111101000111010001110100110001000101 (
1-
1,
b1111 ?
#72620
b1001000010011110100110001000100 (
0-
0,
b10000 ?
#73000
10
#73010
b100101 2
#73620
0A
0B
1D
1E
1F
0I
0Q
0R
1T
1U
1V
0Y
b101001001000101010100110100010101010100 (
1-
b10001 ?
#74000
0F
0J
1A
1B
1"
0D
0E
0V
0Z
0G
0%
1I
1Q
1R
1!
0T
0U
1H
0W
0$
1Y
1X
00
11
#74020
b10010 ?
#75000
1&
0#
0"
1J
1G
1%
0A
0B
0H
1D
1E
1F
0!
1Z
1W
1$
0I
0Q
0R
0X
1T
1U
1V
b1 4
0Y
10
#75010
b100110 2
1.
0/
#75012
16
05
17
0:
18
0;
19
0<
0@
0C
1I
0P
0S
1Y
1O
0M
1N
0L
1_
0]
1^
0\
#75020
b1001000010011110100110001000100 (
0-
b10011 ?
#75920
0%
1H
1C
1"
0E
0F
0J
1@
1A
1B
0$
1X
1S
1!
0K
0U
0V
0Z
1P
1Q
1R
0[
b10101000100111101000111010001110100110001000101 (
1-
1,
b10101 ?
#76000
0B
1E
1F
1%
0@
0A
0R
0C
0"
1K
1U
1V
1$
0P
0Q
1J
0S
0!
1[
1Z
00
01
#76620
b10100110100010101010100 (
0-
b10110 ?
#76820
b10101000100111101000111010001110100110001000101 (
1-
b10111 ?
#77000
0E
0F
1@
1A
1B
0K
0U
0V
1P
1Q
1R
b11 4
0[
10
#77010
b100111 2
#77012
0D
0T
0_
1]
0O
1M
#77820
1K
1[
b1001000010011110100110001000100 (
0-
0,
b11000 ?
#78000
0%
1C
1"
0$
0J
1S
1!
0Z
00
11
#78620
b10100110100010101010100 (
1,
b11001 ?
#78920
b11010 ?
#79000
0&
1#
0K
b10 4
0[
10
#79010
b101000 2
0.
1/
#79012
06
15
07
1:
08
1;
09
1<
1K
0G
1[
0W
0N
1L
0^
1\
#79020
0"
1J
1G
1%
0A
0B
0H
1D
1E
1F
0!
1Z
1W
1$
0I
0Q
0R
0X
1T
1U
1V
0Y
b10101000100111101000111010001110100110001000101 (
1-
b11011 ?
#79420
b11100 ?
#80000
0F
1A
1B
1"
0D
0E
0V
0G
0%
1I
1Q
1R
1!
0T
0U
1H
0W
0$
1Y
1X
00
01
#80220
b1001000010011110100110001000100 (
0-
0,
b11101 ?
#81000
b0 4
10
#81010
b101001 2
#81120
0A
0B
1D
1E
1F
0I
0Q
0R
1T
1U
1V
0Y
b10101000100111101000111010001110100110001000101 (
1-
1,
b11110 ?
#81620
b101001001000101010100110100010101010100 (
0,
b11111 ?
#82000
0F
0J
1A
1B
1"
0D
0E
0V
0Z
0G
0%
1I
1Q
1R
1!
0T
0U
1H
0W
0$
1Y
1X
00
11
#82220
b10101000100111101000111010001110100110001000101 (
1,
b100000 ?
#83000
1&
0#
0"
1J
1G
1%
0A
0B
0H
1D
1E
1F
0!
1Z
1W
1$
0I
0Q
0R
0X
1T
1U
1V
b11 4
0Y
10
#83010
b101010 2
1.
0/
#83012
16
05
17
0:
18
0;
19
0<
0%
1H
1"
0E
0F
0J
0$
1A
1B
1X
1!
0V
0Z
1@
1C
0K
1I
1Q
1R
0U
1S
0[
1Y
1O
0M
1N
0L
1_
0]
1^
0\
#83020
0C
0"
1J
1%
0B
0H
1E
1F
0S
0!
0@
0A
1Z
1$
0R
0X
1K
1U
1V
0P
0Q
1[
b101001001000101010100110100010101010100 (
0,
b100001 ?
#83720
0%
1H
1C
1"
0E
0F
0J
1@
1A
1B
0$
1X
1S
1!
0K
0U
0V
0Z
1P
1Q
1R
0[
b10100110100010101010100 (
0-
1,
b100010 ?
#84000
0B
1E
1F
1%
0@
0A
0R
0C
0"
1K
1U
1V
1$
0P
0Q
1J
0S
0!
1[
1Z
00
01
#84420
b1001000010011110100110001000100 (
0,
b100011 ?
