verilog_project/shift_register/shift_register.v
module shift_register(
input clk,
input rst,
input data_in,
output reg [DATA_WIDTH-1:0] data_out
);

parameter DATA_WIDTH = 8;

always@(posedge clk)begin
if(rst)begin
data_out <=0;
end
else begin
data_out <= {data_out[DATA_WIDTH-2:0],data_in};
end
end

endmodule

verilog_project/shift_register/input_shift_register.v
module input_shift_register(
input int TICKPERIOD,
input TICK,
output reg RST,
output reg D,
output reg eof,
output reg done,
output reg flag_init,
output reg flag_general,flag_lsb_to_msb,
output reg [3:0] start_test
);

reg ch;
reg int mode;
reg int burst;
reg [31:0]flag_group_count[0:5];
reg flag_X;
reg [31:0]tick_count;
reg [31:0]total_flag_group_count[0:1];

reg [INPUT_WIDTH-1:0]INPUT_coverage;
reg [INPUT_WIDTH+DATA_WIDTH-1:0]INPUT_drive;
reg [31:0]prev_total_flag_group_count;
reg flag_done;
reg [31:0]num_of_GROUP;



//PARAMETER
parameter DATA_WIDTH = 1;
parameter coverage_VECTOR_bits = 1;
localparam INPUT_WIDTH = $clog2('b1<<coverage_VECTOR_bits);



//TASK

//task 1 initialize
task initialize; begin

ch = $urandom_range(0,1);
{RST,D} = {1'b0,ch};
eof=0;

for(int j=0; j<6; j++)begin
flag_group_count[j] = 0;
end

tick_count=0;

end
endtask



//task2 task general_input
task general_input; begin

ch = $urandom_range(0,1);

//EOF
if(flag_lsb_to_msb)begin
eof = 1;
end


//2 TEST OF SHIFT from LSB to MSB

else if(flag_general) begin

//display start test
if(start_test[3] !==1)begin
$display ();
$display("%12s ***time = %0d, TEST OF SHIFT from LSB to MSB***","",$time);
$display ();
start_test[3] = 1;
end

//--------------------------------------------------------------------------------

//total flag_group_count
num_of_GROUP = 1;
prev_total_flag_group_count = total_flag_group_count[0];
total_flag_group_count[1] = num_of_GROUP + prev_total_flag_group_count;

//--------------------------------------------------------------------------------


//input section

flag_X = 0;
for(int j=0; j<num_of_GROUP; j++)begin
if(flag_group_count[j + prev_total_flag_group_count] !==1 && !flag_X)begin
INPUT_drive = {j[0],ch};
flag_X = 1;
end
end

tick_count <= tick_count + 1;
//--------------------------------------------------------------------------------

{RST,D} = INPUT_drive; 

//--------------------------------------------------------------------------------

//flag_group_count

if(tick_count === 8)begin
for(int j=0; j<num_of_GROUP; j++)begin
flag_group_count[j + prev_total_flag_group_count]++;
end
end


for(int j=0; j<num_of_GROUP; j++)begin
if(flag_group_count[j + prev_total_flag_group_count])begin
flag_done =1;
tick_count = 0;
end
else begin
flag_done =0;
end
end

//--------------------------------------------------------------------------------
flag_lsb_to_msb = flag_done;
//--------------------------------------------------------------------------------

end




//1 GENERAL TEST OF RST=1 and RST=0

else if(flag_init) begin


//display start test
if(start_test[2] !==1)begin
$display ();
$display("%12s ***time = %0d, GENERAL TEST OF RST=1 and RST=0***","",$time);
$display ();
start_test[2] <= 1;
end

//--------------------------------------------------------------------------------
//total flag_group_count
num_of_GROUP = 'b1<<coverage_VECTOR_bits;
prev_total_flag_group_count = 0;
total_flag_group_count[0] = num_of_GROUP + prev_total_flag_group_count;

//--------------------------------------------------------------------------------

//input section

flag_X = 0;
for(int j=0; j<num_of_GROUP; j++)begin
if(flag_group_count[j + prev_total_flag_group_count] !==1 && !flag_X)begin

if(start_test[j] !==1)begin
$display ();
$display("%12s ***time =%2d, GROUP%2d RST=%2d***","",$time,j,j);
$display ();
start_test[j] = 1;
end

INPUT_drive = {j[0],ch};
flag_X = 1;
end
end

//--------------------------------------------------------------------------------
{RST,D} = INPUT_drive; 

//--------------------------------------------------------------------------------

//flag_group_count
for(int j=0; j<num_of_GROUP; j++)begin
if(INPUT_drive[INPUT_WIDTH+DATA_WIDTH-1:INPUT_WIDTH+DATA_WIDTH-coverage_VECTOR_bits]==j[coverage_VECTOR_bits-1:0])begin
flag_group_count[j + prev_total_flag_group_count]++;
end
end

flag_done <=1;
for(int j=0; j<num_of_GROUP; j++)begin
if(flag_group_count[j + prev_total_flag_group_count]!==1)
flag_done <=0;
end

//--------------------------------------------------------------------------------
flag_general = flag_done;
//--------------------------------------------------------------------------------

end



//INITIAL INPUT
else begin
flag_init = 1;
end

end
endtask



//RANDOM IN

task random_in; begin


//--------------------------------------------------------------------------------

ch= $urandom_range(0,1);
mode = $urandom_range(0,3);
burst = $urandom_range (1,5);

//--------------------------------------------------------------------------------

//input section
repeat(burst)begin

@(negedge TICK);

# ($urandom_range(0,10));

case(mode)
0:begin
INPUT_drive[INPUT_WIDTH+DATA_WIDTH-1] = 1'b0; 
INPUT_drive[INPUT_WIDTH+DATA_WIDTH-2:0] = ch;
end
1:begin
INPUT_drive[INPUT_WIDTH+DATA_WIDTH-1] = 1'b1; 
INPUT_drive[INPUT_WIDTH+DATA_WIDTH-2:0] = ch;
end
endcase

//--------------------------------------------------------------------------------
{RST,D} = INPUT_drive; 
//--------------------------------------------------------------------------------

end

end
endtask



//DRIVER

//INITITALIZE
initial begin
initialize;
end


//INPUT

always @ (negedge TICK) begin

if (!eof) begin
general_input;
end
end

//AFTER EOF

initial begin

wait (eof);

$display ();
$display("%13s ***time = %0d,eof ***","",$time);
$display ();
$display ("%12s random stimulus to improve coverage","");


for (int i = 0; i < 100; i++) begin
if(i==99)begin
random_in;
done = 1;
end else begin
random_in;
end
end

end


endmodule

verilog_project/verilog_project/shift_register/tb_shift_register.v
`timescale 1ns/1ps
module tb_shift_register;

//VECTORS FOR DUT
reg TICK;
wire RST;
wire DATA_IN;
wire [DATA_WIDTH-1:0] DATA_OUT;

//VECTORS FOR TESTING
reg [8*31-1:0] COMMENT;
reg [DATA_WIDTH-1:0]DATA_OUT_EXPECTED;
reg [31:0] VECTORCOUNT, ERRORS;
int i;
reg [31:0] state_input_coverage[0:1];
reg [31:0] input_coverage[0:1];
wire eof;
wire done;
reg flag_init;
wire flag_general,flag_lsb_to_msb;
wire [3:0]start_test;

parameter DATA_WIDTH = 8, TICKPERIOD = 20;


//DUT INSTANTIATION

input_shift_register dut_input_shift_register (.TICKPERIOD(TICKPERIOD), .TICK(TICK), .RST(RST), .D(DATA_IN), .eof(eof), .done(done), .flag_init(flag_init),
                                   .flag_general(flag_general), .flag_lsb_to_msb(flag_lsb_to_msb),
                                   .start_test(start_test));


shift_register dut_shift_register (.clk(TICK),.rst(RST), .data_in(DATA_IN), .data_out(DATA_OUT));




//DUMP EVERYTHING INTO DUMPFILE

initial begin

$dumpfile ("tb_shift_register.vcd");
$dumpvars (0, tb_shift_register);

end


//TICKPERIOD


always begin
#(TICKPERIOD/2) TICK <= ~TICK;
end



//TASKS

//task 1 initialize

task initialize; begin

TICK = 0;
VECTORCOUNT = 0;
ERRORS = 0;

for(i=0; i<2; i++)begin
input_coverage[i] = 0;
end

for(i=0; i<2; i++)begin
state_input_coverage[i] = 0;
end


$display ();
$display ();
$display ("TEST_START-------------------------------------------------------------------------------------------");
$display ();
$display ("                                | TIME | RST | DATA_IN  | DATA_OUT | DATA_OUT_EXPECTED |");
$display ("-----------------------------------------------------------------------------------------------------");


end
endtask


//task4 COMMENT
task comment; begin


if(eof)begin
COMMENT = "RANDOM_INPUT";
end
else if(start_test[3])begin
COMMENT = "LSB_to_MSB";
end
else if(start_test[1])begin
COMMENT = "RST=1";
end
else if(start_test[0])begin
COMMENT = "RST=0";
end
else if(flag_init & $time < 2*TICKPERIOD/2)begin
COMMENT = "INIT";
end

end
endtask



//task 5 close

task close; begin

#10;

$display ();
$display ("COVERAGE_REPORT");
$display ();
$display ();

for (int j=0; j<2; j++) begin
if(input_coverage[j] == 0) begin
$display ("input RST =%b has occured %d times***ERROR***",j[0],input_coverage[j]);
ERRORS = ERRORS + 1;
end
else begin
$display ("input RST =%b has occured %d times",j[0],input_coverage[j]);
end
end

for (int j=0; j<2; j++) begin

if(j==0)begin
if(state_input_coverage[j] == 0) begin
$display ("not all input combination of RST has been tested***ERROR***");
ERRORS = ERRORS + 1;
end
else begin
$display ("all input combination of RST has been tested");
end
end
else if (j==1)begin
if(state_input_coverage[j] == 0) begin
$display ("input shifting from LSB to MSB has not been tested  ***ERROR***");
ERRORS = ERRORS + 1;
end
else begin
$display ("input shifting from LSB to MSB has been tested");
end
end

end

$display ();
$display ("VECTORCOUNT = %d", VECTORCOUNT);
$display ("ERRORS = %15d", ERRORS);
$display ();
$display ("TEST_END--------------------------------------------------------------------------------------------------------------------------");
$display ();

$finish;

end
endtask


//task 6 vectorcount

task vectorcount; begin

VECTORCOUNT = VECTORCOUNT + 1;

end
endtask


//task 7 strobe_vector

task strobe_vector; begin

$strobe ("%10d %20s | %4d |  %1b  | %8b | %8b |     %8b      | ", VECTORCOUNT, COMMENT, $time, RST, DATA_IN, DATA_OUT, DATA_OUT_EXPECTED);
end
endtask



//task 8 coverage_update

task coverage_update; begin

input_coverage[RST]++;

if(flag_general)begin
state_input_coverage[0]++;
end
if(flag_lsb_to_msb)begin
state_input_coverage[1]++;
end


end
endtask




//task 9 errors_warnings_check

task errors_warnings_check; begin
if (DATA_OUT !== DATA_OUT_EXPECTED) begin
$display ("***ERROR: DATA_OUT = %b, DATA_OUT_expected = %b", DATA_OUT, DATA_OUT_EXPECTED);
ERRORS = ERRORS + 1;
end

end
endtask



//DRIVE

//0 initialize

initial begin

initialize;

end



//3 computation and display on  posedge TICK

always  @ (posedge TICK) begin
//OUT_EXP (it has to be written here instead of written as a task otherwise it will cause racing condition's error)
if(RST)begin
DATA_OUT_EXPECTED <= 0;
end
else begin
DATA_OUT_EXPECTED <= {DATA_OUT_EXPECTED[6:0],DATA_IN};
end

coverage_update;
#0;
comment;
strobe_vector;
errors_warnings_check;
vectorcount;

end




//close

always@(posedge TICK)begin

if (VECTORCOUNT==9999)
begin
vectorcount;
close;
end

else if(done)begin
close;
end

end


endmodule

verilog_project/verilog_project/shift_register/tb_shift_register.vcd
$date
	Wed Apr 29 15:24:44 2026
$end
$version
	Icarus Verilog
$end
$timescale
	1ps
$end
$scope module tb_shift_register $end
$var wire 4 ! start_test [3:0] $end
$var wire 1 " flag_lsb_to_msb $end
$var wire 1 # flag_init $end
$var wire 1 $ flag_general $end
$var wire 1 % eof $end
$var wire 1 & done $end
$var wire 1 ' RST $end
$var wire 8 ( DATA_OUT [7:0] $end
$var wire 1 ) DATA_IN $end
$var parameter 32 * DATA_WIDTH $end
$var parameter 32 + TICKPERIOD $end
$var reg 248 , COMMENT [247:0] $end
$var reg 8 - DATA_OUT_EXPECTED [7:0] $end
$var reg 32 . ERRORS [31:0] $end
$var reg 1 / TICK $end
$var reg 32 0 VECTORCOUNT [31:0] $end
$var integer 32 1 i [31:0] $end
$scope module dut_input_shift_register $end
$var wire 1 / TICK $end
$var wire 32 2 TICKPERIOD [31:0] $end
$var parameter 32 3 DATA_WIDTH $end
$var parameter 32 4 INPUT_WIDTH $end
$var parameter 32 5 coverage_VECTOR_bits $end
$var reg 1 ) D $end
$var reg 2 6 INPUT_drive [1:0] $end
$var reg 1 ' RST $end
$var reg 1 7 ch $end
$var reg 1 & done $end
$var reg 1 % eof $end
$var reg 1 8 flag_X $end
$var reg 1 9 flag_done $end
$var reg 1 $ flag_general $end
$var reg 1 # flag_init $end
$var reg 1 " flag_lsb_to_msb $end
$var reg 32 : num_of_GROUP [31:0] $end
$var reg 32 ; prev_total_flag_group_count [31:0] $end
$var reg 4 < start_test [3:0] $end
$var reg 32 = tick_count [31:0] $end
$var integer 32 > burst [31:0] $end
$var integer 32 ? mode [31:0] $end
$scope begin $ivl_for_loop9 $end
$var integer 32 @ i [31:0] $end
$upscope $end
$scope task general_input $end
$scope begin $ivl_for_loop3 $end
$var integer 32 A j [31:0] $end
$upscope $end
$scope begin $ivl_for_loop4 $end
$var integer 32 B j [31:0] $end
$upscope $end
$scope begin $ivl_for_loop5 $end
$var integer 32 C j [31:0] $end
$upscope $end
$scope begin $ivl_for_loop6 $end
$var integer 32 D j [31:0] $end
$upscope $end
$scope begin $ivl_for_loop7 $end
$var integer 32 E j [31:0] $end
$upscope $end
$scope begin $ivl_for_loop8 $end
$var integer 32 F j [31:0] $end
$upscope $end
$upscope $end
$scope task initialize $end
$scope begin $ivl_for_loop2 $end
$var integer 32 G j [31:0] $end
$upscope $end
$upscope $end
$scope task random_in $end
$upscope $end
$upscope $end
$scope module dut_shift_register $end
$var wire 1 / clk $end
$var wire 1 ) data_in $end
$var wire 1 ' rst $end
$var parameter 32 H DATA_WIDTH $end
$var reg 8 I data_out [7:0] $end
$upscope $end
$scope task close $end
$scope begin $ivl_for_loop0 $end
$var integer 32 J j [31:0] $end
$upscope $end
$scope begin $ivl_for_loop1 $end
$var integer 32 K j [31:0] $end
$upscope $end
$upscope $end
$scope task comment $end
$upscope $end
$scope task coverage_update $end
$upscope $end
$scope task errors_warnings_check $end
$upscope $end
$scope task initialize $end
$upscope $end
$scope task strobe_vector $end
$upscope $end
$scope task vectorcount $end
$upscope $end
$upscope $end
$enddefinitions $end
$comment Show the parameter values. $end
$dumpall
b1000 H
b1 5
b1 4
b1 3
b10100 +
b1000 *
$end
#0
$dumpvars
b0 K
b0 J
bx I
b110 G
b0 F
b0 E
b0 D
b0 C
b0 B
b0 A
b0 @
b0 ?
b0 >
b0 =
bx <
bx ;
bx :
x9
x8
07
bx 6
b10100 2
b10 1
b0 0
0/
b0 .
bx -
bx ,
1)
bx (
0'
x&
0%
x$
1#
x"
bx !
$end
#10000
bx1 (
bx1 I
bx1 -
b1 0
b1001001010011100100100101010100 ,
1/
#20000
09
b10 F
b10 E
0)
b10 D
b0 6
bx1x1 !
bx1x1 <
18
b0 ;
b10 :
0/
#30000
bx10 (
bx10 I
bx10 -
b10 0
b101001001010011010101000011110100110000 ,
1/
#40000
19
0$
b10 F
b10 E
1'
b10 6
bx111 !
bx111 <
b10 D
18
0/
#50000
b0 (
b0 I
b0 -
b11 0
b101001001010011010101000011110100110001 ,
1/
#60000
09
1$
b10 F
b10 E
b10 D
08
17
0/
#70000
b100 0
1/
#80000
b1 =
0"
b1 C
0'
1)
b1 A
18
b1 6
b10 ;
b1 :
b1111 !
b1111 <
0/
#90000
b1 (
b1 I
b1 -
b101 0
b1001100010100110100001001011111011101000110111101011111010011010101001101000010 ,
1/
#100000
b10 =
b1 C
0)
b0 6
b1 A
18
07
0/
#110000
b10 (
b10 I
b10 -
b110 0
1/
#120000
b11 =
b1 C
b1 A
18
0/
#130000
b100 (
b100 I
b100 -
b111 0
1/
#140000
b100 =
b1 C
1)
b1 6
b1 A
18
17
0/
#150000
b1001 (
b1001 I
b1001 -
b1000 0
1/
#160000
b101 =
b1 C
b1 A
18
0/
#170000
b10011 (
b10011 I
b10011 -
b1001 0
1/
#180000
b110 =
b1 C
b1 A
18
0/
#190000
b100111 (
b100111 I
b100111 -
b1010 0
1/
#200000
b111 =
b1 C
b1 A
18
0/
#210000
b1001111 (
b1001111 I
b1001111 -
b1011 0
1/
#220000
b1000 =
b1 C
b1 A
18
0/
#230000
b10011111 (
b10011111 I
b10011111 -
b1100 0
1/
#240000
1"
b1001 =
19
b1 C
b1 B
b1 A
18
0/
#250000
b111111 (
b111111 I
b111111 -
b1101 0
1/
#260000
b10 >
b1 ?
07
1%
0/
#270000
b1111111 (
b1111111 I
b1111111 -
b1110 0
b10100100100000101001110010001000100111101001101010111110100100101001110010100000101010101010100 ,
1/
#280000
0/
#290000
b0 (
b0 I
b0 -
b1111 0
1/
1'
0)
b10 6
#300000
0/
#302000
b101 >
b11 ?
b1 @
#310000
b10000 0
1/
#320000
0/
#330000
b10001 0
1/
#340000
0/
#350000
b10010 0
1/
#360000
0/
#370000
b10011 0
1/
#380000
0/
#390000
b10100 0
1/
#400000
0/
#404000
b1 >
b0 ?
b10 @
#410000
b10101 0
1/
#420000
0/
#425000
b101 >
b10 ?
b11 @
0'
b0 6
#430000
b10110 0
1/
#440000
0/
#450000
b10111 0
1/
#460000
0/
#470000
b11000 0
1/
#480000
0/
#490000
b11001 0
1/
#500000
0/
#510000
b11010 0
1/
#520000
0/
#521000
b1 >
b1 ?
17
b100 @
#530000
b11011 0
1/
#540000
0/
#543000
b11 >
b101 @
1'
1)
b11 6
#550000
b11100 0
1/
#560000
0/
#570000
b11101 0
1/
#580000
0/
#590000
b11110 0
1/
#600000
0/
#601000
b100 >
b11 ?
b110 @
#610000
b11111 0
1/
#620000
0/
#630000
b100000 0
1/
#640000
0/
#650000
b100001 0
1/
#660000
0/
#670000
b100010 0
1/
#680000
0/
#690000
b100011 0
1/
b101 >
b111 @
#700000
0/
#710000
b100100 0
1/
#720000
0/
#730000
b100101 0
1/
#740000
0/
#750000
b100110 0
1/
#760000
0/
#770000
b100111 0
1/
#780000
0/
#788000
b100 >
b0 ?
b1000 @
#790000
b101000 0
1/
#800000
0/
#802000
0'
b1 6
#810000
b1 (
b1 I
b1 -
b101001 0
1/
#820000
0/
#830000
b11 (
b11 I
b11 -
b101010 0
1/
#840000
0/
#850000
b111 (
b111 I
b111 -
b101011 0
1/
#860000
0/
#870000
b1111 (
b1111 I
b1111 -
b101100 0
1/
b101 >
b10 ?
b1001 @
#880000
0/
#890000
b11111 (
b11111 I
b11111 -
b101101 0
1/
#900000
0/
#910000
b111111 (
b111111 I
b111111 -
b101110 0
1/
#920000
0/
#930000
b1111111 (
b1111111 I
b1111111 -
b101111 0
1/
#940000
0/
#950000
b11111111 (
b11111111 I
b11111111 -
b110000 0
1/
#960000
0/
#961000
b1 >
b11 ?
07
b1010 @
#970000
b110001 0
1/
#980000
0/
#984000
b100 >
b0 ?
b1011 @
#990000
b110010 0
1/
#1000000
0/
#1005000
0)
b0 6
#1010000
b11111110 (
b11111110 I
b11111110 -
b110011 0
1/
#1020000
0/
#1030000
b11111100 (
b11111100 I
b11111100 -
b110100 0
1/
#1040000
0/
#1050000
b11111000 (
b11111000 I
b11111000 -
b110101 0
1/
#1060000
0/
#1062000
b10 >
b10 ?
17
b1100 @
#1070000
b11110000 (
b11110000 I
b11110000 -
b110110 0
1/
#1080000
0/
#1090000
b11100000 (
b11100000 I
b11100000 -
b110111 0
1/
#1100000
0/
#1106000
b100 >
b1 ?
b1101 @
#1110000
b11000000 (
b11000000 I
b11000000 -
b111000 0
1/
#1120000
0/
#1122000
1'
1)
b11 6
#1130000
b0 (
b0 I
b0 -
b111001 0
1/
#1140000
0/
#1150000
b111010 0
1/
#1160000
0/
#1170000
b111011 0
1/
#1180000
0/
#1181000
b10 >
b10 ?
b1110 @
#1190000
b111100 0
1/
#1200000
0/
#1210000
b111101 0
1/
#1220000
0/
#1223000
b100 >
b0 ?
b1111 @
#1230000
b111110 0
1/
#1240000
0/
#1243000
0'
b1 6
#1250000
b1 (
b1 I
b1 -
b111111 0
1/
#1260000
0/
#1270000
b11 (
b11 I
b11 -
b1000000 0
1/
#1280000
0/
#1290000
b111 (
b111 I
b111 -
b1000001 0
1/
#1300000
0/
#1302000
b10 >
b11 ?
b10000 @
#1310000
b1111 (
b1111 I
b1111 -
b1000010 0
1/
#1320000
0/
#1330000
b11111 (
b11111 I
b11111 -
b1000011 0
1/
#1340000
0/
#1347000
b11 >
b1 ?
b10001 @
#1350000
b111111 (
b111111 I
b111111 -
b1000100 0
1/
#1360000
0/
#1362000
1'
b11 6
#1370000
b0 (
b0 I
b0 -
b1000101 0
1/
#1380000
0/
#1390000
b1000110 0
1/
#1400000
0/
#1404000
b10 ?
b10010 @
#1410000
b1000111 0
1/
#1420000
0/
#1430000
b1001000 0
1/
#1440000
0/
#1450000
b1001001 0
1/
#1460000
0/
#1465000
b1 ?
b10011 @
#1470000
b1001010 0
1/
#1480000
0/
#1490000
b1001011 0
1/
#1500000
0/
#1510000
b1001100 0
1/
#1520000
0/
#1527000
b101 >
b0 ?
07
b10100 @
#1530000
b1001101 0
1/
#1540000
0/
#1541000
0'
0)
b0 6
#1550000
b1001110 0
1/
#1560000
0/
#1570000
b1001111 0
1/
#1580000
0/
#1590000
b1010000 0
1/
#1600000
0/
#1610000
b1010001 0
1/
#1620000
0/
#1628000
b10101 @
#1630000
b1010010 0
1/
#1640000
0/
#1650000
b1010011 0
1/
#1660000
0/
#1670000
b1010100 0
1/
#1680000
0/
#1690000
b1010101 0
1/
#1700000
0/
#1710000
b1010110 0
1/
#1720000
0/
#1729000
b1 >
b11 ?
17
b10110 @
#1730000
b1010111 0
1/
#1740000
0/
#1745000
b10 >
b10 ?
b10111 @
#1750000
b1011000 0
1/
#1760000
0/
#1770000
b1011001 0
1/
#1780000
0/
#1786000
b1 >
b1 ?
07
b11000 @
#1790000
b1011010 0
1/
#1800000
b11 >
17
b11001 @
1'
b10 6
0/
#1810000
b1011011 0
1/
#1820000
1)
b11 6
0/
#1830000
b1011100 0
1/
#1840000
0/
#1850000
b1011101 0
1/
#1860000
0/
#1864000
b10 >
b10 ?
07
b11010 @
#1870000
b1011110 0
1/
#1880000
0/
#1890000
b1011111 0
1/
#1900000
0/
#1909000
b101 >
b11 ?
17
b11011 @
#1910000
b1100000 0
1/
#1920000
0/
#1930000
b1100001 0
1/
#1940000
0/
#1950000
b1100010 0
1/
#1960000
0/
#1970000
b1100011 0
1/
#1980000
0/
#1990000
b1100100 0
1/
#2000000
0/
#2009000
b100 >
b1 ?
b11100 @
#2010000
b1100101 0
1/
#2020000
0/
#2030000
b1100110 0
1/
#2040000
0/
#2050000
b1100111 0
1/
#2060000
0/
#2070000
b1101000 0
1/
#2080000
0/
#2088000
07
b11101 @
#2090000
b1101001 0
1/
#2100000
0/
#2105000
0)
b10 6
#2110000
b1101010 0
1/
#2120000
0/
#2130000
b1101011 0
1/
#2140000
0/
#2150000
b1101100 0
1/
#2160000
0/
#2163000
b101 >
b0 ?
17
b11110 @
#2170000
b1101101 0
1/
#2180000
0/
#2181000
0'
1)
b1 6
#2190000
b1 (
b1 I
b1 -
b1101110 0
1/
#2200000
0/
#2210000
b11 (
b11 I
b11 -
b1101111 0
1/
#2220000
0/
#2230000
b111 (
b111 I
b111 -
b1110000 0
1/
#2240000
0/
#2250000
b1111 (
b1111 I
b1111 -
b1110001 0
1/
#2260000
0/
#2263000
b11 >
b11111 @
#2270000
b11111 (
b11111 I
b11111 -
b1110010 0
1/
#2280000
0/
#2290000
b111111 (
b111111 I
b111111 -
b1110011 0
1/
#2300000
0/
#2310000
b1111111 (
b1111111 I
b1111111 -
b1110100 0
1/
#2320000
0/
#2323000
b1 ?
b100000 @
#2330000
b11111111 (
b11111111 I
b11111111 -
b1110101 0
1/
#2340000
0/
#2344000
1'
b11 6
#2350000
b0 (
b0 I
b0 -
b1110110 0
1/
#2360000
0/
#2370000
b1110111 0
1/
#2380000
0/
#2386000
b101 >
b100001 @
#2390000
b1111000 0
1/
#2400000
0/
#2410000
b1111001 0
1/
#2420000
0/
#2430000
b1111010 0
1/
#2440000
0/
#2450000
b1111011 0
1/
#2460000
0/
#2470000
b1111100 0
1/
#2480000
0/
#2485000
b100010 @
#2490000
b1111101 0
1/
#2500000
0/
#2510000
b1111110 0
1/
#2520000
0/
#2530000
b1111111 0
1/
#2540000
0/
#2550000
b10000000 0
1/
#2560000
0/
#2570000
b10000001 0
1/
#2580000
0/
#2583000
b100011 @
#2590000
b10000010 0
1/
#2600000
0/
#2610000
b10000011 0
1/
#2620000
0/
#2630000
b10000100 0
1/
#2640000
0/
#2650000
b10000101 0
1/
#2660000
0/
#2670000
b10000110 0
1/
#2680000
0/
#2684000
b10 >
b11 ?
b100100 @
#2690000
b10000111 0
1/
#2700000
0/
#2710000
b10001000 0
1/
#2720000
0/
#2725000
b101 >
b1 ?
07
b100101 @
#2730000
b10001001 0
1/
#2740000
0/
#2746000
0)
b10 6
#2750000
b10001010 0
1/
#2760000
0/
#2770000
b10001011 0
1/
#2780000
0/
#2790000
b10001100 0
1/
#2800000
0/
#2810000
b10001101 0
1/
#2820000
0/
#2828000
b100 >
b11 ?
b100110 @
#2830000
b10001110 0
1/
#2840000
0/
#2850000
b10001111 0
1/
#2860000
0/
#2870000
b10010000 0
1/
#2880000
0/
#2890000
b10010001 0
1/
#2900000
0/
#2904000
b101 >
b10 ?
b100111 @
#2910000
b10010010 0
1/
#2920000
0/
#2930000
b10010011 0
1/
#2940000
0/
#2950000
b10010100 0
1/
#2960000
0/
#2970000
b10010101 0
1/
#2980000
0/
#2990000
b10010110 0
1/
#3000000
0/
#3001000
b1 >
17
b101000 @
#3010000
b10010111 0
1/
#3020000
0/
#3021000
b100 >
b0 ?
07
b101001 @
#3030000
b10011000 0
1/
#3040000
0/
#3044000
0'
b0 6
#3050000
b10011001 0
1/
#3060000
0/
#3070000
b10011010 0
1/
#3080000
0/
#3090000
b10011011 0
1/
#3100000
0/
#3101000
b11 >
b1 ?
b101010 @
#3110000
b10011100 0
1/
#3120000
0/
#3128000
1'
b10 6
#3130000
b10011101 0
1/
#3140000
0/
#3150000
b10011110 0
1/
#3160000
0/
#3166000
b1 >
b0 ?
17
b101011 @
#3170000
b10011111 0
1/
#3180000
0/
#3187000
b10 ?
07
b101100 @
0'
1)
b1 6
#3190000
b1 (
b1 I
b1 -
b10100000 0
1/
#3200000
0/
#3203000
b11 >
b101101 @
#3210000
b11 (
b11 I
b11 -
b10100001 0
1/
#3220000
0/
#3230000
b111 (
b111 I
b111 -
b10100010 0
1/
#3240000
0/
#3250000
b1111 (
b1111 I
b1111 -
b10100011 0
1/
#3260000
0/
#3269000
b10 >
b11 ?
b101110 @
#3270000
b11111 (
b11111 I
b11111 -
b10100100 0
1/
#3280000
0/
#3290000
b111111 (
b111111 I
b111111 -
b10100101 0
1/
#3300000
0/
#3303000
b101 >
b101111 @
#3310000
b1111111 (
b1111111 I
b1111111 -
b10100110 0
1/
#3320000
0/
#3330000
b11111111 (
b11111111 I
b11111111 -
b10100111 0
1/
#3340000
0/
#3350000
b10101000 0
1/
#3360000
0/
#3370000
b10101001 0
1/
#3380000
0/
#3390000
b10101010 0
1/
#3400000
0/
#3401000
b10 >
b0 ?
17
b110000 @
#3410000
b10101011 0
1/
#3420000
0/
#3430000
b10101100 0
1/
#3440000
0/
#3442000
b101 >
b11 ?
07
b110001 @
#3450000
b10101101 0
1/
#3460000
0/
#3470000
b10101110 0
1/
#3480000
0/
#3490000
b10101111 0
1/
#3500000
0/
#3510000
b10110000 0
1/
#3520000
0/
#3530000
b10110001 0
1/
#3540000
0/
#3544000
b100 >
b10 ?
17
b110010 @
#3550000
b10110010 0
1/
#3560000
0/
#3570000
b10110011 0
1/
#3580000
0/
#3590000
b10110100 0
1/
#3600000
0/
#3610000
b10110101 0
1/
#3620000
0/
#3627000
b11 >
b1 ?
b110011 @
#3630000
b10110110 0
1/
#3640000
0/
#3641000
1'
b11 6
#3650000
b0 (
b0 I
b0 -
b10110111 0
1/
#3660000
0/
#3670000
b10111000 0
1/
#3680000
0/
#3682000
b10 >
b11 ?
b110100 @
#3690000
b10111001 0
1/
#3700000
0/
#3710000
b10111010 0
1/
#3720000
0/
#3725000
b10 ?
b110101 @
#3730000
b10111011 0
1/
#3740000
0/
#3750000
b10111100 0
1/
#3760000
0/
#3769000
b1 >
b1 ?
07
b110110 @
#3770000
b10111101 0
1/
#3780000
0/
#3787000
b100 >
b110111 @
0)
b10 6
#3790000
b10111110 0
1/
#3800000
0/
#3810000
b10111111 0
1/
#3820000
0/
#3830000
b11000000 0
1/
#3840000
0/
#3850000
b11000001 0
1/
#3860000
0/
#3867000
b11 >
b111000 @
#3870000
b11000010 0
1/
#3880000
0/
#3890000
b11000011 0
1/
#3900000
0/
#3910000
b11000100 0
1/
#3920000
b101 >
b10 ?
17
b111001 @
0/
#3930000
b11000101 0
1/
#3940000
0/
#3950000
b11000110 0
1/
#3960000
0/
#3970000
b11000111 0
1/
#3980000
0/
#3990000
b11001000 0
1/
#4000000
0/
#4010000
b11001001 0
1/
#4020000
0/
#4027000
b1 >
b11 ?
b111010 @
#4030000
b11001010 0
1/
#4040000
0/
#4048000
b100 >
b1 ?
b111011 @
#4050000
b11001011 0
1/
#4060000
0/
#4066000
1)
b11 6
#4070000
b11001100 0
1/
#4080000
0/
#4090000
b11001101 0
1/
#4100000
0/
#4110000
b11001110 0
1/
#4120000
0/
#4123000
b101 >
b0 ?
b111100 @
#4130000
b11001111 0
1/
#4140000
0/
#4142000
0'
b1 6
#4150000
b1 (
b1 I
b1 -
b11010000 0
1/
#4160000
0/
#4170000
b11 (
b11 I
b11 -
b11010001 0
1/
#4180000
0/
#4190000
b111 (
b111 I
b111 -
b11010010 0
1/
#4200000
0/
#4210000
b1111 (
b1111 I
b1111 -
b11010011 0
1/
#4220000
0/
#4223000
b1 >
07
b111101 @
#4230000
b11111 (
b11111 I
b11111 -
b11010100 0
1/
#4240000
0/
#4247000
b100 >
b10 ?
b111110 @
0)
b0 6
#4250000
b111110 (
b111110 I
b111110 -
b11010101 0
1/
#4260000
0/
#4270000
b1111100 (
b1111100 I
b1111100 -
b11010110 0
1/
#4280000
0/
#4290000
b11111000 (
b11111000 I
b11111000 -
b11010111 0
1/
#4300000
0/
#4310000
b11110000 (
b11110000 I
b11110000 -
b11011000 0
1/
#4320000
b10 >
17
b111111 @
0/
#4330000
b11100000 (
b11100000 I
b11100000 -
b11011001 0
1/
#4340000
0/
#4350000
b11000000 (
b11000000 I
b11000000 -
b11011010 0
1/
#4360000
0/
#4370000
b10000000 (
b10000000 I
b10000000 -
b11011011 0
1/
b101 >
07
b1000000 @
#4380000
0/
#4390000
b0 (
b0 I
b0 -
b11011100 0
1/
#4400000
0/
#4410000
b11011101 0
1/
#4420000
0/
#4430000
b11011110 0
1/
#4440000
0/
#4450000
b11011111 0
1/
#4460000
0/
#4464000
b1000001 @
#4470000
b11100000 0
1/
#4480000
0/
#4490000
b11100001 0
1/
#4500000
0/
#4510000
b11100010 0
1/
#4520000
0/
#4530000
b11100011 0
1/
